Workbook

Sheet Instructions
A1: Global Wholesale Machinery Inc.
A2: OEM Compareson Spreadsheet Instructions
A4: NET MARKUP% for each quote must be over 100% otherwise need approval from Quinten.
A5: NET MARGIN% for each quote must be over 50% otherwise need approval from Quinten.
A7: Customer Information Section
B8: Must be fully completed in OEM COMPARISON TAB.
B9: Information entered will be automatically transferred to QUOTE, and SERVICE QUOTE tab.
B10: Customer Information will not be transferred to RFQ tab as we do not give out customer information to vendors.
A12: Machine Information Section
B13: Optional - depends on customer request.
B14: Information entered will be automatically transferred to RFQ, QUOTE, and SERVICE QUOTE tab.
A16: Machine Service Interval Section
B17: Optional - depends on customer request.
B18: For internal use only. Information entered will not be transferred to RFQ, QUOTE, and SERVICE QUOTE tab.
A20: Parts Pricing and Cost Section
B21: Part Number - OEM Part Number (with exception to UC and Tires)
B22: Description - Description of Part
B23: Vendor - Name of the Vendor where we acquire parts from
B24: OEM Name - Name of OEM Manufacturer used for MSRP comparison
B25: Freight Cost - Vendor shipping cost.
A27: Customizable Features
A28: 1) Show or Hide OEM Comparison in Quote or Service Quote to cusomter.
B29: Select from drop down option at cell J13
A34: 2) Enter OEM pricing in USD or CAD.
B35: Select from drop down option at cell G17
A41: 3) Provide customer quotes in USD or CAD.
B42: Select from drop down option at cell L17
A51: 4) Enter Vendor pricing in USD or CAD.
B52: Select from drop down option at cell Q17

Sheet CAT 325 EXCAVATOR
B1: CUSTOMER INFORMATION | D1: MACHINE INFORMATION | H1: MACHINE SERVICE HR INTERVALS | L1: SUMMARY | O1: =K17 -> CAD $ | R1: COMPLETED DEAL INFORMATION
B2: DATE: | D2: UNIT # | H2: ENGINE AIR | L2: OEM MSRP | O2: =H129 -> 210310.33 | R2: SALES REP
B3: COMPANY: | D3: YEAR | H3: ENGINE OIL | L3: GQP LIST | O3: =L129 -> 105158.1 | R3: ORDER PO #
B4: CUSTOMER: | D4: MAKE | H4: FUEL FILTERS | L4: $ SAVINGS | O4: =O2-O3 -> 105152.23 | R4: PROJECT #
B5: PHONE: | D5: MODEL | H5: HYDRAULIC FILTERS | L5: % SAVINGS | O5: =IFERROR((O2-O3)/O2,"") -> 0.49998604 | R5: CUST INVOICE #
B6: EMAIL: | D6: SERIAL NUMBER | H6: TRANSMISSION FILTERS | L6: TOTAL ORDER MARGIN | O6: =S129 -> 105158.1 | R6: PAYMENT TYPE
B7: SALES REP: | D7: ENGINE SER NUMBER | H7: CAB FILTERS | L7: TOTAL ITEM COST | O7: =Q129 -> 0 | R7: DATE DELIVERED
D8: CURRENT HOURS | H8: UNDERCARRIAGE / TIRES | L8: TOTAL ORDER FREIGHT | O8: =IF(O1=P14,Q14,IF(P14="CAD $",Q14*D15,IF(P14="USD $",Q14*E15,0))) -> 0 | R8: TOTAL COST | S8: NET MARGIN | T8: NET MARKUP % | U8: NET MARGIN %
D9: USAGE/MONTH | L9: TOTAL CUSTOMS/BROKERAGE | O9: =U14 -> 0 | R9: =O7+O8+O9 -> 0 | S9: =O3-R9 -> 105158.1 | T9: =IFERROR(((O3-R9)/R9),0) -> 0 | U9: =IFERROR(((O3-R9)/O3),0) -> 1
L10: TOTAL NUMBER PIECES | O10: =E129 -> 1061
D11: ENTER EXCHANGE RATES $ | F11: OEM MSRP | J11: CUSTOMER SELL PRICE | O11: COST ANALYSIS | X11: CAD $
X12: USD $
F13: SHOW OEM MSRP ON QUOTE: | H13: YES | X13: YES
D14: CAD-USD | E14: USD-CAD | F14: OEM NAME | J14: CUSTOMER PRICE % OF OEM LIST | L14: 0.5 | O14: FREIGHT TOTAL ORDER | P14: USD $ | R14: CUSTOMS AND BROKERAGE % | S14: 0.025 | T14: BROKERAGE FEES | U14: =ROUND(Q129*S14,2) -> 0 | X14: NO
D15: =1/E15 -> 0.72463768 | E15: 1.38 | M15: ADDITIONAL +/- DISC % PER ITEM | O15: MARKUP LESS THAN 100% REQUIRES MANAGER APPROVAL
B16: PART NUMBER | C16: DESCRIPTION | D16: SERVICE INTERVAL | E16: QTY | F16: UNIT PRICE | H16: EXT AMOUNT | J16: QTY | K16: UNIT PRICE | L16: EXTENDED AMOUNT | O16: VENDOR | P16: COST EACH | Q16: EXTENDED COST | R16: MARGIN EACH | S16: EXTENDED MARGIN | T16: MARKUP % | U16: MARGIN %
F17: USD $ | G17: =IF(F17="USD $", "CAD $", "USD $") -> CAD $ | H17: =K17 -> CAD $ | K17: CAD $ | P17: USD $ | Q17: =K17 -> CAD $
B18: 1R-1807 | C18: OIL FILTER | E18: 1 | F18: 44.09 | G18: =ROUND(IF($F$17="USD $", F18*$E$15,F18*$D$15),2) -> 60.84 | H18: =ROUND(IF($H$17=$G$17,E18*G18,E18*F18),2) -> 60.84 | J18: =E18 -> 1 | K18: =ROUND(IF($K$17=$F$17,F18*($L$14-M18),G18*($L$14-M18)),2) -> 30.42 | L18: =ROUND((J18*K18),2) -> 30.42 | Q18: =ROUND(IF($Q$17=$P$17,P18,IF($Q$17="USD $",P18*$D$15,P18*$E$15))*E18,2) -> 0 | R18: =IFERROR(ROUND(S18/E18,2),0) -> 30.42 | S18: =ROUND(L18-Q18,2) -> 30.42 | T18: =IFERROR(((K18-(Q18/J18))/(Q18/J18)),0) -> 0 | U18: =IFERROR(((K18-(Q18/J18))/K18),0) -> 1 | Y18: 250
B19: 179-9806 | C19: Hydraulic Filter | E19: 1 | F19: 229 | G19: =ROUND(IF($F$17="USD $", F19*$E$15,F19*$D$15),2) -> 316.02 | H19: =ROUND(IF($H$17=$G$17,E19*G19,E19*F19),2) -> 316.02 | J19: =E19 -> 1 | K19: =ROUND(IF($K$17=$F$17,F19*($L$14-M19),G19*($L$14-M19)),2) -> 158.01 | L19: =ROUND((J19*K19),2) -> 158.01 | Q19: =ROUND(IF($Q$17=$P$17,P19,IF($Q$17="USD $",P19*$D$15,P19*$E$15))*E19,2) -> 0 | R19: =IFERROR(ROUND(S19/E19,2),0) -> 158.01 | S19: =ROUND(L19-Q19,2) -> 158.01 | T19: =IFERROR(((K19-(Q19/J19))/(Q19/J19)),0) -> 0 | U19: =IFERROR(((K19-(Q19/J19))/K19),0) -> 1 | X19: GQP | Y19: 500
B20: 126-1813 | C20: HYDRAULIC/TRANSMISSION OIL FILTER | E20: 1 | F20: 170.36 | G20: =ROUND(IF($F$17="USD $", F20*$E$15,F20*$D$15),2) -> 235.1 | H20: =ROUND(IF($H$17=$G$17,E20*G20,E20*F20),2) -> 235.1 | J20: =E20 -> 1 | K20: =ROUND(IF($K$17=$F$17,F20*($L$14-M20),G20*($L$14-M20)),2) -> 117.55 | L20: =ROUND((J20*K20),2) -> 117.55 | Q20: =ROUND(IF($Q$17=$P$17,P20,IF($Q$17="USD $",P20*$D$15,P20*$E$15))*E20,2) -> 0 | R20: =IFERROR(ROUND(S20/E20,2),0) -> 117.55 | S20: =ROUND(L20-Q20,2) -> 117.55 | T20: =IFERROR(((K20-(Q20/J20))/(Q20/J20)),0) -> 0 | U20: =IFERROR(((K20-(Q20/J20))/K20),0) -> 1 | X20: CTP | Y20: 750
B21: 1R7062 | C21: FUEL FILTER | E21: 1 | F21: 67.44 | G21: =ROUND(IF($F$17="USD $", F21*$E$15,F21*$D$15),2) -> 93.07 | H21: =ROUND(IF($H$17=$G$17,E21*G21,E21*F21),2) -> 93.07 | J21: =E21 -> 1 | K21: =ROUND(IF($K$17=$F$17,F21*($L$14-M21),G21*($L$14-M21)),2) -> 46.54 | L21: =ROUND((J21*K21),2) -> 46.54 | Q21: =ROUND(IF($Q$17=$P$17,P21,IF($Q$17="USD $",P21*$D$15,P21*$E$15))*E21,2) -> 0 | R21: =IFERROR(ROUND(S21/E21,2),0) -> 46.54 | S21: =ROUND(L21-Q21,2) -> 46.54 | T21: =IFERROR(((K21-(Q21/J21))/(Q21/J21)),0) -> 0 | U21: =IFERROR(((K21-(Q21/J21))/K21),0) -> 1 | X21: BLMQ | Y21: 1000
B22: 6I-2504 | C22: SECONDARY AIR FILTER | E22: 1 | F22: 117.3 | G22: =ROUND(IF($F$17="USD $", F22*$E$15,F22*$D$15),2) -> 161.87 | H22: =ROUND(IF($H$17=$G$17,E22*G22,E22*F22),2) -> 161.87 | J22: =E22 -> 1 | K22: =ROUND(IF($K$17=$F$17,F22*($L$14-M22),G22*($L$14-M22)),2) -> 80.94 | L22: =ROUND((J22*K22),2) -> 80.94 | Q22: =ROUND(IF($Q$17=$P$17,P22,IF($Q$17="USD $",P22*$D$15,P22*$E$15))*E22,2) -> 0 | R22: =IFERROR(ROUND(S22/E22,2),0) -> 80.94 | S22: =ROUND(L22-Q22,2) -> 80.94 | T22: =IFERROR(((K22-(Q22/J22))/(Q22/J22)),0) -> 0 | U22: =IFERROR(((K22-(Q22/J22))/K22),0) -> 1 | X22: CAT | Y22: 1200
B23: 6I-2503 | C23: PRIMARY AIR FILTER | E23: 1 | F23: 165.83 | G23: =ROUND(IF($F$17="USD $", F23*$E$15,F23*$D$15),2) -> 228.85 | H23: =ROUND(IF($H$17=$G$17,E23*G23,E23*F23),2) -> 228.85 | J23: =E23 -> 1 | K23: =ROUND(IF($K$17=$F$17,F23*($L$14-M23),G23*($L$14-M23)),2) -> 114.43 | L23: =ROUND((J23*K23),2) -> 114.43 | Q23: =ROUND(IF($Q$17=$P$17,P23,IF($Q$17="USD $",P23*$D$15,P23*$E$15))*E23,2) -> 0 | R23: =IFERROR(ROUND(S23/E23,2),0) -> 114.43 | S23: =ROUND(L23-Q23,2) -> 114.43 | T23: =IFERROR(((K23-(Q23/J23))/(Q23/J23)),0) -> 0 | U23: =IFERROR(((K23-(Q23/J23))/K23),0) -> 1 | X23: FINNING | Y23: 2000
B24: 326-1644 | C24: WATER/FUEL SEPARATOR | E24: 1 | F24: 85.6 | G24: =ROUND(IF($F$17="USD $", F24*$E$15,F24*$D$15),2) -> 118.13 | H24: =ROUND(IF($H$17=$G$17,E24*G24,E24*F24),2) -> 118.13 | J24: =E24 -> 1 | K24: =ROUND(IF($K$17=$F$17,F24*($L$14-M24),G24*($L$14-M24)),2) -> 59.07 | L24: =ROUND((J24*K24),2) -> 59.07 | Q24: =ROUND(IF($Q$17=$P$17,P24,IF($Q$17="USD $",P24*$D$15,P24*$E$15))*E24,2) -> 0 | R24: =IFERROR(ROUND(S24/E24,2),0) -> 59.07 | S24: =ROUND(L24-Q24,2) -> 59.07 | T24: =IFERROR(((K24-(Q24/J24))/(Q24/J24)),0) -> 0 | U24: =IFERROR(((K24-(Q24/J24))/K24),0) -> 1 | X24: JD | Y24: 4000
B25: 177-4754 | C25: INJECTOR | E25: 6 | F25: 1834.86 | G25: =ROUND(IF($F$17="USD $", F25*$E$15,F25*$D$15),2) -> 2532.11 | H25: =ROUND(IF($H$17=$G$17,E25*G25,E25*F25),2) -> 15192.66 | J25: =E25 -> 6 | K25: =ROUND(IF($K$17=$F$17,F25*($L$14-M25),G25*($L$14-M25)),2) -> 1266.06 | L25: =ROUND((J25*K25),2) -> 7596.36 | Q25: =ROUND(IF($Q$17=$P$17,P25,IF($Q$17="USD $",P25*$D$15,P25*$E$15))*E25,2) -> 0 | R25: =IFERROR(ROUND(S25/E25,2),0) -> 1266.06 | S25: =ROUND(L25-Q25,2) -> 7596.36 | T25: =IFERROR(((K25-(Q25/J25))/(Q25/J25)),0) -> 0 | U25: =IFERROR(((K25-(Q25/J25))/K25),0) -> 1 | X25: BRANDT | Y25: 6000
B26: 3T-5760 | C26: BATTERY | E26: 1 | F26: 451.85 | G26: =ROUND(IF($F$17="USD $", F26*$E$15,F26*$D$15),2) -> 623.55 | H26: =ROUND(IF($H$17=$G$17,E26*G26,E26*F26),2) -> 623.55 | J26: =E26 -> 1 | K26: =ROUND(IF($K$17=$F$17,F26*($L$14-M26),G26*($L$14-M26)),2) -> 311.78 | L26: =ROUND((J26*K26),2) -> 311.78 | Q26: =ROUND(IF($Q$17=$P$17,P26,IF($Q$17="USD $",P26*$D$15,P26*$E$15))*E26,2) -> 0 | R26: =IFERROR(ROUND(S26/E26,2),0) -> 311.78 | S26: =ROUND(L26-Q26,2) -> 311.78 | T26: =IFERROR(((K26-(Q26/J26))/(Q26/J26)),0) -> 0 | U26: =IFERROR(((K26-(Q26/J26))/K26),0) -> 1 | X26: PTI | Y26: 8000
G27: =ROUND(IF($F$17="USD $", F27*$E$15,F27*$D$15),2) -> 0 | H27: =ROUND(IF($H$17=$G$17,E27*G27,E27*F27),2) -> 0 | J27: =E27 -> 0 | K27: =ROUND(IF($K$17=$F$17,F27*($L$14-M27),G27*($L$14-M27)),2) -> 0 | L27: =ROUND((J27*K27),2) -> 0 | Q27: =ROUND(IF($Q$17=$P$17,P27,IF($Q$17="USD $",P27*$D$15,P27*$E$15))*E27,2) -> 0 | R27: =IFERROR(ROUND(S27/E27,2),0) -> 0 | S27: =ROUND(L27-Q27,2) -> 0 | T27: =IFERROR(((K27-(Q27/J27))/(Q27/J27)),0) -> 0 | U27: =IFERROR(((K27-(Q27/J27))/K27),0) -> 0 | X27: CONEQUIP | Y27: 10000
B28: 177-0440 | C28: TURBOCHARGER | E28: 1 | F28: 6839.06 | G28: =ROUND(IF($F$17="USD $", F28*$E$15,F28*$D$15),2) -> 9437.9 | H28: =ROUND(IF($H$17=$G$17,E28*G28,E28*F28),2) -> 9437.9 | J28: =E28 -> 1 | K28: =ROUND(IF($K$17=$F$17,F28*($L$14-M28),G28*($L$14-M28)),2) -> 4718.95 | L28: =ROUND((J28*K28),2) -> 4718.95 | Q28: =ROUND(IF($Q$17=$P$17,P28,IF($Q$17="USD $",P28*$D$15,P28*$E$15))*E28,2) -> 0 | R28: =IFERROR(ROUND(S28/E28,2),0) -> 4718.95 | S28: =ROUND(L28-Q28,2) -> 4718.95 | T28: =IFERROR(((K28-(Q28/J28))/(Q28/J28)),0) -> 0 | U28: =IFERROR(((K28-(Q28/J28))/K28),0) -> 1 | X28: CANDY | Y28: AS REQ'D
B29: 205-1259 | C29: CAMSHAFT | E29: 1 | F29: 4419.09 | G29: =ROUND(IF($F$17="USD $", F29*$E$15,F29*$D$15),2) -> 6098.34 | H29: =ROUND(IF($H$17=$G$17,E29*G29,E29*F29),2) -> 6098.34 | J29: =E29 -> 1 | K29: =ROUND(IF($K$17=$F$17,F29*($L$14-M29),G29*($L$14-M29)),2) -> 3049.17 | L29: =ROUND((J29*K29),2) -> 3049.17 | Q29: =ROUND(IF($Q$17=$P$17,P29,IF($Q$17="USD $",P29*$D$15,P29*$E$15))*E29,2) -> 0 | R29: =IFERROR(ROUND(S29/E29,2),0) -> 3049.17 | S29: =ROUND(L29-Q29,2) -> 3049.17 | T29: =IFERROR(((K29-(Q29/J29))/(Q29/J29)),0) -> 0 | U29: =IFERROR(((K29-(Q29/J29))/K29),0) -> 1 | X29: U/C
B30: 4892731 | C30: CRANKSHAFT | E30: 1 | F30: 14944.09 | G30: =ROUND(IF($F$17="USD $", F30*$E$15,F30*$D$15),2) -> 20622.84 | H30: =ROUND(IF($H$17=$G$17,E30*G30,E30*F30),2) -> 20622.84 | J30: =E30 -> 1 | K30: =ROUND(IF($K$17=$F$17,F30*($L$14-M30),G30*($L$14-M30)),2) -> 10311.42 | L30: =ROUND((J30*K30),2) -> 10311.42 | Q30: =ROUND(IF($Q$17=$P$17,P30,IF($Q$17="USD $",P30*$D$15,P30*$E$15))*E30,2) -> 0 | R30: =IFERROR(ROUND(S30/E30,2),0) -> 10311.42 | S30: =ROUND(L30-Q30,2) -> 10311.42 | T30: =IFERROR(((K30-(Q30/J30))/(Q30/J30)),0) -> 0 | U30: =IFERROR(((K30-(Q30/J30))/K30),0) -> 1
B31: CUSTOM | C31: ENGINE REBUILD KIT | G31: =ROUND(IF($F$17="USD $", F31*$E$15,F31*$D$15),2) -> 0 | H31: =ROUND(IF($H$17=$G$17,E31*G31,E31*F31),2) -> 0 | J31: =E31 -> 0 | K31: =ROUND(IF($K$17=$F$17,F31*($L$14-M31),G31*($L$14-M31)),2) -> 0 | L31: =ROUND((J31*K31),2) -> 0 | Q31: =ROUND(IF($Q$17=$P$17,P31,IF($Q$17="USD $",P31*$D$15,P31*$E$15))*E31,2) -> 0 | R31: =IFERROR(ROUND(S31/E31,2),0) -> 0 | S31: =ROUND(L31-Q31,2) -> 0 | T31: =IFERROR(((K31-(Q31/J31))/(Q31/J31)),0) -> 0 | U31: =IFERROR(((K31-(Q31/J31))/K31),0) -> 0
G32: =ROUND(IF($F$17="USD $", F32*$E$15,F32*$D$15),2) -> 0 | H32: =ROUND(IF($H$17=$G$17,E32*G32,E32*F32),2) -> 0 | J32: =E32 -> 0 | K32: =ROUND(IF($K$17=$F$17,F32*($L$14-M32),G32*($L$14-M32)),2) -> 0 | L32: =ROUND((J32*K32),2) -> 0 | Q32: =ROUND(IF($Q$17=$P$17,P32,IF($Q$17="USD $",P32*$D$15,P32*$E$15))*E32,2) -> 0 | R32: =IFERROR(ROUND(S32/E32,2),0) -> 0 | S32: =ROUND(L32-Q32,2) -> 0 | T32: =IFERROR(((K32-(Q32/J32))/(Q32/J32)),0) -> 0 | U32: =IFERROR(((K32-(Q32/J32))/K32),0) -> 0
B33: CUSTOM | C33: UNDERCARRIAGE TRACK GROUP ASSY | E33: 2 | F33: =SUM(F34:F37) -> 10726.82 | G33: =ROUND(IF($F$17="USD $", F33*$E$15,F33*$D$15),2) -> 14803.01 | H33: =ROUND(IF($H$17=$G$17,E33*G33,E33*F33),2) -> 29606.02 | J33: =E33 -> 2 | K33: =ROUND(IF($K$17=$F$17,F33*($L$14-M33),G33*($L$14-M33)),2) -> 7401.51 | L33: =ROUND((J33*K33),2) -> 14803.02 | Q33: =ROUND(IF($Q$17=$P$17,P33,IF($Q$17="USD $",P33*$D$15,P33*$E$15))*E33,2) -> 0 | R33: =IFERROR(ROUND(S33/E33,2),0) -> 7401.51 | S33: =ROUND(L33-Q33,2) -> 14803.02 | T33: =IFERROR(((K33-(Q33/J33))/(Q33/J33)),0) -> 0 | U33: =IFERROR(((K33-(Q33/J33))/K33),0) -> 1
B34: 213-1932 | C34: LINK AS- TRACK | E34: 2 | F34: 10460.7 | G34: =ROUND(IF($F$17="USD $", F34*$E$15,F34*$D$15),2) -> 14435.77 | H34: =ROUND(IF($H$17=$G$17,E34*G34,E34*F34),2) -> 28871.54 | J34: =E34 -> 2 | K34: =ROUND(IF($K$17=$F$17,F34*($L$14-M34),G34*($L$14-M34)),2) -> 7217.89 | L34: =ROUND((J34*K34),2) -> 14435.78 | Q34: =ROUND(IF($Q$17=$P$17,P34,IF($Q$17="USD $",P34*$D$15,P34*$E$15))*E34,2) -> 0 | R34: =IFERROR(ROUND(S34/E34,2),0) -> 7217.89 | S34: =ROUND(L34-Q34,2) -> 14435.78 | T34: =IFERROR(((K34-(Q34/J34))/(Q34/J34)),0) -> 0 | U34: =IFERROR(((K34-(Q34/J34))/K34),0) -> 1
B35: 6I-8651 | C35: TRACK SHOE 36INCH | E35: 96 | F35: 256.66 | G35: =ROUND(IF($F$17="USD $", F35*$E$15,F35*$D$15),2) -> 354.19 | H35: =ROUND(IF($H$17=$G$17,E35*G35,E35*F35),2) -> 34002.24 | J35: =E35 -> 96 | K35: =ROUND(IF($K$17=$F$17,F35*($L$14-M35),G35*($L$14-M35)),2) -> 177.1 | L35: =ROUND((J35*K35),2) -> 17001.6 | Q35: =ROUND(IF($Q$17=$P$17,P35,IF($Q$17="USD $",P35*$D$15,P35*$E$15))*E35,2) -> 0 | R35: =IFERROR(ROUND(S35/E35,2),0) -> 177.1 | S35: =ROUND(L35-Q35,2) -> 17001.6 | T35: =IFERROR(((K35-(Q35/J35))/(Q35/J35)),0) -> 0 | U35: =IFERROR(((K35-(Q35/J35))/K35),0) -> 1
B36: 6Y-0846 | C36: TRACK BOLT | E36: 384 | F36: 6.32 | G36: =ROUND(IF($F$17="USD $", F36*$E$15,F36*$D$15),2) -> 8.72 | H36: =ROUND(IF($H$17=$G$17,E36*G36,E36*F36),2) -> 3348.48 | J36: =E36 -> 384 | K36: =ROUND(IF($K$17=$F$17,F36*($L$14-M36),G36*($L$14-M36)),2) -> 4.36 | L36: =ROUND((J36*K36),2) -> 1674.24 | Q36: =ROUND(IF($Q$17=$P$17,P36,IF($Q$17="USD $",P36*$D$15,P36*$E$15))*E36,2) -> 0 | R36: =IFERROR(ROUND(S36/E36,2),0) -> 4.36 | S36: =ROUND(L36-Q36,2) -> 1674.24 | T36: =IFERROR(((K36-(Q36/J36))/(Q36/J36)),0) -> 0 | U36: =IFERROR(((K36-(Q36/J36))/K36),0) -> 1
B37: 9W-3361 | C37: TRACK NUT | E37: 384 | F37: 3.14 | G37: =ROUND(IF($F$17="USD $", F37*$E$15,F37*$D$15),2) -> 4.33 | H37: =ROUND(IF($H$17=$G$17,E37*G37,E37*F37),2) -> 1662.72 | J37: =E37 -> 384 | K37: =ROUND(IF($K$17=$F$17,F37*($L$14-M37),G37*($L$14-M37)),2) -> 2.17 | L37: =ROUND((J37*K37),2) -> 833.28 | Q37: =ROUND(IF($Q$17=$P$17,P37,IF($Q$17="USD $",P37*$D$15,P37*$E$15))*E37,2) -> 0 | R37: =IFERROR(ROUND(S37/E37,2),0) -> 2.17 | S37: =ROUND(L37-Q37,2) -> 833.28 | T37: =IFERROR(((K37-(Q37/J37))/(Q37/J37)),0) -> 0 | U37: =IFERROR(((K37-(Q37/J37))/K37),0) -> 1
G38: =ROUND(IF($F$17="USD $", F38*$E$15,F38*$D$15),2) -> 0 | H38: =ROUND(IF($H$17=$G$17,E38*G38,E38*F38),2) -> 0 | J38: =E38 -> 0 | K38: =ROUND(IF($K$17=$F$17,F38*($L$14-M38),G38*($L$14-M38)),2) -> 0 | L38: =ROUND((J38*K38),2) -> 0 | Q38: =ROUND(IF($Q$17=$P$17,P38,IF($Q$17="USD $",P38*$D$15,P38*$E$15))*E38,2) -> 0 | R38: =IFERROR(ROUND(S38/E38,2),0) -> 0 | S38: =ROUND(L38-Q38,2) -> 0 | T38: =IFERROR(((K38-(Q38/J38))/(Q38/J38)),0) -> 0 | U38: =IFERROR(((K38-(Q38/J38))/K38),0) -> 0
B39: 602-9393 | C39: FRONT WHEEL IDLER ASSY | E39: 2 | F39: 3159.07 | G39: =ROUND(IF($F$17="USD $", F39*$E$15,F39*$D$15),2) -> 4359.52 | H39: =ROUND(IF($H$17=$G$17,E39*G39,E39*F39),2) -> 8719.04 | J39: =E39 -> 2 | K39: =ROUND(IF($K$17=$F$17,F39*($L$14-M39),G39*($L$14-M39)),2) -> 2179.76 | L39: =ROUND((J39*K39),2) -> 4359.52 | Q39: =ROUND(IF($Q$17=$P$17,P39,IF($Q$17="USD $",P39*$D$15,P39*$E$15))*E39,2) -> 0 | R39: =IFERROR(ROUND(S39/E39,2),0) -> 2179.76 | S39: =ROUND(L39-Q39,2) -> 4359.52 | T39: =IFERROR(((K39-(Q39/J39))/(Q39/J39)),0) -> 0 | U39: =IFERROR(((K39-(Q39/J39))/K39),0) -> 1
B40: 300-4545 | C40: CARRIER ROLLER | E40: 4 | F40: 635.42 | G40: =ROUND(IF($F$17="USD $", F40*$E$15,F40*$D$15),2) -> 876.88 | H40: =ROUND(IF($H$17=$G$17,E40*G40,E40*F40),2) -> 3507.52 | J40: =E40 -> 4 | K40: =ROUND(IF($K$17=$F$17,F40*($L$14-M40),G40*($L$14-M40)),2) -> 438.44 | L40: =ROUND((J40*K40),2) -> 1753.76 | Q40: =ROUND(IF($Q$17=$P$17,P40,IF($Q$17="USD $",P40*$D$15,P40*$E$15))*E40,2) -> 0 | R40: =IFERROR(ROUND(S40/E40,2),0) -> 438.44 | S40: =ROUND(L40-Q40,2) -> 1753.76 | T40: =IFERROR(((K40-(Q40/J40))/(Q40/J40)),0) -> 0 | U40: =IFERROR(((K40-(Q40/J40))/K40),0) -> 1
B41: 114-6099 | C41: CARRIER ROLLER NUT | E41: 4 | F41: 31.9 | G41: =ROUND(IF($F$17="USD $", F41*$E$15,F41*$D$15),2) -> 44.02 | H41: =ROUND(IF($H$17=$G$17,E41*G41,E41*F41),2) -> 176.08 | J41: =E41 -> 4 | K41: =ROUND(IF($K$17=$F$17,F41*($L$14-M41),G41*($L$14-M41)),2) -> 22.01 | L41: =ROUND((J41*K41),2) -> 88.04 | Q41: =ROUND(IF($Q$17=$P$17,P41,IF($Q$17="USD $",P41*$D$15,P41*$E$15))*E41,2) -> 0 | R41: =IFERROR(ROUND(S41/E41,2),0) -> 22.01 | S41: =ROUND(L41-Q41,2) -> 88.04 | T41: =IFERROR(((K41-(Q41/J41))/(Q41/J41)),0) -> 0 | U41: =IFERROR(((K41-(Q41/J41))/K41),0) -> 1
B42: 503-1353 | C42: SINGLE FLANGE ROLER | E42: 18 | F42: 862.15 | G42: =ROUND(IF($F$17="USD $", F42*$E$15,F42*$D$15),2) -> 1189.77 | H42: =ROUND(IF($H$17=$G$17,E42*G42,E42*F42),2) -> 21415.86 | J42: =E42 -> 18 | K42: =ROUND(IF($K$17=$F$17,F42*($L$14-M42),G42*($L$14-M42)),2) -> 594.89 | L42: =ROUND((J42*K42),2) -> 10708.02 | Q42: =ROUND(IF($Q$17=$P$17,P42,IF($Q$17="USD $",P42*$D$15,P42*$E$15))*E42,2) -> 0 | R42: =IFERROR(ROUND(S42/E42,2),0) -> 594.89 | S42: =ROUND(L42-Q42,2) -> 10708.02 | T42: =IFERROR(((K42-(Q42/J42))/(Q42/J42)),0) -> 0 | U42: =IFERROR(((K42-(Q42/J42))/K42),0) -> 1
B43: 7X-2565 | C43: TRACK NUT | E43: 72 | F43: 24.16 | G43: =ROUND(IF($F$17="USD $", F43*$E$15,F43*$D$15),2) -> 33.34 | H43: =ROUND(IF($H$17=$G$17,E43*G43,E43*F43),2) -> 2400.48 | J43: =E43 -> 72 | K43: =ROUND(IF($K$17=$F$17,F43*($L$14-M43),G43*($L$14-M43)),2) -> 16.67 | L43: =ROUND((J43*K43),2) -> 1200.24 | Q43: =ROUND(IF($Q$17=$P$17,P43,IF($Q$17="USD $",P43*$D$15,P43*$E$15))*E43,2) -> 0 | R43: =IFERROR(ROUND(S43/E43,2),0) -> 16.67 | S43: =ROUND(L43-Q43,2) -> 1200.24 | T43: =IFERROR(((K43-(Q43/J43))/(Q43/J43)),0) -> 0 | U43: =IFERROR(((K43-(Q43/J43))/K43),0) -> 1
B44: 8T-4123 | C44: WASHER | E44: 72 | F44: 3.56 | G44: =ROUND(IF($F$17="USD $", F44*$E$15,F44*$D$15),2) -> 4.91 | H44: =ROUND(IF($H$17=$G$17,E44*G44,E44*F44),2) -> 353.52 | J44: =E44 -> 72 | K44: =ROUND(IF($K$17=$F$17,F44*($L$14-M44),G44*($L$14-M44)),2) -> 2.46 | L44: =ROUND((J44*K44),2) -> 177.12 | Q44: =ROUND(IF($Q$17=$P$17,P44,IF($Q$17="USD $",P44*$D$15,P44*$E$15))*E44,2) -> 0 | R44: =IFERROR(ROUND(S44/E44,2),0) -> 2.46 | S44: =ROUND(L44-Q44,2) -> 177.12 | T44: =IFERROR(((K44-(Q44/J44))/(Q44/J44)),0) -> 0 | U44: =IFERROR(((K44-(Q44/J44))/K44),0) -> 1
G45: =ROUND(IF($F$17="USD $", F45*$E$15,F45*$D$15),2) -> 0 | H45: =ROUND(IF($H$17=$G$17,E45*G45,E45*F45),2) -> 0 | J45: =E45 -> 0 | K45: =ROUND(IF($K$17=$F$17,F45*($L$14-M45),G45*($L$14-M45)),2) -> 0 | L45: =ROUND((J45*K45),2) -> 0 | Q45: =ROUND(IF($Q$17=$P$17,P45,IF($Q$17="USD $",P45*$D$15,P45*$E$15))*E45,2) -> 0 | R45: =IFERROR(ROUND(S45/E45,2),0) -> 0 | S45: =ROUND(L45-Q45,2) -> 0 | T45: =IFERROR(((K45-(Q45/J45))/(Q45/J45)),0) -> 0 | U45: =IFERROR(((K45-(Q45/J45))/K45),0) -> 0
B46: 347-6708 | C46: BUCKET GP | E46: 1 | F46: 16503.46 | G46: =ROUND(IF($F$17="USD $", F46*$E$15,F46*$D$15),2) -> 22774.77 | H46: =ROUND(IF($H$17=$G$17,E46*G46,E46*F46),2) -> 22774.77 | J46: =E46 -> 1 | K46: =ROUND(IF($K$17=$F$17,F46*($L$14-M46),G46*($L$14-M46)),2) -> 11387.39 | L46: =ROUND((J46*K46),2) -> 11387.39 | Q46: =ROUND(IF($Q$17=$P$17,P46,IF($Q$17="USD $",P46*$D$15,P46*$E$15))*E46,2) -> 0 | R46: =IFERROR(ROUND(S46/E46,2),0) -> 11387.39 | S46: =ROUND(L46-Q46,2) -> 11387.39 | T46: =IFERROR(((K46-(Q46/J46))/(Q46/J46)),0) -> 0 | U46: =IFERROR(((K46-(Q46/J46))/K46),0) -> 1
B47: 6Y-7409 | C47: BUCKET TIP | E47: 1 | F47: 162.68 | G47: =ROUND(IF($F$17="USD $", F47*$E$15,F47*$D$15),2) -> 224.5 | H47: =ROUND(IF($H$17=$G$17,E47*G47,E47*F47),2) -> 224.5 | J47: =E47 -> 1 | K47: =ROUND(IF($K$17=$F$17,F47*($L$14-M47),G47*($L$14-M47)),2) -> 112.25 | L47: =ROUND((J47*K47),2) -> 112.25 | Q47: =ROUND(IF($Q$17=$P$17,P47,IF($Q$17="USD $",P47*$D$15,P47*$E$15))*E47,2) -> 0 | R47: =IFERROR(ROUND(S47/E47,2),0) -> 112.25 | S47: =ROUND(L47-Q47,2) -> 112.25 | T47: =IFERROR(((K47-(Q47/J47))/(Q47/J47)),0) -> 0 | U47: =IFERROR(((K47-(Q47/J47))/K47),0) -> 1
B48: 116-7408 | C48: GROOVED PIN | E48: 1 | F48: 18.28 | G48: =ROUND(IF($F$17="USD $", F48*$E$15,F48*$D$15),2) -> 25.23 | H48: =ROUND(IF($H$17=$G$17,E48*G48,E48*F48),2) -> 25.23 | J48: =E48 -> 1 | K48: =ROUND(IF($K$17=$F$17,F48*($L$14-M48),G48*($L$14-M48)),2) -> 12.62 | L48: =ROUND((J48*K48),2) -> 12.62 | Q48: =ROUND(IF($Q$17=$P$17,P48,IF($Q$17="USD $",P48*$D$15,P48*$E$15))*E48,2) -> 0 | R48: =IFERROR(ROUND(S48/E48,2),0) -> 12.62 | S48: =ROUND(L48-Q48,2) -> 12.62 | T48: =IFERROR(((K48-(Q48/J48))/(Q48/J48)),0) -> 0 | U48: =IFERROR(((K48-(Q48/J48))/K48),0) -> 1
B49: 116-7409 | C49: RETAINER PIN | E49: 1 | F49: 24.03 | G49: =ROUND(IF($F$17="USD $", F49*$E$15,F49*$D$15),2) -> 33.16 | H49: =ROUND(IF($H$17=$G$17,E49*G49,E49*F49),2) -> 33.16 | J49: =E49 -> 1 | K49: =ROUND(IF($K$17=$F$17,F49*($L$14-M49),G49*($L$14-M49)),2) -> 16.58 | L49: =ROUND((J49*K49),2) -> 16.58 | Q49: =ROUND(IF($Q$17=$P$17,P49,IF($Q$17="USD $",P49*$D$15,P49*$E$15))*E49,2) -> 0 | R49: =IFERROR(ROUND(S49/E49,2),0) -> 16.58 | S49: =ROUND(L49-Q49,2) -> 16.58 | T49: =IFERROR(((K49-(Q49/J49))/(Q49/J49)),0) -> 0 | U49: =IFERROR(((K49-(Q49/J49))/K49),0) -> 1
G50: =ROUND(IF($F$17="USD $", F50*$E$15,F50*$D$15),2) -> 0 | H50: =ROUND(IF($H$17=$G$17,E50*G50,E50*F50),2) -> 0 | J50: =E50 -> 0 | K50: =ROUND(IF($K$17=$F$17,F50*($L$14-M50),G50*($L$14-M50)),2) -> 0 | L50: =ROUND((J50*K50),2) -> 0 | Q50: =ROUND(IF($Q$17=$P$17,P50,IF($Q$17="USD $",P50*$D$15,P50*$E$15))*E50,2) -> 0 | R50: =IFERROR(ROUND(S50/E50,2),0) -> 0 | S50: =ROUND(L50-Q50,2) -> 0 | T50: =IFERROR(((K50-(Q50/J50))/(Q50/J50)),0) -> 0 | U50: =IFERROR(((K50-(Q50/J50))/K50),0) -> 0
G51: =ROUND(IF($F$17="USD $", F51*$E$15,F51*$D$15),2) -> 0 | H51: =ROUND(IF($H$17=$G$17,E51*G51,E51*F51),2) -> 0 | J51: =E51 -> 0 | K51: =ROUND(IF($K$17=$F$17,F51*($L$14-M51),G51*($L$14-M51)),2) -> 0 | L51: =ROUND((J51*K51),2) -> 0 | Q51: =ROUND(IF($Q$17=$P$17,P51,IF($Q$17="USD $",P51*$D$15,P51*$E$15))*E51,2) -> 0 | R51: =IFERROR(ROUND(S51/E51,2),0) -> 0 | S51: =ROUND(L51-Q51,2) -> 0 | T51: =IFERROR(((K51-(Q51/J51))/(Q51/J51)),0) -> 0 | U51: =IFERROR(((K51-(Q51/J51))/K51),0) -> 0
G52: =ROUND(IF($F$17="USD $", F52*$E$15,F52*$D$15),2) -> 0 | H52: =ROUND(IF($H$17=$G$17,E52*G52,E52*F52),2) -> 0 | J52: =E52 -> 0 | K52: =ROUND(IF($K$17=$F$17,F52*($L$14-M52),G52*($L$14-M52)),2) -> 0 | L52: =ROUND((J52*K52),2) -> 0 | Q52: =ROUND(IF($Q$17=$P$17,P52,IF($Q$17="USD $",P52*$D$15,P52*$E$15))*E52,2) -> 0 | R52: =IFERROR(ROUND(S52/E52,2),0) -> 0 | S52: =ROUND(L52-Q52,2) -> 0 | T52: =IFERROR(((K52-(Q52/J52))/(Q52/J52)),0) -> 0 | U52: =IFERROR(((K52-(Q52/J52))/K52),0) -> 0
G53: =ROUND(IF($F$17="USD $", F53*$E$15,F53*$D$15),2) -> 0 | H53: =ROUND(IF($H$17=$G$17,E53*G53,E53*F53),2) -> 0 | J53: =E53 -> 0 | K53: =ROUND(IF($K$17=$F$17,F53*($L$14-M53),G53*($L$14-M53)),2) -> 0 | L53: =ROUND((J53*K53),2) -> 0 | Q53: =ROUND(IF($Q$17=$P$17,P53,IF($Q$17="USD $",P53*$D$15,P53*$E$15))*E53,2) -> 0 | R53: =IFERROR(ROUND(S53/E53,2),0) -> 0 | S53: =ROUND(L53-Q53,2) -> 0 | T53: =IFERROR(((K53-(Q53/J53))/(Q53/J53)),0) -> 0 | U53: =IFERROR(((K53-(Q53/J53))/K53),0) -> 0
G54: =ROUND(IF($F$17="USD $", F54*$E$15,F54*$D$15),2) -> 0 | H54: =ROUND(IF($H$17=$G$17,E54*G54,E54*F54),2) -> 0 | J54: =E54 -> 0 | K54: =ROUND(IF($K$17=$F$17,F54*($L$14-M54),G54*($L$14-M54)),2) -> 0 | L54: =ROUND((J54*K54),2) -> 0 | Q54: =ROUND(IF($Q$17=$P$17,P54,IF($Q$17="USD $",P54*$D$15,P54*$E$15))*E54,2) -> 0 | R54: =IFERROR(ROUND(S54/E54,2),0) -> 0 | S54: =ROUND(L54-Q54,2) -> 0 | T54: =IFERROR(((K54-(Q54/J54))/(Q54/J54)),0) -> 0 | U54: =IFERROR(((K54-(Q54/J54))/K54),0) -> 0
G55: =ROUND(IF($F$17="USD $", F55*$E$15,F55*$D$15),2) -> 0 | H55: =ROUND(IF($H$17=$G$17,E55*G55,E55*F55),2) -> 0 | J55: =E55 -> 0 | K55: =ROUND(IF($K$17=$F$17,F55*($L$14-M55),G55*($L$14-M55)),2) -> 0 | L55: =ROUND((J55*K55),2) -> 0 | Q55: =ROUND(IF($Q$17=$P$17,P55,IF($Q$17="USD $",P55*$D$15,P55*$E$15))*E55,2) -> 0 | R55: =IFERROR(ROUND(S55/E55,2),0) -> 0 | S55: =ROUND(L55-Q55,2) -> 0 | T55: =IFERROR(((K55-(Q55/J55))/(Q55/J55)),0) -> 0 | U55: =IFERROR(((K55-(Q55/J55))/K55),0) -> 0
G56: =ROUND(IF($F$17="USD $", F56*$E$15,F56*$D$15),2) -> 0 | H56: =ROUND(IF($H$17=$G$17,E56*G56,E56*F56),2) -> 0 | J56: =E56 -> 0 | K56: =ROUND(IF($K$17=$F$17,F56*($L$14-M56),G56*($L$14-M56)),2) -> 0 | L56: =ROUND((J56*K56),2) -> 0 | Q56: =ROUND(IF($Q$17=$P$17,P56,IF($Q$17="USD $",P56*$D$15,P56*$E$15))*E56,2) -> 0 | R56: =IFERROR(ROUND(S56/E56,2),0) -> 0 | S56: =ROUND(L56-Q56,2) -> 0 | T56: =IFERROR(((K56-(Q56/J56))/(Q56/J56)),0) -> 0 | U56: =IFERROR(((K56-(Q56/J56))/K56),0) -> 0
G57: =ROUND(IF($F$17="USD $", F57*$E$15,F57*$D$15),2) -> 0 | H57: =ROUND(IF($H$17=$G$17,E57*G57,E57*F57),2) -> 0 | J57: =E57 -> 0 | K57: =ROUND(IF($K$17=$F$17,F57*($L$14-M57),G57*($L$14-M57)),2) -> 0 | L57: =ROUND((J57*K57),2) -> 0 | Q57: =ROUND(IF($Q$17=$P$17,P57,IF($Q$17="USD $",P57*$D$15,P57*$E$15))*E57,2) -> 0 | R57: =IFERROR(ROUND(S57/E57,2),0) -> 0 | S57: =ROUND(L57-Q57,2) -> 0 | T57: =IFERROR(((K57-(Q57/J57))/(Q57/J57)),0) -> 0 | U57: =IFERROR(((K57-(Q57/J57))/K57),0) -> 0
G58: =ROUND(IF($F$17="USD $", F58*$E$15,F58*$D$15),2) -> 0 | H58: =ROUND(IF($H$17=$G$17,E58*G58,E58*F58),2) -> 0 | J58: =E58 -> 0 | K58: =ROUND(IF($K$17=$F$17,F58*($L$14-M58),G58*($L$14-M58)),2) -> 0 | L58: =ROUND((J58*K58),2) -> 0 | Q58: =ROUND(IF($Q$17=$P$17,P58,IF($Q$17="USD $",P58*$D$15,P58*$E$15))*E58,2) -> 0 | R58: =IFERROR(ROUND(S58/E58,2),0) -> 0 | S58: =ROUND(L58-Q58,2) -> 0 | T58: =IFERROR(((K58-(Q58/J58))/(Q58/J58)),0) -> 0 | U58: =IFERROR(((K58-(Q58/J58))/K58),0) -> 0
G59: =ROUND(IF($F$17="USD $", F59*$E$15,F59*$D$15),2) -> 0 | H59: =ROUND(IF($H$17=$G$17,E59*G59,E59*F59),2) -> 0 | J59: =E59 -> 0 | K59: =ROUND(IF($K$17=$F$17,F59*($L$14-M59),G59*($L$14-M59)),2) -> 0 | L59: =ROUND((J59*K59),2) -> 0 | Q59: =ROUND(IF($Q$17=$P$17,P59,IF($Q$17="USD $",P59*$D$15,P59*$E$15))*E59,2) -> 0 | R59: =IFERROR(ROUND(S59/E59,2),0) -> 0 | S59: =ROUND(L59-Q59,2) -> 0 | T59: =IFERROR(((K59-(Q59/J59))/(Q59/J59)),0) -> 0 | U59: =IFERROR(((K59-(Q59/J59))/K59),0) -> 0
G60: =ROUND(IF($F$17="USD $", F60*$E$15,F60*$D$15),2) -> 0 | H60: =ROUND(IF($H$17=$G$17,E60*G60,E60*F60),2) -> 0 | J60: =E60 -> 0 | K60: =ROUND(IF($K$17=$F$17,F60*($L$14-M60),G60*($L$14-M60)),2) -> 0 | L60: =ROUND((J60*K60),2) -> 0 | Q60: =ROUND(IF($Q$17=$P$17,P60,IF($Q$17="USD $",P60*$D$15,P60*$E$15))*E60,2) -> 0 | R60: =IFERROR(ROUND(S60/E60,2),0) -> 0 | S60: =ROUND(L60-Q60,2) -> 0 | T60: =IFERROR(((K60-(Q60/J60))/(Q60/J60)),0) -> 0 | U60: =IFERROR(((K60-(Q60/J60))/K60),0) -> 0
G61: =ROUND(IF($F$17="USD $", F61*$E$15,F61*$D$15),2) -> 0 | H61: =ROUND(IF($H$17=$G$17,E61*G61,E61*F61),2) -> 0 | J61: =E61 -> 0 | K61: =ROUND(IF($K$17=$F$17,F61*($L$14-M61),G61*($L$14-M61)),2) -> 0 | L61: =ROUND((J61*K61),2) -> 0 | Q61: =ROUND(IF($Q$17=$P$17,P61,IF($Q$17="USD $",P61*$D$15,P61*$E$15))*E61,2) -> 0 | R61: =IFERROR(ROUND(S61/E61,2),0) -> 0 | S61: =ROUND(L61-Q61,2) -> 0 | T61: =IFERROR(((K61-(Q61/J61))/(Q61/J61)),0) -> 0 | U61: =IFERROR(((K61-(Q61/J61))/K61),0) -> 0
... G128: =ROUND(IF($F$17="USD $", F128*$E$15,F128*$D$15),2) -> 0 | H128: =ROUND(IF($H$17=$G$17,E128*G128,E128*F128),2) -> 0 | J128: =E128 -> 0 | K128: =ROUND(IF($K$17=$F$17,F128*($L$14-M128),G128*($L$14-M128)),2) -> 0 | L128: =ROUND((J128*K128),2) -> 0 | Q128: =ROUND(IF($Q$17=$P$17,P128,IF($Q$17="USD $",P128*$D$15,P128*$E$15))*E128,2) -> 0 | R128: =IFERROR(ROUND(S128/E128,2),0) -> 0 | S128: =ROUND(L128-Q128,2) -> 0 | T128: =IFERROR(((K128-(Q128/J128))/(Q128/J128)),0) -> 0 | U128: =IFERROR(((K128-(Q128/J128))/K128),0) -> 0
D129: TOTALS | E129: =SUM(E18:E128) -> 1061 | F129: =SUM(F18:F128) -> 72246.92 | G129: =SUM(G18:G128) -> 99700.74 | H129: =SUM(H18:H128) -> 210310.33 | J129: =SUM(J18:J128) -> 1061 | K129: =SUM(K18:K128) -> 49850.44 | L129: =SUM(L18:L128) -> 105158.1 | P129: =SUM(P18:P128) -> 0 | Q129: =SUM(Q18:Q128) -> 0 | R129: =SUM(R18:R128) -> 49850.44 | S129: =SUM(S18:S128) -> 105158.1

Sheet CAT D7R
B1: CUSTOMER INFORMATION | D1: MACHINE INFORMATION | H1: MACHINE SERVICE HR INTERVALS | L1: SUMMARY | O1: =K17 -> CAD $ | R1: COMPLETED DEAL INFORMATION
B2: DATE: | D2: UNIT # | H2: ENGINE AIR | L2: OEM MSRP | O2: =H129 -> 315127.21 | R2: SALES REP
B3: COMPANY: | D3: YEAR | H3: ENGINE OIL | L3: GQP LIST | O3: =L129 -> 157565.35 | R3: ORDER PO #
B4: CUSTOMER: | D4: MAKE | H4: FUEL FILTERS | L4: $ SAVINGS | O4: =O2-O3 -> 157561.86 | R4: PROJECT #
B5: PHONE: | D5: MODEL | H5: HYDRAULIC FILTERS | L5: % SAVINGS | O5: =IFERROR((O2-O3)/O2,"") -> 0.49999446 | R5: CUST INVOICE #
B6: EMAIL: | D6: SERIAL NUMBER | H6: TRANSMISSION FILTERS | L6: TOTAL ORDER MARGIN | O6: =S129 -> 157565.35 | R6: PAYMENT TYPE
B7: SALES REP: | D7: ENGINE SER NUMBER | H7: CAB FILTERS | L7: TOTAL ITEM COST | O7: =Q129 -> 0 | R7: DATE DELIVERED
D8: CURRENT HOURS | H8: UNDERCARRIAGE / TIRES | L8: TOTAL ORDER FREIGHT | O8: =IF(O1=P14,Q14,IF(P14="CAD $",Q14*D15,IF(P14="USD $",Q14*E15,0))) -> 0 | R8: TOTAL COST | S8: NET MARGIN | T8: NET MARKUP % | U8: NET MARGIN %
D9: USAGE/MONTH | L9: TOTAL CUSTOMS/BROKERAGE | O9: =U14 -> 0 | R9: =O7+O8+O9 -> 0 | S9: =O3-R9 -> 157565.35 | T9: =IFERROR(((O3-R9)/R9),0) -> 0 | U9: =IFERROR(((O3-R9)/O3),0) -> 1
L10: TOTAL NUMBER PIECES | O10: =E129 -> 487
D11: ENTER EXCHANGE RATES $ | F11: OEM MSRP | J11: CUSTOMER SELL PRICE | O11: COST ANALYSIS | X11: CAD $
X12: USD $
F13: SHOW OEM MSRP ON QUOTE: | H13: YES | X13: YES
D14: CAD-USD | E14: USD-CAD | F14: OEM NAME | J14: CUSTOMER PRICE % OF OEM LIST | L14: 0.5 | O14: FREIGHT TOTAL ORDER | P14: USD $ | R14: CUSTOMS AND BROKERAGE % | S14: 0.025 | T14: BROKERAGE FEES | U14: =ROUND(Q129*S14,2) -> 0 | X14: NO
D15: =1/E15 -> 0.72463768 | E15: 1.38 | M15: ADDITIONAL +/- DISC % PER ITEM | O15: MARKUP LESS THAN 100% REQUIRES MANAGER APPROVAL
B16: PART NUMBER | C16: DESCRIPTION | D16: SERVICE INTERVAL | E16: QTY | F16: UNIT PRICE | H16: EXT AMOUNT | J16: QTY | K16: UNIT PRICE | L16: EXTENDED AMOUNT | O16: VENDOR | P16: COST EACH | Q16: EXTENDED COST | R16: MARGIN EACH | S16: EXTENDED MARGIN | T16: MARKUP % | U16: MARGIN %
F17: CAD $ | G17: =IF(F17="USD $", "CAD $", "USD $") -> USD $ | H17: =K17 -> CAD $ | K17: CAD $ | P17: USD $ | Q17: =K17 -> CAD $
B18: 1R-0716 | C18: ENGINE OIL FILTER | E18: 1 | F18: 61.62 | G18: =ROUND(IF($F$17="USD $", F18*$E$15,F18*$D$15),2) -> 44.65 | H18: =ROUND(IF($H$17=$G$17,E18*G18,E18*F18),2) -> 61.62 | J18: =E18 -> 1 | K18: =ROUND(IF($K$17=$F$17,F18*($L$14-M18),G18*($L$14-M18)),2) -> 30.81 | L18: =ROUND((J18*K18),2) -> 30.81 | Q18: =ROUND(IF($Q$17=$P$17,P18,IF($Q$17="USD $",P18*$D$15,P18*$E$15))*E18,2) -> 0 | R18: =IFERROR(ROUND(S18/E18,2),0) -> 30.81 | S18: =ROUND(L18-Q18,2) -> 30.81 | T18: =IFERROR(((K18-(Q18/J18))/(Q18/J18)),0) -> 0 | U18: =IFERROR(((K18-(Q18/J18))/K18),0) -> 1 | Y18: 250
B19: 326-1643 | C19: fuel filter | E19: 1 | F19: 104.86 | G19: =ROUND(IF($F$17="USD $", F19*$E$15,F19*$D$15),2) -> 75.99 | H19: =ROUND(IF($H$17=$G$17,E19*G19,E19*F19),2) -> 104.86 | J19: =E19 -> 1 | K19: =ROUND(IF($K$17=$F$17,F19*($L$14-M19),G19*($L$14-M19)),2) -> 52.43 | L19: =ROUND((J19*K19),2) -> 52.43 | Q19: =ROUND(IF($Q$17=$P$17,P19,IF($Q$17="USD $",P19*$D$15,P19*$E$15))*E19,2) -> 0 | R19: =IFERROR(ROUND(S19/E19,2),0) -> 52.43 | S19: =ROUND(L19-Q19,2) -> 52.43 | T19: =IFERROR(((K19-(Q19/J19))/(Q19/J19)),0) -> 0 | U19: =IFERROR(((K19-(Q19/J19))/K19),0) -> 1 | X19: GQP | Y19: 500
B20: 1R-0749 | C20: SECONDARY FUEL FILTER | E20: 1 | F20: 51.52 | G20: =ROUND(IF($F$17="USD $", F20*$E$15,F20*$D$15),2) -> 37.33 | H20: =ROUND(IF($H$17=$G$17,E20*G20,E20*F20),2) -> 51.52 | J20: =E20 -> 1 | K20: =ROUND(IF($K$17=$F$17,F20*($L$14-M20),G20*($L$14-M20)),2) -> 25.76 | L20: =ROUND((J20*K20),2) -> 25.76 | Q20: =ROUND(IF($Q$17=$P$17,P20,IF($Q$17="USD $",P20*$D$15,P20*$E$15))*E20,2) -> 0 | R20: =IFERROR(ROUND(S20/E20,2),0) -> 25.76 | S20: =ROUND(L20-Q20,2) -> 25.76 | T20: =IFERROR(((K20-(Q20/J20))/(Q20/J20)),0) -> 0 | U20: =IFERROR(((K20-(Q20/J20))/K20),0) -> 1 | X20: CTP | Y20: 750
B21: 326-1642 | C21: FUEL WATER SEPARATOR FILTER | E21: 1 | F21: 79.42 | G21: =ROUND(IF($F$17="USD $", F21*$E$15,F21*$D$15),2) -> 57.55 | H21: =ROUND(IF($H$17=$G$17,E21*G21,E21*F21),2) -> 79.42 | J21: =E21 -> 1 | K21: =ROUND(IF($K$17=$F$17,F21*($L$14-M21),G21*($L$14-M21)),2) -> 39.71 | L21: =ROUND((J21*K21),2) -> 39.71 | Q21: =ROUND(IF($Q$17=$P$17,P21,IF($Q$17="USD $",P21*$D$15,P21*$E$15))*E21,2) -> 0 | R21: =IFERROR(ROUND(S21/E21,2),0) -> 39.71 | S21: =ROUND(L21-Q21,2) -> 39.71 | T21: =IFERROR(((K21-(Q21/J21))/(Q21/J21)),0) -> 0 | U21: =IFERROR(((K21-(Q21/J21))/K21),0) -> 1 | X21: BLMQ | Y21: 1000
B22: 1R-0735 | C22: HYDRAULIC FILTER | E22: 1 | F22: 86.67 | G22: =ROUND(IF($F$17="USD $", F22*$E$15,F22*$D$15),2) -> 62.8 | H22: =ROUND(IF($H$17=$G$17,E22*G22,E22*F22),2) -> 86.67 | J22: =E22 -> 1 | K22: =ROUND(IF($K$17=$F$17,F22*($L$14-M22),G22*($L$14-M22)),2) -> 43.34 | L22: =ROUND((J22*K22),2) -> 43.34 | Q22: =ROUND(IF($Q$17=$P$17,P22,IF($Q$17="USD $",P22*$D$15,P22*$E$15))*E22,2) -> 0 | R22: =IFERROR(ROUND(S22/E22,2),0) -> 43.34 | S22: =ROUND(L22-Q22,2) -> 43.34 | T22: =IFERROR(((K22-(Q22/J22))/(Q22/J22)),0) -> 0 | U22: =IFERROR(((K22-(Q22/J22))/K22),0) -> 1 | X22: CAT | Y22: 1200
B23: 1R-0719 | C23: HYDRAULIC TRANSMISSION OIL FILTER | E23: 1 | F23: 30.32 | G23: =ROUND(IF($F$17="USD $", F23*$E$15,F23*$D$15),2) -> 21.97 | H23: =ROUND(IF($H$17=$G$17,E23*G23,E23*F23),2) -> 30.32 | J23: =E23 -> 1 | K23: =ROUND(IF($K$17=$F$17,F23*($L$14-M23),G23*($L$14-M23)),2) -> 15.16 | L23: =ROUND((J23*K23),2) -> 15.16 | Q23: =ROUND(IF($Q$17=$P$17,P23,IF($Q$17="USD $",P23*$D$15,P23*$E$15))*E23,2) -> 0 | R23: =IFERROR(ROUND(S23/E23,2),0) -> 15.16 | S23: =ROUND(L23-Q23,2) -> 15.16 | T23: =IFERROR(((K23-(Q23/J23))/(Q23/J23)),0) -> 0 | U23: =IFERROR(((K23-(Q23/J23))/K23),0) -> 1 | X23: FINNING | Y23: 2000
B24: 6I-0273 | C24: PRIMARY AIR FILTER | E24: 1 | F24: 155.46 | G24: =ROUND(IF($F$17="USD $", F24*$E$15,F24*$D$15),2) -> 112.65 | H24: =ROUND(IF($H$17=$G$17,E24*G24,E24*F24),2) -> 155.46 | J24: =E24 -> 1 | K24: =ROUND(IF($K$17=$F$17,F24*($L$14-M24),G24*($L$14-M24)),2) -> 77.73 | L24: =ROUND((J24*K24),2) -> 77.73 | Q24: =ROUND(IF($Q$17=$P$17,P24,IF($Q$17="USD $",P24*$D$15,P24*$E$15))*E24,2) -> 0 | R24: =IFERROR(ROUND(S24/E24,2),0) -> 77.73 | S24: =ROUND(L24-Q24,2) -> 77.73 | T24: =IFERROR(((K24-(Q24/J24))/(Q24/J24)),0) -> 0 | U24: =IFERROR(((K24-(Q24/J24))/K24),0) -> 1 | X24: JD | Y24: 4000
B25: 6I-0274 | C25: SECONDARY AIR FILTER ELEMENT | E25: 1 | F25: 118.89 | G25: =ROUND(IF($F$17="USD $", F25*$E$15,F25*$D$15),2) -> 86.15 | H25: =ROUND(IF($H$17=$G$17,E25*G25,E25*F25),2) -> 118.89 | J25: =E25 -> 1 | K25: =ROUND(IF($K$17=$F$17,F25*($L$14-M25),G25*($L$14-M25)),2) -> 59.45 | L25: =ROUND((J25*K25),2) -> 59.45 | Q25: =ROUND(IF($Q$17=$P$17,P25,IF($Q$17="USD $",P25*$D$15,P25*$E$15))*E25,2) -> 0 | R25: =IFERROR(ROUND(S25/E25,2),0) -> 59.45 | S25: =ROUND(L25-Q25,2) -> 59.45 | T25: =IFERROR(((K25-(Q25/J25))/(Q25/J25)),0) -> 0 | U25: =IFERROR(((K25-(Q25/J25))/K25),0) -> 1 | X25: BRANDT | Y25: 6000
B26: 6T-0988 | C26: CABIN AIR FILTER ELEMENT | E26: 1 | F26: 102.6 | G26: =ROUND(IF($F$17="USD $", F26*$E$15,F26*$D$15),2) -> 74.35 | H26: =ROUND(IF($H$17=$G$17,E26*G26,E26*F26),2) -> 102.6 | J26: =E26 -> 1 | K26: =ROUND(IF($K$17=$F$17,F26*($L$14-M26),G26*($L$14-M26)),2) -> 51.3 | L26: =ROUND((J26*K26),2) -> 51.3 | Q26: =ROUND(IF($Q$17=$P$17,P26,IF($Q$17="USD $",P26*$D$15,P26*$E$15))*E26,2) -> 0 | R26: =IFERROR(ROUND(S26/E26,2),0) -> 51.3 | S26: =ROUND(L26-Q26,2) -> 51.3 | T26: =IFERROR(((K26-(Q26/J26))/(Q26/J26)),0) -> 0 | U26: =IFERROR(((K26-(Q26/J26))/K26),0) -> 1 | X26: PTI | Y26: 8000
B27: 153-5710 | C27: 12V 4D BCI BATTERY (19.3" X 8.6" X 9.9") | E27: 2 | F27: 811.6 | G27: =ROUND(IF($F$17="USD $", F27*$E$15,F27*$D$15),2) -> 588.12 | H27: =ROUND(IF($H$17=$G$17,E27*G27,E27*F27),2) -> 1623.2 | J27: =E27 -> 2 | K27: =ROUND(IF($K$17=$F$17,F27*($L$14-M27),G27*($L$14-M27)),2) -> 405.8 | L27: =ROUND((J27*K27),2) -> 811.6 | Q27: =ROUND(IF($Q$17=$P$17,P27,IF($Q$17="USD $",P27*$D$15,P27*$E$15))*E27,2) -> 0 | R27: =IFERROR(ROUND(S27/E27,2),0) -> 405.8 | S27: =ROUND(L27-Q27,2) -> 811.6 | T27: =IFERROR(((K27-(Q27/J27))/(Q27/J27)),0) -> 0 | U27: =IFERROR(((K27-(Q27/J27))/K27),0) -> 1 | X27: CONEQUIP | Y27: 10000
G28: =ROUND(IF($F$17="USD $", F28*$E$15,F28*$D$15),2) -> 0 | H28: =ROUND(IF($H$17=$G$17,E28*G28,E28*F28),2) -> 0 | J28: =E28 -> 0 | K28: =ROUND(IF($K$17=$F$17,F28*($L$14-M28),G28*($L$14-M28)),2) -> 0 | L28: =ROUND((J28*K28),2) -> 0 | Q28: =ROUND(IF($Q$17=$P$17,P28,IF($Q$17="USD $",P28*$D$15,P28*$E$15))*E28,2) -> 0 | R28: =IFERROR(ROUND(S28/E28,2),0) -> 0 | S28: =ROUND(L28-Q28,2) -> 0 | T28: =IFERROR(((K28-(Q28/J28))/(Q28/J28)),0) -> 0 | U28: =IFERROR(((K28-(Q28/J28))/K28),0) -> 0 | X28: CANDY | Y28: AS REQ'D
B29: 317-5278 | C29: FUEL INJECTOR | E29: 6 | F29: 1949.47 | G29: =ROUND(IF($F$17="USD $", F29*$E$15,F29*$D$15),2) -> 1412.66 | H29: =ROUND(IF($H$17=$G$17,E29*G29,E29*F29),2) -> 11696.82 | J29: =E29 -> 6 | K29: =ROUND(IF($K$17=$F$17,F29*($L$14-M29),G29*($L$14-M29)),2) -> 974.74 | L29: =ROUND((J29*K29),2) -> 5848.44 | Q29: =ROUND(IF($Q$17=$P$17,P29,IF($Q$17="USD $",P29*$D$15,P29*$E$15))*E29,2) -> 0 | R29: =IFERROR(ROUND(S29/E29,2),0) -> 974.74 | S29: =ROUND(L29-Q29,2) -> 5848.44 | T29: =IFERROR(((K29-(Q29/J29))/(Q29/J29)),0) -> 0 | U29: =IFERROR(((K29-(Q29/J29))/K29),0) -> 1 | X29: U/C
B30: 4P-8730 | C30: TURBOCHARGER ASSEMBLY | E30: 1 | F30: 7023.145 | G30: =ROUND(IF($F$17="USD $", F30*$E$15,F30*$D$15),2) -> 5089.24 | H30: =ROUND(IF($H$17=$G$17,E30*G30,E30*F30),2) -> 7023.15 | J30: =E30 -> 1 | K30: =ROUND(IF($K$17=$F$17,F30*($L$14-M30),G30*($L$14-M30)),2) -> 3511.57 | L30: =ROUND((J30*K30),2) -> 3511.57 | Q30: =ROUND(IF($Q$17=$P$17,P30,IF($Q$17="USD $",P30*$D$15,P30*$E$15))*E30,2) -> 0 | R30: =IFERROR(ROUND(S30/E30,2),0) -> 3511.57 | S30: =ROUND(L30-Q30,2) -> 3511.57 | T30: =IFERROR(((K30-(Q30/J30))/(Q30/J30)),0) -> 0 | U30: =IFERROR(((K30-(Q30/J30))/K30),0) -> 1
G31: =ROUND(IF($F$17="USD $", F31*$E$15,F31*$D$15),2) -> 0 | H31: =ROUND(IF($H$17=$G$17,E31*G31,E31*F31),2) -> 0 | J31: =E31 -> 0 | K31: =ROUND(IF($K$17=$F$17,F31*($L$14-M31),G31*($L$14-M31)),2) -> 0 | L31: =ROUND((J31*K31),2) -> 0 | Q31: =ROUND(IF($Q$17=$P$17,P31,IF($Q$17="USD $",P31*$D$15,P31*$E$15))*E31,2) -> 0 | R31: =IFERROR(ROUND(S31/E31,2),0) -> 0 | S31: =ROUND(L31-Q31,2) -> 0 | T31: =IFERROR(((K31-(Q31/J31))/(Q31/J31)),0) -> 0 | U31: =IFERROR(((K31-(Q31/J31))/K31),0) -> 0
B32: 278-2363 | C32: TRACK SPROCKET SEGMENT | E32: 10 | F32: 395.87 | G32: =ROUND(IF($F$17="USD $", F32*$E$15,F32*$D$15),2) -> 286.86 | H32: =ROUND(IF($H$17=$G$17,E32*G32,E32*F32),2) -> 3958.7 | J32: =E32 -> 10 | K32: =ROUND(IF($K$17=$F$17,F32*($L$14-M32),G32*($L$14-M32)),2) -> 197.94 | L32: =ROUND((J32*K32),2) -> 1979.4 | Q32: =ROUND(IF($Q$17=$P$17,P32,IF($Q$17="USD $",P32*$D$15,P32*$E$15))*E32,2) -> 0 | R32: =IFERROR(ROUND(S32/E32,2),0) -> 197.94 | S32: =ROUND(L32-Q32,2) -> 1979.4 | T32: =IFERROR(((K32-(Q32/J32))/(Q32/J32)),0) -> 0 | U32: =IFERROR(((K32-(Q32/J32))/K32),0) -> 1
B33: 5P-7665 | C33: SPROCKET BOLT | E33: 50 | F33: 5.51 | G33: =ROUND(IF($F$17="USD $", F33*$E$15,F33*$D$15),2) -> 3.99 | H33: =ROUND(IF($H$17=$G$17,E33*G33,E33*F33),2) -> 275.5 | J33: =E33 -> 50 | K33: =ROUND(IF($K$17=$F$17,F33*($L$14-M33),G33*($L$14-M33)),2) -> 2.76 | L33: =ROUND((J33*K33),2) -> 138 | Q33: =ROUND(IF($Q$17=$P$17,P33,IF($Q$17="USD $",P33*$D$15,P33*$E$15))*E33,2) -> 0 | R33: =IFERROR(ROUND(S33/E33,2),0) -> 2.76 | S33: =ROUND(L33-Q33,2) -> 138 | T33: =IFERROR(((K33-(Q33/J33))/(Q33/J33)),0) -> 0 | U33: =IFERROR(((K33-(Q33/J33))/K33),0) -> 1
B34: 6V-5841 | C34: FLAT WASHER | E34: 50 | F34: 4.01 | G34: =ROUND(IF($F$17="USD $", F34*$E$15,F34*$D$15),2) -> 2.91 | H34: =ROUND(IF($H$17=$G$17,E34*G34,E34*F34),2) -> 200.5 | J34: =E34 -> 50 | K34: =ROUND(IF($K$17=$F$17,F34*($L$14-M34),G34*($L$14-M34)),2) -> 2.01 | L34: =ROUND((J34*K34),2) -> 100.5 | Q34: =ROUND(IF($Q$17=$P$17,P34,IF($Q$17="USD $",P34*$D$15,P34*$E$15))*E34,2) -> 0 | R34: =IFERROR(ROUND(S34/E34,2),0) -> 2.01 | S34: =ROUND(L34-Q34,2) -> 100.5 | T34: =IFERROR(((K34-(Q34/J34))/(Q34/J34)),0) -> 0 | U34: =IFERROR(((K34-(Q34/J34))/K34),0) -> 1
B35: 7H-3608 | C35: SPROCKET NUT | E35: 50 | F35: 5.35 | G35: =ROUND(IF($F$17="USD $", F35*$E$15,F35*$D$15),2) -> 3.88 | H35: =ROUND(IF($H$17=$G$17,E35*G35,E35*F35),2) -> 267.5 | J35: =E35 -> 50 | K35: =ROUND(IF($K$17=$F$17,F35*($L$14-M35),G35*($L$14-M35)),2) -> 2.68 | L35: =ROUND((J35*K35),2) -> 134 | Q35: =ROUND(IF($Q$17=$P$17,P35,IF($Q$17="USD $",P35*$D$15,P35*$E$15))*E35,2) -> 0 | R35: =IFERROR(ROUND(S35/E35,2),0) -> 2.68 | S35: =ROUND(L35-Q35,2) -> 134 | T35: =IFERROR(((K35-(Q35/J35))/(Q35/J35)),0) -> 0 | U35: =IFERROR(((K35-(Q35/J35))/K35),0) -> 1
B36: 420-9357 | C36: FRONT IDLER | E36: 2 | F36: 3842.24 | G36: =ROUND(IF($F$17="USD $", F36*$E$15,F36*$D$15),2) -> 2784.23 | H36: =ROUND(IF($H$17=$G$17,E36*G36,E36*F36),2) -> 7684.48 | J36: =E36 -> 2 | K36: =ROUND(IF($K$17=$F$17,F36*($L$14-M36),G36*($L$14-M36)),2) -> 1921.12 | L36: =ROUND((J36*K36),2) -> 3842.24 | Q36: =ROUND(IF($Q$17=$P$17,P36,IF($Q$17="USD $",P36*$D$15,P36*$E$15))*E36,2) -> 0 | R36: =IFERROR(ROUND(S36/E36,2),0) -> 1921.12 | S36: =ROUND(L36-Q36,2) -> 3842.24 | T36: =IFERROR(((K36-(Q36/J36))/(Q36/J36)),0) -> 0 | U36: =IFERROR(((K36-(Q36/J36))/K36),0) -> 1
B37: 428-0056 | C37: CARRIER ROLLER | E37: 4 | F37: 722.36 | G37: =ROUND(IF($F$17="USD $", F37*$E$15,F37*$D$15),2) -> 523.45 | H37: =ROUND(IF($H$17=$G$17,E37*G37,E37*F37),2) -> 2889.44 | J37: =E37 -> 4 | K37: =ROUND(IF($K$17=$F$17,F37*($L$14-M37),G37*($L$14-M37)),2) -> 361.18 | L37: =ROUND((J37*K37),2) -> 1444.72 | Q37: =ROUND(IF($Q$17=$P$17,P37,IF($Q$17="USD $",P37*$D$15,P37*$E$15))*E37,2) -> 0 | R37: =IFERROR(ROUND(S37/E37,2),0) -> 361.18 | S37: =ROUND(L37-Q37,2) -> 1444.72 | T37: =IFERROR(((K37-(Q37/J37))/(Q37/J37)),0) -> 0 | U37: =IFERROR(((K37-(Q37/J37))/K37),0) -> 1
B38: 114-6099 | C38: CARRIER BOLT | E38: 4 | F38: 31.9 | G38: =ROUND(IF($F$17="USD $", F38*$E$15,F38*$D$15),2) -> 23.12 | H38: =ROUND(IF($H$17=$G$17,E38*G38,E38*F38),2) -> 127.6 | J38: =E38 -> 4 | K38: =ROUND(IF($K$17=$F$17,F38*($L$14-M38),G38*($L$14-M38)),2) -> 15.95 | L38: =ROUND((J38*K38),2) -> 63.8 | Q38: =ROUND(IF($Q$17=$P$17,P38,IF($Q$17="USD $",P38*$D$15,P38*$E$15))*E38,2) -> 0 | R38: =IFERROR(ROUND(S38/E38,2),0) -> 15.95 | S38: =ROUND(L38-Q38,2) -> 63.8 | T38: =IFERROR(((K38-(Q38/J38))/(Q38/J38)),0) -> 0 | U38: =IFERROR(((K38-(Q38/J38))/K38),0) -> 1
B39: 422-1054 | C39: SINGLE FLANGE TRACK ROLLER | E39: 8 | F39: 860.3 | G39: =ROUND(IF($F$17="USD $", F39*$E$15,F39*$D$15),2) -> 623.41 | H39: =ROUND(IF($H$17=$G$17,E39*G39,E39*F39),2) -> 6882.4 | J39: =E39 -> 8 | K39: =ROUND(IF($K$17=$F$17,F39*($L$14-M39),G39*($L$14-M39)),2) -> 430.15 | L39: =ROUND((J39*K39),2) -> 3441.2 | Q39: =ROUND(IF($Q$17=$P$17,P39,IF($Q$17="USD $",P39*$D$15,P39*$E$15))*E39,2) -> 0 | R39: =IFERROR(ROUND(S39/E39,2),0) -> 430.15 | S39: =ROUND(L39-Q39,2) -> 3441.2 | T39: =IFERROR(((K39-(Q39/J39))/(Q39/J39)),0) -> 0 | U39: =IFERROR(((K39-(Q39/J39))/K39),0) -> 1
B40: 1D-4630 | C40: ROLLER BOLT | E40: 64 | F40: 24.13 | G40: =ROUND(IF($F$17="USD $", F40*$E$15,F40*$D$15),2) -> 17.49 | H40: =ROUND(IF($H$17=$G$17,E40*G40,E40*F40),2) -> 1544.32 | J40: =E40 -> 64 | K40: =ROUND(IF($K$17=$F$17,F40*($L$14-M40),G40*($L$14-M40)),2) -> 12.07 | L40: =ROUND((J40*K40),2) -> 772.48 | Q40: =ROUND(IF($Q$17=$P$17,P40,IF($Q$17="USD $",P40*$D$15,P40*$E$15))*E40,2) -> 0 | R40: =IFERROR(ROUND(S40/E40,2),0) -> 12.07 | S40: =ROUND(L40-Q40,2) -> 772.48 | T40: =IFERROR(((K40-(Q40/J40))/(Q40/J40)),0) -> 0 | U40: =IFERROR(((K40-(Q40/J40))/K40),0) -> 1
B41: 9H-1031 | C41: FLAT WASHER | E41: 64 | F41: 6.39 | G41: =ROUND(IF($F$17="USD $", F41*$E$15,F41*$D$15),2) -> 4.63 | H41: =ROUND(IF($H$17=$G$17,E41*G41,E41*F41),2) -> 408.96 | J41: =E41 -> 64 | K41: =ROUND(IF($K$17=$F$17,F41*($L$14-M41),G41*($L$14-M41)),2) -> 3.2 | L41: =ROUND((J41*K41),2) -> 204.8 | Q41: =ROUND(IF($Q$17=$P$17,P41,IF($Q$17="USD $",P41*$D$15,P41*$E$15))*E41,2) -> 0 | R41: =IFERROR(ROUND(S41/E41,2),0) -> 3.2 | S41: =ROUND(L41-Q41,2) -> 204.8 | T41: =IFERROR(((K41-(Q41/J41))/(Q41/J41)),0) -> 0 | U41: =IFERROR(((K41-(Q41/J41))/K41),0) -> 1
B42: 422-1051 | C42: DOUBLE FLANGE ROLLER | E42: 8 | F42: 911.71 | G42: =ROUND(IF($F$17="USD $", F42*$E$15,F42*$D$15),2) -> 660.66 | H42: =ROUND(IF($H$17=$G$17,E42*G42,E42*F42),2) -> 7293.68 | J42: =E42 -> 8 | K42: =ROUND(IF($K$17=$F$17,F42*($L$14-M42),G42*($L$14-M42)),2) -> 455.86 | L42: =ROUND((J42*K42),2) -> 3646.88 | Q42: =ROUND(IF($Q$17=$P$17,P42,IF($Q$17="USD $",P42*$D$15,P42*$E$15))*E42,2) -> 0 | R42: =IFERROR(ROUND(S42/E42,2),0) -> 455.86 | S42: =ROUND(L42-Q42,2) -> 3646.88 | T42: =IFERROR(((K42-(Q42/J42))/(Q42/J42)),0) -> 0 | U42: =IFERROR(((K42-(Q42/J42))/K42),0) -> 1
B43: 273-3996 | C43: ROLLER CAP | E43: 32 | F43: 90.66 | G43: =ROUND(IF($F$17="USD $", F43*$E$15,F43*$D$15),2) -> 65.7 | H43: =ROUND(IF($H$17=$G$17,E43*G43,E43*F43),2) -> 2901.12 | J43: =E43 -> 32 | K43: =ROUND(IF($K$17=$F$17,F43*($L$14-M43),G43*($L$14-M43)),2) -> 45.33 | L43: =ROUND((J43*K43),2) -> 1450.56 | Q43: =ROUND(IF($Q$17=$P$17,P43,IF($Q$17="USD $",P43*$D$15,P43*$E$15))*E43,2) -> 0 | R43: =IFERROR(ROUND(S43/E43,2),0) -> 45.33 | S43: =ROUND(L43-Q43,2) -> 1450.56 | T43: =IFERROR(((K43-(Q43/J43))/(Q43/J43)),0) -> 0 | U43: =IFERROR(((K43-(Q43/J43))/K43),0) -> 1
B44: 422-1130 | C44: 41 LINK 24" TRACK GROUP | E44: 2 | F44: 17017.28 | G44: =ROUND(IF($F$17="USD $", F44*$E$15,F44*$D$15),2) -> 12331.36 | H44: =ROUND(IF($H$17=$G$17,E44*G44,E44*F44),2) -> 34034.56 | J44: =E44 -> 2 | K44: =ROUND(IF($K$17=$F$17,F44*($L$14-M44),G44*($L$14-M44)),2) -> 8508.64 | L44: =ROUND((J44*K44),2) -> 17017.28 | Q44: =ROUND(IF($Q$17=$P$17,P44,IF($Q$17="USD $",P44*$D$15,P44*$E$15))*E44,2) -> 0 | R44: =IFERROR(ROUND(S44/E44,2),0) -> 8508.64 | S44: =ROUND(L44-Q44,2) -> 17017.28 | T44: =IFERROR(((K44-(Q44/J44))/(Q44/J44)),0) -> 0 | U44: =IFERROR(((K44-(Q44/J44))/K44),0) -> 1
G45: =ROUND(IF($F$17="USD $", F45*$E$15,F45*$D$15),2) -> 0 | H45: =ROUND(IF($H$17=$G$17,E45*G45,E45*F45),2) -> 0 | J45: =E45 -> 0 | K45: =ROUND(IF($K$17=$F$17,F45*($L$14-M45),G45*($L$14-M45)),2) -> 0 | L45: =ROUND((J45*K45),2) -> 0 | Q45: =ROUND(IF($Q$17=$P$17,P45,IF($Q$17="USD $",P45*$D$15,P45*$E$15))*E45,2) -> 0 | R45: =IFERROR(ROUND(S45/E45,2),0) -> 0 | S45: =ROUND(L45-Q45,2) -> 0 | T45: =IFERROR(((K45-(Q45/J45))/(Q45/J45)),0) -> 0 | U45: =IFERROR(((K45-(Q45/J45))/K45),0) -> 0
B46: 6I-8381 | C46: BLADE AS SEMI UNIVERSAL | E46: 1 | F46: 77155.73 | G46: =ROUND(IF($F$17="USD $", F46*$E$15,F46*$D$15),2) -> 55909.95 | H46: =ROUND(IF($H$17=$G$17,E46*G46,E46*F46),2) -> 77155.73 | J46: =E46 -> 1 | K46: =ROUND(IF($K$17=$F$17,F46*($L$14-M46),G46*($L$14-M46)),2) -> 38577.87 | L46: =ROUND((J46*K46),2) -> 38577.87 | Q46: =ROUND(IF($Q$17=$P$17,P46,IF($Q$17="USD $",P46*$D$15,P46*$E$15))*E46,2) -> 0 | R46: =IFERROR(ROUND(S46/E46,2),0) -> 38577.87 | S46: =ROUND(L46-Q46,2) -> 38577.87 | T46: =IFERROR(((K46-(Q46/J46))/(Q46/J46)),0) -> 0 | U46: =IFERROR(((K46-(Q46/J46))/K46),0) -> 1
B47: 7T-6936 | C47: DOZER CUTTING EDGE | E47: 2 | F47: 453.17 | G47: =ROUND(IF($F$17="USD $", F47*$E$15,F47*$D$15),2) -> 328.38 | H47: =ROUND(IF($H$17=$G$17,E47*G47,E47*F47),2) -> 906.34 | J47: =E47 -> 2 | K47: =ROUND(IF($K$17=$F$17,F47*($L$14-M47),G47*($L$14-M47)),2) -> 226.59 | L47: =ROUND((J47*K47),2) -> 453.18 | Q47: =ROUND(IF($Q$17=$P$17,P47,IF($Q$17="USD $",P47*$D$15,P47*$E$15))*E47,2) -> 0 | R47: =IFERROR(ROUND(S47/E47,2),0) -> 226.59 | S47: =ROUND(L47-Q47,2) -> 453.18 | T47: =IFERROR(((K47-(Q47/J47))/(Q47/J47)),0) -> 0 | U47: =IFERROR(((K47-(Q47/J47))/K47),0) -> 1
B48: 7T-6678 | C48: CUTTING EDGE | E48: 1 | F48: 446.82 | G48: =ROUND(IF($F$17="USD $", F48*$E$15,F48*$D$15),2) -> 323.78 | H48: =ROUND(IF($H$17=$G$17,E48*G48,E48*F48),2) -> 446.82 | J48: =E48 -> 1 | K48: =ROUND(IF($K$17=$F$17,F48*($L$14-M48),G48*($L$14-M48)),2) -> 223.41 | L48: =ROUND((J48*K48),2) -> 223.41 | Q48: =ROUND(IF($Q$17=$P$17,P48,IF($Q$17="USD $",P48*$D$15,P48*$E$15))*E48,2) -> 0 | R48: =IFERROR(ROUND(S48/E48,2),0) -> 223.41 | S48: =ROUND(L48-Q48,2) -> 223.41 | T48: =IFERROR(((K48-(Q48/J48))/(Q48/J48)),0) -> 0 | U48: =IFERROR(((K48-(Q48/J48))/K48),0) -> 1
B49: 9W-6198 | C49: LH END BIT | E49: 1 | F49: 556.86 | G49: =ROUND(IF($F$17="USD $", F49*$E$15,F49*$D$15),2) -> 403.52 | H49: =ROUND(IF($H$17=$G$17,E49*G49,E49*F49),2) -> 556.86 | J49: =E49 -> 1 | K49: =ROUND(IF($K$17=$F$17,F49*($L$14-M49),G49*($L$14-M49)),2) -> 278.43 | L49: =ROUND((J49*K49),2) -> 278.43 | Q49: =ROUND(IF($Q$17=$P$17,P49,IF($Q$17="USD $",P49*$D$15,P49*$E$15))*E49,2) -> 0 | R49: =IFERROR(ROUND(S49/E49,2),0) -> 278.43 | S49: =ROUND(L49-Q49,2) -> 278.43 | T49: =IFERROR(((K49-(Q49/J49))/(Q49/J49)),0) -> 0 | U49: =IFERROR(((K49-(Q49/J49))/K49),0) -> 1
B50: 9W-6199 | C50: RH END BIT | E50: 1 | F50: 556.86 | G50: =ROUND(IF($F$17="USD $", F50*$E$15,F50*$D$15),2) -> 403.52 | H50: =ROUND(IF($H$17=$G$17,E50*G50,E50*F50),2) -> 556.86 | J50: =E50 -> 1 | K50: =ROUND(IF($K$17=$F$17,F50*($L$14-M50),G50*($L$14-M50)),2) -> 278.43 | L50: =ROUND((J50*K50),2) -> 278.43 | Q50: =ROUND(IF($Q$17=$P$17,P50,IF($Q$17="USD $",P50*$D$15,P50*$E$15))*E50,2) -> 0 | R50: =IFERROR(ROUND(S50/E50,2),0) -> 278.43 | S50: =ROUND(L50-Q50,2) -> 278.43 | T50: =IFERROR(((K50-(Q50/J50))/(Q50/J50)),0) -> 0 | U50: =IFERROR(((K50-(Q50/J50))/K50),0) -> 1
B51: 6F-0196 | C51: Plow Bolt | E51: 32 | F51: 6.64 | G51: =ROUND(IF($F$17="USD $", F51*$E$15,F51*$D$15),2) -> 4.81 | H51: =ROUND(IF($H$17=$G$17,E51*G51,E51*F51),2) -> 212.48 | J51: =E51 -> 32 | K51: =ROUND(IF($K$17=$F$17,F51*($L$14-M51),G51*($L$14-M51)),2) -> 3.32 | L51: =ROUND((J51*K51),2) -> 106.24 | Q51: =ROUND(IF($Q$17=$P$17,P51,IF($Q$17="USD $",P51*$D$15,P51*$E$15))*E51,2) -> 0 | R51: =IFERROR(ROUND(S51/E51,2),0) -> 3.32 | S51: =ROUND(L51-Q51,2) -> 106.24 | T51: =IFERROR(((K51-(Q51/J51))/(Q51/J51)),0) -> 0 | U51: =IFERROR(((K51-(Q51/J51))/K51),0) -> 1
B52: 5P-8249 | C52: Washer | E52: 32 | F52: 4.77 | G52: =ROUND(IF($F$17="USD $", F52*$E$15,F52*$D$15),2) -> 3.46 | H52: =ROUND(IF($H$17=$G$17,E52*G52,E52*F52),2) -> 152.64 | J52: =E52 -> 32 | K52: =ROUND(IF($K$17=$F$17,F52*($L$14-M52),G52*($L$14-M52)),2) -> 2.39 | L52: =ROUND((J52*K52),2) -> 76.48 | Q52: =ROUND(IF($Q$17=$P$17,P52,IF($Q$17="USD $",P52*$D$15,P52*$E$15))*E52,2) -> 0 | R52: =IFERROR(ROUND(S52/E52,2),0) -> 2.39 | S52: =ROUND(L52-Q52,2) -> 76.48 | T52: =IFERROR(((K52-(Q52/J52))/(Q52/J52)),0) -> 0 | U52: =IFERROR(((K52-(Q52/J52))/K52),0) -> 1
B53: 2J-3505 | C53: Nut | E53: 32 | F53: 6.24 | G53: =ROUND(IF($F$17="USD $", F53*$E$15,F53*$D$15),2) -> 4.52 | H53: =ROUND(IF($H$17=$G$17,E53*G53,E53*F53),2) -> 199.68 | J53: =E53 -> 32 | K53: =ROUND(IF($K$17=$F$17,F53*($L$14-M53),G53*($L$14-M53)),2) -> 3.12 | L53: =ROUND((J53*K53),2) -> 99.84 | Q53: =ROUND(IF($Q$17=$P$17,P53,IF($Q$17="USD $",P53*$D$15,P53*$E$15))*E53,2) -> 0 | R53: =IFERROR(ROUND(S53/E53,2),0) -> 3.12 | S53: =ROUND(L53-Q53,2) -> 99.84 | T53: =IFERROR(((K53-(Q53/J53))/(Q53/J53)),0) -> 0 | U53: =IFERROR(((K53-(Q53/J53))/K53),0) -> 1
G54: =ROUND(IF($F$17="USD $", F54*$E$15,F54*$D$15),2) -> 0 | H54: =ROUND(IF($H$17=$G$17,E54*G54,E54*F54),2) -> 0 | J54: =E54 -> 0 | K54: =ROUND(IF($K$17=$F$17,F54*($L$14-M54),G54*($L$14-M54)),2) -> 0 | L54: =ROUND((J54*K54),2) -> 0 | Q54: =ROUND(IF($Q$17=$P$17,P54,IF($Q$17="USD $",P54*$D$15,P54*$E$15))*E54,2) -> 0 | R54: =IFERROR(ROUND(S54/E54,2),0) -> 0 | S54: =ROUND(L54-Q54,2) -> 0 | T54: =IFERROR(((K54-(Q54/J54))/(Q54/J54)),0) -> 0 | U54: =IFERROR(((K54-(Q54/J54))/K54),0) -> 0
B55: 614-7778 | C55: RIPPER SHANK | E55: 1 | F55: 6515.49 | G55: =ROUND(IF($F$17="USD $", F55*$E$15,F55*$D$15),2) -> 4721.37 | H55: =ROUND(IF($H$17=$G$17,E55*G55,E55*F55),2) -> 6515.49 | J55: =E55 -> 1 | K55: =ROUND(IF($K$17=$F$17,F55*($L$14-M55),G55*($L$14-M55)),2) -> 3257.75 | L55: =ROUND((J55*K55),2) -> 3257.75 | Q55: =ROUND(IF($Q$17=$P$17,P55,IF($Q$17="USD $",P55*$D$15,P55*$E$15))*E55,2) -> 0 | R55: =IFERROR(ROUND(S55/E55,2),0) -> 3257.75 | S55: =ROUND(L55-Q55,2) -> 3257.75 | T55: =IFERROR(((K55-(Q55/J55))/(Q55/J55)),0) -> 0 | U55: =IFERROR(((K55-(Q55/J55))/K55),0) -> 1
B56: 4T-4501 | C56: RIPPER TIP | E56: 1 | F56: 460.99 | G56: =ROUND(IF($F$17="USD $", F56*$E$15,F56*$D$15),2) -> 334.05 | H56: =ROUND(IF($H$17=$G$17,E56*G56,E56*F56),2) -> 460.99 | J56: =E56 -> 1 | K56: =ROUND(IF($K$17=$F$17,F56*($L$14-M56),G56*($L$14-M56)),2) -> 230.5 | L56: =ROUND((J56*K56),2) -> 230.5 | Q56: =ROUND(IF($Q$17=$P$17,P56,IF($Q$17="USD $",P56*$D$15,P56*$E$15))*E56,2) -> 0 | R56: =IFERROR(ROUND(S56/E56,2),0) -> 230.5 | S56: =ROUND(L56-Q56,2) -> 230.5 | T56: =IFERROR(((K56-(Q56/J56))/(Q56/J56)),0) -> 0 | U56: =IFERROR(((K56-(Q56/J56))/K56),0) -> 1
B57: 114-0358 | C57: PIN | E57: 2 | F57: 12.96 | G57: =ROUND(IF($F$17="USD $", F57*$E$15,F57*$D$15),2) -> 9.39 | H57: =ROUND(IF($H$17=$G$17,E57*G57,E57*F57),2) -> 25.92 | J57: =E57 -> 2 | K57: =ROUND(IF($K$17=$F$17,F57*($L$14-M57),G57*($L$14-M57)),2) -> 6.48 | L57: =ROUND((J57*K57),2) -> 12.96 | Q57: =ROUND(IF($Q$17=$P$17,P57,IF($Q$17="USD $",P57*$D$15,P57*$E$15))*E57,2) -> 0 | R57: =IFERROR(ROUND(S57/E57,2),0) -> 6.48 | S57: =ROUND(L57-Q57,2) -> 12.96 | T57: =IFERROR(((K57-(Q57/J57))/(Q57/J57)),0) -> 0 | U57: =IFERROR(((K57-(Q57/J57))/K57),0) -> 1
B58: 114-0359 | C58: RETAINER | E58: 2 | F58: 22.39 | G58: =ROUND(IF($F$17="USD $", F58*$E$15,F58*$D$15),2) -> 16.22 | H58: =ROUND(IF($H$17=$G$17,E58*G58,E58*F58),2) -> 44.78 | J58: =E58 -> 2 | K58: =ROUND(IF($K$17=$F$17,F58*($L$14-M58),G58*($L$14-M58)),2) -> 11.2 | L58: =ROUND((J58*K58),2) -> 22.4 | Q58: =ROUND(IF($Q$17=$P$17,P58,IF($Q$17="USD $",P58*$D$15,P58*$E$15))*E58,2) -> 0 | R58: =IFERROR(ROUND(S58/E58,2),0) -> 11.2 | S58: =ROUND(L58-Q58,2) -> 22.4 | T58: =IFERROR(((K58-(Q58/J58))/(Q58/J58)),0) -> 0 | U58: =IFERROR(((K58-(Q58/J58))/K58),0) -> 1
B59: 1J-2919 | C59: COTTER PIN | E59: 2 | F59: 11.83 | G59: =ROUND(IF($F$17="USD $", F59*$E$15,F59*$D$15),2) -> 8.57 | H59: =ROUND(IF($H$17=$G$17,E59*G59,E59*F59),2) -> 23.66 | J59: =E59 -> 2 | K59: =ROUND(IF($K$17=$F$17,F59*($L$14-M59),G59*($L$14-M59)),2) -> 5.92 | L59: =ROUND((J59*K59),2) -> 11.84 | Q59: =ROUND(IF($Q$17=$P$17,P59,IF($Q$17="USD $",P59*$D$15,P59*$E$15))*E59,2) -> 0 | R59: =IFERROR(ROUND(S59/E59,2),0) -> 5.92 | S59: =ROUND(L59-Q59,2) -> 11.84 | T59: =IFERROR(((K59-(Q59/J59))/(Q59/J59)),0) -> 0 | U59: =IFERROR(((K59-(Q59/J59))/K59),0) -> 1
B60: 4J-5240 | C60: RIPPER PIN | E60: 1 | F60: 188.46 | G60: =ROUND(IF($F$17="USD $", F60*$E$15,F60*$D$15),2) -> 136.57 | H60: =ROUND(IF($H$17=$G$17,E60*G60,E60*F60),2) -> 188.46 | J60: =E60 -> 1 | K60: =ROUND(IF($K$17=$F$17,F60*($L$14-M60),G60*($L$14-M60)),2) -> 94.23 | L60: =ROUND((J60*K60),2) -> 94.23 | Q60: =ROUND(IF($Q$17=$P$17,P60,IF($Q$17="USD $",P60*$D$15,P60*$E$15))*E60,2) -> 0 | R60: =IFERROR(ROUND(S60/E60,2),0) -> 94.23 | S60: =ROUND(L60-Q60,2) -> 94.23 | T60: =IFERROR(((K60-(Q60/J60))/(Q60/J60)),0) -> 0 | U60: =IFERROR(((K60-(Q60/J60))/K60),0) -> 1
B61: 579-9358 | C61: RIPPER CYLINDER TILT | E61: 2 | F61: 25270.36 | G61: =ROUND(IF($F$17="USD $", F61*$E$15,F61*$D$15),2) -> 18311.86 | H61: =ROUND(IF($H$17=$G$17,E61*G61,E61*F61),2) -> 50540.72 | J61: =E61 -> 2 | K61: =ROUND(IF($K$17=$F$17,F61*($L$14-M61),G61*($L$14-M61)),2) -> 12635.18 | L61: =ROUND((J61*K61),2) -> 25270.36 | Q61: =ROUND(IF($Q$17=$P$17,P61,IF($Q$17="USD $",P61*$D$15,P61*$E$15))*E61,2) -> 0 | R61: =IFERROR(ROUND(S61/E61,2),0) -> 12635.18 | S61: =ROUND(L61-Q61,2) -> 25270.36 | T61: =IFERROR(((K61-(Q61/J61))/(Q61/J61)),0) -> 0 | U61: =IFERROR(((K61-(Q61/J61))/K61),0) -> 1
B62: 164-7320 | C62: RIPPER CYLINDER TLIFT | E62: 2 | F62: 11979.51 | G62: =ROUND(IF($F$17="USD $", F62*$E$15,F62*$D$15),2) -> 8680.8 | H62: =ROUND(IF($H$17=$G$17,E62*G62,E62*F62),2) -> 23959.02 | J62: =E62 -> 2 | K62: =ROUND(IF($K$17=$F$17,F62*($L$14-M62),G62*($L$14-M62)),2) -> 5989.76 | L62: =ROUND((J62*K62),2) -> 11979.52 | Q62: =ROUND(IF($Q$17=$P$17,P62,IF($Q$17="USD $",P62*$D$15,P62*$E$15))*E62,2) -> 0 | R62: =IFERROR(ROUND(S62/E62,2),0) -> 5989.76 | S62: =ROUND(L62-Q62,2) -> 11979.52 | T62: =IFERROR(((K62-(Q62/J62))/(Q62/J62)),0) -> 0 | U62: =IFERROR(((K62-(Q62/J62))/K62),0) -> 1
G63: =ROUND(IF($F$17="USD $", F63*$E$15,F63*$D$15),2) -> 0 | H63: =ROUND(IF($H$17=$G$17,E63*G63,E63*F63),2) -> 0 | J63: =E63 -> 0 | K63: =ROUND(IF($K$17=$F$17,F63*($L$14-M63),G63*($L$14-M63)),2) -> 0 | L63: =ROUND((J63*K63),2) -> 0 | Q63: =ROUND(IF($Q$17=$P$17,P63,IF($Q$17="USD $",P63*$D$15,P63*$E$15))*E63,2) -> 0 | R63: =IFERROR(ROUND(S63/E63,2),0) -> 0 | S63: =ROUND(L63-Q63,2) -> 0 | T63: =IFERROR(((K63-(Q63/J63))/(Q63/J63)),0) -> 0 | U63: =IFERROR(((K63-(Q63/J63))/K63),0) -> 0
B64: CUSTOM | C64: GQP OVERHAUL SILVER KIT | E64: 1 | F64: 16189.54 | G64: =ROUND(IF($F$17="USD $", F64*$E$15,F64*$D$15),2) -> 11731.55 | H64: =ROUND(IF($H$17=$G$17,E64*G64,E64*F64),2) -> 16189.54 | J64: =E64 -> 1 | K64: =ROUND(IF($K$17=$F$17,F64*($L$14-M64),G64*($L$14-M64)),2) -> 8094.77 | L64: =ROUND((J64*K64),2) -> 8094.77 | Q64: =ROUND(IF($Q$17=$P$17,P64,IF($Q$17="USD $",P64*$D$15,P64*$E$15))*E64,2) -> 0 | R64: =IFERROR(ROUND(S64/E64,2),0) -> 8094.77 | S64: =ROUND(L64-Q64,2) -> 8094.77 | T64: =IFERROR(((K64-(Q64/J64))/(Q64/J64)),0) -> 0 | U64: =IFERROR(((K64-(Q64/J64))/K64),0) -> 1
B65: 171-3063 | C65: CAMSHAFT | E65: 1 | F65: 6963.59 | G65: =ROUND(IF($F$17="USD $", F65*$E$15,F65*$D$15),2) -> 5046.08 | H65: =ROUND(IF($H$17=$G$17,E65*G65,E65*F65),2) -> 6963.59 | J65: =E65 -> 1 | K65: =ROUND(IF($K$17=$F$17,F65*($L$14-M65),G65*($L$14-M65)),2) -> 3481.8 | L65: =ROUND((J65*K65),2) -> 3481.8 | Q65: =ROUND(IF($Q$17=$P$17,P65,IF($Q$17="USD $",P65*$D$15,P65*$E$15))*E65,2) -> 0 | R65: =IFERROR(ROUND(S65/E65,2),0) -> 3481.8 | S65: =ROUND(L65-Q65,2) -> 3481.8 | T65: =IFERROR(((K65-(Q65/J65))/(Q65/J65)),0) -> 0 | U65: =IFERROR(((K65-(Q65/J65))/K65),0) -> 1
B66: 326-278 | C66: CRANKSAHFT | E66: 1 | F66: 20827.76 | G66: =ROUND(IF($F$17="USD $", F66*$E$15,F66*$D$15),2) -> 15092.58 | H66: =ROUND(IF($H$17=$G$17,E66*G66,E66*F66),2) -> 20827.76 | J66: =E66 -> 1 | K66: =ROUND(IF($K$17=$F$17,F66*($L$14-M66),G66*($L$14-M66)),2) -> 10413.88 | L66: =ROUND((J66*K66),2) -> 10413.88 | Q66: =ROUND(IF($Q$17=$P$17,P66,IF($Q$17="USD $",P66*$D$15,P66*$E$15))*E66,2) -> 0 | R66: =IFERROR(ROUND(S66/E66,2),0) -> 10413.88 | S66: =ROUND(L66-Q66,2) -> 10413.88 | T66: =IFERROR(((K66-(Q66/J66))/(Q66/J66)),0) -> 0 | U66: =IFERROR(((K66-(Q66/J66))/K66),0) -> 1
B67: 148-2149 | C67: CYLINDER HEAD | E67: 1 | F67: 13749.8 | G67: =ROUND(IF($F$17="USD $", F67*$E$15,F67*$D$15),2) -> 9963.62 | H67: =ROUND(IF($H$17=$G$17,E67*G67,E67*F67),2) -> 13749.8 | J67: =E67 -> 1 | K67: =ROUND(IF($K$17=$F$17,F67*($L$14-M67),G67*($L$14-M67)),2) -> 6874.9 | L67: =ROUND((J67*K67),2) -> 6874.9 | Q67: =ROUND(IF($Q$17=$P$17,P67,IF($Q$17="USD $",P67*$D$15,P67*$E$15))*E67,2) -> 0 | R67: =IFERROR(ROUND(S67/E67,2),0) -> 6874.9 | S67: =ROUND(L67-Q67,2) -> 6874.9 | T67: =IFERROR(((K67-(Q67/J67))/(Q67/J67)),0) -> 0 | U67: =IFERROR(((K67-(Q67/J67))/K67),0) -> 1
G68: =ROUND(IF($F$17="USD $", F68*$E$15,F68*$D$15),2) -> 0 | H68: =ROUND(IF($H$17=$G$17,E68*G68,E68*F68),2) -> 0 | J68: =E68 -> 0 | K68: =ROUND(IF($K$17=$F$17,F68*($L$14-M68),G68*($L$14-M68)),2) -> 0 | L68: =ROUND((J68*K68),2) -> 0 | Q68: =ROUND(IF($Q$17=$P$17,P68,IF($Q$17="USD $",P68*$D$15,P68*$E$15))*E68,2) -> 0 | R68: =IFERROR(ROUND(S68/E68,2),0) -> 0 | S68: =ROUND(L68-Q68,2) -> 0 | T68: =IFERROR(((K68-(Q68/J68))/(Q68/J68)),0) -> 0 | U68: =IFERROR(((K68-(Q68/J68))/K68),0) -> 0
B69: 526-7416 | C69: SEAT ASSEMBLY | E69: 1 | F69: 2482.65 | G69: =ROUND(IF($F$17="USD $", F69*$E$15,F69*$D$15),2) -> 1799.02 | H69: =ROUND(IF($H$17=$G$17,E69*G69,E69*F69),2) -> 2482.65 | J69: =E69 -> 1 | K69: =ROUND(IF($K$17=$F$17,F69*($L$14-M69),G69*($L$14-M69)),2) -> 1241.33 | L69: =ROUND((J69*K69),2) -> 1241.33 | Q69: =ROUND(IF($Q$17=$P$17,P69,IF($Q$17="USD $",P69*$D$15,P69*$E$15))*E69,2) -> 0 | R69: =IFERROR(ROUND(S69/E69,2),0) -> 1241.33 | S69: =ROUND(L69-Q69,2) -> 1241.33 | T69: =IFERROR(((K69-(Q69/J69))/(Q69/J69)),0) -> 0 | U69: =IFERROR(((K69-(Q69/J69))/K69),0) -> 1
B70: 160-7165 | C70: SEAT SUSPENSION | E70: 1 | F70: 3364.13 | G70: =ROUND(IF($F$17="USD $", F70*$E$15,F70*$D$15),2) -> 2437.78 | H70: =ROUND(IF($H$17=$G$17,E70*G70,E70*F70),2) -> 3364.13 | J70: =E70 -> 1 | K70: =ROUND(IF($K$17=$F$17,F70*($L$14-M70),G70*($L$14-M70)),2) -> 1682.07 | L70: =ROUND((J70*K70),2) -> 1682.07 | Q70: =ROUND(IF($Q$17=$P$17,P70,IF($Q$17="USD $",P70*$D$15,P70*$E$15))*E70,2) -> 0 | R70: =IFERROR(ROUND(S70/E70,2),0) -> 1682.07 | S70: =ROUND(L70-Q70,2) -> 1682.07 | T70: =IFERROR(((K70-(Q70/J70))/(Q70/J70)),0) -> 0 | U70: =IFERROR(((K70-(Q70/J70))/K70),0) -> 1
G71: =ROUND(IF($F$17="USD $", F71*$E$15,F71*$D$15),2) -> 0 | H71: =ROUND(IF($H$17=$G$17,E71*G71,E71*F71),2) -> 0 | J71: =E71 -> 0 | K71: =ROUND(IF($K$17=$F$17,F71*($L$14-M71),G71*($L$14-M71)),2) -> 0 | L71: =ROUND((J71*K71),2) -> 0 | Q71: =ROUND(IF($Q$17=$P$17,P71,IF($Q$17="USD $",P71*$D$15,P71*$E$15))*E71,2) -> 0 | R71: =IFERROR(ROUND(S71/E71,2),0) -> 0 | S71: =ROUND(L71-Q71,2) -> 0 | T71: =IFERROR(((K71-(Q71/J71))/(Q71/J71)),0) -> 0 | U71: =IFERROR(((K71-(Q71/J71))/K71),0) -> 0
G72: =ROUND(IF($F$17="USD $", F72*$E$15,F72*$D$15),2) -> 0 | H72: =ROUND(IF($H$17=$G$17,E72*G72,E72*F72),2) -> 0 | J72: =E72 -> 0 | K72: =ROUND(IF($K$17=$F$17,F72*($L$14-M72),G72*($L$14-M72)),2) -> 0 | L72: =ROUND((J72*K72),2) -> 0 | Q72: =ROUND(IF($Q$17=$P$17,P72,IF($Q$17="USD $",P72*$D$15,P72*$E$15))*E72,2) -> 0 | R72: =IFERROR(ROUND(S72/E72,2),0) -> 0 | S72: =ROUND(L72-Q72,2) -> 0 | T72: =IFERROR(((K72-(Q72/J72))/(Q72/J72)),0) -> 0 | U72: =IFERROR(((K72-(Q72/J72))/K72),0) -> 0
G73: =ROUND(IF($F$17="USD $", F73*$E$15,F73*$D$15),2) -> 0 | H73: =ROUND(IF($H$17=$G$17,E73*G73,E73*F73),2) -> 0 | J73: =E73 -> 0 | K73: =ROUND(IF($K$17=$F$17,F73*($L$14-M73),G73*($L$14-M73)),2) -> 0 | L73: =ROUND((J73*K73),2) -> 0 | Q73: =ROUND(IF($Q$17=$P$17,P73,IF($Q$17="USD $",P73*$D$15,P73*$E$15))*E73,2) -> 0 | R73: =IFERROR(ROUND(S73/E73,2),0) -> 0 | S73: =ROUND(L73-Q73,2) -> 0 | T73: =IFERROR(((K73-(Q73/J73))/(Q73/J73)),0) -> 0 | U73: =IFERROR(((K73-(Q73/J73))/K73),0) -> 0
G74: =ROUND(IF($F$17="USD $", F74*$E$15,F74*$D$15),2) -> 0 | H74: =ROUND(IF($H$17=$G$17,E74*G74,E74*F74),2) -> 0 | J74: =E74 -> 0 | K74: =ROUND(IF($K$17=$F$17,F74*($L$14-M74),G74*($L$14-M74)),2) -> 0 | L74: =ROUND((J74*K74),2) -> 0 | Q74: =ROUND(IF($Q$17=$P$17,P74,IF($Q$17="USD $",P74*$D$15,P74*$E$15))*E74,2) -> 0 | R74: =IFERROR(ROUND(S74/E74,2),0) -> 0 | S74: =ROUND(L74-Q74,2) -> 0 | T74: =IFERROR(((K74-(Q74/J74))/(Q74/J74)),0) -> 0 | U74: =IFERROR(((K74-(Q74/J74))/K74),0) -> 0
G75: =ROUND(IF($F$17="USD $", F75*$E$15,F75*$D$15),2) -> 0 | H75: =ROUND(IF($H$17=$G$17,E75*G75,E75*F75),2) -> 0 | J75: =E75 -> 0 | K75: =ROUND(IF($K$17=$F$17,F75*($L$14-M75),G75*($L$14-M75)),2) -> 0 | L75: =ROUND((J75*K75),2) -> 0 | Q75: =ROUND(IF($Q$17=$P$17,P75,IF($Q$17="USD $",P75*$D$15,P75*$E$15))*E75,2) -> 0 | R75: =IFERROR(ROUND(S75/E75,2),0) -> 0 | S75: =ROUND(L75-Q75,2) -> 0 | T75: =IFERROR(((K75-(Q75/J75))/(Q75/J75)),0) -> 0 | U75: =IFERROR(((K75-(Q75/J75))/K75),0) -> 0
G76: =ROUND(IF($F$17="USD $", F76*$E$15,F76*$D$15),2) -> 0 | H76: =ROUND(IF($H$17=$G$17,E76*G76,E76*F76),2) -> 0 | J76: =E76 -> 0 | K76: =ROUND(IF($K$17=$F$17,F76*($L$14-M76),G76*($L$14-M76)),2) -> 0 | L76: =ROUND((J76*K76),2) -> 0 | Q76: =ROUND(IF($Q$17=$P$17,P76,IF($Q$17="USD $",P76*$D$15,P76*$E$15))*E76,2) -> 0 | R76: =IFERROR(ROUND(S76/E76,2),0) -> 0 | S76: =ROUND(L76-Q76,2) -> 0 | T76: =IFERROR(((K76-(Q76/J76))/(Q76/J76)),0) -> 0 | U76: =IFERROR(((K76-(Q76/J76))/K76),0) -> 0
G77: =ROUND(IF($F$17="USD $", F77*$E$15,F77*$D$15),2) -> 0 | H77: =ROUND(IF($H$17=$G$17,E77*G77,E77*F77),2) -> 0 | J77: =E77 -> 0 | K77: =ROUND(IF($K$17=$F$17,F77*($L$14-M77),G77*($L$14-M77)),2) -> 0 | L77: =ROUND((J77*K77),2) -> 0 | Q77: =ROUND(IF($Q$17=$P$17,P77,IF($Q$17="USD $",P77*$D$15,P77*$E$15))*E77,2) -> 0 | R77: =IFERROR(ROUND(S77/E77,2),0) -> 0 | S77: =ROUND(L77-Q77,2) -> 0 | T77: =IFERROR(((K77-(Q77/J77))/(Q77/J77)),0) -> 0 | U77: =IFERROR(((K77-(Q77/J77))/K77),0) -> 0
G78: =ROUND(IF($F$17="USD $", F78*$E$15,F78*$D$15),2) -> 0 | H78: =ROUND(IF($H$17=$G$17,E78*G78,E78*F78),2) -> 0 | J78: =E78 -> 0 | K78: =ROUND(IF($K$17=$F$17,F78*($L$14-M78),G78*($L$14-M78)),2) -> 0 | L78: =ROUND((J78*K78),2) -> 0 | Q78: =ROUND(IF($Q$17=$P$17,P78,IF($Q$17="USD $",P78*$D$15,P78*$E$15))*E78,2) -> 0 | R78: =IFERROR(ROUND(S78/E78,2),0) -> 0 | S78: =ROUND(L78-Q78,2) -> 0 | T78: =IFERROR(((K78-(Q78/J78))/(Q78/J78)),0) -> 0 | U78: =IFERROR(((K78-(Q78/J78))/K78),0) -> 0
G79: =ROUND(IF($F$17="USD $", F79*$E$15,F79*$D$15),2) -> 0 | H79: =ROUND(IF($H$17=$G$17,E79*G79,E79*F79),2) -> 0 | J79: =E79 -> 0 | K79: =ROUND(IF($K$17=$F$17,F79*($L$14-M79),G79*($L$14-M79)),2) -> 0 | L79: =ROUND((J79*K79),2) -> 0 | Q79: =ROUND(IF($Q$17=$P$17,P79,IF($Q$17="USD $",P79*$D$15,P79*$E$15))*E79,2) -> 0 | R79: =IFERROR(ROUND(S79/E79,2),0) -> 0 | S79: =ROUND(L79-Q79,2) -> 0 | T79: =IFERROR(((K79-(Q79/J79))/(Q79/J79)),0) -> 0 | U79: =IFERROR(((K79-(Q79/J79))/K79),0) -> 0
G80: =ROUND(IF($F$17="USD $", F80*$E$15,F80*$D$15),2) -> 0 | H80: =ROUND(IF($H$17=$G$17,E80*G80,E80*F80),2) -> 0 | J80: =E80 -> 0 | K80: =ROUND(IF($K$17=$F$17,F80*($L$14-M80),G80*($L$14-M80)),2) -> 0 | L80: =ROUND((J80*K80),2) -> 0 | Q80: =ROUND(IF($Q$17=$P$17,P80,IF($Q$17="USD $",P80*$D$15,P80*$E$15))*E80,2) -> 0 | R80: =IFERROR(ROUND(S80/E80,2),0) -> 0 | S80: =ROUND(L80-Q80,2) -> 0 | T80: =IFERROR(((K80-(Q80/J80))/(Q80/J80)),0) -> 0 | U80: =IFERROR(((K80-(Q80/J80))/K80),0) -> 0
G81: =ROUND(IF($F$17="USD $", F81*$E$15,F81*$D$15),2) -> 0 | H81: =ROUND(IF($H$17=$G$17,E81*G81,E81*F81),2) -> 0 | J81: =E81 -> 0 | K81: =ROUND(IF($K$17=$F$17,F81*($L$14-M81),G81*($L$14-M81)),2) -> 0 | L81: =ROUND((J81*K81),2) -> 0 | Q81: =ROUND(IF($Q$17=$P$17,P81,IF($Q$17="USD $",P81*$D$15,P81*$E$15))*E81,2) -> 0 | R81: =IFERROR(ROUND(S81/E81,2),0) -> 0 | S81: =ROUND(L81-Q81,2) -> 0 | T81: =IFERROR(((K81-(Q81/J81))/(Q81/J81)),0) -> 0 | U81: =IFERROR(((K81-(Q81/J81))/K81),0) -> 0
G82: =ROUND(IF($F$17="USD $", F82*$E$15,F82*$D$15),2) -> 0 | H82: =ROUND(IF($H$17=$G$17,E82*G82,E82*F82),2) -> 0 | J82: =E82 -> 0 | K82: =ROUND(IF($K$17=$F$17,F82*($L$14-M82),G82*($L$14-M82)),2) -> 0 | L82: =ROUND((J82*K82),2) -> 0 | Q82: =ROUND(IF($Q$17=$P$17,P82,IF($Q$17="USD $",P82*$D$15,P82*$E$15))*E82,2) -> 0 | R82: =IFERROR(ROUND(S82/E82,2),0) -> 0 | S82: =ROUND(L82-Q82,2) -> 0 | T82: =IFERROR(((K82-(Q82/J82))/(Q82/J82)),0) -> 0 | U82: =IFERROR(((K82-(Q82/J82))/K82),0) -> 0
... G128: =ROUND(IF($F$17="USD $", F128*$E$15,F128*$D$15),2) -> 0 | H128: =ROUND(IF($H$17=$G$17,E128*G128,E128*F128),2) -> 0 | J128: =E128 -> 0 | K128: =ROUND(IF($K$17=$F$17,F128*($L$14-M128),G128*($L$14-M128)),2) -> 0 | L128: =ROUND((J128*K128),2) -> 0 | Q128: =ROUND(IF($Q$17=$P$17,P128,IF($Q$17="USD $",P128*$D$15,P128*$E$15))*E128,2) -> 0 | R128: =IFERROR(ROUND(S128/E128,2),0) -> 0 | S128: =ROUND(L128-Q128,2) -> 0 | T128: =IFERROR(((K128-(Q128/J128))/(Q128/J128)),0) -> 0 | U128: =IFERROR(((K128-(Q128/J128))/K128),0) -> 0
D129: TOTALS | E129: =SUM(E18:E128) -> 487 | F129: =SUM(F18:F128) -> 221719.84 | G129: =SUM(G18:G128) -> 160666.55 | H129: =SUM(H18:H128) -> 315127.21 | J129: =SUM(J18:J128) -> 487 | K129: =SUM(K18:K128) -> 110860.02 | L129: =SUM(L18:L128) -> 157565.35 | P129: =SUM(P18:P128) -> 0 | Q129: =SUM(Q18:Q128) -> 0 | R129: =SUM(R18:R128) -> 110860.02 | S129: =SUM(S18:S128) -> 157565.35

Sheet CAT 160M GRADER
B1: CUSTOMER INFORMATION | D1: MACHINE INFORMATION | H1: MACHINE SERVICE HR INTERVALS | L1: SUMMARY | O1: =K17 -> CAD $ | R1: COMPLETED DEAL INFORMATION
B2: DATE: | D2: UNIT # | H2: ENGINE AIR | L2: OEM MSRP | O2: =H129 -> 127177.97 | R2: SALES REP
B3: COMPANY: | D3: YEAR | H3: ENGINE OIL | L3: GQP LIST | O3: =L129 -> 63589.41 | R3: ORDER PO #
B4: CUSTOMER: | D4: MAKE | H4: FUEL FILTERS | L4: $ SAVINGS | O4: =O2-O3 -> 63588.56 | R4: PROJECT #
B5: PHONE: | D5: MODEL | H5: HYDRAULIC FILTERS | L5: % SAVINGS | O5: =IFERROR((O2-O3)/O2,"") -> 0.49999666 | R5: CUST INVOICE #
B6: EMAIL: | D6: SERIAL NUMBER | H6: TRANSMISSION FILTERS | L6: TOTAL ORDER MARGIN | O6: =S129 -> 63589.41 | R6: PAYMENT TYPE
B7: SALES REP: | D7: ENGINE SER NUMBER | H7: CAB FILTERS | L7: TOTAL ITEM COST | O7: =Q129 -> 0 | R7: DATE DELIVERED
D8: CURRENT HOURS | H8: UNDERCARRIAGE / TIRES | L8: TOTAL ORDER FREIGHT | O8: =IF(O1=P14,Q14,IF(P14="CAD $",Q14*D15,IF(P14="USD $",Q14*E15,0))) -> 0 | R8: TOTAL COST | S8: NET MARGIN | T8: NET MARKUP % | U8: NET MARGIN %
D9: USAGE/MONTH | L9: TOTAL CUSTOMS/BROKERAGE | O9: =U14 -> 0 | R9: =O7+O8+O9 -> 0 | S9: =O3-R9 -> 63589.41 | T9: =IFERROR(((O3-R9)/R9),0) -> 0 | U9: =IFERROR(((O3-R9)/O3),0) -> 1
L10: TOTAL NUMBER PIECES | O10: =E129 -> 132
D11: ENTER EXCHANGE RATES $ | F11: OEM MSRP | J11: CUSTOMER SELL PRICE | O11: COST ANALYSIS | X11: CAD $
X12: USD $
F13: SHOW OEM MSRP ON QUOTE: | H13: YES | X13: YES
D14: CAD-USD | E14: USD-CAD | F14: OEM NAME | J14: CUSTOMER PRICE % OF OEM LIST | L14: 0.5 | O14: FREIGHT TOTAL ORDER | P14: USD $ | R14: CUSTOMS AND BROKERAGE % | S14: 0.025 | T14: BROKERAGE FEES | U14: =ROUND(Q129*S14,2) -> 0 | X14: NO
D15: =1/E15 -> 0.72463768 | E15: 1.38 | M15: ADDITIONAL +/- DISC % PER ITEM | O15: MARKUP LESS THAN 100% REQUIRES MANAGER APPROVAL
B16: PART NUMBER | C16: DESCRIPTION | D16: SERVICE INTERVAL | E16: QTY | F16: UNIT PRICE | H16: EXT AMOUNT | J16: QTY | K16: UNIT PRICE | L16: EXTENDED AMOUNT | O16: VENDOR | P16: COST EACH | Q16: EXTENDED COST | R16: MARGIN EACH | S16: EXTENDED MARGIN | T16: MARKUP % | U16: MARGIN %
F17: CAD $ | G17: =IF(F17="USD $", "CAD $", "USD $") -> USD $ | H17: =K17 -> CAD $ | K17: CAD $ | P17: USD $ | Q17: =K17 -> CAD $
B18: 1R-1809 | C18: ENGINE OIL FILTER | E18: 1 | F18: 95.68 | G18: =ROUND(IF($F$17="USD $", F18*$E$15,F18*$D$15),2) -> 69.33 | H18: =ROUND(IF($H$17=$G$17,E18*G18,E18*F18),2) -> 95.68 | J18: =E18 -> 1 | K18: =ROUND(IF($K$17=$F$17,F18*($L$14-M18),G18*($L$14-M18)),2) -> 47.84 | L18: =ROUND((J18*K18),2) -> 47.84 | Q18: =ROUND(IF($Q$17=$P$17,P18,IF($Q$17="USD $",P18*$D$15,P18*$E$15))*E18,2) -> 0 | R18: =IFERROR(ROUND(S18/E18,2),0) -> 47.84 | S18: =ROUND(L18-Q18,2) -> 47.84 | T18: =IFERROR(((K18-(Q18/J18))/(Q18/J18)),0) -> 0 | U18: =IFERROR(((K18-(Q18/J18))/K18),0) -> 1 | Y18: 250
B19: 1R-0749 | C19: FUEL FILTER | E19: 1 | F19: 51.52 | G19: =ROUND(IF($F$17="USD $", F19*$E$15,F19*$D$15),2) -> 37.33 | H19: =ROUND(IF($H$17=$G$17,E19*G19,E19*F19),2) -> 51.52 | J19: =E19 -> 1 | K19: =ROUND(IF($K$17=$F$17,F19*($L$14-M19),G19*($L$14-M19)),2) -> 25.76 | L19: =ROUND((J19*K19),2) -> 25.76 | Q19: =ROUND(IF($Q$17=$P$17,P19,IF($Q$17="USD $",P19*$D$15,P19*$E$15))*E19,2) -> 0 | R19: =IFERROR(ROUND(S19/E19,2),0) -> 25.76 | S19: =ROUND(L19-Q19,2) -> 25.76 | T19: =IFERROR(((K19-(Q19/J19))/(Q19/J19)),0) -> 0 | U19: =IFERROR(((K19-(Q19/J19))/K19),0) -> 1 | X19: GQP | Y19: 500
B20: 326-1644 | C20: FUEL WATER SEPARATOR FILTER | E20: 1 | F20: 85.6 | G20: =ROUND(IF($F$17="USD $", F20*$E$15,F20*$D$15),2) -> 62.03 | H20: =ROUND(IF($H$17=$G$17,E20*G20,E20*F20),2) -> 85.6 | J20: =E20 -> 1 | K20: =ROUND(IF($K$17=$F$17,F20*($L$14-M20),G20*($L$14-M20)),2) -> 42.8 | L20: =ROUND((J20*K20),2) -> 42.8 | Q20: =ROUND(IF($Q$17=$P$17,P20,IF($Q$17="USD $",P20*$D$15,P20*$E$15))*E20,2) -> 0 | R20: =IFERROR(ROUND(S20/E20,2),0) -> 42.8 | S20: =ROUND(L20-Q20,2) -> 42.8 | T20: =IFERROR(((K20-(Q20/J20))/(Q20/J20)),0) -> 0 | U20: =IFERROR(((K20-(Q20/J20))/K20),0) -> 1 | X20: CTP | Y20: 750
B21: 338-3540 | C21: HYDRAULIC FILTER | E21: 1 | F21: 255.48 | G21: =ROUND(IF($F$17="USD $", F21*$E$15,F21*$D$15),2) -> 185.13 | H21: =ROUND(IF($H$17=$G$17,E21*G21,E21*F21),2) -> 255.48 | J21: =E21 -> 1 | K21: =ROUND(IF($K$17=$F$17,F21*($L$14-M21),G21*($L$14-M21)),2) -> 127.74 | L21: =ROUND((J21*K21),2) -> 127.74 | Q21: =ROUND(IF($Q$17=$P$17,P21,IF($Q$17="USD $",P21*$D$15,P21*$E$15))*E21,2) -> 0 | R21: =IFERROR(ROUND(S21/E21,2),0) -> 127.74 | S21: =ROUND(L21-Q21,2) -> 127.74 | T21: =IFERROR(((K21-(Q21/J21))/(Q21/J21)),0) -> 0 | U21: =IFERROR(((K21-(Q21/J21))/K21),0) -> 1 | X21: BLMQ | Y21: 1000
B22: 571-5253 | C22: HYDRAULIC TRANSMISSION OIL FILTER | E22: 1 | F22: 171.55 | G22: =ROUND(IF($F$17="USD $", F22*$E$15,F22*$D$15),2) -> 124.31 | H22: =ROUND(IF($H$17=$G$17,E22*G22,E22*F22),2) -> 171.55 | J22: =E22 -> 1 | K22: =ROUND(IF($K$17=$F$17,F22*($L$14-M22),G22*($L$14-M22)),2) -> 85.78 | L22: =ROUND((J22*K22),2) -> 85.78 | Q22: =ROUND(IF($Q$17=$P$17,P22,IF($Q$17="USD $",P22*$D$15,P22*$E$15))*E22,2) -> 0 | R22: =IFERROR(ROUND(S22/E22,2),0) -> 85.78 | S22: =ROUND(L22-Q22,2) -> 85.78 | T22: =IFERROR(((K22-(Q22/J22))/(Q22/J22)),0) -> 0 | U22: =IFERROR(((K22-(Q22/J22))/K22),0) -> 1 | X22: CAT | Y22: 1200
B23: 245-6375 | C23: PRIMARY AIR FILTER | E23: 1 | F23: 167.02 | G23: =ROUND(IF($F$17="USD $", F23*$E$15,F23*$D$15),2) -> 121.03 | H23: =ROUND(IF($H$17=$G$17,E23*G23,E23*F23),2) -> 167.02 | J23: =E23 -> 1 | K23: =ROUND(IF($K$17=$F$17,F23*($L$14-M23),G23*($L$14-M23)),2) -> 83.51 | L23: =ROUND((J23*K23),2) -> 83.51 | Q23: =ROUND(IF($Q$17=$P$17,P23,IF($Q$17="USD $",P23*$D$15,P23*$E$15))*E23,2) -> 0 | R23: =IFERROR(ROUND(S23/E23,2),0) -> 83.51 | S23: =ROUND(L23-Q23,2) -> 83.51 | T23: =IFERROR(((K23-(Q23/J23))/(Q23/J23)),0) -> 0 | U23: =IFERROR(((K23-(Q23/J23))/K23),0) -> 1 | X23: FINNING | Y23: 2000
B24: 245-6376 | C24: SECONDARY AIR FILTER ELEMENT | E24: 1 | F24: 109.74 | G24: =ROUND(IF($F$17="USD $", F24*$E$15,F24*$D$15),2) -> 79.52 | H24: =ROUND(IF($H$17=$G$17,E24*G24,E24*F24),2) -> 109.74 | J24: =E24 -> 1 | K24: =ROUND(IF($K$17=$F$17,F24*($L$14-M24),G24*($L$14-M24)),2) -> 54.87 | L24: =ROUND((J24*K24),2) -> 54.87 | Q24: =ROUND(IF($Q$17=$P$17,P24,IF($Q$17="USD $",P24*$D$15,P24*$E$15))*E24,2) -> 0 | R24: =IFERROR(ROUND(S24/E24,2),0) -> 54.87 | S24: =ROUND(L24-Q24,2) -> 54.87 | T24: =IFERROR(((K24-(Q24/J24))/(Q24/J24)),0) -> 0 | U24: =IFERROR(((K24-(Q24/J24))/K24),0) -> 1 | X24: JD | Y24: 4000
B25: 211-2660 | C25: CABIN AIR FILTER ELEMENT | E25: 1 | F25: 77.4 | G25: =ROUND(IF($F$17="USD $", F25*$E$15,F25*$D$15),2) -> 56.09 | H25: =ROUND(IF($H$17=$G$17,E25*G25,E25*F25),2) -> 77.4 | J25: =E25 -> 1 | K25: =ROUND(IF($K$17=$F$17,F25*($L$14-M25),G25*($L$14-M25)),2) -> 38.7 | L25: =ROUND((J25*K25),2) -> 38.7 | Q25: =ROUND(IF($Q$17=$P$17,P25,IF($Q$17="USD $",P25*$D$15,P25*$E$15))*E25,2) -> 0 | R25: =IFERROR(ROUND(S25/E25,2),0) -> 38.7 | S25: =ROUND(L25-Q25,2) -> 38.7 | T25: =IFERROR(((K25-(Q25/J25))/(Q25/J25)),0) -> 0 | U25: =IFERROR(((K25-(Q25/J25))/K25),0) -> 1 | X25: BRANDT | Y25: 6000
B26: 153-5700 | C26: 12V 4D BCI BATTERY (20" X 8.6" X 8.7") | E26: 2 | F26: 726.37 | G26: =ROUND(IF($F$17="USD $", F26*$E$15,F26*$D$15),2) -> 526.36 | H26: =ROUND(IF($H$17=$G$17,E26*G26,E26*F26),2) -> 1452.74 | J26: =E26 -> 2 | K26: =ROUND(IF($K$17=$F$17,F26*($L$14-M26),G26*($L$14-M26)),2) -> 363.19 | L26: =ROUND((J26*K26),2) -> 726.38 | Q26: =ROUND(IF($Q$17=$P$17,P26,IF($Q$17="USD $",P26*$D$15,P26*$E$15))*E26,2) -> 0 | R26: =IFERROR(ROUND(S26/E26,2),0) -> 363.19 | S26: =ROUND(L26-Q26,2) -> 726.38 | T26: =IFERROR(((K26-(Q26/J26))/(Q26/J26)),0) -> 0 | U26: =IFERROR(((K26-(Q26/J26))/K26),0) -> 1 | X26: PTI | Y26: 8000
G27: =ROUND(IF($F$17="USD $", F27*$E$15,F27*$D$15),2) -> 0 | H27: =ROUND(IF($H$17=$G$17,E27*G27,E27*F27),2) -> 0 | J27: =E27 -> 0 | K27: =ROUND(IF($K$17=$F$17,F27*($L$14-M27),G27*($L$14-M27)),2) -> 0 | L27: =ROUND((J27*K27),2) -> 0 | Q27: =ROUND(IF($Q$17=$P$17,P27,IF($Q$17="USD $",P27*$D$15,P27*$E$15))*E27,2) -> 0 | R27: =IFERROR(ROUND(S27/E27,2),0) -> 0 | S27: =ROUND(L27-Q27,2) -> 0 | T27: =IFERROR(((K27-(Q27/J27))/(Q27/J27)),0) -> 0 | U27: =IFERROR(((K27-(Q27/J27))/K27),0) -> 0 | X27: CONEQUIP | Y27: 10000
B28: 658-0254 | C28: ENGINE OVERHAUL KIT | E28: 1 | F28: 10386.33 | G28: =ROUND(IF($F$17="USD $", F28*$E$15,F28*$D$15),2) -> 7526.33 | H28: =ROUND(IF($H$17=$G$17,E28*G28,E28*F28),2) -> 10386.33 | J28: =E28 -> 1 | K28: =ROUND(IF($K$17=$F$17,F28*($L$14-M28),G28*($L$14-M28)),2) -> 5193.17 | L28: =ROUND((J28*K28),2) -> 5193.17 | Q28: =ROUND(IF($Q$17=$P$17,P28,IF($Q$17="USD $",P28*$D$15,P28*$E$15))*E28,2) -> 0 | R28: =IFERROR(ROUND(S28/E28,2),0) -> 5193.17 | S28: =ROUND(L28-Q28,2) -> 5193.17 | T28: =IFERROR(((K28-(Q28/J28))/(Q28/J28)),0) -> 0 | U28: =IFERROR(((K28-(Q28/J28))/K28),0) -> 1 | X28: CANDY | Y28: AS REQ'D
B29: 242-0673 | C29: CAMSHAFT | E29: 1 | F29: 4483.87 | G29: =ROUND(IF($F$17="USD $", F29*$E$15,F29*$D$15),2) -> 3249.18 | H29: =ROUND(IF($H$17=$G$17,E29*G29,E29*F29),2) -> 4483.87 | J29: =E29 -> 1 | K29: =ROUND(IF($K$17=$F$17,F29*($L$14-M29),G29*($L$14-M29)),2) -> 2241.94 | L29: =ROUND((J29*K29),2) -> 2241.94 | Q29: =ROUND(IF($Q$17=$P$17,P29,IF($Q$17="USD $",P29*$D$15,P29*$E$15))*E29,2) -> 0 | R29: =IFERROR(ROUND(S29/E29,2),0) -> 2241.94 | S29: =ROUND(L29-Q29,2) -> 2241.94 | T29: =IFERROR(((K29-(Q29/J29))/(Q29/J29)),0) -> 0 | U29: =IFERROR(((K29-(Q29/J29))/K29),0) -> 1 | X29: U/C
B30: 261-1544 | C30: CRANKSHAFT | E30: 1 | F30: 16109.08 | G30: =ROUND(IF($F$17="USD $", F30*$E$15,F30*$D$15),2) -> 11673.25 | H30: =ROUND(IF($H$17=$G$17,E30*G30,E30*F30),2) -> 16109.08 | J30: =E30 -> 1 | K30: =ROUND(IF($K$17=$F$17,F30*($L$14-M30),G30*($L$14-M30)),2) -> 8054.54 | L30: =ROUND((J30*K30),2) -> 8054.54 | Q30: =ROUND(IF($Q$17=$P$17,P30,IF($Q$17="USD $",P30*$D$15,P30*$E$15))*E30,2) -> 0 | R30: =IFERROR(ROUND(S30/E30,2),0) -> 8054.54 | S30: =ROUND(L30-Q30,2) -> 8054.54 | T30: =IFERROR(((K30-(Q30/J30))/(Q30/J30)),0) -> 0 | U30: =IFERROR(((K30-(Q30/J30))/K30),0) -> 1
B31: 344-2149 | C31: CYLINDER HEAD | E31: 1 | F31: 13237.86 | G31: =ROUND(IF($F$17="USD $", F31*$E$15,F31*$D$15),2) -> 9592.65 | H31: =ROUND(IF($H$17=$G$17,E31*G31,E31*F31),2) -> 13237.86 | J31: =E31 -> 1 | K31: =ROUND(IF($K$17=$F$17,F31*($L$14-M31),G31*($L$14-M31)),2) -> 6618.93 | L31: =ROUND((J31*K31),2) -> 6618.93 | Q31: =ROUND(IF($Q$17=$P$17,P31,IF($Q$17="USD $",P31*$D$15,P31*$E$15))*E31,2) -> 0 | R31: =IFERROR(ROUND(S31/E31,2),0) -> 6618.93 | S31: =ROUND(L31-Q31,2) -> 6618.93 | T31: =IFERROR(((K31-(Q31/J31))/(Q31/J31)),0) -> 0 | U31: =IFERROR(((K31-(Q31/J31))/K31),0) -> 1
B32: 352-2395 | C32: TURBOCHARGER | E32: 1 | F32: 6920.52 | G32: =ROUND(IF($F$17="USD $", F32*$E$15,F32*$D$15),2) -> 5014.87 | H32: =ROUND(IF($H$17=$G$17,E32*G32,E32*F32),2) -> 6920.52 | J32: =E32 -> 1 | K32: =ROUND(IF($K$17=$F$17,F32*($L$14-M32),G32*($L$14-M32)),2) -> 3460.26 | L32: =ROUND((J32*K32),2) -> 3460.26 | Q32: =ROUND(IF($Q$17=$P$17,P32,IF($Q$17="USD $",P32*$D$15,P32*$E$15))*E32,2) -> 0 | R32: =IFERROR(ROUND(S32/E32,2),0) -> 3460.26 | S32: =ROUND(L32-Q32,2) -> 3460.26 | T32: =IFERROR(((K32-(Q32/J32))/(Q32/J32)),0) -> 0 | U32: =IFERROR(((K32-(Q32/J32))/K32),0) -> 1
C33: INJECTOR | G33: =ROUND(IF($F$17="USD $", F33*$E$15,F33*$D$15),2) -> 0 | H33: =ROUND(IF($H$17=$G$17,E33*G33,E33*F33),2) -> 0 | J33: =E33 -> 0 | K33: =ROUND(IF($K$17=$F$17,F33*($L$14-M33),G33*($L$14-M33)),2) -> 0 | L33: =ROUND((J33*K33),2) -> 0 | Q33: =ROUND(IF($Q$17=$P$17,P33,IF($Q$17="USD $",P33*$D$15,P33*$E$15))*E33,2) -> 0 | R33: =IFERROR(ROUND(S33/E33,2),0) -> 0 | S33: =ROUND(L33-Q33,2) -> 0 | T33: =IFERROR(((K33-(Q33/J33))/(Q33/J33)),0) -> 0 | U33: =IFERROR(((K33-(Q33/J33))/K33),0) -> 0
B34: 282-4577 | C34: STRAIGHT BLADE AS | E34: 1 | F34: 19075.97 | G34: =ROUND(IF($F$17="USD $", F34*$E$15,F34*$D$15),2) -> 13823.17 | H34: =ROUND(IF($H$17=$G$17,E34*G34,E34*F34),2) -> 19075.97 | J34: =E34 -> 1 | K34: =ROUND(IF($K$17=$F$17,F34*($L$14-M34),G34*($L$14-M34)),2) -> 9537.99 | L34: =ROUND((J34*K34),2) -> 9537.99 | Q34: =ROUND(IF($Q$17=$P$17,P34,IF($Q$17="USD $",P34*$D$15,P34*$E$15))*E34,2) -> 0 | R34: =IFERROR(ROUND(S34/E34,2),0) -> 9537.99 | S34: =ROUND(L34-Q34,2) -> 9537.99 | T34: =IFERROR(((K34-(Q34/J34))/(Q34/J34)),0) -> 0 | U34: =IFERROR(((K34-(Q34/J34))/K34),0) -> 1
B35: 519-2885 | C35: CYLINDER | E35: 2 | F35: 15107.68 | G35: =ROUND(IF($F$17="USD $", F35*$E$15,F35*$D$15),2) -> 10947.59 | H35: =ROUND(IF($H$17=$G$17,E35*G35,E35*F35),2) -> 30215.36 | J35: =E35 -> 2 | K35: =ROUND(IF($K$17=$F$17,F35*($L$14-M35),G35*($L$14-M35)),2) -> 7553.84 | L35: =ROUND((J35*K35),2) -> 15107.68 | Q35: =ROUND(IF($Q$17=$P$17,P35,IF($Q$17="USD $",P35*$D$15,P35*$E$15))*E35,2) -> 0 | R35: =IFERROR(ROUND(S35/E35,2),0) -> 7553.84 | S35: =ROUND(L35-Q35,2) -> 15107.68 | T35: =IFERROR(((K35-(Q35/J35))/(Q35/J35)),0) -> 0 | U35: =IFERROR(((K35-(Q35/J35))/K35),0) -> 1
B36: 1J-6762 | C36: PLOW BOLT | E36: 34 | F36: 5.66 | G36: =ROUND(IF($F$17="USD $", F36*$E$15,F36*$D$15),2) -> 4.1 | H36: =ROUND(IF($H$17=$G$17,E36*G36,E36*F36),2) -> 192.44 | J36: =E36 -> 34 | K36: =ROUND(IF($K$17=$F$17,F36*($L$14-M36),G36*($L$14-M36)),2) -> 2.83 | L36: =ROUND((J36*K36),2) -> 96.22 | Q36: =ROUND(IF($Q$17=$P$17,P36,IF($Q$17="USD $",P36*$D$15,P36*$E$15))*E36,2) -> 0 | R36: =IFERROR(ROUND(S36/E36,2),0) -> 2.83 | S36: =ROUND(L36-Q36,2) -> 96.22 | T36: =IFERROR(((K36-(Q36/J36))/(Q36/J36)),0) -> 0 | U36: =IFERROR(((K36-(Q36/J36))/K36),0) -> 1
B37: 2J-3506 | C37: NUT | E37: 34 | F37: 3.65 | G37: =ROUND(IF($F$17="USD $", F37*$E$15,F37*$D$15),2) -> 2.64 | H37: =ROUND(IF($H$17=$G$17,E37*G37,E37*F37),2) -> 124.1 | J37: =E37 -> 34 | K37: =ROUND(IF($K$17=$F$17,F37*($L$14-M37),G37*($L$14-M37)),2) -> 1.83 | L37: =ROUND((J37*K37),2) -> 62.22 | Q37: =ROUND(IF($Q$17=$P$17,P37,IF($Q$17="USD $",P37*$D$15,P37*$E$15))*E37,2) -> 0 | R37: =IFERROR(ROUND(S37/E37,2),0) -> 1.83 | S37: =ROUND(L37-Q37,2) -> 62.22 | T37: =IFERROR(((K37-(Q37/J37))/(Q37/J37)),0) -> 0 | U37: =IFERROR(((K37-(Q37/J37))/K37),0) -> 1
B38: 8E-5529 | C38: END BIT | E38: 2 | F38: 220.93 | G38: =ROUND(IF($F$17="USD $", F38*$E$15,F38*$D$15),2) -> 160.09 | H38: =ROUND(IF($H$17=$G$17,E38*G38,E38*F38),2) -> 441.86 | J38: =E38 -> 2 | K38: =ROUND(IF($K$17=$F$17,F38*($L$14-M38),G38*($L$14-M38)),2) -> 110.47 | L38: =ROUND((J38*K38),2) -> 220.94 | Q38: =ROUND(IF($Q$17=$P$17,P38,IF($Q$17="USD $",P38*$D$15,P38*$E$15))*E38,2) -> 0 | R38: =IFERROR(ROUND(S38/E38,2),0) -> 110.47 | S38: =ROUND(L38-Q38,2) -> 220.94 | T38: =IFERROR(((K38-(Q38/J38))/(Q38/J38)),0) -> 0 | U38: =IFERROR(((K38-(Q38/J38))/K38),0) -> 1
B39: 5J-4773 | C39: END BIT BOLT | E39: 10 | F39: 4.51 | G39: =ROUND(IF($F$17="USD $", F39*$E$15,F39*$D$15),2) -> 3.27 | H39: =ROUND(IF($H$17=$G$17,E39*G39,E39*F39),2) -> 45.1 | J39: =E39 -> 10 | K39: =ROUND(IF($K$17=$F$17,F39*($L$14-M39),G39*($L$14-M39)),2) -> 2.26 | L39: =ROUND((J39*K39),2) -> 22.6 | Q39: =ROUND(IF($Q$17=$P$17,P39,IF($Q$17="USD $",P39*$D$15,P39*$E$15))*E39,2) -> 0 | R39: =IFERROR(ROUND(S39/E39,2),0) -> 2.26 | S39: =ROUND(L39-Q39,2) -> 22.6 | T39: =IFERROR(((K39-(Q39/J39))/(Q39/J39)),0) -> 0 | U39: =IFERROR(((K39-(Q39/J39))/K39),0) -> 1
B40: 2J-3506 | C40: END BIT NUT | E40: 10 | F40: 3.65 | G40: =ROUND(IF($F$17="USD $", F40*$E$15,F40*$D$15),2) -> 2.64 | H40: =ROUND(IF($H$17=$G$17,E40*G40,E40*F40),2) -> 36.5 | J40: =E40 -> 10 | K40: =ROUND(IF($K$17=$F$17,F40*($L$14-M40),G40*($L$14-M40)),2) -> 1.83 | L40: =ROUND((J40*K40),2) -> 18.3 | Q40: =ROUND(IF($Q$17=$P$17,P40,IF($Q$17="USD $",P40*$D$15,P40*$E$15))*E40,2) -> 0 | R40: =IFERROR(ROUND(S40/E40,2),0) -> 1.83 | S40: =ROUND(L40-Q40,2) -> 18.3 | T40: =IFERROR(((K40-(Q40/J40))/(Q40/J40)),0) -> 0 | U40: =IFERROR(((K40-(Q40/J40))/K40),0) -> 1
B41: 4T-3028 | C41: CUTTING EDGE | E41: 3 | F41: 209.93 | G41: =ROUND(IF($F$17="USD $", F41*$E$15,F41*$D$15),2) -> 152.12 | H41: =ROUND(IF($H$17=$G$17,E41*G41,E41*F41),2) -> 629.79 | J41: =E41 -> 3 | K41: =ROUND(IF($K$17=$F$17,F41*($L$14-M41),G41*($L$14-M41)),2) -> 104.97 | L41: =ROUND((J41*K41),2) -> 314.91 | Q41: =ROUND(IF($Q$17=$P$17,P41,IF($Q$17="USD $",P41*$D$15,P41*$E$15))*E41,2) -> 0 | R41: =IFERROR(ROUND(S41/E41,2),0) -> 104.97 | S41: =ROUND(L41-Q41,2) -> 314.91 | T41: =IFERROR(((K41-(Q41/J41))/(Q41/J41)),0) -> 0 | U41: =IFERROR(((K41-(Q41/J41))/K41),0) -> 1
G42: =ROUND(IF($F$17="USD $", F42*$E$15,F42*$D$15),2) -> 0 | H42: =ROUND(IF($H$17=$G$17,E42*G42,E42*F42),2) -> 0 | J42: =E42 -> 0 | K42: =ROUND(IF($K$17=$F$17,F42*($L$14-M42),G42*($L$14-M42)),2) -> 0 | L42: =ROUND((J42*K42),2) -> 0 | Q42: =ROUND(IF($Q$17=$P$17,P42,IF($Q$17="USD $",P42*$D$15,P42*$E$15))*E42,2) -> 0 | R42: =IFERROR(ROUND(S42/E42,2),0) -> 0 | S42: =ROUND(L42-Q42,2) -> 0 | T42: =IFERROR(((K42-(Q42/J42))/(Q42/J42)),0) -> 0 | U42: =IFERROR(((K42-(Q42/J42))/K42),0) -> 0
B43: 605-8830 | C43: RIPPER CYLINDER | E43: 1 | F43: 9436.24 | G43: =ROUND(IF($F$17="USD $", F43*$E$15,F43*$D$15),2) -> 6837.86 | H43: =ROUND(IF($H$17=$G$17,E43*G43,E43*F43),2) -> 9436.24 | J43: =E43 -> 1 | K43: =ROUND(IF($K$17=$F$17,F43*($L$14-M43),G43*($L$14-M43)),2) -> 4718.12 | L43: =ROUND((J43*K43),2) -> 4718.12 | Q43: =ROUND(IF($Q$17=$P$17,P43,IF($Q$17="USD $",P43*$D$15,P43*$E$15))*E43,2) -> 0 | R43: =IFERROR(ROUND(S43/E43,2),0) -> 4718.12 | S43: =ROUND(L43-Q43,2) -> 4718.12 | T43: =IFERROR(((K43-(Q43/J43))/(Q43/J43)),0) -> 0 | U43: =IFERROR(((K43-(Q43/J43))/K43),0) -> 1
B44: 9J-6586 | C44: RIPPER SHANK | E44: 3 | F44: 1135.71 | G44: =ROUND(IF($F$17="USD $", F44*$E$15,F44*$D$15),2) -> 822.98 | H44: =ROUND(IF($H$17=$G$17,E44*G44,E44*F44),2) -> 3407.13 | J44: =E44 -> 3 | K44: =ROUND(IF($K$17=$F$17,F44*($L$14-M44),G44*($L$14-M44)),2) -> 567.86 | L44: =ROUND((J44*K44),2) -> 1703.58 | Q44: =ROUND(IF($Q$17=$P$17,P44,IF($Q$17="USD $",P44*$D$15,P44*$E$15))*E44,2) -> 0 | R44: =IFERROR(ROUND(S44/E44,2),0) -> 567.86 | S44: =ROUND(L44-Q44,2) -> 1703.58 | T44: =IFERROR(((K44-(Q44/J44))/(Q44/J44)),0) -> 0 | U44: =IFERROR(((K44-(Q44/J44))/K44),0) -> 1
B45: 6Y-0309 | C45: RIPPER TIP | E45: 3 | F45: 144.57 | G45: =ROUND(IF($F$17="USD $", F45*$E$15,F45*$D$15),2) -> 104.76 | H45: =ROUND(IF($H$17=$G$17,E45*G45,E45*F45),2) -> 433.71 | J45: =E45 -> 3 | K45: =ROUND(IF($K$17=$F$17,F45*($L$14-M45),G45*($L$14-M45)),2) -> 72.29 | L45: =ROUND((J45*K45),2) -> 216.87 | Q45: =ROUND(IF($Q$17=$P$17,P45,IF($Q$17="USD $",P45*$D$15,P45*$E$15))*E45,2) -> 0 | R45: =IFERROR(ROUND(S45/E45,2),0) -> 72.29 | S45: =ROUND(L45-Q45,2) -> 216.87 | T45: =IFERROR(((K45-(Q45/J45))/(Q45/J45)),0) -> 0 | U45: =IFERROR(((K45-(Q45/J45))/K45),0) -> 1
B46: 3B-5325 | C46: COTTER | E46: 3 | F46: 7.67 | G46: =ROUND(IF($F$17="USD $", F46*$E$15,F46*$D$15),2) -> 5.56 | H46: =ROUND(IF($H$17=$G$17,E46*G46,E46*F46),2) -> 23.01 | J46: =E46 -> 3 | K46: =ROUND(IF($K$17=$F$17,F46*($L$14-M46),G46*($L$14-M46)),2) -> 3.84 | L46: =ROUND((J46*K46),2) -> 11.52 | Q46: =ROUND(IF($Q$17=$P$17,P46,IF($Q$17="USD $",P46*$D$15,P46*$E$15))*E46,2) -> 0 | R46: =IFERROR(ROUND(S46/E46,2),0) -> 3.84 | S46: =ROUND(L46-Q46,2) -> 11.52 | T46: =IFERROR(((K46-(Q46/J46))/(Q46/J46)),0) -> 0 | U46: =IFERROR(((K46-(Q46/J46))/K46),0) -> 1
B47: 2K-6413 | C47: PIN | E47: 3 | F47: 127.19 | G47: =ROUND(IF($F$17="USD $", F47*$E$15,F47*$D$15),2) -> 92.17 | H47: =ROUND(IF($H$17=$G$17,E47*G47,E47*F47),2) -> 381.57 | J47: =E47 -> 3 | K47: =ROUND(IF($K$17=$F$17,F47*($L$14-M47),G47*($L$14-M47)),2) -> 63.6 | L47: =ROUND((J47*K47),2) -> 190.8 | Q47: =ROUND(IF($Q$17=$P$17,P47,IF($Q$17="USD $",P47*$D$15,P47*$E$15))*E47,2) -> 0 | R47: =IFERROR(ROUND(S47/E47,2),0) -> 63.6 | S47: =ROUND(L47-Q47,2) -> 190.8 | T47: =IFERROR(((K47-(Q47/J47))/(Q47/J47)),0) -> 0 | U47: =IFERROR(((K47-(Q47/J47))/K47),0) -> 1
B48: 114-0359 | C48: RETAINER AS | E48: 3 | F48: 22.39 | G48: =ROUND(IF($F$17="USD $", F48*$E$15,F48*$D$15),2) -> 16.22 | H48: =ROUND(IF($H$17=$G$17,E48*G48,E48*F48),2) -> 67.17 | J48: =E48 -> 3 | K48: =ROUND(IF($K$17=$F$17,F48*($L$14-M48),G48*($L$14-M48)),2) -> 11.2 | L48: =ROUND((J48*K48),2) -> 33.6 | Q48: =ROUND(IF($Q$17=$P$17,P48,IF($Q$17="USD $",P48*$D$15,P48*$E$15))*E48,2) -> 0 | R48: =IFERROR(ROUND(S48/E48,2),0) -> 11.2 | S48: =ROUND(L48-Q48,2) -> 33.6 | T48: =IFERROR(((K48-(Q48/J48))/(Q48/J48)),0) -> 0 | U48: =IFERROR(((K48-(Q48/J48))/K48),0) -> 1
B49: 136-8308 | C49: PIN | E49: 3 | F49: 10.35 | G49: =ROUND(IF($F$17="USD $", F49*$E$15,F49*$D$15),2) -> 7.5 | H49: =ROUND(IF($H$17=$G$17,E49*G49,E49*F49),2) -> 31.05 | J49: =E49 -> 3 | K49: =ROUND(IF($K$17=$F$17,F49*($L$14-M49),G49*($L$14-M49)),2) -> 5.18 | L49: =ROUND((J49*K49),2) -> 15.54 | Q49: =ROUND(IF($Q$17=$P$17,P49,IF($Q$17="USD $",P49*$D$15,P49*$E$15))*E49,2) -> 0 | R49: =IFERROR(ROUND(S49/E49,2),0) -> 5.18 | S49: =ROUND(L49-Q49,2) -> 15.54 | T49: =IFERROR(((K49-(Q49/J49))/(Q49/J49)),0) -> 0 | U49: =IFERROR(((K49-(Q49/J49))/K49),0) -> 1
G50: =ROUND(IF($F$17="USD $", F50*$E$15,F50*$D$15),2) -> 0 | H50: =ROUND(IF($H$17=$G$17,E50*G50,E50*F50),2) -> 0 | J50: =E50 -> 0 | K50: =ROUND(IF($K$17=$F$17,F50*($L$14-M50),G50*($L$14-M50)),2) -> 0 | L50: =ROUND((J50*K50),2) -> 0 | Q50: =ROUND(IF($Q$17=$P$17,P50,IF($Q$17="USD $",P50*$D$15,P50*$E$15))*E50,2) -> 0 | R50: =IFERROR(ROUND(S50/E50,2),0) -> 0 | S50: =ROUND(L50-Q50,2) -> 0 | T50: =IFERROR(((K50-(Q50/J50))/(Q50/J50)),0) -> 0 | U50: =IFERROR(((K50-(Q50/J50))/K50),0) -> 0
B51: 489-6480 | C51: SEAT AS | E51: 1 | F51: 5668.45 | G51: =ROUND(IF($F$17="USD $", F51*$E$15,F51*$D$15),2) -> 4107.57 | H51: =ROUND(IF($H$17=$G$17,E51*G51,E51*F51),2) -> 5668.45 | J51: =E51 -> 1 | K51: =ROUND(IF($K$17=$F$17,F51*($L$14-M51),G51*($L$14-M51)),2) -> 2834.23 | L51: =ROUND((J51*K51),2) -> 2834.23 | Q51: =ROUND(IF($Q$17=$P$17,P51,IF($Q$17="USD $",P51*$D$15,P51*$E$15))*E51,2) -> 0 | R51: =IFERROR(ROUND(S51/E51,2),0) -> 2834.23 | S51: =ROUND(L51-Q51,2) -> 2834.23 | T51: =IFERROR(((K51-(Q51/J51))/(Q51/J51)),0) -> 0 | U51: =IFERROR(((K51-(Q51/J51))/K51),0) -> 1
B52: 160-7165 | C52: SEAT SUSPENSION | E52: 1 | F52: 3364.13 | G52: =ROUND(IF($F$17="USD $", F52*$E$15,F52*$D$15),2) -> 2437.78 | H52: =ROUND(IF($H$17=$G$17,E52*G52,E52*F52),2) -> 3364.13 | J52: =E52 -> 1 | K52: =ROUND(IF($K$17=$F$17,F52*($L$14-M52),G52*($L$14-M52)),2) -> 1682.07 | L52: =ROUND((J52*K52),2) -> 1682.07 | Q52: =ROUND(IF($Q$17=$P$17,P52,IF($Q$17="USD $",P52*$D$15,P52*$E$15))*E52,2) -> 0 | R52: =IFERROR(ROUND(S52/E52,2),0) -> 1682.07 | S52: =ROUND(L52-Q52,2) -> 1682.07 | T52: =IFERROR(((K52-(Q52/J52))/(Q52/J52)),0) -> 0 | U52: =IFERROR(((K52-(Q52/J52))/K52),0) -> 1
G53: =ROUND(IF($F$17="USD $", F53*$E$15,F53*$D$15),2) -> 0 | H53: =ROUND(IF($H$17=$G$17,E53*G53,E53*F53),2) -> 0 | J53: =E53 -> 0 | K53: =ROUND(IF($K$17=$F$17,F53*($L$14-M53),G53*($L$14-M53)),2) -> 0 | L53: =ROUND((J53*K53),2) -> 0 | Q53: =ROUND(IF($Q$17=$P$17,P53,IF($Q$17="USD $",P53*$D$15,P53*$E$15))*E53,2) -> 0 | R53: =IFERROR(ROUND(S53/E53,2),0) -> 0 | S53: =ROUND(L53-Q53,2) -> 0 | T53: =IFERROR(((K53-(Q53/J53))/(Q53/J53)),0) -> 0 | U53: =IFERROR(((K53-(Q53/J53))/K53),0) -> 0
G54: =ROUND(IF($F$17="USD $", F54*$E$15,F54*$D$15),2) -> 0 | H54: =ROUND(IF($H$17=$G$17,E54*G54,E54*F54),2) -> 0 | J54: =E54 -> 0 | K54: =ROUND(IF($K$17=$F$17,F54*($L$14-M54),G54*($L$14-M54)),2) -> 0 | L54: =ROUND((J54*K54),2) -> 0 | Q54: =ROUND(IF($Q$17=$P$17,P54,IF($Q$17="USD $",P54*$D$15,P54*$E$15))*E54,2) -> 0 | R54: =IFERROR(ROUND(S54/E54,2),0) -> 0 | S54: =ROUND(L54-Q54,2) -> 0 | T54: =IFERROR(((K54-(Q54/J54))/(Q54/J54)),0) -> 0 | U54: =IFERROR(((K54-(Q54/J54))/K54),0) -> 0
G55: =ROUND(IF($F$17="USD $", F55*$E$15,F55*$D$15),2) -> 0 | H55: =ROUND(IF($H$17=$G$17,E55*G55,E55*F55),2) -> 0 | J55: =E55 -> 0 | K55: =ROUND(IF($K$17=$F$17,F55*($L$14-M55),G55*($L$14-M55)),2) -> 0 | L55: =ROUND((J55*K55),2) -> 0 | Q55: =ROUND(IF($Q$17=$P$17,P55,IF($Q$17="USD $",P55*$D$15,P55*$E$15))*E55,2) -> 0 | R55: =IFERROR(ROUND(S55/E55,2),0) -> 0 | S55: =ROUND(L55-Q55,2) -> 0 | T55: =IFERROR(((K55-(Q55/J55))/(Q55/J55)),0) -> 0 | U55: =IFERROR(((K55-(Q55/J55))/K55),0) -> 0
G56: =ROUND(IF($F$17="USD $", F56*$E$15,F56*$D$15),2) -> 0 | H56: =ROUND(IF($H$17=$G$17,E56*G56,E56*F56),2) -> 0 | J56: =E56 -> 0 | K56: =ROUND(IF($K$17=$F$17,F56*($L$14-M56),G56*($L$14-M56)),2) -> 0 | L56: =ROUND((J56*K56),2) -> 0 | Q56: =ROUND(IF($Q$17=$P$17,P56,IF($Q$17="USD $",P56*$D$15,P56*$E$15))*E56,2) -> 0 | R56: =IFERROR(ROUND(S56/E56,2),0) -> 0 | S56: =ROUND(L56-Q56,2) -> 0 | T56: =IFERROR(((K56-(Q56/J56))/(Q56/J56)),0) -> 0 | U56: =IFERROR(((K56-(Q56/J56))/K56),0) -> 0
G57: =ROUND(IF($F$17="USD $", F57*$E$15,F57*$D$15),2) -> 0 | H57: =ROUND(IF($H$17=$G$17,E57*G57,E57*F57),2) -> 0 | J57: =E57 -> 0 | K57: =ROUND(IF($K$17=$F$17,F57*($L$14-M57),G57*($L$14-M57)),2) -> 0 | L57: =ROUND((J57*K57),2) -> 0 | Q57: =ROUND(IF($Q$17=$P$17,P57,IF($Q$17="USD $",P57*$D$15,P57*$E$15))*E57,2) -> 0 | R57: =IFERROR(ROUND(S57/E57,2),0) -> 0 | S57: =ROUND(L57-Q57,2) -> 0 | T57: =IFERROR(((K57-(Q57/J57))/(Q57/J57)),0) -> 0 | U57: =IFERROR(((K57-(Q57/J57))/K57),0) -> 0
G58: =ROUND(IF($F$17="USD $", F58*$E$15,F58*$D$15),2) -> 0 | H58: =ROUND(IF($H$17=$G$17,E58*G58,E58*F58),2) -> 0 | J58: =E58 -> 0 | K58: =ROUND(IF($K$17=$F$17,F58*($L$14-M58),G58*($L$14-M58)),2) -> 0 | L58: =ROUND((J58*K58),2) -> 0 | Q58: =ROUND(IF($Q$17=$P$17,P58,IF($Q$17="USD $",P58*$D$15,P58*$E$15))*E58,2) -> 0 | R58: =IFERROR(ROUND(S58/E58,2),0) -> 0 | S58: =ROUND(L58-Q58,2) -> 0 | T58: =IFERROR(((K58-(Q58/J58))/(Q58/J58)),0) -> 0 | U58: =IFERROR(((K58-(Q58/J58))/K58),0) -> 0
G59: =ROUND(IF($F$17="USD $", F59*$E$15,F59*$D$15),2) -> 0 | H59: =ROUND(IF($H$17=$G$17,E59*G59,E59*F59),2) -> 0 | J59: =E59 -> 0 | K59: =ROUND(IF($K$17=$F$17,F59*($L$14-M59),G59*($L$14-M59)),2) -> 0 | L59: =ROUND((J59*K59),2) -> 0 | Q59: =ROUND(IF($Q$17=$P$17,P59,IF($Q$17="USD $",P59*$D$15,P59*$E$15))*E59,2) -> 0 | R59: =IFERROR(ROUND(S59/E59,2),0) -> 0 | S59: =ROUND(L59-Q59,2) -> 0 | T59: =IFERROR(((K59-(Q59/J59))/(Q59/J59)),0) -> 0 | U59: =IFERROR(((K59-(Q59/J59))/K59),0) -> 0
G60: =ROUND(IF($F$17="USD $", F60*$E$15,F60*$D$15),2) -> 0 | H60: =ROUND(IF($H$17=$G$17,E60*G60,E60*F60),2) -> 0 | J60: =E60 -> 0 | K60: =ROUND(IF($K$17=$F$17,F60*($L$14-M60),G60*($L$14-M60)),2) -> 0 | L60: =ROUND((J60*K60),2) -> 0 | Q60: =ROUND(IF($Q$17=$P$17,P60,IF($Q$17="USD $",P60*$D$15,P60*$E$15))*E60,2) -> 0 | R60: =IFERROR(ROUND(S60/E60,2),0) -> 0 | S60: =ROUND(L60-Q60,2) -> 0 | T60: =IFERROR(((K60-(Q60/J60))/(Q60/J60)),0) -> 0 | U60: =IFERROR(((K60-(Q60/J60))/K60),0) -> 0
G61: =ROUND(IF($F$17="USD $", F61*$E$15,F61*$D$15),2) -> 0 | H61: =ROUND(IF($H$17=$G$17,E61*G61,E61*F61),2) -> 0 | J61: =E61 -> 0 | K61: =ROUND(IF($K$17=$F$17,F61*($L$14-M61),G61*($L$14-M61)),2) -> 0 | L61: =ROUND((J61*K61),2) -> 0 | Q61: =ROUND(IF($Q$17=$P$17,P61,IF($Q$17="USD $",P61*$D$15,P61*$E$15))*E61,2) -> 0 | R61: =IFERROR(ROUND(S61/E61,2),0) -> 0 | S61: =ROUND(L61-Q61,2) -> 0 | T61: =IFERROR(((K61-(Q61/J61))/(Q61/J61)),0) -> 0 | U61: =IFERROR(((K61-(Q61/J61))/K61),0) -> 0
G62: =ROUND(IF($F$17="USD $", F62*$E$15,F62*$D$15),2) -> 0 | H62: =ROUND(IF($H$17=$G$17,E62*G62,E62*F62),2) -> 0 | J62: =E62 -> 0 | K62: =ROUND(IF($K$17=$F$17,F62*($L$14-M62),G62*($L$14-M62)),2) -> 0 | L62: =ROUND((J62*K62),2) -> 0 | Q62: =ROUND(IF($Q$17=$P$17,P62,IF($Q$17="USD $",P62*$D$15,P62*$E$15))*E62,2) -> 0 | R62: =IFERROR(ROUND(S62/E62,2),0) -> 0 | S62: =ROUND(L62-Q62,2) -> 0 | T62: =IFERROR(((K62-(Q62/J62))/(Q62/J62)),0) -> 0 | U62: =IFERROR(((K62-(Q62/J62))/K62),0) -> 0
G63: =ROUND(IF($F$17="USD $", F63*$E$15,F63*$D$15),2) -> 0 | H63: =ROUND(IF($H$17=$G$17,E63*G63,E63*F63),2) -> 0 | J63: =E63 -> 0 | K63: =ROUND(IF($K$17=$F$17,F63*($L$14-M63),G63*($L$14-M63)),2) -> 0 | L63: =ROUND((J63*K63),2) -> 0 | Q63: =ROUND(IF($Q$17=$P$17,P63,IF($Q$17="USD $",P63*$D$15,P63*$E$15))*E63,2) -> 0 | R63: =IFERROR(ROUND(S63/E63,2),0) -> 0 | S63: =ROUND(L63-Q63,2) -> 0 | T63: =IFERROR(((K63-(Q63/J63))/(Q63/J63)),0) -> 0 | U63: =IFERROR(((K63-(Q63/J63))/K63),0) -> 0
G64: =ROUND(IF($F$17="USD $", F64*$E$15,F64*$D$15),2) -> 0 | H64: =ROUND(IF($H$17=$G$17,E64*G64,E64*F64),2) -> 0 | J64: =E64 -> 0 | K64: =ROUND(IF($K$17=$F$17,F64*($L$14-M64),G64*($L$14-M64)),2) -> 0 | L64: =ROUND((J64*K64),2) -> 0 | Q64: =ROUND(IF($Q$17=$P$17,P64,IF($Q$17="USD $",P64*$D$15,P64*$E$15))*E64,2) -> 0 | R64: =IFERROR(ROUND(S64/E64,2),0) -> 0 | S64: =ROUND(L64-Q64,2) -> 0 | T64: =IFERROR(((K64-(Q64/J64))/(Q64/J64)),0) -> 0 | U64: =IFERROR(((K64-(Q64/J64))/K64),0) -> 0
... G128: =ROUND(IF($F$17="USD $", F128*$E$15,F128*$D$15),2) -> 0 | H128: =ROUND(IF($H$17=$G$17,E128*G128,E128*F128),2) -> 0 | J128: =E128 -> 0 | K128: =ROUND(IF($K$17=$F$17,F128*($L$14-M128),G128*($L$14-M128)),2) -> 0 | L128: =ROUND((J128*K128),2) -> 0 | Q128: =ROUND(IF($Q$17=$P$17,P128,IF($Q$17="USD $",P128*$D$15,P128*$E$15))*E128,2) -> 0 | R128: =IFERROR(ROUND(S128/E128,2),0) -> 0 | S128: =ROUND(L128-Q128,2) -> 0 | T128: =IFERROR(((K128-(Q128/J128))/(Q128/J128)),0) -> 0 | U128: =IFERROR(((K128-(Q128/J128))/K128),0) -> 0
D129: TOTALS | E129: =SUM(E18:E128) -> 132 | F129: =SUM(F18:F128) -> 107426.7 | G129: =SUM(G18:G128) -> 77845.43 | H129: =SUM(H18:H128) -> 127177.97 | J129: =SUM(J18:J128) -> 132 | K129: =SUM(K18:K128) -> 53713.44 | L129: =SUM(L18:L128) -> 63589.41 | P129: =SUM(P18:P128) -> 0 | Q129: =SUM(Q18:Q128) -> 0 | R129: =SUM(R18:R128) -> 53713.44 | S129: =SUM(S18:S128) -> 63589.41

Sheet CAT 950H LOADER
B1: CUSTOMER INFORMATION | D1: MACHINE INFORMATION | H1: MACHINE SERVICE HR INTERVALS | L1: SUMMARY | O1: =K17 -> CAD $ | R1: COMPLETED DEAL INFORMATION
B2: DATE: | D2: UNIT # | H2: ENGINE AIR | L2: OEM MSRP | O2: =H129 -> 114313.26 | R2: SALES REP
B3: COMPANY: | D3: YEAR | H3: ENGINE OIL | L3: GQP LIST | O3: =L129 -> 57156.78 | R3: ORDER PO #
B4: CUSTOMER: | D4: MAKE | H4: FUEL FILTERS | L4: $ SAVINGS | O4: =O2-O3 -> 57156.48 | R4: PROJECT #
B5: PHONE: | D5: MODEL | H5: HYDRAULIC FILTERS | L5: % SAVINGS | O5: =IFERROR((O2-O3)/O2,"") -> 0.49999869 | R5: CUST INVOICE #
B6: EMAIL: | D6: SERIAL NUMBER | H6: TRANSMISSION FILTERS | L6: TOTAL ORDER MARGIN | O6: =S129 -> 57156.78 | R6: PAYMENT TYPE
B7: SALES REP: | D7: ENGINE SER NUMBER | H7: CAB FILTERS | L7: TOTAL ITEM COST | O7: =Q129 -> 0 | R7: DATE DELIVERED
D8: CURRENT HOURS | H8: UNDERCARRIAGE / TIRES | L8: TOTAL ORDER FREIGHT | O8: =IF(O1=P14,Q14,IF(P14="CAD $",Q14*D15,IF(P14="USD $",Q14*E15,0))) -> 0 | R8: TOTAL COST | S8: NET MARGIN | T8: NET MARKUP % | U8: NET MARGIN %
D9: USAGE/MONTH | L9: TOTAL CUSTOMS/BROKERAGE | O9: =U14 -> 0 | R9: =O7+O8+O9 -> 0 | S9: =O3-R9 -> 57156.78 | T9: =IFERROR(((O3-R9)/R9),0) -> 0 | U9: =IFERROR(((O3-R9)/O3),0) -> 1
L10: TOTAL NUMBER PIECES | O10: =E129 -> 49
D11: ENTER EXCHANGE RATES $ | F11: OEM MSRP | J11: CUSTOMER SELL PRICE | O11: COST ANALYSIS | X11: CAD $
X12: USD $
F13: SHOW OEM MSRP ON QUOTE: | H13: YES | X13: YES
D14: CAD-USD | E14: USD-CAD | F14: OEM NAME | J14: CUSTOMER PRICE % OF OEM LIST | L14: 0.5 | O14: FREIGHT TOTAL ORDER | P14: USD $ | R14: CUSTOMS AND BROKERAGE % | S14: 0.025 | T14: BROKERAGE FEES | U14: =ROUND(Q129*S14,2) -> 0 | X14: NO
D15: =1/E15 -> 0.72463768 | E15: 1.38 | M15: ADDITIONAL +/- DISC % PER ITEM | O15: MARKUP LESS THAN 100% REQUIRES MANAGER APPROVAL
B16: PART NUMBER | C16: DESCRIPTION | D16: SERVICE INTERVAL | E16: QTY | F16: UNIT PRICE | H16: EXT AMOUNT | J16: QTY | K16: UNIT PRICE | L16: EXTENDED AMOUNT | O16: VENDOR | P16: COST EACH | Q16: EXTENDED COST | R16: MARGIN EACH | S16: EXTENDED MARGIN | T16: MARKUP % | U16: MARGIN %
F17: USD $ | G17: =IF(F17="USD $", "CAD $", "USD $") -> CAD $ | H17: =K17 -> CAD $ | K17: CAD $ | P17: USD $ | Q17: =K17 -> CAD $
B18: 1R-1807 | C18: Oil Filter | E18: 1 | F18: 44.09 | G18: =ROUND(IF($F$17="USD $", F18*$E$15,F18*$D$15),2) -> 60.84 | H18: =ROUND(IF($H$17=$G$17,E18*G18,E18*F18),2) -> 60.84 | J18: =E18 -> 1 | K18: =ROUND(IF($K$17=$F$17,F18*($L$14-M18),G18*($L$14-M18)),2) -> 30.42 | L18: =ROUND((J18*K18),2) -> 30.42 | Q18: =ROUND(IF($Q$17=$P$17,P18,IF($Q$17="USD $",P18*$D$15,P18*$E$15))*E18,2) -> 0 | R18: =IFERROR(ROUND(S18/E18,2),0) -> 30.42 | S18: =ROUND(L18-Q18,2) -> 30.42 | T18: =IFERROR(((K18-(Q18/J18))/(Q18/J18)),0) -> 0 | U18: =IFERROR(((K18-(Q18/J18))/K18),0) -> 1 | Y18: 250
B19: 330-9358 | C19: Hydarulic Oil Filter | E19: 1 | F19: 1227.31 | G19: =ROUND(IF($F$17="USD $", F19*$E$15,F19*$D$15),2) -> 1693.69 | H19: =ROUND(IF($H$17=$G$17,E19*G19,E19*F19),2) -> 1693.69 | J19: =E19 -> 1 | K19: =ROUND(IF($K$17=$F$17,F19*($L$14-M19),G19*($L$14-M19)),2) -> 846.85 | L19: =ROUND((J19*K19),2) -> 846.85 | Q19: =ROUND(IF($Q$17=$P$17,P19,IF($Q$17="USD $",P19*$D$15,P19*$E$15))*E19,2) -> 0 | R19: =IFERROR(ROUND(S19/E19,2),0) -> 846.85 | S19: =ROUND(L19-Q19,2) -> 846.85 | T19: =IFERROR(((K19-(Q19/J19))/(Q19/J19)),0) -> 0 | U19: =IFERROR(((K19-(Q19/J19))/K19),0) -> 1 | X19: GQP | Y19: 500
B20: 326-1644 | C20: Fuel/Water Separator Filter (Primary) | E20: 1 | F20: 85.6 | G20: =ROUND(IF($F$17="USD $", F20*$E$15,F20*$D$15),2) -> 118.13 | H20: =ROUND(IF($H$17=$G$17,E20*G20,E20*F20),2) -> 118.13 | J20: =E20 -> 1 | K20: =ROUND(IF($K$17=$F$17,F20*($L$14-M20),G20*($L$14-M20)),2) -> 59.07 | L20: =ROUND((J20*K20),2) -> 59.07 | Q20: =ROUND(IF($Q$17=$P$17,P20,IF($Q$17="USD $",P20*$D$15,P20*$E$15))*E20,2) -> 0 | R20: =IFERROR(ROUND(S20/E20,2),0) -> 59.07 | S20: =ROUND(L20-Q20,2) -> 59.07 | T20: =IFERROR(((K20-(Q20/J20))/(Q20/J20)),0) -> 0 | U20: =IFERROR(((K20-(Q20/J20))/K20),0) -> 1 | X20: CTP | Y20: 750
B21: 245-6375 | C21: PRIMAERY AIR FILTER | E21: 1 | F21: 167.02 | G21: =ROUND(IF($F$17="USD $", F21*$E$15,F21*$D$15),2) -> 230.49 | H21: =ROUND(IF($H$17=$G$17,E21*G21,E21*F21),2) -> 230.49 | J21: =E21 -> 1 | K21: =ROUND(IF($K$17=$F$17,F21*($L$14-M21),G21*($L$14-M21)),2) -> 115.25 | L21: =ROUND((J21*K21),2) -> 115.25 | Q21: =ROUND(IF($Q$17=$P$17,P21,IF($Q$17="USD $",P21*$D$15,P21*$E$15))*E21,2) -> 0 | R21: =IFERROR(ROUND(S21/E21,2),0) -> 115.25 | S21: =ROUND(L21-Q21,2) -> 115.25 | T21: =IFERROR(((K21-(Q21/J21))/(Q21/J21)),0) -> 0 | U21: =IFERROR(((K21-(Q21/J21))/K21),0) -> 1 | X21: BLMQ | Y21: 1000
B22: 245-6376 | C22: SECONDARY AIR FILTER | E22: 1 | F22: 109.74 | G22: =ROUND(IF($F$17="USD $", F22*$E$15,F22*$D$15),2) -> 151.44 | H22: =ROUND(IF($H$17=$G$17,E22*G22,E22*F22),2) -> 151.44 | J22: =E22 -> 1 | K22: =ROUND(IF($K$17=$F$17,F22*($L$14-M22),G22*($L$14-M22)),2) -> 75.72 | L22: =ROUND((J22*K22),2) -> 75.72 | Q22: =ROUND(IF($Q$17=$P$17,P22,IF($Q$17="USD $",P22*$D$15,P22*$E$15))*E22,2) -> 0 | R22: =IFERROR(ROUND(S22/E22,2),0) -> 75.72 | S22: =ROUND(L22-Q22,2) -> 75.72 | T22: =IFERROR(((K22-(Q22/J22))/(Q22/J22)),0) -> 0 | U22: =IFERROR(((K22-(Q22/J22))/K22),0) -> 1 | X22: CAT | Y22: 1200
B23: 7X-6041 | C23: CABIN AIR FILTER | E23: 1 | F23: 92 | G23: =ROUND(IF($F$17="USD $", F23*$E$15,F23*$D$15),2) -> 126.96 | H23: =ROUND(IF($H$17=$G$17,E23*G23,E23*F23),2) -> 126.96 | J23: =E23 -> 1 | K23: =ROUND(IF($K$17=$F$17,F23*($L$14-M23),G23*($L$14-M23)),2) -> 63.48 | L23: =ROUND((J23*K23),2) -> 63.48 | Q23: =ROUND(IF($Q$17=$P$17,P23,IF($Q$17="USD $",P23*$D$15,P23*$E$15))*E23,2) -> 0 | R23: =IFERROR(ROUND(S23/E23,2),0) -> 63.48 | S23: =ROUND(L23-Q23,2) -> 63.48 | T23: =IFERROR(((K23-(Q23/J23))/(Q23/J23)),0) -> 0 | U23: =IFERROR(((K23-(Q23/J23))/K23),0) -> 1 | X23: FINNING | Y23: 2000
B24: 1G-8878 | C24: TRANSMISSION FILTER | E24: 1 | F24: 150.47 | G24: =ROUND(IF($F$17="USD $", F24*$E$15,F24*$D$15),2) -> 207.65 | H24: =ROUND(IF($H$17=$G$17,E24*G24,E24*F24),2) -> 207.65 | J24: =E24 -> 1 | K24: =ROUND(IF($K$17=$F$17,F24*($L$14-M24),G24*($L$14-M24)),2) -> 103.83 | L24: =ROUND((J24*K24),2) -> 103.83 | Q24: =ROUND(IF($Q$17=$P$17,P24,IF($Q$17="USD $",P24*$D$15,P24*$E$15))*E24,2) -> 0 | R24: =IFERROR(ROUND(S24/E24,2),0) -> 103.83 | S24: =ROUND(L24-Q24,2) -> 103.83 | T24: =IFERROR(((K24-(Q24/J24))/(Q24/J24)),0) -> 0 | U24: =IFERROR(((K24-(Q24/J24))/K24),0) -> 1 | X24: JD | Y24: 4000
B25: 1R-0762 | C25: SECONDARY FUEL FILTER | E25: 1 | F25: 67.44 | G25: =ROUND(IF($F$17="USD $", F25*$E$15,F25*$D$15),2) -> 93.07 | H25: =ROUND(IF($H$17=$G$17,E25*G25,E25*F25),2) -> 93.07 | J25: =E25 -> 1 | K25: =ROUND(IF($K$17=$F$17,F25*($L$14-M25),G25*($L$14-M25)),2) -> 46.54 | L25: =ROUND((J25*K25),2) -> 46.54 | Q25: =ROUND(IF($Q$17=$P$17,P25,IF($Q$17="USD $",P25*$D$15,P25*$E$15))*E25,2) -> 0 | R25: =IFERROR(ROUND(S25/E25,2),0) -> 46.54 | S25: =ROUND(L25-Q25,2) -> 46.54 | T25: =IFERROR(((K25-(Q25/J25))/(Q25/J25)),0) -> 0 | U25: =IFERROR(((K25-(Q25/J25))/K25),0) -> 1 | X25: BRANDT | Y25: 6000
G26: =ROUND(IF($F$17="USD $", F26*$E$15,F26*$D$15),2) -> 0 | H26: =ROUND(IF($H$17=$G$17,E26*G26,E26*F26),2) -> 0 | J26: =E26 -> 0 | K26: =ROUND(IF($K$17=$F$17,F26*($L$14-M26),G26*($L$14-M26)),2) -> 0 | L26: =ROUND((J26*K26),2) -> 0 | Q26: =ROUND(IF($Q$17=$P$17,P26,IF($Q$17="USD $",P26*$D$15,P26*$E$15))*E26,2) -> 0 | R26: =IFERROR(ROUND(S26/E26,2),0) -> 0 | S26: =ROUND(L26-Q26,2) -> 0 | T26: =IFERROR(((K26-(Q26/J26))/(Q26/J26)),0) -> 0 | U26: =IFERROR(((K26-(Q26/J26))/K26),0) -> 0 | X26: PTI | Y26: 8000
B27: 134-4483 | C27: MAJOR ENGINE OVERHAUL KIT | E27: 1 | F27: 11907.74 | G27: =ROUND(IF($F$17="USD $", F27*$E$15,F27*$D$15),2) -> 16432.68 | H27: =ROUND(IF($H$17=$G$17,E27*G27,E27*F27),2) -> 16432.68 | J27: =E27 -> 1 | K27: =ROUND(IF($K$17=$F$17,F27*($L$14-M27),G27*($L$14-M27)),2) -> 8216.34 | L27: =ROUND((J27*K27),2) -> 8216.34 | Q27: =ROUND(IF($Q$17=$P$17,P27,IF($Q$17="USD $",P27*$D$15,P27*$E$15))*E27,2) -> 0 | R27: =IFERROR(ROUND(S27/E27,2),0) -> 8216.34 | S27: =ROUND(L27-Q27,2) -> 8216.34 | T27: =IFERROR(((K27-(Q27/J27))/(Q27/J27)),0) -> 0 | U27: =IFERROR(((K27-(Q27/J27))/K27),0) -> 1 | X27: CONEQUIP | Y27: 10000
B28: 212-4288 | C28: Camshaft Assembly | E28: 1 | F28: 3804.56 | G28: =ROUND(IF($F$17="USD $", F28*$E$15,F28*$D$15),2) -> 5250.29 | H28: =ROUND(IF($H$17=$G$17,E28*G28,E28*F28),2) -> 5250.29 | J28: =E28 -> 1 | K28: =ROUND(IF($K$17=$F$17,F28*($L$14-M28),G28*($L$14-M28)),2) -> 2625.15 | L28: =ROUND((J28*K28),2) -> 2625.15 | Q28: =ROUND(IF($Q$17=$P$17,P28,IF($Q$17="USD $",P28*$D$15,P28*$E$15))*E28,2) -> 0 | R28: =IFERROR(ROUND(S28/E28,2),0) -> 2625.15 | S28: =ROUND(L28-Q28,2) -> 2625.15 | T28: =IFERROR(((K28-(Q28/J28))/(Q28/J28)),0) -> 0 | U28: =IFERROR(((K28-(Q28/J28))/K28),0) -> 1 | X28: CANDY | Y28: AS REQ'D
B29: 134-0734 | C29: Crankshaft Group | E29: 1 | F29: 5410.74 | G29: =ROUND(IF($F$17="USD $", F29*$E$15,F29*$D$15),2) -> 7466.82 | H29: =ROUND(IF($H$17=$G$17,E29*G29,E29*F29),2) -> 7466.82 | J29: =E29 -> 1 | K29: =ROUND(IF($K$17=$F$17,F29*($L$14-M29),G29*($L$14-M29)),2) -> 3733.41 | L29: =ROUND((J29*K29),2) -> 3733.41 | Q29: =ROUND(IF($Q$17=$P$17,P29,IF($Q$17="USD $",P29*$D$15,P29*$E$15))*E29,2) -> 0 | R29: =IFERROR(ROUND(S29/E29,2),0) -> 3733.41 | S29: =ROUND(L29-Q29,2) -> 3733.41 | T29: =IFERROR(((K29-(Q29/J29))/(Q29/J29)),0) -> 0 | U29: =IFERROR(((K29-(Q29/J29))/K29),0) -> 1 | X29: U/C
B30: 3058141 | C30: Cylinder Block | E30: 1 | F30: 18371.68 | G30: =ROUND(IF($F$17="USD $", F30*$E$15,F30*$D$15),2) -> 25352.92 | H30: =ROUND(IF($H$17=$G$17,E30*G30,E30*F30),2) -> 25352.92 | J30: =E30 -> 1 | K30: =ROUND(IF($K$17=$F$17,F30*($L$14-M30),G30*($L$14-M30)),2) -> 12676.46 | L30: =ROUND((J30*K30),2) -> 12676.46 | Q30: =ROUND(IF($Q$17=$P$17,P30,IF($Q$17="USD $",P30*$D$15,P30*$E$15))*E30,2) -> 0 | R30: =IFERROR(ROUND(S30/E30,2),0) -> 12676.46 | S30: =ROUND(L30-Q30,2) -> 12676.46 | T30: =IFERROR(((K30-(Q30/J30))/(Q30/J30)),0) -> 0 | U30: =IFERROR(((K30-(Q30/J30))/K30),0) -> 1
B31: 4872807 | C31: Cylinder Head GP | E31: 1 | F31: 10196.18 | G31: =ROUND(IF($F$17="USD $", F31*$E$15,F31*$D$15),2) -> 14070.73 | H31: =ROUND(IF($H$17=$G$17,E31*G31,E31*F31),2) -> 14070.73 | J31: =E31 -> 1 | K31: =ROUND(IF($K$17=$F$17,F31*($L$14-M31),G31*($L$14-M31)),2) -> 7035.37 | L31: =ROUND((J31*K31),2) -> 7035.37 | Q31: =ROUND(IF($Q$17=$P$17,P31,IF($Q$17="USD $",P31*$D$15,P31*$E$15))*E31,2) -> 0 | R31: =IFERROR(ROUND(S31/E31,2),0) -> 7035.37 | S31: =ROUND(L31-Q31,2) -> 7035.37 | T31: =IFERROR(((K31-(Q31/J31))/(Q31/J31)),0) -> 0 | U31: =IFERROR(((K31-(Q31/J31))/K31),0) -> 1
B32: 557-7627 | C32: Fuel Injector | E32: 4 | F32: 1906.27 | G32: =ROUND(IF($F$17="USD $", F32*$E$15,F32*$D$15),2) -> 2630.65 | H32: =ROUND(IF($H$17=$G$17,E32*G32,E32*F32),2) -> 10522.6 | J32: =E32 -> 4 | K32: =ROUND(IF($K$17=$F$17,F32*($L$14-M32),G32*($L$14-M32)),2) -> 1315.33 | L32: =ROUND((J32*K32),2) -> 5261.32 | Q32: =ROUND(IF($Q$17=$P$17,P32,IF($Q$17="USD $",P32*$D$15,P32*$E$15))*E32,2) -> 0 | R32: =IFERROR(ROUND(S32/E32,2),0) -> 1315.33 | S32: =ROUND(L32-Q32,2) -> 5261.32 | T32: =IFERROR(((K32-(Q32/J32))/(Q32/J32)),0) -> 0 | U32: =IFERROR(((K32-(Q32/J32))/K32),0) -> 1
B33: 250-0841 | C33: Turbo Charger | E33: 1 | F33: 6920.52 | G33: =ROUND(IF($F$17="USD $", F33*$E$15,F33*$D$15),2) -> 9550.32 | H33: =ROUND(IF($H$17=$G$17,E33*G33,E33*F33),2) -> 9550.32 | J33: =E33 -> 1 | K33: =ROUND(IF($K$17=$F$17,F33*($L$14-M33),G33*($L$14-M33)),2) -> 4775.16 | L33: =ROUND((J33*K33),2) -> 4775.16 | Q33: =ROUND(IF($Q$17=$P$17,P33,IF($Q$17="USD $",P33*$D$15,P33*$E$15))*E33,2) -> 0 | R33: =IFERROR(ROUND(S33/E33,2),0) -> 4775.16 | S33: =ROUND(L33-Q33,2) -> 4775.16 | T33: =IFERROR(((K33-(Q33/J33))/(Q33/J33)),0) -> 0 | U33: =IFERROR(((K33-(Q33/J33))/K33),0) -> 1
G34: =ROUND(IF($F$17="USD $", F34*$E$15,F34*$D$15),2) -> 0 | H34: =ROUND(IF($H$17=$G$17,E34*G34,E34*F34),2) -> 0 | J34: =E34 -> 0 | K34: =ROUND(IF($K$17=$F$17,F34*($L$14-M34),G34*($L$14-M34)),2) -> 0 | L34: =ROUND((J34*K34),2) -> 0 | Q34: =ROUND(IF($Q$17=$P$17,P34,IF($Q$17="USD $",P34*$D$15,P34*$E$15))*E34,2) -> 0 | R34: =IFERROR(ROUND(S34/E34,2),0) -> 0 | S34: =ROUND(L34-Q34,2) -> 0 | T34: =IFERROR(((K34-(Q34/J34))/(Q34/J34)),0) -> 0 | U34: =IFERROR(((K34-(Q34/J34))/K34),0) -> 0
B35: 528-9582 | C35: SEAT-SUSPENSION AS | E35: 1 | F35: 9037.67 | G35: =ROUND(IF($F$17="USD $", F35*$E$15,F35*$D$15),2) -> 12471.98 | H35: =ROUND(IF($H$17=$G$17,E35*G35,E35*F35),2) -> 12471.98 | J35: =E35 -> 1 | K35: =ROUND(IF($K$17=$F$17,F35*($L$14-M35),G35*($L$14-M35)),2) -> 6235.99 | L35: =ROUND((J35*K35),2) -> 6235.99 | Q35: =ROUND(IF($Q$17=$P$17,P35,IF($Q$17="USD $",P35*$D$15,P35*$E$15))*E35,2) -> 0 | R35: =IFERROR(ROUND(S35/E35,2),0) -> 6235.99 | S35: =ROUND(L35-Q35,2) -> 6235.99 | T35: =IFERROR(((K35-(Q35/J35))/(Q35/J35)),0) -> 0 | U35: =IFERROR(((K35-(Q35/J35))/K35),0) -> 1
G36: =ROUND(IF($F$17="USD $", F36*$E$15,F36*$D$15),2) -> 0 | H36: =ROUND(IF($H$17=$G$17,E36*G36,E36*F36),2) -> 0 | J36: =E36 -> 0 | K36: =ROUND(IF($K$17=$F$17,F36*($L$14-M36),G36*($L$14-M36)),2) -> 0 | L36: =ROUND((J36*K36),2) -> 0 | Q36: =ROUND(IF($Q$17=$P$17,P36,IF($Q$17="USD $",P36*$D$15,P36*$E$15))*E36,2) -> 0 | R36: =IFERROR(ROUND(S36/E36,2),0) -> 0 | S36: =ROUND(L36-Q36,2) -> 0 | T36: =IFERROR(((K36-(Q36/J36))/(Q36/J36)),0) -> 0 | U36: =IFERROR(((K36-(Q36/J36))/K36),0) -> 0
B37: 153-5710 | C37: Battery (L:11.9" x W:7.5" x H:7.5") | E37: 1 | F37: 811.6 | G37: =ROUND(IF($F$17="USD $", F37*$E$15,F37*$D$15),2) -> 1120.01 | H37: =ROUND(IF($H$17=$G$17,E37*G37,E37*F37),2) -> 1120.01 | J37: =E37 -> 1 | K37: =ROUND(IF($K$17=$F$17,F37*($L$14-M37),G37*($L$14-M37)),2) -> 560.01 | L37: =ROUND((J37*K37),2) -> 560.01 | Q37: =ROUND(IF($Q$17=$P$17,P37,IF($Q$17="USD $",P37*$D$15,P37*$E$15))*E37,2) -> 0 | R37: =IFERROR(ROUND(S37/E37,2),0) -> 560.01 | S37: =ROUND(L37-Q37,2) -> 560.01 | T37: =IFERROR(((K37-(Q37/J37))/(Q37/J37)),0) -> 0 | U37: =IFERROR(((K37-(Q37/J37))/K37),0) -> 1
G38: =ROUND(IF($F$17="USD $", F38*$E$15,F38*$D$15),2) -> 0 | H38: =ROUND(IF($H$17=$G$17,E38*G38,E38*F38),2) -> 0 | J38: =E38 -> 0 | K38: =ROUND(IF($K$17=$F$17,F38*($L$14-M38),G38*($L$14-M38)),2) -> 0 | L38: =ROUND((J38*K38),2) -> 0 | Q38: =ROUND(IF($Q$17=$P$17,P38,IF($Q$17="USD $",P38*$D$15,P38*$E$15))*E38,2) -> 0 | R38: =IFERROR(ROUND(S38/E38,2),0) -> 0 | S38: =ROUND(L38-Q38,2) -> 0 | T38: =IFERROR(((K38-(Q38/J38))/(Q38/J38)),0) -> 0 | U38: =IFERROR(((K38-(Q38/J38))/K38),0) -> 0
B39: 311-6949 | C39: Bucket As | E39: 1 | F39: 6221.62 | G39: =ROUND(IF($F$17="USD $", F39*$E$15,F39*$D$15),2) -> 8585.84 | H39: =ROUND(IF($H$17=$G$17,E39*G39,E39*F39),2) -> 8585.84 | J39: =E39 -> 1 | K39: =ROUND(IF($K$17=$F$17,F39*($L$14-M39),G39*($L$14-M39)),2) -> 4292.92 | L39: =ROUND((J39*K39),2) -> 4292.92 | Q39: =ROUND(IF($Q$17=$P$17,P39,IF($Q$17="USD $",P39*$D$15,P39*$E$15))*E39,2) -> 0 | R39: =IFERROR(ROUND(S39/E39,2),0) -> 4292.92 | S39: =ROUND(L39-Q39,2) -> 4292.92 | T39: =IFERROR(((K39-(Q39/J39))/(Q39/J39)),0) -> 0 | U39: =IFERROR(((K39-(Q39/J39))/K39),0) -> 1
B40: 273-3761 | C40: Bucket Cutting Edge | E40: 1 | F40: 269.92 | G40: =ROUND(IF($F$17="USD $", F40*$E$15,F40*$D$15),2) -> 372.49 | H40: =ROUND(IF($H$17=$G$17,E40*G40,E40*F40),2) -> 372.49 | J40: =E40 -> 1 | K40: =ROUND(IF($K$17=$F$17,F40*($L$14-M40),G40*($L$14-M40)),2) -> 186.25 | L40: =ROUND((J40*K40),2) -> 186.25 | Q40: =ROUND(IF($Q$17=$P$17,P40,IF($Q$17="USD $",P40*$D$15,P40*$E$15))*E40,2) -> 0 | R40: =IFERROR(ROUND(S40/E40,2),0) -> 186.25 | S40: =ROUND(L40-Q40,2) -> 186.25 | T40: =IFERROR(((K40-(Q40/J40))/(Q40/J40)),0) -> 0 | U40: =IFERROR(((K40-(Q40/J40))/K40),0) -> 1
B41: 4F-7827 | C41: Plow Bolt | E41: 8 | F41: 3.22 | G41: =ROUND(IF($F$17="USD $", F41*$E$15,F41*$D$15),2) -> 4.44 | H41: =ROUND(IF($H$17=$G$17,E41*G41,E41*F41),2) -> 35.52 | J41: =E41 -> 8 | K41: =ROUND(IF($K$17=$F$17,F41*($L$14-M41),G41*($L$14-M41)),2) -> 2.22 | L41: =ROUND((J41*K41),2) -> 17.76 | Q41: =ROUND(IF($Q$17=$P$17,P41,IF($Q$17="USD $",P41*$D$15,P41*$E$15))*E41,2) -> 0 | R41: =IFERROR(ROUND(S41/E41,2),0) -> 2.22 | S41: =ROUND(L41-Q41,2) -> 17.76 | T41: =IFERROR(((K41-(Q41/J41))/(Q41/J41)),0) -> 0 | U41: =IFERROR(((K41-(Q41/J41))/K41),0) -> 1
B42: 2J-3506 | C42: Nut | E42: 8 | F42: 2.44 | G42: =ROUND(IF($F$17="USD $", F42*$E$15,F42*$D$15),2) -> 3.37 | H42: =ROUND(IF($H$17=$G$17,E42*G42,E42*F42),2) -> 26.96 | J42: =E42 -> 8 | K42: =ROUND(IF($K$17=$F$17,F42*($L$14-M42),G42*($L$14-M42)),2) -> 1.69 | L42: =ROUND((J42*K42),2) -> 13.52 | Q42: =ROUND(IF($Q$17=$P$17,P42,IF($Q$17="USD $",P42*$D$15,P42*$E$15))*E42,2) -> 0 | R42: =IFERROR(ROUND(S42/E42,2),0) -> 1.69 | S42: =ROUND(L42-Q42,2) -> 13.52 | T42: =IFERROR(((K42-(Q42/J42))/(Q42/J42)),0) -> 0 | U42: =IFERROR(((K42-(Q42/J42))/K42),0) -> 1
B43: 5P-8248 | C43: Washer | E43: 8 | F43: 3.56 | G43: =ROUND(IF($F$17="USD $", F43*$E$15,F43*$D$15),2) -> 4.91 | H43: =ROUND(IF($H$17=$G$17,E43*G43,E43*F43),2) -> 39.28 | J43: =E43 -> 8 | K43: =ROUND(IF($K$17=$F$17,F43*($L$14-M43),G43*($L$14-M43)),2) -> 2.46 | L43: =ROUND((J43*K43),2) -> 19.68 | Q43: =ROUND(IF($Q$17=$P$17,P43,IF($Q$17="USD $",P43*$D$15,P43*$E$15))*E43,2) -> 0 | R43: =IFERROR(ROUND(S43/E43,2),0) -> 2.46 | S43: =ROUND(L43-Q43,2) -> 19.68 | T43: =IFERROR(((K43-(Q43/J43))/(Q43/J43)),0) -> 0 | U43: =IFERROR(((K43-(Q43/J43))/K43),0) -> 1
B44: 7T-5961 | C44: Edge LH | E44: 1 | F44: 64.26 | G44: =ROUND(IF($F$17="USD $", F44*$E$15,F44*$D$15),2) -> 88.68 | H44: =ROUND(IF($H$17=$G$17,E44*G44,E44*F44),2) -> 88.68 | J44: =E44 -> 1 | K44: =ROUND(IF($K$17=$F$17,F44*($L$14-M44),G44*($L$14-M44)),2) -> 44.34 | L44: =ROUND((J44*K44),2) -> 44.34 | Q44: =ROUND(IF($Q$17=$P$17,P44,IF($Q$17="USD $",P44*$D$15,P44*$E$15))*E44,2) -> 0 | R44: =IFERROR(ROUND(S44/E44,2),0) -> 44.34 | S44: =ROUND(L44-Q44,2) -> 44.34 | T44: =IFERROR(((K44-(Q44/J44))/(Q44/J44)),0) -> 0 | U44: =IFERROR(((K44-(Q44/J44))/K44),0) -> 1
B45: 7T-5963 | C45: Edge RH | E45: 1 | F45: 64.26 | G45: =ROUND(IF($F$17="USD $", F45*$E$15,F45*$D$15),2) -> 88.68 | H45: =ROUND(IF($H$17=$G$17,E45*G45,E45*F45),2) -> 88.68 | J45: =E45 -> 1 | K45: =ROUND(IF($K$17=$F$17,F45*($L$14-M45),G45*($L$14-M45)),2) -> 44.34 | L45: =ROUND((J45*K45),2) -> 44.34 | Q45: =ROUND(IF($Q$17=$P$17,P45,IF($Q$17="USD $",P45*$D$15,P45*$E$15))*E45,2) -> 0 | R45: =IFERROR(ROUND(S45/E45,2),0) -> 44.34 | S45: =ROUND(L45-Q45,2) -> 44.34 | T45: =IFERROR(((K45-(Q45/J45))/(Q45/J45)),0) -> 0 | U45: =IFERROR(((K45-(Q45/J45))/K45),0) -> 1
B46: 109-9052 | C46: Sidebar | E46: 1 | F46: 112.46 | G46: =ROUND(IF($F$17="USD $", F46*$E$15,F46*$D$15),2) -> 155.19 | H46: =ROUND(IF($H$17=$G$17,E46*G46,E46*F46),2) -> 155.19 | J46: =E46 -> 1 | K46: =ROUND(IF($K$17=$F$17,F46*($L$14-M46),G46*($L$14-M46)),2) -> 77.6 | L46: =ROUND((J46*K46),2) -> 77.6 | Q46: =ROUND(IF($Q$17=$P$17,P46,IF($Q$17="USD $",P46*$D$15,P46*$E$15))*E46,2) -> 0 | R46: =IFERROR(ROUND(S46/E46,2),0) -> 77.6 | S46: =ROUND(L46-Q46,2) -> 77.6 | T46: =IFERROR(((K46-(Q46/J46))/(Q46/J46)),0) -> 0 | U46: =IFERROR(((K46-(Q46/J46))/K46),0) -> 1
G47: =ROUND(IF($F$17="USD $", F47*$E$15,F47*$D$15),2) -> 0 | H47: =ROUND(IF($H$17=$G$17,E47*G47,E47*F47),2) -> 0 | J47: =E47 -> 0 | K47: =ROUND(IF($K$17=$F$17,F47*($L$14-M47),G47*($L$14-M47)),2) -> 0 | L47: =ROUND((J47*K47),2) -> 0 | Q47: =ROUND(IF($Q$17=$P$17,P47,IF($Q$17="USD $",P47*$D$15,P47*$E$15))*E47,2) -> 0 | R47: =IFERROR(ROUND(S47/E47,2),0) -> 0 | S47: =ROUND(L47-Q47,2) -> 0 | T47: =IFERROR(((K47-(Q47/J47))/(Q47/J47)),0) -> 0 | U47: =IFERROR(((K47-(Q47/J47))/K47),0) -> 0
G48: =ROUND(IF($F$17="USD $", F48*$E$15,F48*$D$15),2) -> 0 | H48: =ROUND(IF($H$17=$G$17,E48*G48,E48*F48),2) -> 0 | J48: =E48 -> 0 | K48: =ROUND(IF($K$17=$F$17,F48*($L$14-M48),G48*($L$14-M48)),2) -> 0 | L48: =ROUND((J48*K48),2) -> 0 | Q48: =ROUND(IF($Q$17=$P$17,P48,IF($Q$17="USD $",P48*$D$15,P48*$E$15))*E48,2) -> 0 | R48: =IFERROR(ROUND(S48/E48,2),0) -> 0 | S48: =ROUND(L48-Q48,2) -> 0 | T48: =IFERROR(((K48-(Q48/J48))/(Q48/J48)),0) -> 0 | U48: =IFERROR(((K48-(Q48/J48))/K48),0) -> 0
G49: =ROUND(IF($F$17="USD $", F49*$E$15,F49*$D$15),2) -> 0 | H49: =ROUND(IF($H$17=$G$17,E49*G49,E49*F49),2) -> 0 | J49: =E49 -> 0 | K49: =ROUND(IF($K$17=$F$17,F49*($L$14-M49),G49*($L$14-M49)),2) -> 0 | L49: =ROUND((J49*K49),2) -> 0 | Q49: =ROUND(IF($Q$17=$P$17,P49,IF($Q$17="USD $",P49*$D$15,P49*$E$15))*E49,2) -> 0 | R49: =IFERROR(ROUND(S49/E49,2),0) -> 0 | S49: =ROUND(L49-Q49,2) -> 0 | T49: =IFERROR(((K49-(Q49/J49))/(Q49/J49)),0) -> 0 | U49: =IFERROR(((K49-(Q49/J49))/K49),0) -> 0
G50: =ROUND(IF($F$17="USD $", F50*$E$15,F50*$D$15),2) -> 0 | H50: =ROUND(IF($H$17=$G$17,E50*G50,E50*F50),2) -> 0 | J50: =E50 -> 0 | K50: =ROUND(IF($K$17=$F$17,F50*($L$14-M50),G50*($L$14-M50)),2) -> 0 | L50: =ROUND((J50*K50),2) -> 0 | Q50: =ROUND(IF($Q$17=$P$17,P50,IF($Q$17="USD $",P50*$D$15,P50*$E$15))*E50,2) -> 0 | R50: =IFERROR(ROUND(S50/E50,2),0) -> 0 | S50: =ROUND(L50-Q50,2) -> 0 | T50: =IFERROR(((K50-(Q50/J50))/(Q50/J50)),0) -> 0 | U50: =IFERROR(((K50-(Q50/J50))/K50),0) -> 0
G51: =ROUND(IF($F$17="USD $", F51*$E$15,F51*$D$15),2) -> 0 | H51: =ROUND(IF($H$17=$G$17,E51*G51,E51*F51),2) -> 0 | J51: =E51 -> 0 | K51: =ROUND(IF($K$17=$F$17,F51*($L$14-M51),G51*($L$14-M51)),2) -> 0 | L51: =ROUND((J51*K51),2) -> 0 | Q51: =ROUND(IF($Q$17=$P$17,P51,IF($Q$17="USD $",P51*$D$15,P51*$E$15))*E51,2) -> 0 | R51: =IFERROR(ROUND(S51/E51,2),0) -> 0 | S51: =ROUND(L51-Q51,2) -> 0 | T51: =IFERROR(((K51-(Q51/J51))/(Q51/J51)),0) -> 0 | U51: =IFERROR(((K51-(Q51/J51))/K51),0) -> 0
G52: =ROUND(IF($F$17="USD $", F52*$E$15,F52*$D$15),2) -> 0 | H52: =ROUND(IF($H$17=$G$17,E52*G52,E52*F52),2) -> 0 | J52: =E52 -> 0 | K52: =ROUND(IF($K$17=$F$17,F52*($L$14-M52),G52*($L$14-M52)),2) -> 0 | L52: =ROUND((J52*K52),2) -> 0 | Q52: =ROUND(IF($Q$17=$P$17,P52,IF($Q$17="USD $",P52*$D$15,P52*$E$15))*E52,2) -> 0 | R52: =IFERROR(ROUND(S52/E52,2),0) -> 0 | S52: =ROUND(L52-Q52,2) -> 0 | T52: =IFERROR(((K52-(Q52/J52))/(Q52/J52)),0) -> 0 | U52: =IFERROR(((K52-(Q52/J52))/K52),0) -> 0
G53: =ROUND(IF($F$17="USD $", F53*$E$15,F53*$D$15),2) -> 0 | H53: =ROUND(IF($H$17=$G$17,E53*G53,E53*F53),2) -> 0 | J53: =E53 -> 0 | K53: =ROUND(IF($K$17=$F$17,F53*($L$14-M53),G53*($L$14-M53)),2) -> 0 | L53: =ROUND((J53*K53),2) -> 0 | Q53: =ROUND(IF($Q$17=$P$17,P53,IF($Q$17="USD $",P53*$D$15,P53*$E$15))*E53,2) -> 0 | R53: =IFERROR(ROUND(S53/E53,2),0) -> 0 | S53: =ROUND(L53-Q53,2) -> 0 | T53: =IFERROR(((K53-(Q53/J53))/(Q53/J53)),0) -> 0 | U53: =IFERROR(((K53-(Q53/J53))/K53),0) -> 0
G54: =ROUND(IF($F$17="USD $", F54*$E$15,F54*$D$15),2) -> 0 | H54: =ROUND(IF($H$17=$G$17,E54*G54,E54*F54),2) -> 0 | J54: =E54 -> 0 | K54: =ROUND(IF($K$17=$F$17,F54*($L$14-M54),G54*($L$14-M54)),2) -> 0 | L54: =ROUND((J54*K54),2) -> 0 | Q54: =ROUND(IF($Q$17=$P$17,P54,IF($Q$17="USD $",P54*$D$15,P54*$E$15))*E54,2) -> 0 | R54: =IFERROR(ROUND(S54/E54,2),0) -> 0 | S54: =ROUND(L54-Q54,2) -> 0 | T54: =IFERROR(((K54-(Q54/J54))/(Q54/J54)),0) -> 0 | U54: =IFERROR(((K54-(Q54/J54))/K54),0) -> 0
G55: =ROUND(IF($F$17="USD $", F55*$E$15,F55*$D$15),2) -> 0 | H55: =ROUND(IF($H$17=$G$17,E55*G55,E55*F55),2) -> 0 | J55: =E55 -> 0 | K55: =ROUND(IF($K$17=$F$17,F55*($L$14-M55),G55*($L$14-M55)),2) -> 0 | L55: =ROUND((J55*K55),2) -> 0 | Q55: =ROUND(IF($Q$17=$P$17,P55,IF($Q$17="USD $",P55*$D$15,P55*$E$15))*E55,2) -> 0 | R55: =IFERROR(ROUND(S55/E55,2),0) -> 0 | S55: =ROUND(L55-Q55,2) -> 0 | T55: =IFERROR(((K55-(Q55/J55))/(Q55/J55)),0) -> 0 | U55: =IFERROR(((K55-(Q55/J55))/K55),0) -> 0
G56: =ROUND(IF($F$17="USD $", F56*$E$15,F56*$D$15),2) -> 0 | H56: =ROUND(IF($H$17=$G$17,E56*G56,E56*F56),2) -> 0 | J56: =E56 -> 0 | K56: =ROUND(IF($K$17=$F$17,F56*($L$14-M56),G56*($L$14-M56)),2) -> 0 | L56: =ROUND((J56*K56),2) -> 0 | Q56: =ROUND(IF($Q$17=$P$17,P56,IF($Q$17="USD $",P56*$D$15,P56*$E$15))*E56,2) -> 0 | R56: =IFERROR(ROUND(S56/E56,2),0) -> 0 | S56: =ROUND(L56-Q56,2) -> 0 | T56: =IFERROR(((K56-(Q56/J56))/(Q56/J56)),0) -> 0 | U56: =IFERROR(((K56-(Q56/J56))/K56),0) -> 0
G57: =ROUND(IF($F$17="USD $", F57*$E$15,F57*$D$15),2) -> 0 | H57: =ROUND(IF($H$17=$G$17,E57*G57,E57*F57),2) -> 0 | J57: =E57 -> 0 | K57: =ROUND(IF($K$17=$F$17,F57*($L$14-M57),G57*($L$14-M57)),2) -> 0 | L57: =ROUND((J57*K57),2) -> 0 | Q57: =ROUND(IF($Q$17=$P$17,P57,IF($Q$17="USD $",P57*$D$15,P57*$E$15))*E57,2) -> 0 | R57: =IFERROR(ROUND(S57/E57,2),0) -> 0 | S57: =ROUND(L57-Q57,2) -> 0 | T57: =IFERROR(((K57-(Q57/J57))/(Q57/J57)),0) -> 0 | U57: =IFERROR(((K57-(Q57/J57))/K57),0) -> 0
G58: =ROUND(IF($F$17="USD $", F58*$E$15,F58*$D$15),2) -> 0 | H58: =ROUND(IF($H$17=$G$17,E58*G58,E58*F58),2) -> 0 | J58: =E58 -> 0 | K58: =ROUND(IF($K$17=$F$17,F58*($L$14-M58),G58*($L$14-M58)),2) -> 0 | L58: =ROUND((J58*K58),2) -> 0 | Q58: =ROUND(IF($Q$17=$P$17,P58,IF($Q$17="USD $",P58*$D$15,P58*$E$15))*E58,2) -> 0 | R58: =IFERROR(ROUND(S58/E58,2),0) -> 0 | S58: =ROUND(L58-Q58,2) -> 0 | T58: =IFERROR(((K58-(Q58/J58))/(Q58/J58)),0) -> 0 | U58: =IFERROR(((K58-(Q58/J58))/K58),0) -> 0
... G128: =ROUND(IF($F$17="USD $", F128*$E$15,F128*$D$15),2) -> 0 | H128: =ROUND(IF($H$17=$G$17,E128*G128,E128*F128),2) -> 0 | J128: =E128 -> 0 | K128: =ROUND(IF($K$17=$F$17,F128*($L$14-M128),G128*($L$14-M128)),2) -> 0 | L128: =ROUND((J128*K128),2) -> 0 | Q128: =ROUND(IF($Q$17=$P$17,P128,IF($Q$17="USD $",P128*$D$15,P128*$E$15))*E128,2) -> 0 | R128: =IFERROR(ROUND(S128/E128,2),0) -> 0 | S128: =ROUND(L128-Q128,2) -> 0 | T128: =IFERROR(((K128-(Q128/J128))/(Q128/J128)),0) -> 0 | U128: =IFERROR(((K128-(Q128/J128))/K128),0) -> 0
D129: TOTALS | E129: =SUM(E18:E128) -> 49 | F129: =SUM(F18:F128) -> 77052.37 | G129: =SUM(G18:G128) -> 106332.27 | H129: =SUM(H18:H128) -> 114313.26 | J129: =SUM(J18:J128) -> 49 | K129: =SUM(K18:K128) -> 53166.2 | L129: =SUM(L18:L128) -> 57156.78 | P129: =SUM(P18:P128) -> 0 | Q129: =SUM(Q18:Q128) -> 0 | R129: =SUM(R18:R128) -> 53166.2 | S129: =SUM(S18:S128) -> 57156.78

Sheet CAT 963C LOADER
B1: CUSTOMER INFORMATION | D1: MACHINE INFORMATION | H1: MACHINE SERVICE HR INTERVALS | L1: SUMMARY | O1: =K17 -> CAD $ | R1: COMPLETED DEAL INFORMATION
B2: DATE: | D2: UNIT # | H2: ENGINE AIR | L2: OEM MSRP | O2: =H129 -> 0 | R2: SALES REP
B3: COMPANY: | D3: YEAR | H3: ENGINE OIL | L3: GQP LIST | O3: =L129 -> 0 | R3: ORDER PO #
B4: CUSTOMER: | D4: MAKE | H4: FUEL FILTERS | L4: $ SAVINGS | O4: =O2-O3 -> 0 | R4: PROJECT #
B5: PHONE: | D5: MODEL | H5: HYDRAULIC FILTERS | L5: % SAVINGS | O5: =IFERROR((O2-O3)/O2,"") | R5: CUST INVOICE #
B6: EMAIL: | D6: SERIAL NUMBER | H6: TRANSMISSION FILTERS | L6: TOTAL ORDER MARGIN | O6: =S129 -> 0 | R6: PAYMENT TYPE
B7: SALES REP: | D7: ENGINE SER NUMBER | H7: CAB FILTERS | L7: TOTAL ITEM COST | O7: =Q129 -> 0 | R7: DATE DELIVERED
D8: CURRENT HOURS | H8: UNDERCARRIAGE / TIRES | L8: TOTAL ORDER FREIGHT | O8: =IF(O1=P14,Q14,IF(P14="CAD $",Q14*D15,IF(P14="USD $",Q14*E15,0))) -> 0 | R8: TOTAL COST | S8: NET MARGIN | T8: NET MARKUP % | U8: NET MARGIN %
D9: USAGE/MONTH | L9: TOTAL CUSTOMS/BROKERAGE | O9: =U14 -> 0 | R9: =O7+O8+O9 -> 0 | S9: =O3-R9 -> 0 | T9: =IFERROR(((O3-R9)/R9),0) -> 0 | U9: =IFERROR(((O3-R9)/O3),0) -> 0
L10: TOTAL NUMBER PIECES | O10: =E129 -> 0
D11: ENTER EXCHANGE RATES $ | F11: OEM MSRP | J11: CUSTOMER SELL PRICE | O11: COST ANALYSIS | X11: CAD $
X12: USD $
F13: SHOW OEM MSRP ON QUOTE: | H13: YES | X13: YES
D14: CAD-USD | E14: USD-CAD | F14: OEM NAME | J14: CUSTOMER PRICE % OF OEM LIST | L14: 0.5 | O14: FREIGHT TOTAL ORDER | P14: USD $ | R14: CUSTOMS AND BROKERAGE % | S14: 0.025 | T14: BROKERAGE FEES | U14: =ROUND(Q129*S14,2) -> 0 | X14: NO
D15: =1/E15 -> 0.72463768 | E15: 1.38 | M15: ADDITIONAL +/- DISC % PER ITEM | O15: MARKUP LESS THAN 100% REQUIRES MANAGER APPROVAL
B16: PART NUMBER | C16: DESCRIPTION | D16: SERVICE INTERVAL | E16: QTY | F16: UNIT PRICE | H16: EXT AMOUNT | J16: QTY | K16: UNIT PRICE | L16: EXTENDED AMOUNT | O16: VENDOR | P16: COST EACH | Q16: EXTENDED COST | R16: MARGIN EACH | S16: EXTENDED MARGIN | T16: MARKUP % | U16: MARGIN %
F17: USD $ | G17: =IF(F17="USD $", "CAD $", "USD $") -> CAD $ | H17: =K17 -> CAD $ | K17: CAD $ | P17: USD $ | Q17: =K17 -> CAD $
C18: ENGINE OIL FILTER | G18: =ROUND(IF($F$17="USD $", F18*$E$15,F18*$D$15),2) -> 0 | H18: =ROUND(IF($H$17=$G$17,E18*G18,E18*F18),2) -> 0 | J18: =E18 -> 0 | K18: =ROUND(IF($K$17=$F$17,F18*($L$14-M18),G18*($L$14-M18)),2) -> 0 | L18: =ROUND((J18*K18),2) -> 0 | Q18: =ROUND(IF($Q$17=$P$17,P18,IF($Q$17="USD $",P18*$D$15,P18*$E$15))*E18,2) -> 0 | R18: =IFERROR(ROUND(S18/E18,2),0) -> 0 | S18: =ROUND(L18-Q18,2) -> 0 | T18: =IFERROR(((K18-(Q18/J18))/(Q18/J18)),0) -> 0 | U18: =IFERROR(((K18-(Q18/J18))/K18),0) -> 0 | Y18: 250
C19: FUEL FILTER | G19: =ROUND(IF($F$17="USD $", F19*$E$15,F19*$D$15),2) -> 0 | H19: =ROUND(IF($H$17=$G$17,E19*G19,E19*F19),2) -> 0 | J19: =E19 -> 0 | K19: =ROUND(IF($K$17=$F$17,F19*($L$14-M19),G19*($L$14-M19)),2) -> 0 | L19: =ROUND((J19*K19),2) -> 0 | Q19: =ROUND(IF($Q$17=$P$17,P19,IF($Q$17="USD $",P19*$D$15,P19*$E$15))*E19,2) -> 0 | R19: =IFERROR(ROUND(S19/E19,2),0) -> 0 | S19: =ROUND(L19-Q19,2) -> 0 | T19: =IFERROR(((K19-(Q19/J19))/(Q19/J19)),0) -> 0 | U19: =IFERROR(((K19-(Q19/J19))/K19),0) -> 0 | X19: GQP | Y19: 500
C20: FUEL WATER SEPARATOR FILTER | G20: =ROUND(IF($F$17="USD $", F20*$E$15,F20*$D$15),2) -> 0 | H20: =ROUND(IF($H$17=$G$17,E20*G20,E20*F20),2) -> 0 | J20: =E20 -> 0 | K20: =ROUND(IF($K$17=$F$17,F20*($L$14-M20),G20*($L$14-M20)),2) -> 0 | L20: =ROUND((J20*K20),2) -> 0 | Q20: =ROUND(IF($Q$17=$P$17,P20,IF($Q$17="USD $",P20*$D$15,P20*$E$15))*E20,2) -> 0 | R20: =IFERROR(ROUND(S20/E20,2),0) -> 0 | S20: =ROUND(L20-Q20,2) -> 0 | T20: =IFERROR(((K20-(Q20/J20))/(Q20/J20)),0) -> 0 | U20: =IFERROR(((K20-(Q20/J20))/K20),0) -> 0 | X20: CTP | Y20: 750
C21: HYDRAULIC FILTER | G21: =ROUND(IF($F$17="USD $", F21*$E$15,F21*$D$15),2) -> 0 | H21: =ROUND(IF($H$17=$G$17,E21*G21,E21*F21),2) -> 0 | J21: =E21 -> 0 | K21: =ROUND(IF($K$17=$F$17,F21*($L$14-M21),G21*($L$14-M21)),2) -> 0 | L21: =ROUND((J21*K21),2) -> 0 | Q21: =ROUND(IF($Q$17=$P$17,P21,IF($Q$17="USD $",P21*$D$15,P21*$E$15))*E21,2) -> 0 | R21: =IFERROR(ROUND(S21/E21,2),0) -> 0 | S21: =ROUND(L21-Q21,2) -> 0 | T21: =IFERROR(((K21-(Q21/J21))/(Q21/J21)),0) -> 0 | U21: =IFERROR(((K21-(Q21/J21))/K21),0) -> 0 | X21: BLMQ | Y21: 1000
C22: HYDRAULIC TRANSMISSION OIL FILTER | G22: =ROUND(IF($F$17="USD $", F22*$E$15,F22*$D$15),2) -> 0 | H22: =ROUND(IF($H$17=$G$17,E22*G22,E22*F22),2) -> 0 | J22: =E22 -> 0 | K22: =ROUND(IF($K$17=$F$17,F22*($L$14-M22),G22*($L$14-M22)),2) -> 0 | L22: =ROUND((J22*K22),2) -> 0 | Q22: =ROUND(IF($Q$17=$P$17,P22,IF($Q$17="USD $",P22*$D$15,P22*$E$15))*E22,2) -> 0 | R22: =IFERROR(ROUND(S22/E22,2),0) -> 0 | S22: =ROUND(L22-Q22,2) -> 0 | T22: =IFERROR(((K22-(Q22/J22))/(Q22/J22)),0) -> 0 | U22: =IFERROR(((K22-(Q22/J22))/K22),0) -> 0 | X22: CAT | Y22: 1200
C23: PRIMARY AIR FILTER | G23: =ROUND(IF($F$17="USD $", F23*$E$15,F23*$D$15),2) -> 0 | H23: =ROUND(IF($H$17=$G$17,E23*G23,E23*F23),2) -> 0 | J23: =E23 -> 0 | K23: =ROUND(IF($K$17=$F$17,F23*($L$14-M23),G23*($L$14-M23)),2) -> 0 | L23: =ROUND((J23*K23),2) -> 0 | Q23: =ROUND(IF($Q$17=$P$17,P23,IF($Q$17="USD $",P23*$D$15,P23*$E$15))*E23,2) -> 0 | R23: =IFERROR(ROUND(S23/E23,2),0) -> 0 | S23: =ROUND(L23-Q23,2) -> 0 | T23: =IFERROR(((K23-(Q23/J23))/(Q23/J23)),0) -> 0 | U23: =IFERROR(((K23-(Q23/J23))/K23),0) -> 0 | X23: FINNING | Y23: 2000
C24: SECONDARY AIR FILTER ELEMENT | G24: =ROUND(IF($F$17="USD $", F24*$E$15,F24*$D$15),2) -> 0 | H24: =ROUND(IF($H$17=$G$17,E24*G24,E24*F24),2) -> 0 | J24: =E24 -> 0 | K24: =ROUND(IF($K$17=$F$17,F24*($L$14-M24),G24*($L$14-M24)),2) -> 0 | L24: =ROUND((J24*K24),2) -> 0 | Q24: =ROUND(IF($Q$17=$P$17,P24,IF($Q$17="USD $",P24*$D$15,P24*$E$15))*E24,2) -> 0 | R24: =IFERROR(ROUND(S24/E24,2),0) -> 0 | S24: =ROUND(L24-Q24,2) -> 0 | T24: =IFERROR(((K24-(Q24/J24))/(Q24/J24)),0) -> 0 | U24: =IFERROR(((K24-(Q24/J24))/K24),0) -> 0 | X24: JD | Y24: 4000
C25: CABIN AIR FILTER ELEMENT | G25: =ROUND(IF($F$17="USD $", F25*$E$15,F25*$D$15),2) -> 0 | H25: =ROUND(IF($H$17=$G$17,E25*G25,E25*F25),2) -> 0 | J25: =E25 -> 0 | K25: =ROUND(IF($K$17=$F$17,F25*($L$14-M25),G25*($L$14-M25)),2) -> 0 | L25: =ROUND((J25*K25),2) -> 0 | Q25: =ROUND(IF($Q$17=$P$17,P25,IF($Q$17="USD $",P25*$D$15,P25*$E$15))*E25,2) -> 0 | R25: =IFERROR(ROUND(S25/E25,2),0) -> 0 | S25: =ROUND(L25-Q25,2) -> 0 | T25: =IFERROR(((K25-(Q25/J25))/(Q25/J25)),0) -> 0 | U25: =IFERROR(((K25-(Q25/J25))/K25),0) -> 0 | X25: BRANDT | Y25: 6000
C26: 12V 4D BCI BATTERY (19.3" X 8.6" X 9.9") | G26: =ROUND(IF($F$17="USD $", F26*$E$15,F26*$D$15),2) -> 0 | H26: =ROUND(IF($H$17=$G$17,E26*G26,E26*F26),2) -> 0 | J26: =E26 -> 0 | K26: =ROUND(IF($K$17=$F$17,F26*($L$14-M26),G26*($L$14-M26)),2) -> 0 | L26: =ROUND((J26*K26),2) -> 0 | Q26: =ROUND(IF($Q$17=$P$17,P26,IF($Q$17="USD $",P26*$D$15,P26*$E$15))*E26,2) -> 0 | R26: =IFERROR(ROUND(S26/E26,2),0) -> 0 | S26: =ROUND(L26-Q26,2) -> 0 | T26: =IFERROR(((K26-(Q26/J26))/(Q26/J26)),0) -> 0 | U26: =IFERROR(((K26-(Q26/J26))/K26),0) -> 0 | X26: PTI | Y26: 8000
G27: =ROUND(IF($F$17="USD $", F27*$E$15,F27*$D$15),2) -> 0 | H27: =ROUND(IF($H$17=$G$17,E27*G27,E27*F27),2) -> 0 | J27: =E27 -> 0 | K27: =ROUND(IF($K$17=$F$17,F27*($L$14-M27),G27*($L$14-M27)),2) -> 0 | L27: =ROUND((J27*K27),2) -> 0 | Q27: =ROUND(IF($Q$17=$P$17,P27,IF($Q$17="USD $",P27*$D$15,P27*$E$15))*E27,2) -> 0 | R27: =IFERROR(ROUND(S27/E27,2),0) -> 0 | S27: =ROUND(L27-Q27,2) -> 0 | T27: =IFERROR(((K27-(Q27/J27))/(Q27/J27)),0) -> 0 | U27: =IFERROR(((K27-(Q27/J27))/K27),0) -> 0 | X27: CONEQUIP | Y27: 10000
C28: ENGINE OVERHAUL KIT | G28: =ROUND(IF($F$17="USD $", F28*$E$15,F28*$D$15),2) -> 0 | H28: =ROUND(IF($H$17=$G$17,E28*G28,E28*F28),2) -> 0 | J28: =E28 -> 0 | K28: =ROUND(IF($K$17=$F$17,F28*($L$14-M28),G28*($L$14-M28)),2) -> 0 | L28: =ROUND((J28*K28),2) -> 0 | Q28: =ROUND(IF($Q$17=$P$17,P28,IF($Q$17="USD $",P28*$D$15,P28*$E$15))*E28,2) -> 0 | R28: =IFERROR(ROUND(S28/E28,2),0) -> 0 | S28: =ROUND(L28-Q28,2) -> 0 | T28: =IFERROR(((K28-(Q28/J28))/(Q28/J28)),0) -> 0 | U28: =IFERROR(((K28-(Q28/J28))/K28),0) -> 0 | X28: CANDY | Y28: AS REQ'D
C29: CAMSHAFT | G29: =ROUND(IF($F$17="USD $", F29*$E$15,F29*$D$15),2) -> 0 | H29: =ROUND(IF($H$17=$G$17,E29*G29,E29*F29),2) -> 0 | J29: =E29 -> 0 | K29: =ROUND(IF($K$17=$F$17,F29*($L$14-M29),G29*($L$14-M29)),2) -> 0 | L29: =ROUND((J29*K29),2) -> 0 | Q29: =ROUND(IF($Q$17=$P$17,P29,IF($Q$17="USD $",P29*$D$15,P29*$E$15))*E29,2) -> 0 | R29: =IFERROR(ROUND(S29/E29,2),0) -> 0 | S29: =ROUND(L29-Q29,2) -> 0 | T29: =IFERROR(((K29-(Q29/J29))/(Q29/J29)),0) -> 0 | U29: =IFERROR(((K29-(Q29/J29))/K29),0) -> 0 | X29: U/C
C30: CRANKSHAFT | G30: =ROUND(IF($F$17="USD $", F30*$E$15,F30*$D$15),2) -> 0 | H30: =ROUND(IF($H$17=$G$17,E30*G30,E30*F30),2) -> 0 | J30: =E30 -> 0 | K30: =ROUND(IF($K$17=$F$17,F30*($L$14-M30),G30*($L$14-M30)),2) -> 0 | L30: =ROUND((J30*K30),2) -> 0 | Q30: =ROUND(IF($Q$17=$P$17,P30,IF($Q$17="USD $",P30*$D$15,P30*$E$15))*E30,2) -> 0 | R30: =IFERROR(ROUND(S30/E30,2),0) -> 0 | S30: =ROUND(L30-Q30,2) -> 0 | T30: =IFERROR(((K30-(Q30/J30))/(Q30/J30)),0) -> 0 | U30: =IFERROR(((K30-(Q30/J30))/K30),0) -> 0
C31: CYLINDER HEAD | G31: =ROUND(IF($F$17="USD $", F31*$E$15,F31*$D$15),2) -> 0 | H31: =ROUND(IF($H$17=$G$17,E31*G31,E31*F31),2) -> 0 | J31: =E31 -> 0 | K31: =ROUND(IF($K$17=$F$17,F31*($L$14-M31),G31*($L$14-M31)),2) -> 0 | L31: =ROUND((J31*K31),2) -> 0 | Q31: =ROUND(IF($Q$17=$P$17,P31,IF($Q$17="USD $",P31*$D$15,P31*$E$15))*E31,2) -> 0 | R31: =IFERROR(ROUND(S31/E31,2),0) -> 0 | S31: =ROUND(L31-Q31,2) -> 0 | T31: =IFERROR(((K31-(Q31/J31))/(Q31/J31)),0) -> 0 | U31: =IFERROR(((K31-(Q31/J31))/K31),0) -> 0
C32: TURBOCHARGER | G32: =ROUND(IF($F$17="USD $", F32*$E$15,F32*$D$15),2) -> 0 | H32: =ROUND(IF($H$17=$G$17,E32*G32,E32*F32),2) -> 0 | J32: =E32 -> 0 | K32: =ROUND(IF($K$17=$F$17,F32*($L$14-M32),G32*($L$14-M32)),2) -> 0 | L32: =ROUND((J32*K32),2) -> 0 | Q32: =ROUND(IF($Q$17=$P$17,P32,IF($Q$17="USD $",P32*$D$15,P32*$E$15))*E32,2) -> 0 | R32: =IFERROR(ROUND(S32/E32,2),0) -> 0 | S32: =ROUND(L32-Q32,2) -> 0 | T32: =IFERROR(((K32-(Q32/J32))/(Q32/J32)),0) -> 0 | U32: =IFERROR(((K32-(Q32/J32))/K32),0) -> 0
C33: INJECTOR | G33: =ROUND(IF($F$17="USD $", F33*$E$15,F33*$D$15),2) -> 0 | H33: =ROUND(IF($H$17=$G$17,E33*G33,E33*F33),2) -> 0 | J33: =E33 -> 0 | K33: =ROUND(IF($K$17=$F$17,F33*($L$14-M33),G33*($L$14-M33)),2) -> 0 | L33: =ROUND((J33*K33),2) -> 0 | Q33: =ROUND(IF($Q$17=$P$17,P33,IF($Q$17="USD $",P33*$D$15,P33*$E$15))*E33,2) -> 0 | R33: =IFERROR(ROUND(S33/E33,2),0) -> 0 | S33: =ROUND(L33-Q33,2) -> 0 | T33: =IFERROR(((K33-(Q33/J33))/(Q33/J33)),0) -> 0 | U33: =IFERROR(((K33-(Q33/J33))/K33),0) -> 0
G34: =ROUND(IF($F$17="USD $", F34*$E$15,F34*$D$15),2) -> 0 | H34: =ROUND(IF($H$17=$G$17,E34*G34,E34*F34),2) -> 0 | J34: =E34 -> 0 | K34: =ROUND(IF($K$17=$F$17,F34*($L$14-M34),G34*($L$14-M34)),2) -> 0 | L34: =ROUND((J34*K34),2) -> 0 | Q34: =ROUND(IF($Q$17=$P$17,P34,IF($Q$17="USD $",P34*$D$15,P34*$E$15))*E34,2) -> 0 | R34: =IFERROR(ROUND(S34/E34,2),0) -> 0 | S34: =ROUND(L34-Q34,2) -> 0 | T34: =IFERROR(((K34-(Q34/J34))/(Q34/J34)),0) -> 0 | U34: =IFERROR(((K34-(Q34/J34))/K34),0) -> 0
C35: BUCKET AS GENERAL PURPOSE | G35: =ROUND(IF($F$17="USD $", F35*$E$15,F35*$D$15),2) -> 0 | H35: =ROUND(IF($H$17=$G$17,E35*G35,E35*F35),2) -> 0 | J35: =E35 -> 0 | K35: =ROUND(IF($K$17=$F$17,F35*($L$14-M35),G35*($L$14-M35)),2) -> 0 | L35: =ROUND((J35*K35),2) -> 0 | Q35: =ROUND(IF($Q$17=$P$17,P35,IF($Q$17="USD $",P35*$D$15,P35*$E$15))*E35,2) -> 0 | R35: =IFERROR(ROUND(S35/E35,2),0) -> 0 | S35: =ROUND(L35-Q35,2) -> 0 | T35: =IFERROR(((K35-(Q35/J35))/(Q35/J35)),0) -> 0 | U35: =IFERROR(((K35-(Q35/J35))/K35),0) -> 0
C36: TILT CYLINDER | G36: =ROUND(IF($F$17="USD $", F36*$E$15,F36*$D$15),2) -> 0 | H36: =ROUND(IF($H$17=$G$17,E36*G36,E36*F36),2) -> 0 | J36: =E36 -> 0 | K36: =ROUND(IF($K$17=$F$17,F36*($L$14-M36),G36*($L$14-M36)),2) -> 0 | L36: =ROUND((J36*K36),2) -> 0 | Q36: =ROUND(IF($Q$17=$P$17,P36,IF($Q$17="USD $",P36*$D$15,P36*$E$15))*E36,2) -> 0 | R36: =IFERROR(ROUND(S36/E36,2),0) -> 0 | S36: =ROUND(L36-Q36,2) -> 0 | T36: =IFERROR(((K36-(Q36/J36))/(Q36/J36)),0) -> 0 | U36: =IFERROR(((K36-(Q36/J36))/K36),0) -> 0
C37: LIFT CYLINDER | G37: =ROUND(IF($F$17="USD $", F37*$E$15,F37*$D$15),2) -> 0 | H37: =ROUND(IF($H$17=$G$17,E37*G37,E37*F37),2) -> 0 | J37: =E37 -> 0 | K37: =ROUND(IF($K$17=$F$17,F37*($L$14-M37),G37*($L$14-M37)),2) -> 0 | L37: =ROUND((J37*K37),2) -> 0 | Q37: =ROUND(IF($Q$17=$P$17,P37,IF($Q$17="USD $",P37*$D$15,P37*$E$15))*E37,2) -> 0 | R37: =IFERROR(ROUND(S37/E37,2),0) -> 0 | S37: =ROUND(L37-Q37,2) -> 0 | T37: =IFERROR(((K37-(Q37/J37))/(Q37/J37)),0) -> 0 | U37: =IFERROR(((K37-(Q37/J37))/K37),0) -> 0
C38: CUTTING EDGE | G38: =ROUND(IF($F$17="USD $", F38*$E$15,F38*$D$15),2) -> 0 | H38: =ROUND(IF($H$17=$G$17,E38*G38,E38*F38),2) -> 0 | J38: =E38 -> 0 | K38: =ROUND(IF($K$17=$F$17,F38*($L$14-M38),G38*($L$14-M38)),2) -> 0 | L38: =ROUND((J38*K38),2) -> 0 | Q38: =ROUND(IF($Q$17=$P$17,P38,IF($Q$17="USD $",P38*$D$15,P38*$E$15))*E38,2) -> 0 | R38: =IFERROR(ROUND(S38/E38,2),0) -> 0 | S38: =ROUND(L38-Q38,2) -> 0 | T38: =IFERROR(((K38-(Q38/J38))/(Q38/J38)),0) -> 0 | U38: =IFERROR(((K38-(Q38/J38))/K38),0) -> 0
C39: CUTTING EDGE | G39: =ROUND(IF($F$17="USD $", F39*$E$15,F39*$D$15),2) -> 0 | H39: =ROUND(IF($H$17=$G$17,E39*G39,E39*F39),2) -> 0 | J39: =E39 -> 0 | K39: =ROUND(IF($K$17=$F$17,F39*($L$14-M39),G39*($L$14-M39)),2) -> 0 | L39: =ROUND((J39*K39),2) -> 0 | Q39: =ROUND(IF($Q$17=$P$17,P39,IF($Q$17="USD $",P39*$D$15,P39*$E$15))*E39,2) -> 0 | R39: =IFERROR(ROUND(S39/E39,2),0) -> 0 | S39: =ROUND(L39-Q39,2) -> 0 | T39: =IFERROR(((K39-(Q39/J39))/(Q39/J39)),0) -> 0 | U39: =IFERROR(((K39-(Q39/J39))/K39),0) -> 0
C40: CUTTING EDGE | G40: =ROUND(IF($F$17="USD $", F40*$E$15,F40*$D$15),2) -> 0 | H40: =ROUND(IF($H$17=$G$17,E40*G40,E40*F40),2) -> 0 | J40: =E40 -> 0 | K40: =ROUND(IF($K$17=$F$17,F40*($L$14-M40),G40*($L$14-M40)),2) -> 0 | L40: =ROUND((J40*K40),2) -> 0 | Q40: =ROUND(IF($Q$17=$P$17,P40,IF($Q$17="USD $",P40*$D$15,P40*$E$15))*E40,2) -> 0 | R40: =IFERROR(ROUND(S40/E40,2),0) -> 0 | S40: =ROUND(L40-Q40,2) -> 0 | T40: =IFERROR(((K40-(Q40/J40))/(Q40/J40)),0) -> 0 | U40: =IFERROR(((K40-(Q40/J40))/K40),0) -> 0
C41: CUTTING EDGE | G41: =ROUND(IF($F$17="USD $", F41*$E$15,F41*$D$15),2) -> 0 | H41: =ROUND(IF($H$17=$G$17,E41*G41,E41*F41),2) -> 0 | J41: =E41 -> 0 | K41: =ROUND(IF($K$17=$F$17,F41*($L$14-M41),G41*($L$14-M41)),2) -> 0 | L41: =ROUND((J41*K41),2) -> 0 | Q41: =ROUND(IF($Q$17=$P$17,P41,IF($Q$17="USD $",P41*$D$15,P41*$E$15))*E41,2) -> 0 | R41: =IFERROR(ROUND(S41/E41,2),0) -> 0 | S41: =ROUND(L41-Q41,2) -> 0 | T41: =IFERROR(((K41-(Q41/J41))/(Q41/J41)),0) -> 0 | U41: =IFERROR(((K41-(Q41/J41))/K41),0) -> 0
C42: CUTTING EDGE | G42: =ROUND(IF($F$17="USD $", F42*$E$15,F42*$D$15),2) -> 0 | H42: =ROUND(IF($H$17=$G$17,E42*G42,E42*F42),2) -> 0 | J42: =E42 -> 0 | K42: =ROUND(IF($K$17=$F$17,F42*($L$14-M42),G42*($L$14-M42)),2) -> 0 | L42: =ROUND((J42*K42),2) -> 0 | Q42: =ROUND(IF($Q$17=$P$17,P42,IF($Q$17="USD $",P42*$D$15,P42*$E$15))*E42,2) -> 0 | R42: =IFERROR(ROUND(S42/E42,2),0) -> 0 | S42: =ROUND(L42-Q42,2) -> 0 | T42: =IFERROR(((K42-(Q42/J42))/(Q42/J42)),0) -> 0 | U42: =IFERROR(((K42-(Q42/J42))/K42),0) -> 0
C43: PLOW BOLT | G43: =ROUND(IF($F$17="USD $", F43*$E$15,F43*$D$15),2) -> 0 | H43: =ROUND(IF($H$17=$G$17,E43*G43,E43*F43),2) -> 0 | J43: =E43 -> 0 | K43: =ROUND(IF($K$17=$F$17,F43*($L$14-M43),G43*($L$14-M43)),2) -> 0 | L43: =ROUND((J43*K43),2) -> 0 | Q43: =ROUND(IF($Q$17=$P$17,P43,IF($Q$17="USD $",P43*$D$15,P43*$E$15))*E43,2) -> 0 | R43: =IFERROR(ROUND(S43/E43,2),0) -> 0 | S43: =ROUND(L43-Q43,2) -> 0 | T43: =IFERROR(((K43-(Q43/J43))/(Q43/J43)),0) -> 0 | U43: =IFERROR(((K43-(Q43/J43))/K43),0) -> 0
C44: NUT FULL | G44: =ROUND(IF($F$17="USD $", F44*$E$15,F44*$D$15),2) -> 0 | H44: =ROUND(IF($H$17=$G$17,E44*G44,E44*F44),2) -> 0 | J44: =E44 -> 0 | K44: =ROUND(IF($K$17=$F$17,F44*($L$14-M44),G44*($L$14-M44)),2) -> 0 | L44: =ROUND((J44*K44),2) -> 0 | Q44: =ROUND(IF($Q$17=$P$17,P44,IF($Q$17="USD $",P44*$D$15,P44*$E$15))*E44,2) -> 0 | R44: =IFERROR(ROUND(S44/E44,2),0) -> 0 | S44: =ROUND(L44-Q44,2) -> 0 | T44: =IFERROR(((K44-(Q44/J44))/(Q44/J44)),0) -> 0 | U44: =IFERROR(((K44-(Q44/J44))/K44),0) -> 0
C45: WASHER | G45: =ROUND(IF($F$17="USD $", F45*$E$15,F45*$D$15),2) -> 0 | H45: =ROUND(IF($H$17=$G$17,E45*G45,E45*F45),2) -> 0 | J45: =E45 -> 0 | K45: =ROUND(IF($K$17=$F$17,F45*($L$14-M45),G45*($L$14-M45)),2) -> 0 | L45: =ROUND((J45*K45),2) -> 0 | Q45: =ROUND(IF($Q$17=$P$17,P45,IF($Q$17="USD $",P45*$D$15,P45*$E$15))*E45,2) -> 0 | R45: =IFERROR(ROUND(S45/E45,2),0) -> 0 | S45: =ROUND(L45-Q45,2) -> 0 | T45: =IFERROR(((K45-(Q45/J45))/(Q45/J45)),0) -> 0 | U45: =IFERROR(((K45-(Q45/J45))/K45),0) -> 0
C46: TIP RETAINER | G46: =ROUND(IF($F$17="USD $", F46*$E$15,F46*$D$15),2) -> 0 | H46: =ROUND(IF($H$17=$G$17,E46*G46,E46*F46),2) -> 0 | J46: =E46 -> 0 | K46: =ROUND(IF($K$17=$F$17,F46*($L$14-M46),G46*($L$14-M46)),2) -> 0 | L46: =ROUND((J46*K46),2) -> 0 | Q46: =ROUND(IF($Q$17=$P$17,P46,IF($Q$17="USD $",P46*$D$15,P46*$E$15))*E46,2) -> 0 | R46: =IFERROR(ROUND(S46/E46,2),0) -> 0 | S46: =ROUND(L46-Q46,2) -> 0 | T46: =IFERROR(((K46-(Q46/J46))/(Q46/J46)),0) -> 0 | U46: =IFERROR(((K46-(Q46/J46))/K46),0) -> 0
C47: TIP | G47: =ROUND(IF($F$17="USD $", F47*$E$15,F47*$D$15),2) -> 0 | H47: =ROUND(IF($H$17=$G$17,E47*G47,E47*F47),2) -> 0 | J47: =E47 -> 0 | K47: =ROUND(IF($K$17=$F$17,F47*($L$14-M47),G47*($L$14-M47)),2) -> 0 | L47: =ROUND((J47*K47),2) -> 0 | Q47: =ROUND(IF($Q$17=$P$17,P47,IF($Q$17="USD $",P47*$D$15,P47*$E$15))*E47,2) -> 0 | R47: =IFERROR(ROUND(S47/E47,2),0) -> 0 | S47: =ROUND(L47-Q47,2) -> 0 | T47: =IFERROR(((K47-(Q47/J47))/(Q47/J47)),0) -> 0 | U47: =IFERROR(((K47-(Q47/J47))/K47),0) -> 0
G48: =ROUND(IF($F$17="USD $", F48*$E$15,F48*$D$15),2) -> 0 | H48: =ROUND(IF($H$17=$G$17,E48*G48,E48*F48),2) -> 0 | J48: =E48 -> 0 | K48: =ROUND(IF($K$17=$F$17,F48*($L$14-M48),G48*($L$14-M48)),2) -> 0 | L48: =ROUND((J48*K48),2) -> 0 | Q48: =ROUND(IF($Q$17=$P$17,P48,IF($Q$17="USD $",P48*$D$15,P48*$E$15))*E48,2) -> 0 | R48: =IFERROR(ROUND(S48/E48,2),0) -> 0 | S48: =ROUND(L48-Q48,2) -> 0 | T48: =IFERROR(((K48-(Q48/J48))/(Q48/J48)),0) -> 0 | U48: =IFERROR(((K48-(Q48/J48))/K48),0) -> 0
C49: SEAT GP | G49: =ROUND(IF($F$17="USD $", F49*$E$15,F49*$D$15),2) -> 0 | H49: =ROUND(IF($H$17=$G$17,E49*G49,E49*F49),2) -> 0 | J49: =E49 -> 0 | K49: =ROUND(IF($K$17=$F$17,F49*($L$14-M49),G49*($L$14-M49)),2) -> 0 | L49: =ROUND((J49*K49),2) -> 0 | Q49: =ROUND(IF($Q$17=$P$17,P49,IF($Q$17="USD $",P49*$D$15,P49*$E$15))*E49,2) -> 0 | R49: =IFERROR(ROUND(S49/E49,2),0) -> 0 | S49: =ROUND(L49-Q49,2) -> 0 | T49: =IFERROR(((K49-(Q49/J49))/(Q49/J49)),0) -> 0 | U49: =IFERROR(((K49-(Q49/J49))/K49),0) -> 0
C50: SEAT SUSPENSION | G50: =ROUND(IF($F$17="USD $", F50*$E$15,F50*$D$15),2) -> 0 | H50: =ROUND(IF($H$17=$G$17,E50*G50,E50*F50),2) -> 0 | J50: =E50 -> 0 | K50: =ROUND(IF($K$17=$F$17,F50*($L$14-M50),G50*($L$14-M50)),2) -> 0 | L50: =ROUND((J50*K50),2) -> 0 | Q50: =ROUND(IF($Q$17=$P$17,P50,IF($Q$17="USD $",P50*$D$15,P50*$E$15))*E50,2) -> 0 | R50: =IFERROR(ROUND(S50/E50,2),0) -> 0 | S50: =ROUND(L50-Q50,2) -> 0 | T50: =IFERROR(((K50-(Q50/J50))/(Q50/J50)),0) -> 0 | U50: =IFERROR(((K50-(Q50/J50))/K50),0) -> 0
G51: =ROUND(IF($F$17="USD $", F51*$E$15,F51*$D$15),2) -> 0 | H51: =ROUND(IF($H$17=$G$17,E51*G51,E51*F51),2) -> 0 | J51: =E51 -> 0 | K51: =ROUND(IF($K$17=$F$17,F51*($L$14-M51),G51*($L$14-M51)),2) -> 0 | L51: =ROUND((J51*K51),2) -> 0 | Q51: =ROUND(IF($Q$17=$P$17,P51,IF($Q$17="USD $",P51*$D$15,P51*$E$15))*E51,2) -> 0 | R51: =IFERROR(ROUND(S51/E51,2),0) -> 0 | S51: =ROUND(L51-Q51,2) -> 0 | T51: =IFERROR(((K51-(Q51/J51))/(Q51/J51)),0) -> 0 | U51: =IFERROR(((K51-(Q51/J51))/K51),0) -> 0
G52: =ROUND(IF($F$17="USD $", F52*$E$15,F52*$D$15),2) -> 0 | H52: =ROUND(IF($H$17=$G$17,E52*G52,E52*F52),2) -> 0 | J52: =E52 -> 0 | K52: =ROUND(IF($K$17=$F$17,F52*($L$14-M52),G52*($L$14-M52)),2) -> 0 | L52: =ROUND((J52*K52),2) -> 0 | Q52: =ROUND(IF($Q$17=$P$17,P52,IF($Q$17="USD $",P52*$D$15,P52*$E$15))*E52,2) -> 0 | R52: =IFERROR(ROUND(S52/E52,2),0) -> 0 | S52: =ROUND(L52-Q52,2) -> 0 | T52: =IFERROR(((K52-(Q52/J52))/(Q52/J52)),0) -> 0 | U52: =IFERROR(((K52-(Q52/J52))/K52),0) -> 0
G53: =ROUND(IF($F$17="USD $", F53*$E$15,F53*$D$15),2) -> 0 | H53: =ROUND(IF($H$17=$G$17,E53*G53,E53*F53),2) -> 0 | J53: =E53 -> 0 | K53: =ROUND(IF($K$17=$F$17,F53*($L$14-M53),G53*($L$14-M53)),2) -> 0 | L53: =ROUND((J53*K53),2) -> 0 | Q53: =ROUND(IF($Q$17=$P$17,P53,IF($Q$17="USD $",P53*$D$15,P53*$E$15))*E53,2) -> 0 | R53: =IFERROR(ROUND(S53/E53,2),0) -> 0 | S53: =ROUND(L53-Q53,2) -> 0 | T53: =IFERROR(((K53-(Q53/J53))/(Q53/J53)),0) -> 0 | U53: =IFERROR(((K53-(Q53/J53))/K53),0) -> 0
G54: =ROUND(IF($F$17="USD $", F54*$E$15,F54*$D$15),2) -> 0 | H54: =ROUND(IF($H$17=$G$17,E54*G54,E54*F54),2) -> 0 | J54: =E54 -> 0 | K54: =ROUND(IF($K$17=$F$17,F54*($L$14-M54),G54*($L$14-M54)),2) -> 0 | L54: =ROUND((J54*K54),2) -> 0 | Q54: =ROUND(IF($Q$17=$P$17,P54,IF($Q$17="USD $",P54*$D$15,P54*$E$15))*E54,2) -> 0 | R54: =IFERROR(ROUND(S54/E54,2),0) -> 0 | S54: =ROUND(L54-Q54,2) -> 0 | T54: =IFERROR(((K54-(Q54/J54))/(Q54/J54)),0) -> 0 | U54: =IFERROR(((K54-(Q54/J54))/K54),0) -> 0
G55: =ROUND(IF($F$17="USD $", F55*$E$15,F55*$D$15),2) -> 0 | H55: =ROUND(IF($H$17=$G$17,E55*G55,E55*F55),2) -> 0 | J55: =E55 -> 0 | K55: =ROUND(IF($K$17=$F$17,F55*($L$14-M55),G55*($L$14-M55)),2) -> 0 | L55: =ROUND((J55*K55),2) -> 0 | Q55: =ROUND(IF($Q$17=$P$17,P55,IF($Q$17="USD $",P55*$D$15,P55*$E$15))*E55,2) -> 0 | R55: =IFERROR(ROUND(S55/E55,2),0) -> 0 | S55: =ROUND(L55-Q55,2) -> 0 | T55: =IFERROR(((K55-(Q55/J55))/(Q55/J55)),0) -> 0 | U55: =IFERROR(((K55-(Q55/J55))/K55),0) -> 0
G56: =ROUND(IF($F$17="USD $", F56*$E$15,F56*$D$15),2) -> 0 | H56: =ROUND(IF($H$17=$G$17,E56*G56,E56*F56),2) -> 0 | J56: =E56 -> 0 | K56: =ROUND(IF($K$17=$F$17,F56*($L$14-M56),G56*($L$14-M56)),2) -> 0 | L56: =ROUND((J56*K56),2) -> 0 | Q56: =ROUND(IF($Q$17=$P$17,P56,IF($Q$17="USD $",P56*$D$15,P56*$E$15))*E56,2) -> 0 | R56: =IFERROR(ROUND(S56/E56,2),0) -> 0 | S56: =ROUND(L56-Q56,2) -> 0 | T56: =IFERROR(((K56-(Q56/J56))/(Q56/J56)),0) -> 0 | U56: =IFERROR(((K56-(Q56/J56))/K56),0) -> 0
G57: =ROUND(IF($F$17="USD $", F57*$E$15,F57*$D$15),2) -> 0 | H57: =ROUND(IF($H$17=$G$17,E57*G57,E57*F57),2) -> 0 | J57: =E57 -> 0 | K57: =ROUND(IF($K$17=$F$17,F57*($L$14-M57),G57*($L$14-M57)),2) -> 0 | L57: =ROUND((J57*K57),2) -> 0 | Q57: =ROUND(IF($Q$17=$P$17,P57,IF($Q$17="USD $",P57*$D$15,P57*$E$15))*E57,2) -> 0 | R57: =IFERROR(ROUND(S57/E57,2),0) -> 0 | S57: =ROUND(L57-Q57,2) -> 0 | T57: =IFERROR(((K57-(Q57/J57))/(Q57/J57)),0) -> 0 | U57: =IFERROR(((K57-(Q57/J57))/K57),0) -> 0
G58: =ROUND(IF($F$17="USD $", F58*$E$15,F58*$D$15),2) -> 0 | H58: =ROUND(IF($H$17=$G$17,E58*G58,E58*F58),2) -> 0 | J58: =E58 -> 0 | K58: =ROUND(IF($K$17=$F$17,F58*($L$14-M58),G58*($L$14-M58)),2) -> 0 | L58: =ROUND((J58*K58),2) -> 0 | Q58: =ROUND(IF($Q$17=$P$17,P58,IF($Q$17="USD $",P58*$D$15,P58*$E$15))*E58,2) -> 0 | R58: =IFERROR(ROUND(S58/E58,2),0) -> 0 | S58: =ROUND(L58-Q58,2) -> 0 | T58: =IFERROR(((K58-(Q58/J58))/(Q58/J58)),0) -> 0 | U58: =IFERROR(((K58-(Q58/J58))/K58),0) -> 0
G59: =ROUND(IF($F$17="USD $", F59*$E$15,F59*$D$15),2) -> 0 | H59: =ROUND(IF($H$17=$G$17,E59*G59,E59*F59),2) -> 0 | J59: =E59 -> 0 | K59: =ROUND(IF($K$17=$F$17,F59*($L$14-M59),G59*($L$14-M59)),2) -> 0 | L59: =ROUND((J59*K59),2) -> 0 | Q59: =ROUND(IF($Q$17=$P$17,P59,IF($Q$17="USD $",P59*$D$15,P59*$E$15))*E59,2) -> 0 | R59: =IFERROR(ROUND(S59/E59,2),0) -> 0 | S59: =ROUND(L59-Q59,2) -> 0 | T59: =IFERROR(((K59-(Q59/J59))/(Q59/J59)),0) -> 0 | U59: =IFERROR(((K59-(Q59/J59))/K59),0) -> 0
G60: =ROUND(IF($F$17="USD $", F60*$E$15,F60*$D$15),2) -> 0 | H60: =ROUND(IF($H$17=$G$17,E60*G60,E60*F60),2) -> 0 | J60: =E60 -> 0 | K60: =ROUND(IF($K$17=$F$17,F60*($L$14-M60),G60*($L$14-M60)),2) -> 0 | L60: =ROUND((J60*K60),2) -> 0 | Q60: =ROUND(IF($Q$17=$P$17,P60,IF($Q$17="USD $",P60*$D$15,P60*$E$15))*E60,2) -> 0 | R60: =IFERROR(ROUND(S60/E60,2),0) -> 0 | S60: =ROUND(L60-Q60,2) -> 0 | T60: =IFERROR(((K60-(Q60/J60))/(Q60/J60)),0) -> 0 | U60: =IFERROR(((K60-(Q60/J60))/K60),0) -> 0
G61: =ROUND(IF($F$17="USD $", F61*$E$15,F61*$D$15),2) -> 0 | H61: =ROUND(IF($H$17=$G$17,E61*G61,E61*F61),2) -> 0 | J61: =E61 -> 0 | K61: =ROUND(IF($K$17=$F$17,F61*($L$14-M61),G61*($L$14-M61)),2) -> 0 | L61: =ROUND((J61*K61),2) -> 0 | Q61: =ROUND(IF($Q$17=$P$17,P61,IF($Q$17="USD $",P61*$D$15,P61*$E$15))*E61,2) -> 0 | R61: =IFERROR(ROUND(S61/E61,2),0) -> 0 | S61: =ROUND(L61-Q61,2) -> 0 | T61: =IFERROR(((K61-(Q61/J61))/(Q61/J61)),0) -> 0 | U61: =IFERROR(((K61-(Q61/J61))/K61),0) -> 0
G62: =ROUND(IF($F$17="USD $", F62*$E$15,F62*$D$15),2) -> 0 | H62: =ROUND(IF($H$17=$G$17,E62*G62,E62*F62),2) -> 0 | J62: =E62 -> 0 | K62: =ROUND(IF($K$17=$F$17,F62*($L$14-M62),G62*($L$14-M62)),2) -> 0 | L62: =ROUND((J62*K62),2) -> 0 | Q62: =ROUND(IF($Q$17=$P$17,P62,IF($Q$17="USD $",P62*$D$15,P62*$E$15))*E62,2) -> 0 | R62: =IFERROR(ROUND(S62/E62,2),0) -> 0 | S62: =ROUND(L62-Q62,2) -> 0 | T62: =IFERROR(((K62-(Q62/J62))/(Q62/J62)),0) -> 0 | U62: =IFERROR(((K62-(Q62/J62))/K62),0) -> 0
... G128: =ROUND(IF($F$17="USD $", F128*$E$15,F128*$D$15),2) -> 0 | H128: =ROUND(IF($H$17=$G$17,E128*G128,E128*F128),2) -> 0 | J128: =E128 -> 0 | K128: =ROUND(IF($K$17=$F$17,F128*($L$14-M128),G128*($L$14-M128)),2) -> 0 | L128: =ROUND((J128*K128),2) -> 0 | Q128: =ROUND(IF($Q$17=$P$17,P128,IF($Q$17="USD $",P128*$D$15,P128*$E$15))*E128,2) -> 0 | R128: =IFERROR(ROUND(S128/E128,2),0) -> 0 | S128: =ROUND(L128-Q128,2) -> 0 | T128: =IFERROR(((K128-(Q128/J128))/(Q128/J128)),0) -> 0 | U128: =IFERROR(((K128-(Q128/J128))/K128),0) -> 0
D129: TOTALS | E129: =SUM(E18:E128) -> 0 | F129: =SUM(F18:F128) -> 0 | G129: =SUM(G18:G128) -> 0 | H129: =SUM(H18:H128) -> 0 | J129: =SUM(J18:J128) -> 0 | K129: =SUM(K18:K128) -> 0 | L129: =SUM(L18:L128) -> 0 | P129: =SUM(P18:P128) -> 0 | Q129: =SUM(Q18:Q128) -> 0 | R129: =SUM(R18:R128) -> 0 | S129: =SUM(S18:S128) -> 0

Sheet RFQ
D1: REQUEST FOR QUOTE (RFQ)
B7: COMPANY: | D7: DATE: | E7: ='CAT 963C LOADER'!C2 -> 0
B8: CUSTOMER | D8: MACHINE INFORMATION
B9: PHONE NUMBER: | D9: YEAR | E9: ='CAT 963C LOADER'!F2 -> 0
B10: EMAIL ADDRESS: | D10: MAKE | E10: ='CAT 963C LOADER'!F3 -> 0
B11: BILLING ADDRESS: | D11: MODEL | E11: ='CAT 963C LOADER'!F4 -> 0
D12: SERIAL NUM | E12: ='CAT 963C LOADER'!F5 -> 0
D13: HOURS | E13: ='CAT 963C LOADER'!F8 -> 0
B14: SHIPPING ADDRESS: | D14: SALES REP: | E14: ='CAT 963C LOADER'!C7 -> 0
D15: PO NUMBER
B17: PART NUMBER | C17: DESCRIPTION | D17: QTY | E17: PRICE / UNIT | F17: TOTAL
B18: ='CAT 963C LOADER'!B18 -> 0 | C18: ='CAT 963C LOADER'!C18 -> ENGINE OIL FILTER | D18: ='CAT 963C LOADER'!E18 -> 0 | F18: =D18*E18 -> 0
B19: ='CAT 963C LOADER'!B19 -> 0 | C19: ='CAT 963C LOADER'!C19 -> FUEL FILTER | D19: ='CAT 963C LOADER'!E19 -> 0 | F19: =D19*E19 -> 0
B20: ='CAT 963C LOADER'!B20 -> 0 | C20: ='CAT 963C LOADER'!C20 -> FUEL WATER SEPARATOR FILTER | D20: ='CAT 963C LOADER'!E20 -> 0 | F20: =D20*E20 -> 0
B21: ='CAT 963C LOADER'!B21 -> 0 | C21: ='CAT 963C LOADER'!C21 -> HYDRAULIC FILTER | D21: ='CAT 963C LOADER'!E21 -> 0 | F21: =D21*E21 -> 0
B22: ='CAT 963C LOADER'!B22 -> 0 | C22: ='CAT 963C LOADER'!C22 -> HYDRAULIC TRANSMISSION OIL FILTER | D22: ='CAT 963C LOADER'!E22 -> 0 | F22: =D22*E22 -> 0
B23: ='CAT 963C LOADER'!B23 -> 0 | C23: ='CAT 963C LOADER'!C23 -> PRIMARY AIR FILTER | D23: ='CAT 963C LOADER'!E23 -> 0 | F23: =D23*E23 -> 0
B24: ='CAT 963C LOADER'!B24 -> 0 | C24: ='CAT 963C LOADER'!C24 -> SECONDARY AIR FILTER ELEMENT | D24: ='CAT 963C LOADER'!E24 -> 0 | F24: =D24*E24 -> 0
B25: ='CAT 963C LOADER'!B25 -> 0 | C25: ='CAT 963C LOADER'!C25 -> CABIN AIR FILTER ELEMENT | D25: ='CAT 963C LOADER'!E25 -> 0 | F25: =D25*E25 -> 0
B26: ='CAT 963C LOADER'!B26 -> 0 | C26: ='CAT 963C LOADER'!C26 -> 12V 4D BCI BATTERY (19.3" X 8.6" X 9.9") | D26: ='CAT 963C LOADER'!E26 -> 0 | F26: =D26*E26 -> 0
B27: ='CAT 963C LOADER'!B27 -> 0 | C27: ='CAT 963C LOADER'!C27 -> 0 | D27: ='CAT 963C LOADER'!E27 -> 0 | F27: =D27*E27 -> 0
B28: ='CAT 963C LOADER'!B28 -> 0 | C28: ='CAT 963C LOADER'!C28 -> ENGINE OVERHAUL KIT | D28: ='CAT 963C LOADER'!E28 -> 0 | F28: =D28*E28 -> 0
B29: ='CAT 963C LOADER'!B29 -> 0 | C29: ='CAT 963C LOADER'!C29 -> CAMSHAFT | D29: ='CAT 963C LOADER'!E29 -> 0 | F29: =D29*E29 -> 0
... B128: ='CAT 963C LOADER'!B128 -> 0 | C128: ='CAT 963C LOADER'!C128 -> 0 | D128: ='CAT 963C LOADER'!E128 -> 0 | F128: =D128*E128 -> 0
E129: Subtotal | F129: =SUM(F18:F125) -> 0
B130: Please quote all parts and quantities included on this form. | E130: Shipping | F130: 0
E131: Customs/BrokerFee | F131: 0
B132: Global Wholesale Machinery Inc. | E132: Total | F132: =SUM(F129:F131) -> 0
B133: 2808 5th Street, | E133: GST | F133: =ROUND(F132*0.05,2) -> 0
B134: Nisku AB T9E 0H1 | E134: PST / QST
E135: Grand Total | F135: =SUM(F132:F134) -> 0

Sheet QUOTE
D1: CUSTOMER PARTS QUOTE
B7: COMPANY: | C7: ='CAT 963C LOADER'!C3 -> 0 | D7: DATE: | E7: ='CAT 963C LOADER'!C2 -> 0
B8: CUSTOMER | C8: ='CAT 963C LOADER'!C4 -> 0 | D8: MACHINE INFORMATION
B9: PHONE NUMBER: | C9: ='CAT 963C LOADER'!C5 -> 0 | D9: YEAR: | E9: ='CAT 963C LOADER'!F3 -> 0 | F9: UNIT #: | G9: ='CAT 963C LOADER'!F2 -> 0
B10: EMAIL ADDRESS: | C10: ='CAT 963C LOADER'!C6 -> 0 | D10: MAKE: | E10: ='CAT 963C LOADER'!F4 -> 0
B11: BILLING ADDRESS: | D11: MODEL: | E11: ='CAT 963C LOADER'!F5 -> 0
D12: SERIAL NUM: | E12: ='CAT 963C LOADER'!F6 -> 0
D13: HOURS: | E13: ='CAT 963C LOADER'!F8 -> 0
B14: SHIPPING ADDRESS: | D14: SALES REP: | E14: ='CAT 963C LOADER'!C7 -> 0
D15: PO NUMBER:
E16: ='CAT 963C LOADER'!K17 -> CAD $
B17: PART NUMBER | C17: DESCRIPTION | D17: QTY | E17: OEM MSRP / UNIT | F17: GQP PRICE / UNIT | G17: TOTAL
B18: ='CAT 963C LOADER'!B18 -> 0 | C18: ='CAT 963C LOADER'!C18 -> ENGINE OIL FILTER | D18: ='CAT 963C LOADER'!E18 -> 0 | E18: =IFERROR('CAT 963C LOADER'!H18/'CAT 963C LOADER'!E18,0) -> 0 | F18: ='CAT 963C LOADER'!K18 -> 0 | G18: =D18*F18 -> 0
B19: ='CAT 963C LOADER'!B19 -> 0 | C19: ='CAT 963C LOADER'!C19 -> FUEL FILTER | D19: ='CAT 963C LOADER'!E19 -> 0 | E19: =IFERROR('CAT 963C LOADER'!H19/'CAT 963C LOADER'!E19,0) -> 0 | F19: ='CAT 963C LOADER'!K19 -> 0 | G19: =D19*F19 -> 0
B20: ='CAT 963C LOADER'!B20 -> 0 | C20: ='CAT 963C LOADER'!C20 -> FUEL WATER SEPARATOR FILTER | D20: ='CAT 963C LOADER'!E20 -> 0 | E20: =IFERROR('CAT 963C LOADER'!H20/'CAT 963C LOADER'!E20,0) -> 0 | F20: ='CAT 963C LOADER'!K20 -> 0 | G20: =D20*F20 -> 0
B21: ='CAT 963C LOADER'!B21 -> 0 | C21: ='CAT 963C LOADER'!C21 -> HYDRAULIC FILTER | D21: ='CAT 963C LOADER'!E21 -> 0 | E21: =IFERROR('CAT 963C LOADER'!H21/'CAT 963C LOADER'!E21,0) -> 0 | F21: ='CAT 963C LOADER'!K21 -> 0 | G21: =D21*F21 -> 0
B22: ='CAT 963C LOADER'!B22 -> 0 | C22: ='CAT 963C LOADER'!C22 -> HYDRAULIC TRANSMISSION OIL FILTER | D22: ='CAT 963C LOADER'!E22 -> 0 | E22: =IFERROR('CAT 963C LOADER'!H22/'CAT 963C LOADER'!E22,0) -> 0 | F22: ='CAT 963C LOADER'!K22 -> 0 | G22: =D22*F22 -> 0
B23: ='CAT 963C LOADER'!B23 -> 0 | C23: ='CAT 963C LOADER'!C23 -> PRIMARY AIR FILTER | D23: ='CAT 963C LOADER'!E23 -> 0 | E23: =IFERROR('CAT 963C LOADER'!H23/'CAT 963C LOADER'!E23,0) -> 0 | F23: ='CAT 963C LOADER'!K23 -> 0 | G23: =D23*F23 -> 0
B24: ='CAT 963C LOADER'!B24 -> 0 | C24: ='CAT 963C LOADER'!C24 -> SECONDARY AIR FILTER ELEMENT | D24: ='CAT 963C LOADER'!E24 -> 0 | E24: =IFERROR('CAT 963C LOADER'!H24/'CAT 963C LOADER'!E24,0) -> 0 | F24: ='CAT 963C LOADER'!K24 -> 0 | G24: =D24*F24 -> 0
B25: ='CAT 963C LOADER'!B25 -> 0 | C25: ='CAT 963C LOADER'!C25 -> CABIN AIR FILTER ELEMENT | D25: ='CAT 963C LOADER'!E25 -> 0 | E25: =IFERROR('CAT 963C LOADER'!H25/'CAT 963C LOADER'!E25,0) -> 0 | F25: ='CAT 963C LOADER'!K25 -> 0 | G25: =D25*F25 -> 0
B26: ='CAT 963C LOADER'!B26 -> 0 | C26: ='CAT 963C LOADER'!C26 -> 12V 4D BCI BATTERY (19.3" X 8.6" X 9.9") | D26: ='CAT 963C LOADER'!E26 -> 0 | E26: =IFERROR('CAT 963C LOADER'!H26/'CAT 963C LOADER'!E26,0) -> 0 | F26: ='CAT 963C LOADER'!K26 -> 0 | G26: =D26*F26 -> 0
B27: ='CAT 963C LOADER'!B27 -> 0 | C27: ='CAT 963C LOADER'!C27 -> 0 | D27: ='CAT 963C LOADER'!E27 -> 0 | E27: =IFERROR('CAT 963C LOADER'!H27/'CAT 963C LOADER'!E27,0) -> 0 | F27: ='CAT 963C LOADER'!K27 -> 0 | G27: =D27*F27 -> 0
B28: ='CAT 963C LOADER'!B28 -> 0 | C28: ='CAT 963C LOADER'!C28 -> ENGINE OVERHAUL KIT | D28: ='CAT 963C LOADER'!E28 -> 0 | E28: =IFERROR('CAT 963C LOADER'!H28/'CAT 963C LOADER'!E28,0) -> 0 | F28: ='CAT 963C LOADER'!K28 -> 0 | G28: =D28*F28 -> 0
B29: ='CAT 963C LOADER'!B29 -> 0 | C29: ='CAT 963C LOADER'!C29 -> CAMSHAFT | D29: ='CAT 963C LOADER'!E29 -> 0 | E29: =IFERROR('CAT 963C LOADER'!H29/'CAT 963C LOADER'!E29,0) -> 0 | F29: ='CAT 963C LOADER'!K29 -> 0 | G29: =D29*F29 -> 0
... B53: ='CAT 963C LOADER'!B53 -> 0 | C53: ='CAT 963C LOADER'!C53 -> 0 | D53: ='CAT 963C LOADER'!E53 -> 0 | E53: =IFERROR('CAT 963C LOADER'!H53/'CAT 963C LOADER'!E53,0) -> 0 | F53: ='CAT 963C LOADER'!K53 -> 0 | G53: =D53*F53 -> 0
E54: Quote valid for 14 days, shipping subject to delays in supply chain. Labour rate subject to change. Labour times quoted for repairs are estimates only, actual repair times subject to change, any changes will be communicated and agreed to by both the customer and Global Wholesale Machinery Inc. Credit Card Payment Subject to 2.5% Processing Fee.
D60: CUSTOMER SERVICE QUOTE
B66: =IF('CAT 963C LOADER'!C3="",'CAT 963C LOADER'!B4,'CAT 963C LOADER'!B3) -> CUSTOMER: | C66: =IF('CAT 963C LOADER'!C3="",'CAT 963C LOADER'!C4,'CAT 963C LOADER'!C3) -> 0 | D66: DATE: | E66: ='CAT 963C LOADER'!C2 -> 0
E67: ='CAT 963C LOADER'!#REF! -> #REF!
B68: PART NUMBER | C68: DESCRIPTION | D68: QTY | E68: OEM MSRP / UNIT | F68: GQP PRICE / UNIT | G68: TOTAL
B69: ='CAT 963C LOADER'!B54 -> 0 | C69: ='CAT 963C LOADER'!C54 -> 0 | D69: ='CAT 963C LOADER'!E54 -> 0 | E69: =IFERROR('CAT 963C LOADER'!H54/'CAT 963C LOADER'!E54,0) -> 0 | F69: ='CAT 963C LOADER'!K54 -> 0 | G69: =D69*F69 -> 0
B70: ='CAT 963C LOADER'!B55 -> 0 | C70: ='CAT 963C LOADER'!C55 -> 0 | D70: ='CAT 963C LOADER'!E55 -> 0 | E70: =IFERROR('CAT 963C LOADER'!H55/'CAT 963C LOADER'!E55,0) -> 0 | F70: ='CAT 963C LOADER'!K55 -> 0 | G70: =D70*F70 -> 0
B71: ='CAT 963C LOADER'!B56 -> 0 | C71: ='CAT 963C LOADER'!C56 -> 0 | D71: ='CAT 963C LOADER'!E56 -> 0 | E71: =IFERROR('CAT 963C LOADER'!H56/'CAT 963C LOADER'!E56,0) -> 0 | F71: ='CAT 963C LOADER'!K56 -> 0 | G71: =D71*F71 -> 0
B72: ='CAT 963C LOADER'!B57 -> 0 | C72: ='CAT 963C LOADER'!C57 -> 0 | D72: ='CAT 963C LOADER'!E57 -> 0 | E72: =IFERROR('CAT 963C LOADER'!H57/'CAT 963C LOADER'!E57,0) -> 0 | F72: ='CAT 963C LOADER'!K57 -> 0 | G72: =D72*F72 -> 0
B73: ='CAT 963C LOADER'!B58 -> 0 | C73: ='CAT 963C LOADER'!C58 -> 0 | D73: ='CAT 963C LOADER'!E58 -> 0 | E73: =IFERROR('CAT 963C LOADER'!H58/'CAT 963C LOADER'!E58,0) -> 0 | F73: ='CAT 963C LOADER'!K58 -> 0 | G73: =D73*F73 -> 0
B74: ='CAT 963C LOADER'!B59 -> 0 | C74: ='CAT 963C LOADER'!C59 -> 0 | D74: ='CAT 963C LOADER'!E59 -> 0 | E74: =IFERROR('CAT 963C LOADER'!H59/'CAT 963C LOADER'!E59,0) -> 0 | F74: ='CAT 963C LOADER'!K59 -> 0 | G74: =D74*F74 -> 0
B75: ='CAT 963C LOADER'!B60 -> 0 | C75: ='CAT 963C LOADER'!C60 -> 0 | D75: ='CAT 963C LOADER'!E60 -> 0 | E75: =IFERROR('CAT 963C LOADER'!H60/'CAT 963C LOADER'!E60,0) -> 0 | F75: ='CAT 963C LOADER'!K60 -> 0 | G75: =D75*F75 -> 0
B76: ='CAT 963C LOADER'!B61 -> 0 | C76: ='CAT 963C LOADER'!C61 -> 0 | D76: ='CAT 963C LOADER'!E61 -> 0 | E76: =IFERROR('CAT 963C LOADER'!H61/'CAT 963C LOADER'!E61,0) -> 0 | F76: ='CAT 963C LOADER'!K61 -> 0 | G76: =D76*F76 -> 0
B77: ='CAT 963C LOADER'!B62 -> 0 | C77: ='CAT 963C LOADER'!C62 -> 0 | D77: ='CAT 963C LOADER'!E62 -> 0 | E77: =IFERROR('CAT 963C LOADER'!H62/'CAT 963C LOADER'!E62,0) -> 0 | F77: ='CAT 963C LOADER'!K62 -> 0 | G77: =D77*F77 -> 0
B78: ='CAT 963C LOADER'!B63 -> 0 | C78: ='CAT 963C LOADER'!C63 -> 0 | D78: ='CAT 963C LOADER'!E63 -> 0 | E78: =IFERROR('CAT 963C LOADER'!H63/'CAT 963C LOADER'!E63,0) -> 0 | F78: ='CAT 963C LOADER'!K63 -> 0 | G78: =D78*F78 -> 0
B79: ='CAT 963C LOADER'!B64 -> 0 | C79: ='CAT 963C LOADER'!C64 -> 0 | D79: ='CAT 963C LOADER'!E64 -> 0 | E79: =IFERROR('CAT 963C LOADER'!H64/'CAT 963C LOADER'!E64,0) -> 0 | F79: ='CAT 963C LOADER'!K64 -> 0 | G79: =D79*F79 -> 0
B80: ='CAT 963C LOADER'!B65 -> 0 | C80: ='CAT 963C LOADER'!C65 -> 0 | D80: ='CAT 963C LOADER'!E65 -> 0 | E80: =IFERROR('CAT 963C LOADER'!H65/'CAT 963C LOADER'!E65,0) -> 0 | F80: ='CAT 963C LOADER'!K65 -> 0 | G80: =D80*F80 -> 0
... B113: ='CAT 963C LOADER'!B98 -> 0 | C113: ='CAT 963C LOADER'!C98 -> 0 | D113: ='CAT 963C LOADER'!E98 -> 0 | E113: =IFERROR('CAT 963C LOADER'!H98/'CAT 963C LOADER'!E98,0) -> 0 | F113: ='CAT 963C LOADER'!K98 -> 0 | G113: =D113*F113 -> 0
E114: Quote valid for 14 days, shipping subject to delays in supply chain. Labour rate subject to change. Labour times quoted for repairs are estimates only, actual repair times subject to change, any changes will be communicated and agreed to by both the customer and Global Wholesale Machinery Inc. Credit Card Payment Subject to 2.5% Processing Fee.
D120: CUSTOMER SERVICE QUOTE
B126: =IF('CAT 963C LOADER'!C3="",'CAT 963C LOADER'!B4,'CAT 963C LOADER'!B3) -> CUSTOMER: | C126: =IF('CAT 963C LOADER'!C3="",'CAT 963C LOADER'!C4,'CAT 963C LOADER'!C3) -> 0 | D126: DATE: | E126: ='CAT 963C LOADER'!C2 -> 0
E127: ='CAT 963C LOADER'!K17 -> CAD $
B128: PART NUMBER | C128: DESCRIPTION | D128: QTY | E128: OEM MSRP / UNIT | F128: GQP PRICE / UNIT | G128: TOTAL
B129: ='CAT 963C LOADER'!B99 -> 0 | C129: ='CAT 963C LOADER'!C99 -> 0 | D129: ='CAT 963C LOADER'!E99 -> 0 | E129: =IFERROR('CAT 963C LOADER'!H99/'CAT 963C LOADER'!E99,0) -> 0 | F129: ='CAT 963C LOADER'!K99 -> 0 | G129: =D129*F129 -> 0
B130: ='CAT 963C LOADER'!B100 -> 0 | C130: ='CAT 963C LOADER'!C100 -> 0 | D130: ='CAT 963C LOADER'!E100 -> 0 | E130: =IFERROR('CAT 963C LOADER'!H100/'CAT 963C LOADER'!E100,0) -> 0 | F130: ='CAT 963C LOADER'!K100 -> 0 | G130: =D130*F130 -> 0
B131: ='CAT 963C LOADER'!B101 -> 0 | C131: ='CAT 963C LOADER'!C101 -> 0 | D131: ='CAT 963C LOADER'!E101 -> 0 | E131: =IFERROR('CAT 963C LOADER'!H101/'CAT 963C LOADER'!E101,0) -> 0 | F131: ='CAT 963C LOADER'!K101 -> 0 | G131: =D131*F131 -> 0
B132: ='CAT 963C LOADER'!B102 -> 0 | C132: ='CAT 963C LOADER'!C102 -> 0 | D132: ='CAT 963C LOADER'!E102 -> 0 | E132: =IFERROR('CAT 963C LOADER'!H102/'CAT 963C LOADER'!E102,0) -> 0 | F132: ='CAT 963C LOADER'!K102 -> 0 | G132: =D132*F132 -> 0
B133: ='CAT 963C LOADER'!B103 -> 0 | C133: ='CAT 963C LOADER'!C103 -> 0 | D133: ='CAT 963C LOADER'!E103 -> 0 | E133: =IFERROR('CAT 963C LOADER'!H103/'CAT 963C LOADER'!E103,0) -> 0 | F133: ='CAT 963C LOADER'!K103 -> 0 | G133: =D133*F133 -> 0
B134: ='CAT 963C LOADER'!B104 -> 0 | C134: ='CAT 963C LOADER'!C104 -> 0 | D134: ='CAT 963C LOADER'!E104 -> 0 | E134: =IFERROR('CAT 963C LOADER'!H104/'CAT 963C LOADER'!E104,0) -> 0 | F134: ='CAT 963C LOADER'!K104 -> 0 | G134: =D134*F134 -> 0
B135: ='CAT 963C LOADER'!B105 -> 0 | C135: ='CAT 963C LOADER'!C105 -> 0 | D135: ='CAT 963C LOADER'!E105 -> 0 | E135: =IFERROR('CAT 963C LOADER'!H105/'CAT 963C LOADER'!E105,0) -> 0 | F135: ='CAT 963C LOADER'!K105 -> 0 | G135: =D135*F135 -> 0
B136: ='CAT 963C LOADER'!B106 -> 0 | C136: ='CAT 963C LOADER'!C106 -> 0 | D136: ='CAT 963C LOADER'!E106 -> 0 | E136: =IFERROR('CAT 963C LOADER'!H106/'CAT 963C LOADER'!E106,0) -> 0 | F136: ='CAT 963C LOADER'!K106 -> 0 | G136: =D136*F136 -> 0
B137: ='CAT 963C LOADER'!B107 -> 0 | C137: ='CAT 963C LOADER'!C107 -> 0 | D137: ='CAT 963C LOADER'!E107 -> 0 | E137: =IFERROR('CAT 963C LOADER'!H107/'CAT 963C LOADER'!E107,0) -> 0 | F137: ='CAT 963C LOADER'!K107 -> 0 | G137: =D137*F137 -> 0
B138: ='CAT 963C LOADER'!B108 -> 0 | C138: ='CAT 963C LOADER'!C108 -> 0 | D138: ='CAT 963C LOADER'!E108 -> 0 | E138: =IFERROR('CAT 963C LOADER'!H108/'CAT 963C LOADER'!E108,0) -> 0 | F138: ='CAT 963C LOADER'!K108 -> 0 | G138: =D138*F138 -> 0
B139: ='CAT 963C LOADER'!B109 -> 0 | C139: ='CAT 963C LOADER'!C109 -> 0 | D139: ='CAT 963C LOADER'!E109 -> 0 | E139: =IFERROR('CAT 963C LOADER'!H109/'CAT 963C LOADER'!E109,0) -> 0 | F139: ='CAT 963C LOADER'!K109 -> 0 | G139: =D139*F139 -> 0
B140: ='CAT 963C LOADER'!B110 -> 0 | C140: ='CAT 963C LOADER'!C110 -> 0 | D140: ='CAT 963C LOADER'!E110 -> 0 | E140: =IFERROR('CAT 963C LOADER'!H110/'CAT 963C LOADER'!E110,0) -> 0 | F140: ='CAT 963C LOADER'!K110 -> 0 | G140: =D140*F140 -> 0
... B158: ='CAT 963C LOADER'!B128 -> 0 | C158: ='CAT 963C LOADER'!C128 -> 0 | D158: ='CAT 963C LOADER'!E128 -> 0 | E158: =IFERROR('CAT 963C LOADER'!H128/'CAT 963C LOADER'!E128,0) -> 0 | F158: ='CAT 963C LOADER'!K128 -> 0 | G158: =D158*F158 -> 0
B159: ='CAT 963C LOADER'!B129 -> 0 | C159: ='CAT 963C LOADER'!C129 -> 0 | G159: =D159*F159 -> 0
B160: ='CAT 963C LOADER'!B130 -> 0 | C160: ='CAT 963C LOADER'!C130 -> 0 | G160: =D160*F160 -> 0
B161: ='CAT 963C LOADER'!B131 -> 0 | C161: ='CAT 963C LOADER'!C131 -> 0 | G161: =D161*F161 -> 0
B162: ='CAT 963C LOADER'!B132 -> 0 | C162: ='CAT 963C LOADER'!C132 -> 0 | G162: =D162*F162 -> 0
B163: ='CAT 963C LOADER'!B133 -> 0 | C163: ='CAT 963C LOADER'!C133 -> 0 | G163: =D163*F163 -> 0
B164: ='CAT 963C LOADER'!B134 -> 0 | C164: ='CAT 963C LOADER'!C134 -> 0 | G164: =D164*F164 -> 0
B165: ='CAT 963C LOADER'!B135 -> 0 | C165: ='CAT 963C LOADER'!C135 -> 0 | G165: =D165*F165 -> 0
B166: ='CAT 963C LOADER'!B136 -> 0 | C166: ='CAT 963C LOADER'!C136 -> 0 | G166: =D166*F166 -> 0
B167: ='CAT 963C LOADER'!B137 -> 0 | C167: ='CAT 963C LOADER'!C137 -> 0 | G167: =D167*F167 -> 0
F168: SUBTOTAL | G168: =SUM(G18:G167) -> 0
F169: SHIPPING | G169: 0
C170: OEM MSRP : | D170: ='CAT 963C LOADER'!O2 -> 0 | F170: CUSTOMS/BROKER FEE | G170: 0
C171: GQP : | D171: ='CAT 963C LOADER'!O3 -> 0 | F171: TOTAL | G171: =SUM(G168:G170) -> 0
C172: GQP SAVINGS : | D172: ='CAT 963C LOADER'!O4 -> 0 | F172: =IF(C177=TRUE,("GST"),("GST 5%")) -> GST 5% | G172: =ROUND(IF(C177=FALSE,(G171*0.05),0),2) -> 0
F173: PST / QST
C174: GST EXEMPT | F174: GRAND TOTAL | G174: =SUM(G171:G173) -> 0
C175: CUSTOMER GST # | F175: CREDIT CARD FEE | G175: =IF(B177=TRUE,(G174*0.025),0) -> 0
B176: Credit Card Payment Subject to 2.5% Processing Fee. Quote valid for 14 days, shipping subject to delays in supply chain. | F176: Total Due | G176: =G174+G175 -> 0
B177: FALSE | C177: FALSE

Sheet SERVICE QUOTE
D1: CUSTOMER SERVICE QUOTE
B7: COMPANY: | C7: ='CAT 963C LOADER'!C3 -> 0 | D7: DATE: | E7: ='CAT 963C LOADER'!C2 -> 0
B8: CUSTOMER: | C8: ='CAT 963C LOADER'!C4 -> 0 | D8: MACHINE INFORMATION
B9: PHONE NUMBER: | C9: ='CAT 963C LOADER'!C5 -> 0 | D9: YEAR: | E9: ='CAT 963C LOADER'!F3 -> 0 | F9: UNIT #: | G9: ='CAT 963C LOADER'!F2 -> 0
B10: EMAIL ADDRESS: | C10: ='CAT 963C LOADER'!C6 -> 0 | D10: MAKE: | E10: ='CAT 963C LOADER'!F4 -> 0
B11: BILLING ADDRESS: | D11: MODEL: | E11: ='CAT 963C LOADER'!F5 -> 0
D12: SERIAL NUM: | E12: ='CAT 963C LOADER'!F6 -> 0
D13: HOURS: | E13: ='CAT 963C LOADER'!F8 -> 0
B14: SHIPPING ADDRESS: | D14: SALES REP: | E14: ='CAT 963C LOADER'!C7 -> 0
D15: PO NUMBER:
E16: ='CAT 963C LOADER'!K17 -> CAD $
B17: PART NUMBER | C17: DESCRIPTION | D17: QTY | E17: OEM MSRP / UNIT | F17: GQP PRICE / UNIT | G17: TOTAL
B18: ='CAT 963C LOADER'!B18 -> 0 | C18: ='CAT 963C LOADER'!C18 -> ENGINE OIL FILTER | D18: ='CAT 963C LOADER'!E18 -> 0 | E18: =IFERROR('CAT 963C LOADER'!H18/'CAT 963C LOADER'!E18,0) -> 0 | F18: ='CAT 963C LOADER'!K18 -> 0 | G18: =D18*F18 -> 0
B19: ='CAT 963C LOADER'!B19 -> 0 | C19: ='CAT 963C LOADER'!C19 -> FUEL FILTER | D19: ='CAT 963C LOADER'!E19 -> 0 | E19: =IFERROR('CAT 963C LOADER'!H19/'CAT 963C LOADER'!E19,0) -> 0 | F19: ='CAT 963C LOADER'!K19 -> 0 | G19: =D19*F19 -> 0
B20: ='CAT 963C LOADER'!B20 -> 0 | C20: ='CAT 963C LOADER'!C20 -> FUEL WATER SEPARATOR FILTER | D20: ='CAT 963C LOADER'!E20 -> 0 | E20: =IFERROR('CAT 963C LOADER'!H20/'CAT 963C LOADER'!E20,0) -> 0 | F20: ='CAT 963C LOADER'!K20 -> 0 | G20: =D20*F20 -> 0
B21: ='CAT 963C LOADER'!B21 -> 0 | C21: ='CAT 963C LOADER'!C21 -> HYDRAULIC FILTER | D21: ='CAT 963C LOADER'!E21 -> 0 | E21: =IFERROR('CAT 963C LOADER'!H21/'CAT 963C LOADER'!E21,0) -> 0 | F21: ='CAT 963C LOADER'!K21 -> 0 | G21: =D21*F21 -> 0
B22: ='CAT 963C LOADER'!B22 -> 0 | C22: ='CAT 963C LOADER'!C22 -> HYDRAULIC TRANSMISSION OIL FILTER | D22: ='CAT 963C LOADER'!E22 -> 0 | E22: =IFERROR('CAT 963C LOADER'!H22/'CAT 963C LOADER'!E22,0) -> 0 | F22: ='CAT 963C LOADER'!K22 -> 0 | G22: =D22*F22 -> 0
B23: ='CAT 963C LOADER'!B23 -> 0 | C23: ='CAT 963C LOADER'!C23 -> PRIMARY AIR FILTER | D23: ='CAT 963C LOADER'!E23 -> 0 | E23: =IFERROR('CAT 963C LOADER'!H23/'CAT 963C LOADER'!E23,0) -> 0 | F23: ='CAT 963C LOADER'!K23 -> 0 | G23: =D23*F23 -> 0
B24: ='CAT 963C LOADER'!B24 -> 0 | C24: ='CAT 963C LOADER'!C24 -> SECONDARY AIR FILTER ELEMENT | D24: ='CAT 963C LOADER'!E24 -> 0 | E24: =IFERROR('CAT 963C LOADER'!H24/'CAT 963C LOADER'!E24,0) -> 0 | F24: ='CAT 963C LOADER'!K24 -> 0 | G24: =D24*F24 -> 0
B25: ='CAT 963C LOADER'!B25 -> 0 | C25: ='CAT 963C LOADER'!C25 -> CABIN AIR FILTER ELEMENT | D25: ='CAT 963C LOADER'!E25 -> 0 | E25: =IFERROR('CAT 963C LOADER'!H25/'CAT 963C LOADER'!E25,0) -> 0 | F25: ='CAT 963C LOADER'!K25 -> 0 | G25: =D25*F25 -> 0
B26: ='CAT 963C LOADER'!B26 -> 0 | C26: ='CAT 963C LOADER'!C26 -> 12V 4D BCI BATTERY (19.3" X 8.6" X 9.9") | D26: ='CAT 963C LOADER'!E26 -> 0 | E26: =IFERROR('CAT 963C LOADER'!H26/'CAT 963C LOADER'!E26,0) -> 0 | F26: ='CAT 963C LOADER'!K26 -> 0 | G26: =D26*F26 -> 0
B27: ='CAT 963C LOADER'!B27 -> 0 | C27: ='CAT 963C LOADER'!C27 -> 0 | D27: ='CAT 963C LOADER'!E27 -> 0 | E27: =IFERROR('CAT 963C LOADER'!H27/'CAT 963C LOADER'!E27,0) -> 0 | F27: ='CAT 963C LOADER'!K27 -> 0 | G27: =D27*F27 -> 0
B28: ='CAT 963C LOADER'!B28 -> 0 | C28: ='CAT 963C LOADER'!C28 -> ENGINE OVERHAUL KIT | D28: ='CAT 963C LOADER'!E28 -> 0 | E28: =IFERROR('CAT 963C LOADER'!H28/'CAT 963C LOADER'!E28,0) -> 0 | F28: ='CAT 963C LOADER'!K28 -> 0 | G28: =D28*F28 -> 0
B29: ='CAT 963C LOADER'!B29 -> 0 | C29: ='CAT 963C LOADER'!C29 -> CAMSHAFT | D29: ='CAT 963C LOADER'!E29 -> 0 | E29: =IFERROR('CAT 963C LOADER'!H29/'CAT 963C LOADER'!E29,0) -> 0 | F29: ='CAT 963C LOADER'!K29 -> 0 | G29: =D29*F29 -> 0
... B54: ='CAT 963C LOADER'!B54 -> 0 | C54: ='CAT 963C LOADER'!C54 -> 0 | D54: ='CAT 963C LOADER'!E54 -> 0 | E54: =IFERROR('CAT 963C LOADER'!H54/'CAT 963C LOADER'!E54,0) -> 0 | F54: ='CAT 963C LOADER'!K54 -> 0 | G54: =D54*F54 -> 0
E55: Quote valid for 14 days, shipping subject to delays in supply chain. Labour rate subject to change. Labour times quoted for repairs are estimates only, actual repair times subject to change, any changes will be communicated and agreed to by both the customer and Global Wholesale Machinery Inc. Credit Card Payment Subject to 2.5% Processing Fee.
D61: CUSTOMER SERVICE QUOTE
B67: =IF('CAT 963C LOADER'!C3="",'CAT 963C LOADER'!B4,'CAT 963C LOADER'!B3) -> CUSTOMER: | C67: =IF('CAT 963C LOADER'!C3="",'CAT 963C LOADER'!C4,'CAT 963C LOADER'!C3) -> 0 | D67: DATE: | E67: ='CAT 963C LOADER'!C2 -> 0
E68: ='CAT 963C LOADER'!K17 -> CAD $
B69: PART NUMBER | C69: DESCRIPTION | D69: QTY | E69: OEM MSRP / UNIT | F69: GQP PRICE / UNIT | G69: TOTAL
B70: ='CAT 963C LOADER'!B55 -> 0 | C70: ='CAT 963C LOADER'!C55 -> 0 | D70: ='CAT 963C LOADER'!E55 -> 0 | E70: =IFERROR('CAT 963C LOADER'!H55/'CAT 963C LOADER'!E55,0) -> 0 | F70: ='CAT 963C LOADER'!K55 -> 0 | G70: =D70*F70 -> 0
B71: ='CAT 963C LOADER'!B56 -> 0 | C71: ='CAT 963C LOADER'!C56 -> 0 | D71: ='CAT 963C LOADER'!E56 -> 0 | E71: =IFERROR('CAT 963C LOADER'!H56/'CAT 963C LOADER'!E56,0) -> 0 | F71: ='CAT 963C LOADER'!K56 -> 0 | G71: =D71*F71 -> 0
B72: ='CAT 963C LOADER'!B57 -> 0 | C72: ='CAT 963C LOADER'!C57 -> 0 | D72: ='CAT 963C LOADER'!E57 -> 0 | E72: =IFERROR('CAT 963C LOADER'!H57/'CAT 963C LOADER'!E57,0) -> 0 | F72: ='CAT 963C LOADER'!K57 -> 0 | G72: =D72*F72 -> 0
B73: ='CAT 963C LOADER'!B58 -> 0 | C73: ='CAT 963C LOADER'!C58 -> 0 | D73: ='CAT 963C LOADER'!E58 -> 0 | E73: =IFERROR('CAT 963C LOADER'!H58/'CAT 963C LOADER'!E58,0) -> 0 | F73: ='CAT 963C LOADER'!K58 -> 0 | G73: =D73*F73 -> 0
B74: ='CAT 963C LOADER'!B59 -> 0 | C74: ='CAT 963C LOADER'!C59 -> 0 | D74: ='CAT 963C LOADER'!E59 -> 0 | E74: =IFERROR('CAT 963C LOADER'!H59/'CAT 963C LOADER'!E59,0) -> 0 | F74: ='CAT 963C LOADER'!K59 -> 0 | G74: =D74*F74 -> 0
B75: ='CAT 963C LOADER'!B60 -> 0 | C75: ='CAT 963C LOADER'!C60 -> 0 | D75: ='CAT 963C LOADER'!E60 -> 0 | E75: =IFERROR('CAT 963C LOADER'!H60/'CAT 963C LOADER'!E60,0) -> 0 | F75: ='CAT 963C LOADER'!K60 -> 0 | G75: =D75*F75 -> 0
B76: ='CAT 963C LOADER'!B61 -> 0 | C76: ='CAT 963C LOADER'!C61 -> 0 | D76: ='CAT 963C LOADER'!E61 -> 0 | E76: =IFERROR('CAT 963C LOADER'!H61/'CAT 963C LOADER'!E61,0) -> 0 | F76: ='CAT 963C LOADER'!K61 -> 0 | G76: =D76*F76 -> 0
B77: ='CAT 963C LOADER'!B62 -> 0 | C77: ='CAT 963C LOADER'!C62 -> 0 | D77: ='CAT 963C LOADER'!E62 -> 0 | E77: =IFERROR('CAT 963C LOADER'!H62/'CAT 963C LOADER'!E62,0) -> 0 | F77: ='CAT 963C LOADER'!K62 -> 0 | G77: =D77*F77 -> 0
B78: ='CAT 963C LOADER'!B63 -> 0 | C78: ='CAT 963C LOADER'!C63 -> 0 | D78: ='CAT 963C LOADER'!E63 -> 0 | E78: =IFERROR('CAT 963C LOADER'!H63/'CAT 963C LOADER'!E63,0) -> 0 | F78: ='CAT 963C LOADER'!K63 -> 0 | G78: =D78*F78 -> 0
B79: ='CAT 963C LOADER'!B64 -> 0 | C79: ='CAT 963C LOADER'!C64 -> 0 | D79: ='CAT 963C LOADER'!E64 -> 0 | E79: =IFERROR('CAT 963C LOADER'!H64/'CAT 963C LOADER'!E64,0) -> 0 | F79: ='CAT 963C LOADER'!K64 -> 0 | G79: =D79*F79 -> 0
B80: ='CAT 963C LOADER'!B65 -> 0 | C80: ='CAT 963C LOADER'!C65 -> 0 | D80: ='CAT 963C LOADER'!E65 -> 0 | E80: =IFERROR('CAT 963C LOADER'!H65/'CAT 963C LOADER'!E65,0) -> 0 | F80: ='CAT 963C LOADER'!K65 -> 0 | G80: =D80*F80 -> 0
B81: ='CAT 963C LOADER'!B66 -> 0 | C81: ='CAT 963C LOADER'!C66 -> 0 | D81: ='CAT 963C LOADER'!E66 -> 0 | E81: =IFERROR('CAT 963C LOADER'!H66/'CAT 963C LOADER'!E66,0) -> 0 | F81: ='CAT 963C LOADER'!K66 -> 0 | G81: =D81*F81 -> 0
... B115: ='CAT 963C LOADER'!B100 -> 0 | C115: ='CAT 963C LOADER'!C100 -> 0 | D115: ='CAT 963C LOADER'!E100 -> 0 | E115: =IFERROR('CAT 963C LOADER'!H100/'CAT 963C LOADER'!E100,0) -> 0 | F115: ='CAT 963C LOADER'!K100 -> 0 | G115: =D115*F115 -> 0
E116: Quote valid for 14 days, shipping subject to delays in supply chain. Labour rate subject to change. Labour times quoted for repairs are estimates only, actual repair times subject to change, any changes will be communicated and agreed to by both the customer and Global Wholesale Machinery Inc. Credit Card Payment Subject to 2.5% Processing Fee.
D122: CUSTOMER SERVICE QUOTE
B128: =IF('CAT 963C LOADER'!C3="",'CAT 963C LOADER'!B4,'CAT 963C LOADER'!B3) -> CUSTOMER: | C128: =IF('CAT 963C LOADER'!C3="",'CAT 963C LOADER'!C4,'CAT 963C LOADER'!C3) -> 0 | D128: DATE: | E128: ='CAT 963C LOADER'!C2 -> 0
E129: ='CAT 963C LOADER'!K17 -> CAD $
B130: PART NUMBER | C130: DESCRIPTION | D130: QTY | E130: OEM MSRP / UNIT | F130: GQP PRICE / UNIT | G130: TOTAL
B131: ='CAT 963C LOADER'!B101 -> 0 | C131: ='CAT 963C LOADER'!C101 -> 0 | D131: ='CAT 963C LOADER'!E101 -> 0 | E131: =IFERROR('CAT 963C LOADER'!H101/'CAT 963C LOADER'!E101,0) -> 0 | F131: ='CAT 963C LOADER'!K101 -> 0 | G131: =D131*F131 -> 0
B132: ='CAT 963C LOADER'!B102 -> 0 | C132: ='CAT 963C LOADER'!C102 -> 0 | D132: ='CAT 963C LOADER'!E102 -> 0 | E132: =IFERROR('CAT 963C LOADER'!H102/'CAT 963C LOADER'!E102,0) -> 0 | F132: ='CAT 963C LOADER'!K102 -> 0 | G132: =D132*F132 -> 0
B133: ='CAT 963C LOADER'!B103 -> 0 | C133: ='CAT 963C LOADER'!C103 -> 0 | D133: ='CAT 963C LOADER'!E103 -> 0 | E133: =IFERROR('CAT 963C LOADER'!H103/'CAT 963C LOADER'!E103,0) -> 0 | F133: ='CAT 963C LOADER'!K103 -> 0 | G133: =D133*F133 -> 0
B134: ='CAT 963C LOADER'!B104 -> 0 | C134: ='CAT 963C LOADER'!C104 -> 0 | D134: ='CAT 963C LOADER'!E104 -> 0 | E134: =IFERROR('CAT 963C LOADER'!H104/'CAT 963C LOADER'!E104,0) -> 0 | F134: ='CAT 963C LOADER'!K104 -> 0 | G134: =D134*F134 -> 0
B135: ='CAT 963C LOADER'!B105 -> 0 | C135: ='CAT 963C LOADER'!C105 -> 0 | D135: ='CAT 963C LOADER'!E105 -> 0 | E135: =IFERROR('CAT 963C LOADER'!H105/'CAT 963C LOADER'!E105,0) -> 0 | F135: ='CAT 963C LOADER'!K105 -> 0 | G135: =D135*F135 -> 0
B136: ='CAT 963C LOADER'!B106 -> 0 | C136: ='CAT 963C LOADER'!C106 -> 0 | D136: ='CAT 963C LOADER'!E106 -> 0 | E136: =IFERROR('CAT 963C LOADER'!H106/'CAT 963C LOADER'!E106,0) -> 0 | F136: ='CAT 963C LOADER'!K106 -> 0 | G136: =D136*F136 -> 0
B137: ='CAT 963C LOADER'!B107 -> 0 | C137: ='CAT 963C LOADER'!C107 -> 0 | D137: ='CAT 963C LOADER'!E107 -> 0 | E137: =IFERROR('CAT 963C LOADER'!H107/'CAT 963C LOADER'!E107,0) -> 0 | F137: ='CAT 963C LOADER'!K107 -> 0 | G137: =D137*F137 -> 0
B138: ='CAT 963C LOADER'!B108 -> 0 | C138: ='CAT 963C LOADER'!C108 -> 0 | D138: ='CAT 963C LOADER'!E108 -> 0 | E138: =IFERROR('CAT 963C LOADER'!H108/'CAT 963C LOADER'!E108,0) -> 0 | F138: ='CAT 963C LOADER'!K108 -> 0 | G138: =D138*F138 -> 0
B139: ='CAT 963C LOADER'!B109 -> 0 | C139: ='CAT 963C LOADER'!C109 -> 0 | D139: ='CAT 963C LOADER'!E109 -> 0 | E139: =IFERROR('CAT 963C LOADER'!H109/'CAT 963C LOADER'!E109,0) -> 0 | F139: ='CAT 963C LOADER'!K109 -> 0 | G139: =D139*F139 -> 0
B140: ='CAT 963C LOADER'!B110 -> 0 | C140: ='CAT 963C LOADER'!C110 -> 0 | D140: ='CAT 963C LOADER'!E110 -> 0 | E140: =IFERROR('CAT 963C LOADER'!H110/'CAT 963C LOADER'!E110,0) -> 0 | F140: ='CAT 963C LOADER'!K110 -> 0 | G140: =D140*F140 -> 0
B141: ='CAT 963C LOADER'!B111 -> 0 | C141: ='CAT 963C LOADER'!C111 -> 0 | D141: ='CAT 963C LOADER'!E111 -> 0 | E141: =IFERROR('CAT 963C LOADER'!H111/'CAT 963C LOADER'!E111,0) -> 0 | F141: ='CAT 963C LOADER'!K111 -> 0 | G141: =D141*F141 -> 0
B142: ='CAT 963C LOADER'!B112 -> 0 | C142: ='CAT 963C LOADER'!C112 -> 0 | D142: ='CAT 963C LOADER'!E112 -> 0 | E142: =IFERROR('CAT 963C LOADER'!H112/'CAT 963C LOADER'!E112,0) -> 0 | F142: ='CAT 963C LOADER'!K112 -> 0 | G142: =D142*F142 -> 0
... B158: ='CAT 963C LOADER'!B128 -> 0 | C158: ='CAT 963C LOADER'!C128 -> 0 | D158: ='CAT 963C LOADER'!E128 -> 0 | E158: =IFERROR('CAT 963C LOADER'!H128/'CAT 963C LOADER'!E128,0) -> 0 | F158: ='CAT 963C LOADER'!K128 -> 0 | G158: =D158*F158 -> 0
E159: Parts Subtotal | G159: =SUM(G18:G158) -> 0
C160: SERVICE
B161: DESCRIPTION OF WORK TO BE COMPLETED | D161: Labour Hours | E161: Industry Rate | F161: Global Rate | G161: Total
G162: =ROUND(F162*D162,2) -> 0
G163: =ROUND(F163*D163,2) -> 0
G164: =ROUND(F164*D164,2) -> 0
G165: =ROUND(F165*D165,2) -> 0
G166: =ROUND(F166*D166,2) -> 0
G167: =ROUND(F167*D167,2) -> 0
C168: SUBLET WORK / MISC
G169: 0
G170: 0
G171: 0
F172: Service Subtotal | G172: =SUM(G162:G171) -> 0
C173: OEM MSRP : | D173: ='CAT 963C LOADER'!O2 -> 0 | F173: Total | G173: =G159+G172 -> 0
C174: GQP : | D174: ='CAT 963C LOADER'!O3 -> 0 | F174: Shop Supplies | G174: =ROUND(G172*0.09,2) -> 0
C175: GQP SAVINGS : | D175: =D173-D174 -> 0 | F175: Shipping | G175: 0
C176: GLOBAL SAVINGS : | D176: =(D162*E162+D163*E163+D164*E164+D165*E165+D166*E166+D167*E167)-SUM(G162:G167) -> 0 | E176: FALSE | F176: Customs/Broker Fee | G176: 0
C177: TOTAL SAVINGS : | D177: =D175+D176 -> 0 | F177: Sub Total | G177: =SUM(G173:G176) -> 0
F178: =IF(B183=TRUE,("GST"),("GST 5%")) -> GST 5% | G178: =ROUND(IF(B183=FALSE,(G177*0.05),0),2) -> 0
B179: Quote valid for 14 days, shipping subject to delays in supply chain. Labour rate subject to change. Labour times quoted for repairs are estimates only, actual repair times subject to change, any changes will be communicated and agreed to by both the customer and Global Wholesale Machinery Inc. Credit Card Payment Subject to 2.5% Processing Fee. | F179: PST / QST
D180: GST EXEMPT | F180: Grand Total | G180: =SUM(G177:G179) -> 0
D181: CUST GST # | F181: Credit Card Fee | G181: =IF(C183=TRUE,(G180*0.025),0) -> 0
F182: Total Due | G182: =G180+G181 -> 0
B183: FALSE | C183: FALSE
