Workbook

Sheet Instructions
A1: Global Wholesale Machinery Inc.
A2: OEM Compareson Spreadsheet Instructions
A4: NET MARKUP% for each quote must be over 100% otherwise need approval from Quinten.
A5: NET MARGIN% for each quote must be over 50% otherwise need approval from Quinten.
A7: Customer Information Section
B8: Must be fully completed in OEM COMPARISON TAB.
B9: Information entered will be automatically transferred to QUOTE, and SERVICE QUOTE tab.
B10: Customer Information will not be transferred to RFQ tab as we do not give out customer information to vendors.
A12: Machine Information Section
B13: Optional - depends on customer request.
B14: Information entered will be automatically transferred to RFQ, QUOTE, and SERVICE QUOTE tab.
A16: Machine Service Interval Section
B17: Optional - depends on customer request.
B18: For internal use only. Information entered will not be transferred to RFQ, QUOTE, and SERVICE QUOTE tab.
A20: Parts Pricing and Cost Section
B21: Part Number - OEM Part Number (with exception to UC and Tires)
B22: Description - Description of Part
B23: Vendor - Name of the Vendor where we acquire parts from
B24: OEM Name - Name of OEM Manufacturer used for MSRP comparison
B25: Freight Cost - Vendor shipping cost.
A27: Customizable Features
A28: 1) Show or Hide OEM Comparison in Quote or Service Quote to cusomter.
B29: Select from drop down option at cell J13
A34: 2) Enter OEM pricing in USD or CAD.
B35: Select from drop down option at cell G17
A41: 3) Provide customer quotes in USD or CAD.
B42: Select from drop down option at cell L17
A51: 4) Enter Vendor pricing in USD or CAD.
B52: Select from drop down option at cell Q17

Sheet CAT 740
B1: CUSTOMER INFORMATION | D1: MACHINE INFORMATION | H1: MACHINE SERVICE HR INTERVALS | L1: SUMMARY | P1: =K17 -> CAD $ | S1: COMPLETED DEAL INFORMATION
B2: DATE: | D2: UNIT # | F2: AT-08 | H2: ENGINE AIR | L2: OEM MSRP | P2: =H49 -> 77837.91 | S2: SALES REP
B3: COMPANY: | D3: YEAR | F3: 2009 | H3: ENGINE OIL | L3: GQP LIST | P3: =L49 -> 42810.89 | S3: ORDER PO #
B4: CUSTOMER: | D4: MAKE | F4: CAT | H4: FUEL FILTERS | L4: $ SAVINGS | P4: =P2-P3 -> 35027.02 | S4: PROJECT #
B5: PHONE: | D5: MODEL | F5: 740 | H5: HYDRAULIC FILTERS | L5: % SAVINGS | P5: =IFERROR((P2-P3)/P2,"") -> 0.44999949 | S5: CUST INVOICE #
B6: EMAIL: | D6: SERIAL NUMBER | F6: B1P04757 | H6: TRANSMISSION FILTERS | L6: TOTAL ORDER MARGIN | P6: =T49 -> 42810.89 | S6: PAYMENT TYPE
B7: SALES REP: | D7: ENGINE SER NUMBER | F7: LHX21840 | H7: CAB FILTERS | L7: TOTAL ITEM COST | P7: =R49 -> 0 | S7: DATE DELIVERED
D8: CURRENT HOURS | H8: UNDERCARRIAGE / TIRES | L8: TOTAL ORDER FREIGHT | P8: =IF(P1=Q14,R14,IF(Q14="CAD $",R14*D15,IF(Q14="USD $",R14*E15,0))) -> 0 | S8: TOTAL COST | T8: NET MARGIN | U8: NET MARKUP % | V8: NET MARGIN %
D9: USAGE/MONTH | F9: Articulated Dump Truck | L9: TOTAL CUSTOMS/BROKERAGE | P9: =V14 -> 0 | S9: =P7+P8+P9 -> 0 | T9: =P3-S9 -> 42810.89 | U9: =IFERROR(((P3-S9)/S9),0) -> 0 | V9: =IFERROR(T9/P3,0) -> 1
L10: TOTAL NUMBER PIECES | P10: =E49 -> 24
D11: ENTER EXCHANGE RATES $ | F11: OEM MSRP | J11: CUSTOMER SELL PRICE | P11: COST ANALYSIS | Y11: CAD $
Y12: USD $
F13: SHOW OEM MSRP ON QUOTE: | H13: YES | Y13: YES
D14: CAD-USD | E14: USD-CAD | F14: OEM NAME | J14: CUSTOMER TYPE/TIER | L14: IE: VIP - Gold | P14: FREIGHT TOTAL ORDER | Q14: USD $ | S14: CUSTOMS AND BROKERAGE % | T14: 0.025 | U14: BROKERAGE FEES | V14: =ROUND(R49*T14,2) -> 0 | Y14: NO
D15: =1/E15 -> 0.70422535 | E15: 1.42 | P15: MARKUP LESS THAN 100% REQUIRES MANAGER APPROVAL
B16: PART NUMBER | C16: DESCRIPTION | D16: SERVICE INTERVAL | E16: QTY | F16: UNIT PRICE | H16: EXT AMOUNT | J16: QTY | K16: UNIT PRICE | L16: EXTENDED AMOUNT | M16: PRCING METHOD %OEM / MARKUP | N16: OEM DISC % / MARKUP % | P16: VENDOR | Q16: COST EACH | R16: EXTENDED COST | S16: MARGIN EACH | T16: EXTENDED MARGIN | U16: MARKUP % | V16: MARGIN %
F17: USD $ | G17: =IF(F17="USD $", "CAD $", "USD $") -> CAD $ | H17: =K17 -> CAD $ | K17: CAD $ | Q17: USD $ | R17: =K17 -> CAD $
B18: 1R-0716 | C18: ENGINE OIL FILTER | D18: 250 | E18: 1 | F18: 33.88 | G18: =ROUND(IF($F$17="USD $", F18*$E$15,F18*$D$15),2) -> 48.11 | H18: =ROUND(IF($H$17=$G$17,E18*G18,E18*F18),2) -> 48.11 | J18: =E18 -> 1 | K18: =IFERROR(IF(M18="OEM DISC %",ROUND(IF($K$17=$F$17,F18*(1-N18),G18*(1-N18)),2),IF(M18="MARKUP %",ROUND(R18/J18*(1+N18),2))),0) -> 26.46 | L18: =ROUND((J18*K18),2) -> 26.46 | M18: OEM DISC % | N18: 0.45 | R18: =ROUND(IF($R$17=$Q$17,Q18,IF($R$17="USD $",Q18*$D$15,Q18*$E$15))*E18,2) -> 0 | S18: =IFERROR(ROUND(T18/E18,2),0) -> 26.46 | T18: =ROUND(L18-R18,2) -> 26.46 | U18: =IFERROR(((K18-(R18/J18))/(R18/J18)),0) -> 0 | V18: =IFERROR(((K18-(R18/J18))/K18),0) -> 1 | Z18: 250
B19: 1R-0762 | C19: FUEL FILTER | D19: 250 | E19: 1 | F19: 45.86 | G19: =ROUND(IF($F$17="USD $", F19*$E$15,F19*$D$15),2) -> 65.12 | H19: =ROUND(IF($H$17=$G$17,E19*G19,E19*F19),2) -> 65.12 | J19: =E19 -> 1 | K19: =IFERROR(IF(M19="OEM DISC %",ROUND(IF($K$17=$F$17,F19*(1-N19),G19*(1-N19)),2),IF(M19="MARKUP %",ROUND(R19/J19*(1+N19),2))),0) -> 35.82 | L19: =ROUND((J19*K19),2) -> 35.82 | M19: OEM DISC % | N19: 0.45 | R19: =ROUND(IF($R$17=$Q$17,Q19,IF($R$17="USD $",Q19*$D$15,Q19*$E$15))*E19,2) -> 0 | S19: =IFERROR(ROUND(T19/E19,2),0) -> 35.82 | T19: =ROUND(L19-R19,2) -> 35.82 | U19: =IFERROR(((K19-(R19/J19))/(R19/J19)),0) -> 0 | V19: =IFERROR(((K19-(R19/J19))/K19),0) -> 1 | Y19: GQP | Z19: 500
B20: 326-1644 | C20: FUEL WATER SEPARATOR FILTER | D20: 500 | E20: 1 | F20: 58.2 | G20: =ROUND(IF($F$17="USD $", F20*$E$15,F20*$D$15),2) -> 82.64 | H20: =ROUND(IF($H$17=$G$17,E20*G20,E20*F20),2) -> 82.64 | J20: =E20 -> 1 | K20: =IFERROR(IF(M20="OEM DISC %",ROUND(IF($K$17=$F$17,F20*(1-N20),G20*(1-N20)),2),IF(M20="MARKUP %",ROUND(R20/J20*(1+N20),2))),0) -> 45.45 | L20: =ROUND((J20*K20),2) -> 45.45 | M20: OEM DISC % | N20: 0.45 | R20: =ROUND(IF($R$17=$Q$17,Q20,IF($R$17="USD $",Q20*$D$15,Q20*$E$15))*E20,2) -> 0 | S20: =IFERROR(ROUND(T20/E20,2),0) -> 45.45 | T20: =ROUND(L20-R20,2) -> 45.45 | U20: =IFERROR(((K20-(R20/J20))/(R20/J20)),0) -> 0 | V20: =IFERROR(((K20-(R20/J20))/K20),0) -> 1 | Y20: CTP | Z20: 750
B21: 1R-0719 | C21: TRANSMISSION FILTER | D21: 500 | E21: 1 | F21: 26.06 | G21: =ROUND(IF($F$17="USD $", F21*$E$15,F21*$D$15),2) -> 37.01 | H21: =ROUND(IF($H$17=$G$17,E21*G21,E21*F21),2) -> 37.01 | J21: =E21 -> 1 | K21: =IFERROR(IF(M21="OEM DISC %",ROUND(IF($K$17=$F$17,F21*(1-N21),G21*(1-N21)),2),IF(M21="MARKUP %",ROUND(R21/J21*(1+N21),2))),0) -> 20.36 | L21: =ROUND((J21*K21),2) -> 20.36 | M21: OEM DISC % | N21: 0.45 | R21: =ROUND(IF($R$17=$Q$17,Q21,IF($R$17="USD $",Q21*$D$15,Q21*$E$15))*E21,2) -> 0 | S21: =IFERROR(ROUND(T21/E21,2),0) -> 20.36 | T21: =ROUND(L21-R21,2) -> 20.36 | U21: =IFERROR(((K21-(R21/J21))/(R21/J21)),0) -> 0 | V21: =IFERROR(((K21-(R21/J21))/K21),0) -> 1 | Y21: BLMQ | Z21: 1000
B22: 1G-8878 | C22: HYDRAULIC FILTER | D22: 500 | E22: 1 | F22: 102.31 | G22: =ROUND(IF($F$17="USD $", F22*$E$15,F22*$D$15),2) -> 145.28 | H22: =ROUND(IF($H$17=$G$17,E22*G22,E22*F22),2) -> 145.28 | J22: =E22 -> 1 | K22: =IFERROR(IF(M22="OEM DISC %",ROUND(IF($K$17=$F$17,F22*(1-N22),G22*(1-N22)),2),IF(M22="MARKUP %",ROUND(R22/J22*(1+N22),2))),0) -> 79.9 | L22: =ROUND((J22*K22),2) -> 79.9 | M22: OEM DISC % | N22: 0.45 | R22: =ROUND(IF($R$17=$Q$17,Q22,IF($R$17="USD $",Q22*$D$15,Q22*$E$15))*E22,2) -> 0 | S22: =IFERROR(ROUND(T22/E22,2),0) -> 79.9 | T22: =ROUND(L22-R22,2) -> 79.9 | U22: =IFERROR(((K22-(R22/J22))/(R22/J22)),0) -> 0 | V22: =IFERROR(((K22-(R22/J22))/K22),0) -> 1 | Y22: CAT | Z22: 1200
B23: 142-1340 | C23: PRIMARY AIR FILTER | D23: 500 | E23: 1 | F23: 178.61 | G23: =ROUND(IF($F$17="USD $", F23*$E$15,F23*$D$15),2) -> 253.63 | H23: =ROUND(IF($H$17=$G$17,E23*G23,E23*F23),2) -> 253.63 | J23: =E23 -> 1 | K23: =IFERROR(IF(M23="OEM DISC %",ROUND(IF($K$17=$F$17,F23*(1-N23),G23*(1-N23)),2),IF(M23="MARKUP %",ROUND(R23/J23*(1+N23),2))),0) -> 139.5 | L23: =ROUND((J23*K23),2) -> 139.5 | M23: OEM DISC % | N23: 0.45 | R23: =ROUND(IF($R$17=$Q$17,Q23,IF($R$17="USD $",Q23*$D$15,Q23*$E$15))*E23,2) -> 0 | S23: =IFERROR(ROUND(T23/E23,2),0) -> 139.5 | T23: =ROUND(L23-R23,2) -> 139.5 | U23: =IFERROR(((K23-(R23/J23))/(R23/J23)),0) -> 0 | V23: =IFERROR(((K23-(R23/J23))/K23),0) -> 1 | Y23: FINNING | Z23: 2000
B24: 142-1403 | C24: SECONDARY AIR FILTER | D24: 250 | E24: 1 | F24: 99.07 | G24: =ROUND(IF($F$17="USD $", F24*$E$15,F24*$D$15),2) -> 140.68 | H24: =ROUND(IF($H$17=$G$17,E24*G24,E24*F24),2) -> 140.68 | J24: =E24 -> 1 | K24: =IFERROR(IF(M24="OEM DISC %",ROUND(IF($K$17=$F$17,F24*(1-N24),G24*(1-N24)),2),IF(M24="MARKUP %",ROUND(R24/J24*(1+N24),2))),0) -> 77.37 | L24: =ROUND((J24*K24),2) -> 77.37 | M24: OEM DISC % | N24: 0.45 | R24: =ROUND(IF($R$17=$Q$17,Q24,IF($R$17="USD $",Q24*$D$15,Q24*$E$15))*E24,2) -> 0 | S24: =IFERROR(ROUND(T24/E24,2),0) -> 77.37 | T24: =ROUND(L24-R24,2) -> 77.37 | U24: =IFERROR(((K24-(R24/J24))/(R24/J24)),0) -> 0 | V24: =IFERROR(((K24-(R24/J24))/K24),0) -> 1 | Y24: JD | Z24: 4000
B25: 268-6704 | C25: CABIN AIR FILTER | D25: 250 | E25: 1 | F25: 86.44 | G25: =ROUND(IF($F$17="USD $", F25*$E$15,F25*$D$15),2) -> 122.74 | H25: =ROUND(IF($H$17=$G$17,E25*G25,E25*F25),2) -> 122.74 | J25: =E25 -> 1 | K25: =IFERROR(IF(M25="OEM DISC %",ROUND(IF($K$17=$F$17,F25*(1-N25),G25*(1-N25)),2),IF(M25="MARKUP %",ROUND(R25/J25*(1+N25),2))),0) -> 67.51 | L25: =ROUND((J25*K25),2) -> 67.51 | M25: OEM DISC % | N25: 0.45 | R25: =ROUND(IF($R$17=$Q$17,Q25,IF($R$17="USD $",Q25*$D$15,Q25*$E$15))*E25,2) -> 0 | S25: =IFERROR(ROUND(T25/E25,2),0) -> 67.51 | T25: =ROUND(L25-R25,2) -> 67.51 | U25: =IFERROR(((K25-(R25/J25))/(R25/J25)),0) -> 0 | V25: =IFERROR(((K25-(R25/J25))/K25),0) -> 1 | Y25: BRANDT | Z25: 6000
G26: =ROUND(IF($F$17="USD $", F26*$E$15,F26*$D$15),2) -> 0 | H26: =ROUND(IF($H$17=$G$17,E26*G26,E26*F26),2) -> 0 | J26: =E26 -> 0 | K26: =IFERROR(IF(M26="OEM DISC %",ROUND(IF($K$17=$F$17,F26*(1-N26),G26*(1-N26)),2),IF(M26="MARKUP %",ROUND(R26/J26*(1+N26),2))),0) -> 0 | L26: =ROUND((J26*K26),2) -> 0 | M26: OEM DISC % | N26: 0.45 | R26: =ROUND(IF($R$17=$Q$17,Q26,IF($R$17="USD $",Q26*$D$15,Q26*$E$15))*E26,2) -> 0 | S26: =IFERROR(ROUND(T26/E26,2),0) -> 0 | T26: =ROUND(L26-R26,2) -> 0 | U26: =IFERROR(((K26-(R26/J26))/(R26/J26)),0) -> 0 | V26: =IFERROR(((K26-(R26/J26))/K26),0) -> 0 | Y26: PTI | Z26: 8000
B27: 447-1525 | C27: ENGINE OVERHAUL KIT SILVER | D27: 10000 | E27: 1 | G27: =ROUND(IF($F$17="USD $", F27*$E$15,F27*$D$15),2) -> 0 | H27: =ROUND(IF($H$17=$G$17,E27*G27,E27*F27),2) -> 0 | J27: =E27 -> 1 | K27: =IFERROR(IF(M27="OEM DISC %",ROUND(IF($K$17=$F$17,F27*(1-N27),G27*(1-N27)),2),IF(M27="MARKUP %",ROUND(R27/J27*(1+N27),2))),0) -> 0 | L27: =ROUND((J27*K27),2) -> 0 | M27: OEM DISC % | N27: 0.45 | R27: =ROUND(IF($R$17=$Q$17,Q27,IF($R$17="USD $",Q27*$D$15,Q27*$E$15))*E27,2) -> 0 | S27: =IFERROR(ROUND(T27/E27,2),0) -> 0 | T27: =ROUND(L27-R27,2) -> 0 | U27: =IFERROR(((K27-(R27/J27))/(R27/J27)),0) -> 0 | V27: =IFERROR(((K27-(R27/J27))/K27),0) -> 0 | Y27: CONEQUIP | Z27: 10000
C28: SEAT GP-SUSPENSION | G28: =ROUND(IF($F$17="USD $", F28*$E$15,F28*$D$15),2) -> 0 | H28: =ROUND(IF($H$17=$G$17,E28*G28,E28*F28),2) -> 0 | J28: =E28 -> 0 | K28: =IFERROR(IF(M28="OEM DISC %",ROUND(IF($K$17=$F$17,F28*(1-N28),G28*(1-N28)),2),IF(M28="MARKUP %",ROUND(R28/J28*(1+N28),2))),0) -> 0 | L28: =ROUND((J28*K28),2) -> 0 | M28: OEM DISC % | N28: 0.45 | R28: =ROUND(IF($R$17=$Q$17,Q28,IF($R$17="USD $",Q28*$D$15,Q28*$E$15))*E28,2) -> 0 | S28: =IFERROR(ROUND(T28/E28,2),0) -> 0 | T28: =ROUND(L28-R28,2) -> 0 | U28: =IFERROR(((K28-(R28/J28))/(R28/J28)),0) -> 0 | V28: =IFERROR(((K28-(R28/J28))/K28),0) -> 0 | Y28: CANDY | Z28: AS REQ'D
B29: 153-5700 | C29: BATTERY | D29: AS REQ'D | E29: 2 | F29: 493.89 | G29: =ROUND(IF($F$17="USD $", F29*$E$15,F29*$D$15),2) -> 701.32 | H29: =ROUND(IF($H$17=$G$17,E29*G29,E29*F29),2) -> 1402.64 | J29: =E29 -> 2 | K29: =IFERROR(IF(M29="OEM DISC %",ROUND(IF($K$17=$F$17,F29*(1-N29),G29*(1-N29)),2),IF(M29="MARKUP %",ROUND(R29/J29*(1+N29),2))),0) -> 385.73 | L29: =ROUND((J29*K29),2) -> 771.46 | M29: OEM DISC % | N29: 0.45 | R29: =ROUND(IF($R$17=$Q$17,Q29,IF($R$17="USD $",Q29*$D$15,Q29*$E$15))*E29,2) -> 0 | S29: =IFERROR(ROUND(T29/E29,2),0) -> 385.73 | T29: =ROUND(L29-R29,2) -> 771.46 | U29: =IFERROR(((K29-(R29/J29))/(R29/J29)),0) -> 0 | V29: =IFERROR(((K29-(R29/J29))/K29),0) -> 1 | Y29: U/C
B30: 230-3542 | C30: TURBOCHARGER | D30: 6000 | E30: 1 | F30: 4583.66 | G30: =ROUND(IF($F$17="USD $", F30*$E$15,F30*$D$15),2) -> 6508.8 | H30: =ROUND(IF($H$17=$G$17,E30*G30,E30*F30),2) -> 6508.8 | J30: =E30 -> 1 | K30: =IFERROR(IF(M30="OEM DISC %",ROUND(IF($K$17=$F$17,F30*(1-N30),G30*(1-N30)),2),IF(M30="MARKUP %",ROUND(R30/J30*(1+N30),2))),0) -> 3579.84 | L30: =ROUND((J30*K30),2) -> 3579.84 | M30: OEM DISC % | N30: 0.45 | R30: =ROUND(IF($R$17=$Q$17,Q30,IF($R$17="USD $",Q30*$D$15,Q30*$E$15))*E30,2) -> 0 | S30: =IFERROR(ROUND(T30/E30,2),0) -> 3579.84 | T30: =ROUND(L30-R30,2) -> 3579.84 | U30: =IFERROR(((K30-(R30/J30))/(R30/J30)),0) -> 0 | V30: =IFERROR(((K30-(R30/J30))/K30),0) -> 1
B31: 647-0750 | C31: INJECTOR | D31: 6000 | E31: 6 | F31: 1430.29 | G31: =ROUND(IF($F$17="USD $", F31*$E$15,F31*$D$15),2) -> 2031.01 | H31: =ROUND(IF($H$17=$G$17,E31*G31,E31*F31),2) -> 12186.06 | J31: =E31 -> 6 | K31: =IFERROR(IF(M31="OEM DISC %",ROUND(IF($K$17=$F$17,F31*(1-N31),G31*(1-N31)),2),IF(M31="MARKUP %",ROUND(R31/J31*(1+N31),2))),0) -> 1117.06 | L31: =ROUND((J31*K31),2) -> 6702.36 | M31: OEM DISC % | N31: 0.45 | R31: =ROUND(IF($R$17=$Q$17,Q31,IF($R$17="USD $",Q31*$D$15,Q31*$E$15))*E31,2) -> 0 | S31: =IFERROR(ROUND(T31/E31,2),0) -> 1117.06 | T31: =ROUND(L31-R31,2) -> 6702.36 | U31: =IFERROR(((K31-(R31/J31))/(R31/J31)),0) -> 0 | V31: =IFERROR(((K31-(R31/J31))/K31),0) -> 1 | Y31: OEM DISC %
G32: =ROUND(IF($F$17="USD $", F32*$E$15,F32*$D$15),2) -> 0 | H32: =ROUND(IF($H$17=$G$17,E32*G32,E32*F32),2) -> 0 | J32: =E32 -> 0 | K32: =IFERROR(IF(M32="OEM DISC %",ROUND(IF($K$17=$F$17,F32*(1-N32),G32*(1-N32)),2),IF(M32="MARKUP %",ROUND(R32/J32*(1+N32),2))),0) -> 0 | L32: =ROUND((J32*K32),2) -> 0 | M32: OEM DISC % | N32: 0.45 | R32: =ROUND(IF($R$17=$Q$17,Q32,IF($R$17="USD $",Q32*$D$15,Q32*$E$15))*E32,2) -> 0 | S32: =IFERROR(ROUND(T32/E32,2),0) -> 0 | T32: =ROUND(L32-R32,2) -> 0 | U32: =IFERROR(((K32-(R32/J32))/(R32/J32)),0) -> 0 | V32: =IFERROR(((K32-(R32/J32))/K32),0) -> 0 | Y32: MARKUP %
C33: TIRES 29.5r25 | D33: 5000 | E33: 6 | F33: 6671.97 | G33: =ROUND(IF($F$17="USD $", F33*$E$15,F33*$D$15),2) -> 9474.2 | H33: =ROUND(IF($H$17=$G$17,E33*G33,E33*F33),2) -> 56845.2 | J33: =E33 -> 6 | K33: =IFERROR(IF(M33="OEM DISC %",ROUND(IF($K$17=$F$17,F33*(1-N33),G33*(1-N33)),2),IF(M33="MARKUP %",ROUND(R33/J33*(1+N33),2))),0) -> 5210.81 | L33: =ROUND((J33*K33),2) -> 31264.86 | M33: OEM DISC % | N33: 0.45 | R33: =ROUND(IF($R$17=$Q$17,Q33,IF($R$17="USD $",Q33*$D$15,Q33*$E$15))*E33,2) -> 0 | S33: =IFERROR(ROUND(T33/E33,2),0) -> 5210.81 | T33: =ROUND(L33-R33,2) -> 31264.86 | U33: =IFERROR(((K33-(R33/J33))/(R33/J33)),0) -> 0 | V33: =IFERROR(((K33-(R33/J33))/K33),0) -> 1
G34: =ROUND(IF($F$17="USD $", F34*$E$15,F34*$D$15),2) -> 0 | H34: =ROUND(IF($H$17=$G$17,E34*G34,E34*F34),2) -> 0 | J34: =E34 -> 0 | K34: =IFERROR(IF(M34="OEM DISC %",ROUND(IF($K$17=$F$17,F34*(1-N34),G34*(1-N34)),2),IF(M34="MARKUP %",ROUND(R34/J34*(1+N34),2))),0) -> 0 | L34: =ROUND((J34*K34),2) -> 0 | M34: OEM DISC % | N34: 0.45 | R34: =ROUND(IF($R$17=$Q$17,Q34,IF($R$17="USD $",Q34*$D$15,Q34*$E$15))*E34,2) -> 0 | S34: =IFERROR(ROUND(T34/E34,2),0) -> 0 | T34: =ROUND(L34-R34,2) -> 0 | U34: =IFERROR(((K34-(R34/J34))/(R34/J34)),0) -> 0 | V34: =IFERROR(((K34-(R34/J34))/K34),0) -> 0
G35: =ROUND(IF($F$17="USD $", F35*$E$15,F35*$D$15),2) -> 0 | H35: =ROUND(IF($H$17=$G$17,E35*G35,E35*F35),2) -> 0 | J35: =E35 -> 0 | K35: =IFERROR(IF(M35="OEM DISC %",ROUND(IF($K$17=$F$17,F35*(1-N35),G35*(1-N35)),2),IF(M35="MARKUP %",ROUND(R35/J35*(1+N35),2))),0) -> 0 | L35: =ROUND((J35*K35),2) -> 0 | M35: OEM DISC % | N35: 0.45 | R35: =ROUND(IF($R$17=$Q$17,Q35,IF($R$17="USD $",Q35*$D$15,Q35*$E$15))*E35,2) -> 0 | S35: =IFERROR(ROUND(T35/E35,2),0) -> 0 | T35: =ROUND(L35-R35,2) -> 0 | U35: =IFERROR(((K35-(R35/J35))/(R35/J35)),0) -> 0 | V35: =IFERROR(((K35-(R35/J35))/K35),0) -> 0
G36: =ROUND(IF($F$17="USD $", F36*$E$15,F36*$D$15),2) -> 0 | H36: =ROUND(IF($H$17=$G$17,E36*G36,E36*F36),2) -> 0 | J36: =E36 -> 0 | K36: =IFERROR(IF(M36="OEM DISC %",ROUND(IF($K$17=$F$17,F36*(1-N36),G36*(1-N36)),2),IF(M36="MARKUP %",ROUND(R36/J36*(1+N36),2))),0) -> 0 | L36: =ROUND((J36*K36),2) -> 0 | M36: OEM DISC % | N36: 0.45 | R36: =ROUND(IF($R$17=$Q$17,Q36,IF($R$17="USD $",Q36*$D$15,Q36*$E$15))*E36,2) -> 0 | S36: =IFERROR(ROUND(T36/E36,2),0) -> 0 | T36: =ROUND(L36-R36,2) -> 0 | U36: =IFERROR(((K36-(R36/J36))/(R36/J36)),0) -> 0 | V36: =IFERROR(((K36-(R36/J36))/K36),0) -> 0
G37: =ROUND(IF($F$17="USD $", F37*$E$15,F37*$D$15),2) -> 0 | H37: =ROUND(IF($H$17=$G$17,E37*G37,E37*F37),2) -> 0 | J37: =E37 -> 0 | K37: =IFERROR(IF(M37="OEM DISC %",ROUND(IF($K$17=$F$17,F37*(1-N37),G37*(1-N37)),2),IF(M37="MARKUP %",ROUND(R37/J37*(1+N37),2))),0) -> 0 | L37: =ROUND((J37*K37),2) -> 0 | M37: OEM DISC % | N37: 0.45 | R37: =ROUND(IF($R$17=$Q$17,Q37,IF($R$17="USD $",Q37*$D$15,Q37*$E$15))*E37,2) -> 0 | S37: =IFERROR(ROUND(T37/E37,2),0) -> 0 | T37: =ROUND(L37-R37,2) -> 0 | U37: =IFERROR(((K37-(R37/J37))/(R37/J37)),0) -> 0 | V37: =IFERROR(((K37-(R37/J37))/K37),0) -> 0
G38: =ROUND(IF($F$17="USD $", F38*$E$15,F38*$D$15),2) -> 0 | H38: =ROUND(IF($H$17=$G$17,E38*G38,E38*F38),2) -> 0 | J38: =E38 -> 0 | K38: =IFERROR(IF(M38="OEM DISC %",ROUND(IF($K$17=$F$17,F38*(1-N38),G38*(1-N38)),2),IF(M38="MARKUP %",ROUND(R38/J38*(1+N38),2))),0) -> 0 | L38: =ROUND((J38*K38),2) -> 0 | M38: OEM DISC % | N38: 0.45 | R38: =ROUND(IF($R$17=$Q$17,Q38,IF($R$17="USD $",Q38*$D$15,Q38*$E$15))*E38,2) -> 0 | S38: =IFERROR(ROUND(T38/E38,2),0) -> 0 | T38: =ROUND(L38-R38,2) -> 0 | U38: =IFERROR(((K38-(R38/J38))/(R38/J38)),0) -> 0 | V38: =IFERROR(((K38-(R38/J38))/K38),0) -> 0
G39: =ROUND(IF($F$17="USD $", F39*$E$15,F39*$D$15),2) -> 0 | H39: =ROUND(IF($H$17=$G$17,E39*G39,E39*F39),2) -> 0 | J39: =E39 -> 0 | K39: =IFERROR(IF(M39="OEM DISC %",ROUND(IF($K$17=$F$17,F39*(1-N39),G39*(1-N39)),2),IF(M39="MARKUP %",ROUND(R39/J39*(1+N39),2))),0) -> 0 | L39: =ROUND((J39*K39),2) -> 0 | M39: OEM DISC % | N39: 0.45 | R39: =ROUND(IF($R$17=$Q$17,Q39,IF($R$17="USD $",Q39*$D$15,Q39*$E$15))*E39,2) -> 0 | S39: =IFERROR(ROUND(T39/E39,2),0) -> 0 | T39: =ROUND(L39-R39,2) -> 0 | U39: =IFERROR(((K39-(R39/J39))/(R39/J39)),0) -> 0 | V39: =IFERROR(((K39-(R39/J39))/K39),0) -> 0
G40: =ROUND(IF($F$17="USD $", F40*$E$15,F40*$D$15),2) -> 0 | H40: =ROUND(IF($H$17=$G$17,E40*G40,E40*F40),2) -> 0 | J40: =E40 -> 0 | K40: =IFERROR(IF(M40="OEM DISC %",ROUND(IF($K$17=$F$17,F40*(1-N40),G40*(1-N40)),2),IF(M40="MARKUP %",ROUND(R40/J40*(1+N40),2))),0) -> 0 | L40: =ROUND((J40*K40),2) -> 0 | M40: OEM DISC % | N40: 0.45 | R40: =ROUND(IF($R$17=$Q$17,Q40,IF($R$17="USD $",Q40*$D$15,Q40*$E$15))*E40,2) -> 0 | S40: =IFERROR(ROUND(T40/E40,2),0) -> 0 | T40: =ROUND(L40-R40,2) -> 0 | U40: =IFERROR(((K40-(R40/J40))/(R40/J40)),0) -> 0 | V40: =IFERROR(((K40-(R40/J40))/K40),0) -> 0
G41: =ROUND(IF($F$17="USD $", F41*$E$15,F41*$D$15),2) -> 0 | H41: =ROUND(IF($H$17=$G$17,E41*G41,E41*F41),2) -> 0 | J41: =E41 -> 0 | K41: =IFERROR(IF(M41="OEM DISC %",ROUND(IF($K$17=$F$17,F41*(1-N41),G41*(1-N41)),2),IF(M41="MARKUP %",ROUND(R41/J41*(1+N41),2))),0) -> 0 | L41: =ROUND((J41*K41),2) -> 0 | M41: OEM DISC % | N41: 0.45 | R41: =ROUND(IF($R$17=$Q$17,Q41,IF($R$17="USD $",Q41*$D$15,Q41*$E$15))*E41,2) -> 0 | S41: =IFERROR(ROUND(T41/E41,2),0) -> 0 | T41: =ROUND(L41-R41,2) -> 0 | U41: =IFERROR(((K41-(R41/J41))/(R41/J41)),0) -> 0 | V41: =IFERROR(((K41-(R41/J41))/K41),0) -> 0
G42: =ROUND(IF($F$17="USD $", F42*$E$15,F42*$D$15),2) -> 0 | H42: =ROUND(IF($H$17=$G$17,E42*G42,E42*F42),2) -> 0 | J42: =E42 -> 0 | K42: =IFERROR(IF(M42="OEM DISC %",ROUND(IF($K$17=$F$17,F42*(1-N42),G42*(1-N42)),2),IF(M42="MARKUP %",ROUND(R42/J42*(1+N42),2))),0) -> 0 | L42: =ROUND((J42*K42),2) -> 0 | M42: MARKUP % | N42: 0.45 | R42: =ROUND(IF($R$17=$Q$17,Q42,IF($R$17="USD $",Q42*$D$15,Q42*$E$15))*E42,2) -> 0 | S42: =IFERROR(ROUND(T42/E42,2),0) -> 0 | T42: =ROUND(L42-R42,2) -> 0 | U42: =IFERROR(((K42-(R42/J42))/(R42/J42)),0) -> 0 | V42: =IFERROR(((K42-(R42/J42))/K42),0) -> 0
G43: =ROUND(IF($F$17="USD $", F43*$E$15,F43*$D$15),2) -> 0 | H43: =ROUND(IF($H$17=$G$17,E43*G43,E43*F43),2) -> 0 | J43: =E43 -> 0 | K43: =IFERROR(IF(M43="OEM DISC %",ROUND(IF($K$17=$F$17,F43*(1-N43),G43*(1-N43)),2),IF(M43="MARKUP %",ROUND(R43/J43*(1+N43),2))),0) -> 0 | L43: =ROUND((J43*K43),2) -> 0 | M43: OEM DISC % | N43: 0.45 | R43: =ROUND(IF($R$17=$Q$17,Q43,IF($R$17="USD $",Q43*$D$15,Q43*$E$15))*E43,2) -> 0 | S43: =IFERROR(ROUND(T43/E43,2),0) -> 0 | T43: =ROUND(L43-R43,2) -> 0 | U43: =IFERROR(((K43-(R43/J43))/(R43/J43)),0) -> 0 | V43: =IFERROR(((K43-(R43/J43))/K43),0) -> 0
G44: =ROUND(IF($F$17="USD $", F44*$E$15,F44*$D$15),2) -> 0 | H44: =ROUND(IF($H$17=$G$17,E44*G44,E44*F44),2) -> 0 | J44: =E44 -> 0 | K44: =IFERROR(IF(M44="OEM DISC %",ROUND(IF($K$17=$F$17,F44*(1-N44),G44*(1-N44)),2),IF(M44="MARKUP %",ROUND(R44/J44*(1+N44),2))),0) -> 0 | L44: =ROUND((J44*K44),2) -> 0 | M44: OEM DISC % | N44: 0.45 | R44: =ROUND(IF($R$17=$Q$17,Q44,IF($R$17="USD $",Q44*$D$15,Q44*$E$15))*E44,2) -> 0 | S44: =IFERROR(ROUND(T44/E44,2),0) -> 0 | T44: =ROUND(L44-R44,2) -> 0 | U44: =IFERROR(((K44-(R44/J44))/(R44/J44)),0) -> 0 | V44: =IFERROR(((K44-(R44/J44))/K44),0) -> 0
G45: =ROUND(IF($F$17="USD $", F45*$E$15,F45*$D$15),2) -> 0 | H45: =ROUND(IF($H$17=$G$17,E45*G45,E45*F45),2) -> 0 | J45: =E45 -> 0 | K45: =IFERROR(IF(M45="OEM DISC %",ROUND(IF($K$17=$F$17,F45*(1-N45),G45*(1-N45)),2),IF(M45="MARKUP %",ROUND(R45/J45*(1+N45),2))),0) -> 0 | L45: =ROUND((J45*K45),2) -> 0 | M45: OEM DISC % | N45: 0.45 | R45: =ROUND(IF($R$17=$Q$17,Q45,IF($R$17="USD $",Q45*$D$15,Q45*$E$15))*E45,2) -> 0 | S45: =IFERROR(ROUND(T45/E45,2),0) -> 0 | T45: =ROUND(L45-R45,2) -> 0 | U45: =IFERROR(((K45-(R45/J45))/(R45/J45)),0) -> 0 | V45: =IFERROR(((K45-(R45/J45))/K45),0) -> 0
... G48: =ROUND(IF($F$17="USD $", F48*$E$15,F48*$D$15),2) -> 0 | H48: =ROUND(IF($H$17=$G$17,E48*G48,E48*F48),2) -> 0 | J48: =E48 -> 0 | K48: =IFERROR(IF(M48="OEM DISC %",ROUND(IF($K$17=$F$17,F48*(1-N48),G48*(1-N48)),2),IF(M48="MARKUP %",ROUND(R48/J48*(1+N48),2))),0) -> 0 | L48: =ROUND((J48*K48),2) -> 0 | M48: OEM DISC % | N48: 0.45 | R48: =ROUND(IF($R$17=$Q$17,Q48,IF($R$17="USD $",Q48*$D$15,Q48*$E$15))*E48,2) -> 0 | S48: =IFERROR(ROUND(T48/E48,2),0) -> 0 | T48: =ROUND(L48-R48,2) -> 0 | U48: =IFERROR(((K48-(R48/J48))/(R48/J48)),0) -> 0 | V48: =IFERROR(((K48-(R48/J48))/K48),0) -> 0
D49: TOTALS | E49: =SUM(E18:E48) -> 24 | F49: =SUM(F18:F48) -> 13810.24 | G49: =SUM(G18:G48) -> 19610.54 | H49: =SUM(H18:H48) -> 77837.91 | J49: =SUM(J18:J48) -> 24 | K49: =SUM(K18:K48) -> 10785.81 | L49: =SUM(L18:L48) -> 42810.89 | Q49: =SUM(Q18:Q48) -> 0 | R49: =SUM(R18:R48) -> 0 | S49: =SUM(S18:S48) -> 10785.81 | T49: =SUM(T18:T48) -> 42810.89

Sheet CAT 740 (2)
B1: CUSTOMER INFORMATION | D1: MACHINE INFORMATION | H1: MACHINE SERVICE HR INTERVALS | L1: SUMMARY | P1: =K17 -> CAD $ | S1: COMPLETED DEAL INFORMATION
B2: DATE: | D2: UNIT # | F2: AT-07 | H2: ENGINE AIR | L2: OEM MSRP | P2: =H49 -> 77837.91 | S2: SALES REP
B3: COMPANY: | D3: YEAR | F3: 2009 | H3: ENGINE OIL | L3: GQP LIST | P3: =L49 -> 42810.89 | S3: ORDER PO #
B4: CUSTOMER: | D4: MAKE | F4: CAT | H4: FUEL FILTERS | L4: $ SAVINGS | P4: =P2-P3 -> 35027.02 | S4: PROJECT #
B5: PHONE: | D5: MODEL | F5: 740 | H5: HYDRAULIC FILTERS | L5: % SAVINGS | P5: =IFERROR((P2-P3)/P2,"") -> 0.44999949 | S5: CUST INVOICE #
B6: EMAIL: | D6: SERIAL NUMBER | F6: B1P05108 | H6: TRANSMISSION FILTERS | L6: TOTAL ORDER MARGIN | P6: =T49 -> 42810.89 | S6: PAYMENT TYPE
B7: SALES REP: | D7: ENGINE SER NUMBER | F7: LHX23321 | H7: CAB FILTERS | L7: TOTAL ITEM COST | P7: =R49 -> 0 | S7: DATE DELIVERED
D8: CURRENT HOURS | H8: UNDERCARRIAGE / TIRES | L8: TOTAL ORDER FREIGHT | P8: =IF(P1=Q14,R14,IF(Q14="CAD $",R14*D15,IF(Q14="USD $",R14*E15,0))) -> 0 | S8: TOTAL COST | T8: NET MARGIN | U8: NET MARKUP % | V8: NET MARGIN %
D9: USAGE/MONTH | F9: Articulated Dump Truck | L9: TOTAL CUSTOMS/BROKERAGE | P9: =V14 -> 0 | S9: =P7+P8+P9 -> 0 | T9: =P3-S9 -> 42810.89 | U9: =IFERROR(((P3-S9)/S9),0) -> 0 | V9: =IFERROR(T9/P3,0) -> 1
L10: TOTAL NUMBER PIECES | P10: =E49 -> 24
D11: ENTER EXCHANGE RATES $ | F11: OEM MSRP | J11: CUSTOMER SELL PRICE | P11: COST ANALYSIS | Y11: CAD $
Y12: USD $
F13: SHOW OEM MSRP ON QUOTE: | H13: YES | Y13: YES
D14: CAD-USD | E14: USD-CAD | F14: OEM NAME | J14: CUSTOMER TYPE/TIER | L14: IE: VIP - Gold | P14: FREIGHT TOTAL ORDER | Q14: USD $ | S14: CUSTOMS AND BROKERAGE % | T14: 0.025 | U14: BROKERAGE FEES | V14: =ROUND(R49*T14,2) -> 0 | Y14: NO
D15: =1/E15 -> 0.70422535 | E15: 1.42 | P15: MARKUP LESS THAN 100% REQUIRES MANAGER APPROVAL
B16: PART NUMBER | C16: DESCRIPTION | D16: SERVICE INTERVAL | E16: QTY | F16: UNIT PRICE | H16: EXT AMOUNT | J16: QTY | K16: UNIT PRICE | L16: EXTENDED AMOUNT | M16: PRCING METHOD %OEM / MARKUP | N16: OEM DISC % / MARKUP % | P16: VENDOR | Q16: COST EACH | R16: EXTENDED COST | S16: MARGIN EACH | T16: EXTENDED MARGIN | U16: MARKUP % | V16: MARGIN %
F17: USD $ | G17: =IF(F17="USD $", "CAD $", "USD $") -> CAD $ | H17: =K17 -> CAD $ | K17: CAD $ | Q17: USD $ | R17: =K17 -> CAD $
B18: 1R-0716 | C18: ENGINE OIL FILTER | D18: 250 | E18: 1 | F18: 33.88 | G18: =ROUND(IF($F$17="USD $", F18*$E$15,F18*$D$15),2) -> 48.11 | H18: =ROUND(IF($H$17=$G$17,E18*G18,E18*F18),2) -> 48.11 | J18: =E18 -> 1 | K18: =IFERROR(IF(M18="OEM DISC %",ROUND(IF($K$17=$F$17,F18*(1-N18),G18*(1-N18)),2),IF(M18="MARKUP %",ROUND(R18/J18*(1+N18),2))),0) -> 26.46 | L18: =ROUND((J18*K18),2) -> 26.46 | M18: OEM DISC % | N18: 0.45 | R18: =ROUND(IF($R$17=$Q$17,Q18,IF($R$17="USD $",Q18*$D$15,Q18*$E$15))*E18,2) -> 0 | S18: =IFERROR(ROUND(T18/E18,2),0) -> 26.46 | T18: =ROUND(L18-R18,2) -> 26.46 | U18: =IFERROR(((K18-(R18/J18))/(R18/J18)),0) -> 0 | V18: =IFERROR(((K18-(R18/J18))/K18),0) -> 1 | Z18: 250
B19: 1R-0762 | C19: FUEL FILTER | D19: 250 | E19: 1 | F19: 45.86 | G19: =ROUND(IF($F$17="USD $", F19*$E$15,F19*$D$15),2) -> 65.12 | H19: =ROUND(IF($H$17=$G$17,E19*G19,E19*F19),2) -> 65.12 | J19: =E19 -> 1 | K19: =IFERROR(IF(M19="OEM DISC %",ROUND(IF($K$17=$F$17,F19*(1-N19),G19*(1-N19)),2),IF(M19="MARKUP %",ROUND(R19/J19*(1+N19),2))),0) -> 35.82 | L19: =ROUND((J19*K19),2) -> 35.82 | M19: OEM DISC % | N19: 0.45 | R19: =ROUND(IF($R$17=$Q$17,Q19,IF($R$17="USD $",Q19*$D$15,Q19*$E$15))*E19,2) -> 0 | S19: =IFERROR(ROUND(T19/E19,2),0) -> 35.82 | T19: =ROUND(L19-R19,2) -> 35.82 | U19: =IFERROR(((K19-(R19/J19))/(R19/J19)),0) -> 0 | V19: =IFERROR(((K19-(R19/J19))/K19),0) -> 1 | Y19: GQP | Z19: 500
B20: 326-1644 | C20: FUEL WATER SEPARATOR FILTER | D20: 500 | E20: 1 | F20: 58.2 | G20: =ROUND(IF($F$17="USD $", F20*$E$15,F20*$D$15),2) -> 82.64 | H20: =ROUND(IF($H$17=$G$17,E20*G20,E20*F20),2) -> 82.64 | J20: =E20 -> 1 | K20: =IFERROR(IF(M20="OEM DISC %",ROUND(IF($K$17=$F$17,F20*(1-N20),G20*(1-N20)),2),IF(M20="MARKUP %",ROUND(R20/J20*(1+N20),2))),0) -> 45.45 | L20: =ROUND((J20*K20),2) -> 45.45 | M20: OEM DISC % | N20: 0.45 | R20: =ROUND(IF($R$17=$Q$17,Q20,IF($R$17="USD $",Q20*$D$15,Q20*$E$15))*E20,2) -> 0 | S20: =IFERROR(ROUND(T20/E20,2),0) -> 45.45 | T20: =ROUND(L20-R20,2) -> 45.45 | U20: =IFERROR(((K20-(R20/J20))/(R20/J20)),0) -> 0 | V20: =IFERROR(((K20-(R20/J20))/K20),0) -> 1 | Y20: CTP | Z20: 750
B21: 1R-0719 | C21: TRANSMISSION FILTER | D21: 500 | E21: 1 | F21: 26.06 | G21: =ROUND(IF($F$17="USD $", F21*$E$15,F21*$D$15),2) -> 37.01 | H21: =ROUND(IF($H$17=$G$17,E21*G21,E21*F21),2) -> 37.01 | J21: =E21 -> 1 | K21: =IFERROR(IF(M21="OEM DISC %",ROUND(IF($K$17=$F$17,F21*(1-N21),G21*(1-N21)),2),IF(M21="MARKUP %",ROUND(R21/J21*(1+N21),2))),0) -> 20.36 | L21: =ROUND((J21*K21),2) -> 20.36 | M21: OEM DISC % | N21: 0.45 | R21: =ROUND(IF($R$17=$Q$17,Q21,IF($R$17="USD $",Q21*$D$15,Q21*$E$15))*E21,2) -> 0 | S21: =IFERROR(ROUND(T21/E21,2),0) -> 20.36 | T21: =ROUND(L21-R21,2) -> 20.36 | U21: =IFERROR(((K21-(R21/J21))/(R21/J21)),0) -> 0 | V21: =IFERROR(((K21-(R21/J21))/K21),0) -> 1 | Y21: BLMQ | Z21: 1000
B22: 1G-8878 | C22: HYDRAULIC FILTER | D22: 500 | E22: 1 | F22: 102.31 | G22: =ROUND(IF($F$17="USD $", F22*$E$15,F22*$D$15),2) -> 145.28 | H22: =ROUND(IF($H$17=$G$17,E22*G22,E22*F22),2) -> 145.28 | J22: =E22 -> 1 | K22: =IFERROR(IF(M22="OEM DISC %",ROUND(IF($K$17=$F$17,F22*(1-N22),G22*(1-N22)),2),IF(M22="MARKUP %",ROUND(R22/J22*(1+N22),2))),0) -> 79.9 | L22: =ROUND((J22*K22),2) -> 79.9 | M22: OEM DISC % | N22: 0.45 | R22: =ROUND(IF($R$17=$Q$17,Q22,IF($R$17="USD $",Q22*$D$15,Q22*$E$15))*E22,2) -> 0 | S22: =IFERROR(ROUND(T22/E22,2),0) -> 79.9 | T22: =ROUND(L22-R22,2) -> 79.9 | U22: =IFERROR(((K22-(R22/J22))/(R22/J22)),0) -> 0 | V22: =IFERROR(((K22-(R22/J22))/K22),0) -> 1 | Y22: CAT | Z22: 1200
B23: 142-1340 | C23: PRIMARY AIR FILTER | D23: 500 | E23: 1 | F23: 178.61 | G23: =ROUND(IF($F$17="USD $", F23*$E$15,F23*$D$15),2) -> 253.63 | H23: =ROUND(IF($H$17=$G$17,E23*G23,E23*F23),2) -> 253.63 | J23: =E23 -> 1 | K23: =IFERROR(IF(M23="OEM DISC %",ROUND(IF($K$17=$F$17,F23*(1-N23),G23*(1-N23)),2),IF(M23="MARKUP %",ROUND(R23/J23*(1+N23),2))),0) -> 139.5 | L23: =ROUND((J23*K23),2) -> 139.5 | M23: OEM DISC % | N23: 0.45 | R23: =ROUND(IF($R$17=$Q$17,Q23,IF($R$17="USD $",Q23*$D$15,Q23*$E$15))*E23,2) -> 0 | S23: =IFERROR(ROUND(T23/E23,2),0) -> 139.5 | T23: =ROUND(L23-R23,2) -> 139.5 | U23: =IFERROR(((K23-(R23/J23))/(R23/J23)),0) -> 0 | V23: =IFERROR(((K23-(R23/J23))/K23),0) -> 1 | Y23: FINNING | Z23: 2000
B24: 142-1403 | C24: SECONDARY AIR FILTER | D24: 250 | E24: 1 | F24: 99.07 | G24: =ROUND(IF($F$17="USD $", F24*$E$15,F24*$D$15),2) -> 140.68 | H24: =ROUND(IF($H$17=$G$17,E24*G24,E24*F24),2) -> 140.68 | J24: =E24 -> 1 | K24: =IFERROR(IF(M24="OEM DISC %",ROUND(IF($K$17=$F$17,F24*(1-N24),G24*(1-N24)),2),IF(M24="MARKUP %",ROUND(R24/J24*(1+N24),2))),0) -> 77.37 | L24: =ROUND((J24*K24),2) -> 77.37 | M24: OEM DISC % | N24: 0.45 | R24: =ROUND(IF($R$17=$Q$17,Q24,IF($R$17="USD $",Q24*$D$15,Q24*$E$15))*E24,2) -> 0 | S24: =IFERROR(ROUND(T24/E24,2),0) -> 77.37 | T24: =ROUND(L24-R24,2) -> 77.37 | U24: =IFERROR(((K24-(R24/J24))/(R24/J24)),0) -> 0 | V24: =IFERROR(((K24-(R24/J24))/K24),0) -> 1 | Y24: JD | Z24: 4000
B25: 268-6704 | C25: CABIN AIR FILTER | D25: 250 | E25: 1 | F25: 86.44 | G25: =ROUND(IF($F$17="USD $", F25*$E$15,F25*$D$15),2) -> 122.74 | H25: =ROUND(IF($H$17=$G$17,E25*G25,E25*F25),2) -> 122.74 | J25: =E25 -> 1 | K25: =IFERROR(IF(M25="OEM DISC %",ROUND(IF($K$17=$F$17,F25*(1-N25),G25*(1-N25)),2),IF(M25="MARKUP %",ROUND(R25/J25*(1+N25),2))),0) -> 67.51 | L25: =ROUND((J25*K25),2) -> 67.51 | M25: OEM DISC % | N25: 0.45 | R25: =ROUND(IF($R$17=$Q$17,Q25,IF($R$17="USD $",Q25*$D$15,Q25*$E$15))*E25,2) -> 0 | S25: =IFERROR(ROUND(T25/E25,2),0) -> 67.51 | T25: =ROUND(L25-R25,2) -> 67.51 | U25: =IFERROR(((K25-(R25/J25))/(R25/J25)),0) -> 0 | V25: =IFERROR(((K25-(R25/J25))/K25),0) -> 1 | Y25: BRANDT | Z25: 6000
G26: =ROUND(IF($F$17="USD $", F26*$E$15,F26*$D$15),2) -> 0 | H26: =ROUND(IF($H$17=$G$17,E26*G26,E26*F26),2) -> 0 | J26: =E26 -> 0 | K26: =IFERROR(IF(M26="OEM DISC %",ROUND(IF($K$17=$F$17,F26*(1-N26),G26*(1-N26)),2),IF(M26="MARKUP %",ROUND(R26/J26*(1+N26),2))),0) -> 0 | L26: =ROUND((J26*K26),2) -> 0 | M26: OEM DISC % | N26: 0.45 | R26: =ROUND(IF($R$17=$Q$17,Q26,IF($R$17="USD $",Q26*$D$15,Q26*$E$15))*E26,2) -> 0 | S26: =IFERROR(ROUND(T26/E26,2),0) -> 0 | T26: =ROUND(L26-R26,2) -> 0 | U26: =IFERROR(((K26-(R26/J26))/(R26/J26)),0) -> 0 | V26: =IFERROR(((K26-(R26/J26))/K26),0) -> 0 | Y26: PTI | Z26: 8000
B27: 447-1525 | C27: ENGINE OVERHAUL KIT SILVER | D27: 10000 | E27: 1 | G27: =ROUND(IF($F$17="USD $", F27*$E$15,F27*$D$15),2) -> 0 | H27: =ROUND(IF($H$17=$G$17,E27*G27,E27*F27),2) -> 0 | J27: =E27 -> 1 | K27: =IFERROR(IF(M27="OEM DISC %",ROUND(IF($K$17=$F$17,F27*(1-N27),G27*(1-N27)),2),IF(M27="MARKUP %",ROUND(R27/J27*(1+N27),2))),0) -> 0 | L27: =ROUND((J27*K27),2) -> 0 | M27: OEM DISC % | N27: 0.45 | R27: =ROUND(IF($R$17=$Q$17,Q27,IF($R$17="USD $",Q27*$D$15,Q27*$E$15))*E27,2) -> 0 | S27: =IFERROR(ROUND(T27/E27,2),0) -> 0 | T27: =ROUND(L27-R27,2) -> 0 | U27: =IFERROR(((K27-(R27/J27))/(R27/J27)),0) -> 0 | V27: =IFERROR(((K27-(R27/J27))/K27),0) -> 0 | Y27: CONEQUIP | Z27: 10000
C28: SEAT GP-SUSPENSION | G28: =ROUND(IF($F$17="USD $", F28*$E$15,F28*$D$15),2) -> 0 | H28: =ROUND(IF($H$17=$G$17,E28*G28,E28*F28),2) -> 0 | J28: =E28 -> 0 | K28: =IFERROR(IF(M28="OEM DISC %",ROUND(IF($K$17=$F$17,F28*(1-N28),G28*(1-N28)),2),IF(M28="MARKUP %",ROUND(R28/J28*(1+N28),2))),0) -> 0 | L28: =ROUND((J28*K28),2) -> 0 | M28: OEM DISC % | N28: 0.45 | R28: =ROUND(IF($R$17=$Q$17,Q28,IF($R$17="USD $",Q28*$D$15,Q28*$E$15))*E28,2) -> 0 | S28: =IFERROR(ROUND(T28/E28,2),0) -> 0 | T28: =ROUND(L28-R28,2) -> 0 | U28: =IFERROR(((K28-(R28/J28))/(R28/J28)),0) -> 0 | V28: =IFERROR(((K28-(R28/J28))/K28),0) -> 0 | Y28: CANDY | Z28: AS REQ'D
B29: 153-5700 | C29: BATTERY | D29: AS REQ'D | E29: 2 | F29: 493.89 | G29: =ROUND(IF($F$17="USD $", F29*$E$15,F29*$D$15),2) -> 701.32 | H29: =ROUND(IF($H$17=$G$17,E29*G29,E29*F29),2) -> 1402.64 | J29: =E29 -> 2 | K29: =IFERROR(IF(M29="OEM DISC %",ROUND(IF($K$17=$F$17,F29*(1-N29),G29*(1-N29)),2),IF(M29="MARKUP %",ROUND(R29/J29*(1+N29),2))),0) -> 385.73 | L29: =ROUND((J29*K29),2) -> 771.46 | M29: OEM DISC % | N29: 0.45 | R29: =ROUND(IF($R$17=$Q$17,Q29,IF($R$17="USD $",Q29*$D$15,Q29*$E$15))*E29,2) -> 0 | S29: =IFERROR(ROUND(T29/E29,2),0) -> 385.73 | T29: =ROUND(L29-R29,2) -> 771.46 | U29: =IFERROR(((K29-(R29/J29))/(R29/J29)),0) -> 0 | V29: =IFERROR(((K29-(R29/J29))/K29),0) -> 1 | Y29: U/C
B30: 230-3542 | C30: TURBOCHARGER | D30: 6000 | E30: 1 | F30: 4583.66 | G30: =ROUND(IF($F$17="USD $", F30*$E$15,F30*$D$15),2) -> 6508.8 | H30: =ROUND(IF($H$17=$G$17,E30*G30,E30*F30),2) -> 6508.8 | J30: =E30 -> 1 | K30: =IFERROR(IF(M30="OEM DISC %",ROUND(IF($K$17=$F$17,F30*(1-N30),G30*(1-N30)),2),IF(M30="MARKUP %",ROUND(R30/J30*(1+N30),2))),0) -> 3579.84 | L30: =ROUND((J30*K30),2) -> 3579.84 | M30: OEM DISC % | N30: 0.45 | R30: =ROUND(IF($R$17=$Q$17,Q30,IF($R$17="USD $",Q30*$D$15,Q30*$E$15))*E30,2) -> 0 | S30: =IFERROR(ROUND(T30/E30,2),0) -> 3579.84 | T30: =ROUND(L30-R30,2) -> 3579.84 | U30: =IFERROR(((K30-(R30/J30))/(R30/J30)),0) -> 0 | V30: =IFERROR(((K30-(R30/J30))/K30),0) -> 1
B31: 647-0750 | C31: INJECTOR | D31: 6000 | E31: 6 | F31: 1430.29 | G31: =ROUND(IF($F$17="USD $", F31*$E$15,F31*$D$15),2) -> 2031.01 | H31: =ROUND(IF($H$17=$G$17,E31*G31,E31*F31),2) -> 12186.06 | J31: =E31 -> 6 | K31: =IFERROR(IF(M31="OEM DISC %",ROUND(IF($K$17=$F$17,F31*(1-N31),G31*(1-N31)),2),IF(M31="MARKUP %",ROUND(R31/J31*(1+N31),2))),0) -> 1117.06 | L31: =ROUND((J31*K31),2) -> 6702.36 | M31: OEM DISC % | N31: 0.45 | R31: =ROUND(IF($R$17=$Q$17,Q31,IF($R$17="USD $",Q31*$D$15,Q31*$E$15))*E31,2) -> 0 | S31: =IFERROR(ROUND(T31/E31,2),0) -> 1117.06 | T31: =ROUND(L31-R31,2) -> 6702.36 | U31: =IFERROR(((K31-(R31/J31))/(R31/J31)),0) -> 0 | V31: =IFERROR(((K31-(R31/J31))/K31),0) -> 1 | Y31: OEM DISC %
G32: =ROUND(IF($F$17="USD $", F32*$E$15,F32*$D$15),2) -> 0 | H32: =ROUND(IF($H$17=$G$17,E32*G32,E32*F32),2) -> 0 | J32: =E32 -> 0 | K32: =IFERROR(IF(M32="OEM DISC %",ROUND(IF($K$17=$F$17,F32*(1-N32),G32*(1-N32)),2),IF(M32="MARKUP %",ROUND(R32/J32*(1+N32),2))),0) -> 0 | L32: =ROUND((J32*K32),2) -> 0 | M32: OEM DISC % | N32: 0.45 | R32: =ROUND(IF($R$17=$Q$17,Q32,IF($R$17="USD $",Q32*$D$15,Q32*$E$15))*E32,2) -> 0 | S32: =IFERROR(ROUND(T32/E32,2),0) -> 0 | T32: =ROUND(L32-R32,2) -> 0 | U32: =IFERROR(((K32-(R32/J32))/(R32/J32)),0) -> 0 | V32: =IFERROR(((K32-(R32/J32))/K32),0) -> 0 | Y32: MARKUP %
C33: TIRES 29.5r25 | D33: 5000 | E33: 6 | F33: 6671.97 | G33: =ROUND(IF($F$17="USD $", F33*$E$15,F33*$D$15),2) -> 9474.2 | H33: =ROUND(IF($H$17=$G$17,E33*G33,E33*F33),2) -> 56845.2 | J33: =E33 -> 6 | K33: =IFERROR(IF(M33="OEM DISC %",ROUND(IF($K$17=$F$17,F33*(1-N33),G33*(1-N33)),2),IF(M33="MARKUP %",ROUND(R33/J33*(1+N33),2))),0) -> 5210.81 | L33: =ROUND((J33*K33),2) -> 31264.86 | M33: OEM DISC % | N33: 0.45 | R33: =ROUND(IF($R$17=$Q$17,Q33,IF($R$17="USD $",Q33*$D$15,Q33*$E$15))*E33,2) -> 0 | S33: =IFERROR(ROUND(T33/E33,2),0) -> 5210.81 | T33: =ROUND(L33-R33,2) -> 31264.86 | U33: =IFERROR(((K33-(R33/J33))/(R33/J33)),0) -> 0 | V33: =IFERROR(((K33-(R33/J33))/K33),0) -> 1
G34: =ROUND(IF($F$17="USD $", F34*$E$15,F34*$D$15),2) -> 0 | H34: =ROUND(IF($H$17=$G$17,E34*G34,E34*F34),2) -> 0 | J34: =E34 -> 0 | K34: =IFERROR(IF(M34="OEM DISC %",ROUND(IF($K$17=$F$17,F34*(1-N34),G34*(1-N34)),2),IF(M34="MARKUP %",ROUND(R34/J34*(1+N34),2))),0) -> 0 | L34: =ROUND((J34*K34),2) -> 0 | M34: OEM DISC % | N34: 0.45 | R34: =ROUND(IF($R$17=$Q$17,Q34,IF($R$17="USD $",Q34*$D$15,Q34*$E$15))*E34,2) -> 0 | S34: =IFERROR(ROUND(T34/E34,2),0) -> 0 | T34: =ROUND(L34-R34,2) -> 0 | U34: =IFERROR(((K34-(R34/J34))/(R34/J34)),0) -> 0 | V34: =IFERROR(((K34-(R34/J34))/K34),0) -> 0
G35: =ROUND(IF($F$17="USD $", F35*$E$15,F35*$D$15),2) -> 0 | H35: =ROUND(IF($H$17=$G$17,E35*G35,E35*F35),2) -> 0 | J35: =E35 -> 0 | K35: =IFERROR(IF(M35="OEM DISC %",ROUND(IF($K$17=$F$17,F35*(1-N35),G35*(1-N35)),2),IF(M35="MARKUP %",ROUND(R35/J35*(1+N35),2))),0) -> 0 | L35: =ROUND((J35*K35),2) -> 0 | M35: OEM DISC % | N35: 0.45 | R35: =ROUND(IF($R$17=$Q$17,Q35,IF($R$17="USD $",Q35*$D$15,Q35*$E$15))*E35,2) -> 0 | S35: =IFERROR(ROUND(T35/E35,2),0) -> 0 | T35: =ROUND(L35-R35,2) -> 0 | U35: =IFERROR(((K35-(R35/J35))/(R35/J35)),0) -> 0 | V35: =IFERROR(((K35-(R35/J35))/K35),0) -> 0
G36: =ROUND(IF($F$17="USD $", F36*$E$15,F36*$D$15),2) -> 0 | H36: =ROUND(IF($H$17=$G$17,E36*G36,E36*F36),2) -> 0 | J36: =E36 -> 0 | K36: =IFERROR(IF(M36="OEM DISC %",ROUND(IF($K$17=$F$17,F36*(1-N36),G36*(1-N36)),2),IF(M36="MARKUP %",ROUND(R36/J36*(1+N36),2))),0) -> 0 | L36: =ROUND((J36*K36),2) -> 0 | M36: OEM DISC % | N36: 0.45 | R36: =ROUND(IF($R$17=$Q$17,Q36,IF($R$17="USD $",Q36*$D$15,Q36*$E$15))*E36,2) -> 0 | S36: =IFERROR(ROUND(T36/E36,2),0) -> 0 | T36: =ROUND(L36-R36,2) -> 0 | U36: =IFERROR(((K36-(R36/J36))/(R36/J36)),0) -> 0 | V36: =IFERROR(((K36-(R36/J36))/K36),0) -> 0
G37: =ROUND(IF($F$17="USD $", F37*$E$15,F37*$D$15),2) -> 0 | H37: =ROUND(IF($H$17=$G$17,E37*G37,E37*F37),2) -> 0 | J37: =E37 -> 0 | K37: =IFERROR(IF(M37="OEM DISC %",ROUND(IF($K$17=$F$17,F37*(1-N37),G37*(1-N37)),2),IF(M37="MARKUP %",ROUND(R37/J37*(1+N37),2))),0) -> 0 | L37: =ROUND((J37*K37),2) -> 0 | M37: OEM DISC % | N37: 0.45 | R37: =ROUND(IF($R$17=$Q$17,Q37,IF($R$17="USD $",Q37*$D$15,Q37*$E$15))*E37,2) -> 0 | S37: =IFERROR(ROUND(T37/E37,2),0) -> 0 | T37: =ROUND(L37-R37,2) -> 0 | U37: =IFERROR(((K37-(R37/J37))/(R37/J37)),0) -> 0 | V37: =IFERROR(((K37-(R37/J37))/K37),0) -> 0
G38: =ROUND(IF($F$17="USD $", F38*$E$15,F38*$D$15),2) -> 0 | H38: =ROUND(IF($H$17=$G$17,E38*G38,E38*F38),2) -> 0 | J38: =E38 -> 0 | K38: =IFERROR(IF(M38="OEM DISC %",ROUND(IF($K$17=$F$17,F38*(1-N38),G38*(1-N38)),2),IF(M38="MARKUP %",ROUND(R38/J38*(1+N38),2))),0) -> 0 | L38: =ROUND((J38*K38),2) -> 0 | M38: OEM DISC % | N38: 0.45 | R38: =ROUND(IF($R$17=$Q$17,Q38,IF($R$17="USD $",Q38*$D$15,Q38*$E$15))*E38,2) -> 0 | S38: =IFERROR(ROUND(T38/E38,2),0) -> 0 | T38: =ROUND(L38-R38,2) -> 0 | U38: =IFERROR(((K38-(R38/J38))/(R38/J38)),0) -> 0 | V38: =IFERROR(((K38-(R38/J38))/K38),0) -> 0
G39: =ROUND(IF($F$17="USD $", F39*$E$15,F39*$D$15),2) -> 0 | H39: =ROUND(IF($H$17=$G$17,E39*G39,E39*F39),2) -> 0 | J39: =E39 -> 0 | K39: =IFERROR(IF(M39="OEM DISC %",ROUND(IF($K$17=$F$17,F39*(1-N39),G39*(1-N39)),2),IF(M39="MARKUP %",ROUND(R39/J39*(1+N39),2))),0) -> 0 | L39: =ROUND((J39*K39),2) -> 0 | M39: OEM DISC % | N39: 0.45 | R39: =ROUND(IF($R$17=$Q$17,Q39,IF($R$17="USD $",Q39*$D$15,Q39*$E$15))*E39,2) -> 0 | S39: =IFERROR(ROUND(T39/E39,2),0) -> 0 | T39: =ROUND(L39-R39,2) -> 0 | U39: =IFERROR(((K39-(R39/J39))/(R39/J39)),0) -> 0 | V39: =IFERROR(((K39-(R39/J39))/K39),0) -> 0
G40: =ROUND(IF($F$17="USD $", F40*$E$15,F40*$D$15),2) -> 0 | H40: =ROUND(IF($H$17=$G$17,E40*G40,E40*F40),2) -> 0 | J40: =E40 -> 0 | K40: =IFERROR(IF(M40="OEM DISC %",ROUND(IF($K$17=$F$17,F40*(1-N40),G40*(1-N40)),2),IF(M40="MARKUP %",ROUND(R40/J40*(1+N40),2))),0) -> 0 | L40: =ROUND((J40*K40),2) -> 0 | M40: OEM DISC % | N40: 0.45 | R40: =ROUND(IF($R$17=$Q$17,Q40,IF($R$17="USD $",Q40*$D$15,Q40*$E$15))*E40,2) -> 0 | S40: =IFERROR(ROUND(T40/E40,2),0) -> 0 | T40: =ROUND(L40-R40,2) -> 0 | U40: =IFERROR(((K40-(R40/J40))/(R40/J40)),0) -> 0 | V40: =IFERROR(((K40-(R40/J40))/K40),0) -> 0
G41: =ROUND(IF($F$17="USD $", F41*$E$15,F41*$D$15),2) -> 0 | H41: =ROUND(IF($H$17=$G$17,E41*G41,E41*F41),2) -> 0 | J41: =E41 -> 0 | K41: =IFERROR(IF(M41="OEM DISC %",ROUND(IF($K$17=$F$17,F41*(1-N41),G41*(1-N41)),2),IF(M41="MARKUP %",ROUND(R41/J41*(1+N41),2))),0) -> 0 | L41: =ROUND((J41*K41),2) -> 0 | M41: OEM DISC % | N41: 0.45 | R41: =ROUND(IF($R$17=$Q$17,Q41,IF($R$17="USD $",Q41*$D$15,Q41*$E$15))*E41,2) -> 0 | S41: =IFERROR(ROUND(T41/E41,2),0) -> 0 | T41: =ROUND(L41-R41,2) -> 0 | U41: =IFERROR(((K41-(R41/J41))/(R41/J41)),0) -> 0 | V41: =IFERROR(((K41-(R41/J41))/K41),0) -> 0
G42: =ROUND(IF($F$17="USD $", F42*$E$15,F42*$D$15),2) -> 0 | H42: =ROUND(IF($H$17=$G$17,E42*G42,E42*F42),2) -> 0 | J42: =E42 -> 0 | K42: =IFERROR(IF(M42="OEM DISC %",ROUND(IF($K$17=$F$17,F42*(1-N42),G42*(1-N42)),2),IF(M42="MARKUP %",ROUND(R42/J42*(1+N42),2))),0) -> 0 | L42: =ROUND((J42*K42),2) -> 0 | M42: MARKUP % | N42: 0.45 | R42: =ROUND(IF($R$17=$Q$17,Q42,IF($R$17="USD $",Q42*$D$15,Q42*$E$15))*E42,2) -> 0 | S42: =IFERROR(ROUND(T42/E42,2),0) -> 0 | T42: =ROUND(L42-R42,2) -> 0 | U42: =IFERROR(((K42-(R42/J42))/(R42/J42)),0) -> 0 | V42: =IFERROR(((K42-(R42/J42))/K42),0) -> 0
G43: =ROUND(IF($F$17="USD $", F43*$E$15,F43*$D$15),2) -> 0 | H43: =ROUND(IF($H$17=$G$17,E43*G43,E43*F43),2) -> 0 | J43: =E43 -> 0 | K43: =IFERROR(IF(M43="OEM DISC %",ROUND(IF($K$17=$F$17,F43*(1-N43),G43*(1-N43)),2),IF(M43="MARKUP %",ROUND(R43/J43*(1+N43),2))),0) -> 0 | L43: =ROUND((J43*K43),2) -> 0 | M43: OEM DISC % | N43: 0.45 | R43: =ROUND(IF($R$17=$Q$17,Q43,IF($R$17="USD $",Q43*$D$15,Q43*$E$15))*E43,2) -> 0 | S43: =IFERROR(ROUND(T43/E43,2),0) -> 0 | T43: =ROUND(L43-R43,2) -> 0 | U43: =IFERROR(((K43-(R43/J43))/(R43/J43)),0) -> 0 | V43: =IFERROR(((K43-(R43/J43))/K43),0) -> 0
G44: =ROUND(IF($F$17="USD $", F44*$E$15,F44*$D$15),2) -> 0 | H44: =ROUND(IF($H$17=$G$17,E44*G44,E44*F44),2) -> 0 | J44: =E44 -> 0 | K44: =IFERROR(IF(M44="OEM DISC %",ROUND(IF($K$17=$F$17,F44*(1-N44),G44*(1-N44)),2),IF(M44="MARKUP %",ROUND(R44/J44*(1+N44),2))),0) -> 0 | L44: =ROUND((J44*K44),2) -> 0 | M44: OEM DISC % | N44: 0.45 | R44: =ROUND(IF($R$17=$Q$17,Q44,IF($R$17="USD $",Q44*$D$15,Q44*$E$15))*E44,2) -> 0 | S44: =IFERROR(ROUND(T44/E44,2),0) -> 0 | T44: =ROUND(L44-R44,2) -> 0 | U44: =IFERROR(((K44-(R44/J44))/(R44/J44)),0) -> 0 | V44: =IFERROR(((K44-(R44/J44))/K44),0) -> 0
G45: =ROUND(IF($F$17="USD $", F45*$E$15,F45*$D$15),2) -> 0 | H45: =ROUND(IF($H$17=$G$17,E45*G45,E45*F45),2) -> 0 | J45: =E45 -> 0 | K45: =IFERROR(IF(M45="OEM DISC %",ROUND(IF($K$17=$F$17,F45*(1-N45),G45*(1-N45)),2),IF(M45="MARKUP %",ROUND(R45/J45*(1+N45),2))),0) -> 0 | L45: =ROUND((J45*K45),2) -> 0 | M45: OEM DISC % | N45: 0.45 | R45: =ROUND(IF($R$17=$Q$17,Q45,IF($R$17="USD $",Q45*$D$15,Q45*$E$15))*E45,2) -> 0 | S45: =IFERROR(ROUND(T45/E45,2),0) -> 0 | T45: =ROUND(L45-R45,2) -> 0 | U45: =IFERROR(((K45-(R45/J45))/(R45/J45)),0) -> 0 | V45: =IFERROR(((K45-(R45/J45))/K45),0) -> 0
... G48: =ROUND(IF($F$17="USD $", F48*$E$15,F48*$D$15),2) -> 0 | H48: =ROUND(IF($H$17=$G$17,E48*G48,E48*F48),2) -> 0 | J48: =E48 -> 0 | K48: =IFERROR(IF(M48="OEM DISC %",ROUND(IF($K$17=$F$17,F48*(1-N48),G48*(1-N48)),2),IF(M48="MARKUP %",ROUND(R48/J48*(1+N48),2))),0) -> 0 | L48: =ROUND((J48*K48),2) -> 0 | M48: OEM DISC % | N48: 0.45 | R48: =ROUND(IF($R$17=$Q$17,Q48,IF($R$17="USD $",Q48*$D$15,Q48*$E$15))*E48,2) -> 0 | S48: =IFERROR(ROUND(T48/E48,2),0) -> 0 | T48: =ROUND(L48-R48,2) -> 0 | U48: =IFERROR(((K48-(R48/J48))/(R48/J48)),0) -> 0 | V48: =IFERROR(((K48-(R48/J48))/K48),0) -> 0
D49: TOTALS | E49: =SUM(E18:E48) -> 24 | F49: =SUM(F18:F48) -> 13810.24 | G49: =SUM(G18:G48) -> 19610.54 | H49: =SUM(H18:H48) -> 77837.91 | J49: =SUM(J18:J48) -> 24 | K49: =SUM(K18:K48) -> 10785.81 | L49: =SUM(L18:L48) -> 42810.89 | Q49: =SUM(Q18:Q48) -> 0 | R49: =SUM(R18:R48) -> 0 | S49: =SUM(S18:S48) -> 10785.81 | T49: =SUM(T18:T48) -> 42810.89

Sheet CAT 740 (3)
B1: CUSTOMER INFORMATION | D1: MACHINE INFORMATION | H1: MACHINE SERVICE HR INTERVALS | L1: SUMMARY | P1: =K17 -> CAD $ | S1: COMPLETED DEAL INFORMATION
B2: DATE: | D2: UNIT # | F2: AT-09 | H2: ENGINE AIR | L2: OEM MSRP | P2: =H49 -> 77837.91 | S2: SALES REP
B3: COMPANY: | D3: YEAR | F3: 2009 | H3: ENGINE OIL | L3: GQP LIST | P3: =L49 -> 42810.89 | S3: ORDER PO #
B4: CUSTOMER: | D4: MAKE | F4: CAT | H4: FUEL FILTERS | L4: $ SAVINGS | P4: =P2-P3 -> 35027.02 | S4: PROJECT #
B5: PHONE: | D5: MODEL | F5: 740 | H5: HYDRAULIC FILTERS | L5: % SAVINGS | P5: =IFERROR((P2-P3)/P2,"") -> 0.44999949 | S5: CUST INVOICE #
B6: EMAIL: | D6: SERIAL NUMBER | F6: B1P04865 | H6: TRANSMISSION FILTERS | L6: TOTAL ORDER MARGIN | P6: =T49 -> 42810.89 | S6: PAYMENT TYPE
B7: SALES REP: | D7: ENGINE SER NUMBER | F7: LHX22515 | H7: CAB FILTERS | L7: TOTAL ITEM COST | P7: =R49 -> 0 | S7: DATE DELIVERED
D8: CURRENT HOURS | H8: UNDERCARRIAGE / TIRES | L8: TOTAL ORDER FREIGHT | P8: =IF(P1=Q14,R14,IF(Q14="CAD $",R14*D15,IF(Q14="USD $",R14*E15,0))) -> 0 | S8: TOTAL COST | T8: NET MARGIN | U8: NET MARKUP % | V8: NET MARGIN %
D9: USAGE/MONTH | F9: Articulated Dump Truck | L9: TOTAL CUSTOMS/BROKERAGE | P9: =V14 -> 0 | S9: =P7+P8+P9 -> 0 | T9: =P3-S9 -> 42810.89 | U9: =IFERROR(((P3-S9)/S9),0) -> 0 | V9: =IFERROR(T9/P3,0) -> 1
L10: TOTAL NUMBER PIECES | P10: =E49 -> 24
D11: ENTER EXCHANGE RATES $ | F11: OEM MSRP | J11: CUSTOMER SELL PRICE | P11: COST ANALYSIS | Y11: CAD $
Y12: USD $
F13: SHOW OEM MSRP ON QUOTE: | H13: YES | Y13: YES
D14: CAD-USD | E14: USD-CAD | F14: OEM NAME | J14: CUSTOMER TYPE/TIER | L14: IE: VIP - Gold | P14: FREIGHT TOTAL ORDER | Q14: USD $ | S14: CUSTOMS AND BROKERAGE % | T14: 0.025 | U14: BROKERAGE FEES | V14: =ROUND(R49*T14,2) -> 0 | Y14: NO
D15: =1/E15 -> 0.70422535 | E15: 1.42 | P15: MARKUP LESS THAN 100% REQUIRES MANAGER APPROVAL
B16: PART NUMBER | C16: DESCRIPTION | D16: SERVICE INTERVAL | E16: QTY | F16: UNIT PRICE | H16: EXT AMOUNT | J16: QTY | K16: UNIT PRICE | L16: EXTENDED AMOUNT | M16: PRCING METHOD %OEM / MARKUP | N16: OEM DISC % / MARKUP % | P16: VENDOR | Q16: COST EACH | R16: EXTENDED COST | S16: MARGIN EACH | T16: EXTENDED MARGIN | U16: MARKUP % | V16: MARGIN %
F17: USD $ | G17: =IF(F17="USD $", "CAD $", "USD $") -> CAD $ | H17: =K17 -> CAD $ | K17: CAD $ | Q17: USD $ | R17: =K17 -> CAD $
B18: 1R-0716 | C18: ENGINE OIL FILTER | D18: 250 | E18: 1 | F18: 33.88 | G18: =ROUND(IF($F$17="USD $", F18*$E$15,F18*$D$15),2) -> 48.11 | H18: =ROUND(IF($H$17=$G$17,E18*G18,E18*F18),2) -> 48.11 | J18: =E18 -> 1 | K18: =IFERROR(IF(M18="OEM DISC %",ROUND(IF($K$17=$F$17,F18*(1-N18),G18*(1-N18)),2),IF(M18="MARKUP %",ROUND(R18/J18*(1+N18),2))),0) -> 26.46 | L18: =ROUND((J18*K18),2) -> 26.46 | M18: OEM DISC % | N18: 0.45 | R18: =ROUND(IF($R$17=$Q$17,Q18,IF($R$17="USD $",Q18*$D$15,Q18*$E$15))*E18,2) -> 0 | S18: =IFERROR(ROUND(T18/E18,2),0) -> 26.46 | T18: =ROUND(L18-R18,2) -> 26.46 | U18: =IFERROR(((K18-(R18/J18))/(R18/J18)),0) -> 0 | V18: =IFERROR(((K18-(R18/J18))/K18),0) -> 1 | Z18: 250
B19: 1R-0762 | C19: FUEL FILTER | D19: 250 | E19: 1 | F19: 45.86 | G19: =ROUND(IF($F$17="USD $", F19*$E$15,F19*$D$15),2) -> 65.12 | H19: =ROUND(IF($H$17=$G$17,E19*G19,E19*F19),2) -> 65.12 | J19: =E19 -> 1 | K19: =IFERROR(IF(M19="OEM DISC %",ROUND(IF($K$17=$F$17,F19*(1-N19),G19*(1-N19)),2),IF(M19="MARKUP %",ROUND(R19/J19*(1+N19),2))),0) -> 35.82 | L19: =ROUND((J19*K19),2) -> 35.82 | M19: OEM DISC % | N19: 0.45 | R19: =ROUND(IF($R$17=$Q$17,Q19,IF($R$17="USD $",Q19*$D$15,Q19*$E$15))*E19,2) -> 0 | S19: =IFERROR(ROUND(T19/E19,2),0) -> 35.82 | T19: =ROUND(L19-R19,2) -> 35.82 | U19: =IFERROR(((K19-(R19/J19))/(R19/J19)),0) -> 0 | V19: =IFERROR(((K19-(R19/J19))/K19),0) -> 1 | Y19: GQP | Z19: 500
B20: 326-1644 | C20: FUEL WATER SEPARATOR FILTER | D20: 500 | E20: 1 | F20: 58.2 | G20: =ROUND(IF($F$17="USD $", F20*$E$15,F20*$D$15),2) -> 82.64 | H20: =ROUND(IF($H$17=$G$17,E20*G20,E20*F20),2) -> 82.64 | J20: =E20 -> 1 | K20: =IFERROR(IF(M20="OEM DISC %",ROUND(IF($K$17=$F$17,F20*(1-N20),G20*(1-N20)),2),IF(M20="MARKUP %",ROUND(R20/J20*(1+N20),2))),0) -> 45.45 | L20: =ROUND((J20*K20),2) -> 45.45 | M20: OEM DISC % | N20: 0.45 | R20: =ROUND(IF($R$17=$Q$17,Q20,IF($R$17="USD $",Q20*$D$15,Q20*$E$15))*E20,2) -> 0 | S20: =IFERROR(ROUND(T20/E20,2),0) -> 45.45 | T20: =ROUND(L20-R20,2) -> 45.45 | U20: =IFERROR(((K20-(R20/J20))/(R20/J20)),0) -> 0 | V20: =IFERROR(((K20-(R20/J20))/K20),0) -> 1 | Y20: CTP | Z20: 750
B21: 1R-0719 | C21: TRANSMISSION FILTER | D21: 500 | E21: 1 | F21: 26.06 | G21: =ROUND(IF($F$17="USD $", F21*$E$15,F21*$D$15),2) -> 37.01 | H21: =ROUND(IF($H$17=$G$17,E21*G21,E21*F21),2) -> 37.01 | J21: =E21 -> 1 | K21: =IFERROR(IF(M21="OEM DISC %",ROUND(IF($K$17=$F$17,F21*(1-N21),G21*(1-N21)),2),IF(M21="MARKUP %",ROUND(R21/J21*(1+N21),2))),0) -> 20.36 | L21: =ROUND((J21*K21),2) -> 20.36 | M21: OEM DISC % | N21: 0.45 | R21: =ROUND(IF($R$17=$Q$17,Q21,IF($R$17="USD $",Q21*$D$15,Q21*$E$15))*E21,2) -> 0 | S21: =IFERROR(ROUND(T21/E21,2),0) -> 20.36 | T21: =ROUND(L21-R21,2) -> 20.36 | U21: =IFERROR(((K21-(R21/J21))/(R21/J21)),0) -> 0 | V21: =IFERROR(((K21-(R21/J21))/K21),0) -> 1 | Y21: BLMQ | Z21: 1000
B22: 1G-8878 | C22: HYDRAULIC FILTER | D22: 500 | E22: 1 | F22: 102.31 | G22: =ROUND(IF($F$17="USD $", F22*$E$15,F22*$D$15),2) -> 145.28 | H22: =ROUND(IF($H$17=$G$17,E22*G22,E22*F22),2) -> 145.28 | J22: =E22 -> 1 | K22: =IFERROR(IF(M22="OEM DISC %",ROUND(IF($K$17=$F$17,F22*(1-N22),G22*(1-N22)),2),IF(M22="MARKUP %",ROUND(R22/J22*(1+N22),2))),0) -> 79.9 | L22: =ROUND((J22*K22),2) -> 79.9 | M22: OEM DISC % | N22: 0.45 | R22: =ROUND(IF($R$17=$Q$17,Q22,IF($R$17="USD $",Q22*$D$15,Q22*$E$15))*E22,2) -> 0 | S22: =IFERROR(ROUND(T22/E22,2),0) -> 79.9 | T22: =ROUND(L22-R22,2) -> 79.9 | U22: =IFERROR(((K22-(R22/J22))/(R22/J22)),0) -> 0 | V22: =IFERROR(((K22-(R22/J22))/K22),0) -> 1 | Y22: CAT | Z22: 1200
B23: 142-1340 | C23: PRIMARY AIR FILTER | D23: 500 | E23: 1 | F23: 178.61 | G23: =ROUND(IF($F$17="USD $", F23*$E$15,F23*$D$15),2) -> 253.63 | H23: =ROUND(IF($H$17=$G$17,E23*G23,E23*F23),2) -> 253.63 | J23: =E23 -> 1 | K23: =IFERROR(IF(M23="OEM DISC %",ROUND(IF($K$17=$F$17,F23*(1-N23),G23*(1-N23)),2),IF(M23="MARKUP %",ROUND(R23/J23*(1+N23),2))),0) -> 139.5 | L23: =ROUND((J23*K23),2) -> 139.5 | M23: OEM DISC % | N23: 0.45 | R23: =ROUND(IF($R$17=$Q$17,Q23,IF($R$17="USD $",Q23*$D$15,Q23*$E$15))*E23,2) -> 0 | S23: =IFERROR(ROUND(T23/E23,2),0) -> 139.5 | T23: =ROUND(L23-R23,2) -> 139.5 | U23: =IFERROR(((K23-(R23/J23))/(R23/J23)),0) -> 0 | V23: =IFERROR(((K23-(R23/J23))/K23),0) -> 1 | Y23: FINNING | Z23: 2000
B24: 142-1403 | C24: SECONDARY AIR FILTER | D24: 250 | E24: 1 | F24: 99.07 | G24: =ROUND(IF($F$17="USD $", F24*$E$15,F24*$D$15),2) -> 140.68 | H24: =ROUND(IF($H$17=$G$17,E24*G24,E24*F24),2) -> 140.68 | J24: =E24 -> 1 | K24: =IFERROR(IF(M24="OEM DISC %",ROUND(IF($K$17=$F$17,F24*(1-N24),G24*(1-N24)),2),IF(M24="MARKUP %",ROUND(R24/J24*(1+N24),2))),0) -> 77.37 | L24: =ROUND((J24*K24),2) -> 77.37 | M24: OEM DISC % | N24: 0.45 | R24: =ROUND(IF($R$17=$Q$17,Q24,IF($R$17="USD $",Q24*$D$15,Q24*$E$15))*E24,2) -> 0 | S24: =IFERROR(ROUND(T24/E24,2),0) -> 77.37 | T24: =ROUND(L24-R24,2) -> 77.37 | U24: =IFERROR(((K24-(R24/J24))/(R24/J24)),0) -> 0 | V24: =IFERROR(((K24-(R24/J24))/K24),0) -> 1 | Y24: JD | Z24: 4000
B25: 268-6704 | C25: CABIN AIR FILTER | D25: 250 | E25: 1 | F25: 86.44 | G25: =ROUND(IF($F$17="USD $", F25*$E$15,F25*$D$15),2) -> 122.74 | H25: =ROUND(IF($H$17=$G$17,E25*G25,E25*F25),2) -> 122.74 | J25: =E25 -> 1 | K25: =IFERROR(IF(M25="OEM DISC %",ROUND(IF($K$17=$F$17,F25*(1-N25),G25*(1-N25)),2),IF(M25="MARKUP %",ROUND(R25/J25*(1+N25),2))),0) -> 67.51 | L25: =ROUND((J25*K25),2) -> 67.51 | M25: OEM DISC % | N25: 0.45 | R25: =ROUND(IF($R$17=$Q$17,Q25,IF($R$17="USD $",Q25*$D$15,Q25*$E$15))*E25,2) -> 0 | S25: =IFERROR(ROUND(T25/E25,2),0) -> 67.51 | T25: =ROUND(L25-R25,2) -> 67.51 | U25: =IFERROR(((K25-(R25/J25))/(R25/J25)),0) -> 0 | V25: =IFERROR(((K25-(R25/J25))/K25),0) -> 1 | Y25: BRANDT | Z25: 6000
G26: =ROUND(IF($F$17="USD $", F26*$E$15,F26*$D$15),2) -> 0 | H26: =ROUND(IF($H$17=$G$17,E26*G26,E26*F26),2) -> 0 | J26: =E26 -> 0 | K26: =IFERROR(IF(M26="OEM DISC %",ROUND(IF($K$17=$F$17,F26*(1-N26),G26*(1-N26)),2),IF(M26="MARKUP %",ROUND(R26/J26*(1+N26),2))),0) -> 0 | L26: =ROUND((J26*K26),2) -> 0 | M26: OEM DISC % | N26: 0.45 | R26: =ROUND(IF($R$17=$Q$17,Q26,IF($R$17="USD $",Q26*$D$15,Q26*$E$15))*E26,2) -> 0 | S26: =IFERROR(ROUND(T26/E26,2),0) -> 0 | T26: =ROUND(L26-R26,2) -> 0 | U26: =IFERROR(((K26-(R26/J26))/(R26/J26)),0) -> 0 | V26: =IFERROR(((K26-(R26/J26))/K26),0) -> 0 | Y26: PTI | Z26: 8000
B27: 447-1525 | C27: ENGINE OVERHAUL KIT SILVER | D27: 10000 | E27: 1 | G27: =ROUND(IF($F$17="USD $", F27*$E$15,F27*$D$15),2) -> 0 | H27: =ROUND(IF($H$17=$G$17,E27*G27,E27*F27),2) -> 0 | J27: =E27 -> 1 | K27: =IFERROR(IF(M27="OEM DISC %",ROUND(IF($K$17=$F$17,F27*(1-N27),G27*(1-N27)),2),IF(M27="MARKUP %",ROUND(R27/J27*(1+N27),2))),0) -> 0 | L27: =ROUND((J27*K27),2) -> 0 | M27: OEM DISC % | N27: 0.45 | R27: =ROUND(IF($R$17=$Q$17,Q27,IF($R$17="USD $",Q27*$D$15,Q27*$E$15))*E27,2) -> 0 | S27: =IFERROR(ROUND(T27/E27,2),0) -> 0 | T27: =ROUND(L27-R27,2) -> 0 | U27: =IFERROR(((K27-(R27/J27))/(R27/J27)),0) -> 0 | V27: =IFERROR(((K27-(R27/J27))/K27),0) -> 0 | Y27: CONEQUIP | Z27: 10000
C28: SEAT GP-SUSPENSION | G28: =ROUND(IF($F$17="USD $", F28*$E$15,F28*$D$15),2) -> 0 | H28: =ROUND(IF($H$17=$G$17,E28*G28,E28*F28),2) -> 0 | J28: =E28 -> 0 | K28: =IFERROR(IF(M28="OEM DISC %",ROUND(IF($K$17=$F$17,F28*(1-N28),G28*(1-N28)),2),IF(M28="MARKUP %",ROUND(R28/J28*(1+N28),2))),0) -> 0 | L28: =ROUND((J28*K28),2) -> 0 | M28: OEM DISC % | N28: 0.45 | R28: =ROUND(IF($R$17=$Q$17,Q28,IF($R$17="USD $",Q28*$D$15,Q28*$E$15))*E28,2) -> 0 | S28: =IFERROR(ROUND(T28/E28,2),0) -> 0 | T28: =ROUND(L28-R28,2) -> 0 | U28: =IFERROR(((K28-(R28/J28))/(R28/J28)),0) -> 0 | V28: =IFERROR(((K28-(R28/J28))/K28),0) -> 0 | Y28: CANDY | Z28: AS REQ'D
B29: 153-5700 | C29: BATTERY | D29: AS REQ'D | E29: 2 | F29: 493.89 | G29: =ROUND(IF($F$17="USD $", F29*$E$15,F29*$D$15),2) -> 701.32 | H29: =ROUND(IF($H$17=$G$17,E29*G29,E29*F29),2) -> 1402.64 | J29: =E29 -> 2 | K29: =IFERROR(IF(M29="OEM DISC %",ROUND(IF($K$17=$F$17,F29*(1-N29),G29*(1-N29)),2),IF(M29="MARKUP %",ROUND(R29/J29*(1+N29),2))),0) -> 385.73 | L29: =ROUND((J29*K29),2) -> 771.46 | M29: OEM DISC % | N29: 0.45 | R29: =ROUND(IF($R$17=$Q$17,Q29,IF($R$17="USD $",Q29*$D$15,Q29*$E$15))*E29,2) -> 0 | S29: =IFERROR(ROUND(T29/E29,2),0) -> 385.73 | T29: =ROUND(L29-R29,2) -> 771.46 | U29: =IFERROR(((K29-(R29/J29))/(R29/J29)),0) -> 0 | V29: =IFERROR(((K29-(R29/J29))/K29),0) -> 1 | Y29: U/C
B30: 230-3542 | C30: TURBOCHARGER | D30: 6000 | E30: 1 | F30: 4583.66 | G30: =ROUND(IF($F$17="USD $", F30*$E$15,F30*$D$15),2) -> 6508.8 | H30: =ROUND(IF($H$17=$G$17,E30*G30,E30*F30),2) -> 6508.8 | J30: =E30 -> 1 | K30: =IFERROR(IF(M30="OEM DISC %",ROUND(IF($K$17=$F$17,F30*(1-N30),G30*(1-N30)),2),IF(M30="MARKUP %",ROUND(R30/J30*(1+N30),2))),0) -> 3579.84 | L30: =ROUND((J30*K30),2) -> 3579.84 | M30: OEM DISC % | N30: 0.45 | R30: =ROUND(IF($R$17=$Q$17,Q30,IF($R$17="USD $",Q30*$D$15,Q30*$E$15))*E30,2) -> 0 | S30: =IFERROR(ROUND(T30/E30,2),0) -> 3579.84 | T30: =ROUND(L30-R30,2) -> 3579.84 | U30: =IFERROR(((K30-(R30/J30))/(R30/J30)),0) -> 0 | V30: =IFERROR(((K30-(R30/J30))/K30),0) -> 1
B31: 647-0750 | C31: INJECTOR | D31: 6000 | E31: 6 | F31: 1430.29 | G31: =ROUND(IF($F$17="USD $", F31*$E$15,F31*$D$15),2) -> 2031.01 | H31: =ROUND(IF($H$17=$G$17,E31*G31,E31*F31),2) -> 12186.06 | J31: =E31 -> 6 | K31: =IFERROR(IF(M31="OEM DISC %",ROUND(IF($K$17=$F$17,F31*(1-N31),G31*(1-N31)),2),IF(M31="MARKUP %",ROUND(R31/J31*(1+N31),2))),0) -> 1117.06 | L31: =ROUND((J31*K31),2) -> 6702.36 | M31: OEM DISC % | N31: 0.45 | R31: =ROUND(IF($R$17=$Q$17,Q31,IF($R$17="USD $",Q31*$D$15,Q31*$E$15))*E31,2) -> 0 | S31: =IFERROR(ROUND(T31/E31,2),0) -> 1117.06 | T31: =ROUND(L31-R31,2) -> 6702.36 | U31: =IFERROR(((K31-(R31/J31))/(R31/J31)),0) -> 0 | V31: =IFERROR(((K31-(R31/J31))/K31),0) -> 1 | Y31: OEM DISC %
G32: =ROUND(IF($F$17="USD $", F32*$E$15,F32*$D$15),2) -> 0 | H32: =ROUND(IF($H$17=$G$17,E32*G32,E32*F32),2) -> 0 | J32: =E32 -> 0 | K32: =IFERROR(IF(M32="OEM DISC %",ROUND(IF($K$17=$F$17,F32*(1-N32),G32*(1-N32)),2),IF(M32="MARKUP %",ROUND(R32/J32*(1+N32),2))),0) -> 0 | L32: =ROUND((J32*K32),2) -> 0 | M32: OEM DISC % | N32: 0.45 | R32: =ROUND(IF($R$17=$Q$17,Q32,IF($R$17="USD $",Q32*$D$15,Q32*$E$15))*E32,2) -> 0 | S32: =IFERROR(ROUND(T32/E32,2),0) -> 0 | T32: =ROUND(L32-R32,2) -> 0 | U32: =IFERROR(((K32-(R32/J32))/(R32/J32)),0) -> 0 | V32: =IFERROR(((K32-(R32/J32))/K32),0) -> 0 | Y32: MARKUP %
C33: TIRES 29.5r25 | D33: 5000 | E33: 6 | F33: 6671.97 | G33: =ROUND(IF($F$17="USD $", F33*$E$15,F33*$D$15),2) -> 9474.2 | H33: =ROUND(IF($H$17=$G$17,E33*G33,E33*F33),2) -> 56845.2 | J33: =E33 -> 6 | K33: =IFERROR(IF(M33="OEM DISC %",ROUND(IF($K$17=$F$17,F33*(1-N33),G33*(1-N33)),2),IF(M33="MARKUP %",ROUND(R33/J33*(1+N33),2))),0) -> 5210.81 | L33: =ROUND((J33*K33),2) -> 31264.86 | M33: OEM DISC % | N33: 0.45 | R33: =ROUND(IF($R$17=$Q$17,Q33,IF($R$17="USD $",Q33*$D$15,Q33*$E$15))*E33,2) -> 0 | S33: =IFERROR(ROUND(T33/E33,2),0) -> 5210.81 | T33: =ROUND(L33-R33,2) -> 31264.86 | U33: =IFERROR(((K33-(R33/J33))/(R33/J33)),0) -> 0 | V33: =IFERROR(((K33-(R33/J33))/K33),0) -> 1
G34: =ROUND(IF($F$17="USD $", F34*$E$15,F34*$D$15),2) -> 0 | H34: =ROUND(IF($H$17=$G$17,E34*G34,E34*F34),2) -> 0 | J34: =E34 -> 0 | K34: =IFERROR(IF(M34="OEM DISC %",ROUND(IF($K$17=$F$17,F34*(1-N34),G34*(1-N34)),2),IF(M34="MARKUP %",ROUND(R34/J34*(1+N34),2))),0) -> 0 | L34: =ROUND((J34*K34),2) -> 0 | M34: OEM DISC % | N34: 0.45 | R34: =ROUND(IF($R$17=$Q$17,Q34,IF($R$17="USD $",Q34*$D$15,Q34*$E$15))*E34,2) -> 0 | S34: =IFERROR(ROUND(T34/E34,2),0) -> 0 | T34: =ROUND(L34-R34,2) -> 0 | U34: =IFERROR(((K34-(R34/J34))/(R34/J34)),0) -> 0 | V34: =IFERROR(((K34-(R34/J34))/K34),0) -> 0
G35: =ROUND(IF($F$17="USD $", F35*$E$15,F35*$D$15),2) -> 0 | H35: =ROUND(IF($H$17=$G$17,E35*G35,E35*F35),2) -> 0 | J35: =E35 -> 0 | K35: =IFERROR(IF(M35="OEM DISC %",ROUND(IF($K$17=$F$17,F35*(1-N35),G35*(1-N35)),2),IF(M35="MARKUP %",ROUND(R35/J35*(1+N35),2))),0) -> 0 | L35: =ROUND((J35*K35),2) -> 0 | M35: OEM DISC % | N35: 0.45 | R35: =ROUND(IF($R$17=$Q$17,Q35,IF($R$17="USD $",Q35*$D$15,Q35*$E$15))*E35,2) -> 0 | S35: =IFERROR(ROUND(T35/E35,2),0) -> 0 | T35: =ROUND(L35-R35,2) -> 0 | U35: =IFERROR(((K35-(R35/J35))/(R35/J35)),0) -> 0 | V35: =IFERROR(((K35-(R35/J35))/K35),0) -> 0
G36: =ROUND(IF($F$17="USD $", F36*$E$15,F36*$D$15),2) -> 0 | H36: =ROUND(IF($H$17=$G$17,E36*G36,E36*F36),2) -> 0 | J36: =E36 -> 0 | K36: =IFERROR(IF(M36="OEM DISC %",ROUND(IF($K$17=$F$17,F36*(1-N36),G36*(1-N36)),2),IF(M36="MARKUP %",ROUND(R36/J36*(1+N36),2))),0) -> 0 | L36: =ROUND((J36*K36),2) -> 0 | M36: OEM DISC % | N36: 0.45 | R36: =ROUND(IF($R$17=$Q$17,Q36,IF($R$17="USD $",Q36*$D$15,Q36*$E$15))*E36,2) -> 0 | S36: =IFERROR(ROUND(T36/E36,2),0) -> 0 | T36: =ROUND(L36-R36,2) -> 0 | U36: =IFERROR(((K36-(R36/J36))/(R36/J36)),0) -> 0 | V36: =IFERROR(((K36-(R36/J36))/K36),0) -> 0
G37: =ROUND(IF($F$17="USD $", F37*$E$15,F37*$D$15),2) -> 0 | H37: =ROUND(IF($H$17=$G$17,E37*G37,E37*F37),2) -> 0 | J37: =E37 -> 0 | K37: =IFERROR(IF(M37="OEM DISC %",ROUND(IF($K$17=$F$17,F37*(1-N37),G37*(1-N37)),2),IF(M37="MARKUP %",ROUND(R37/J37*(1+N37),2))),0) -> 0 | L37: =ROUND((J37*K37),2) -> 0 | M37: OEM DISC % | N37: 0.45 | R37: =ROUND(IF($R$17=$Q$17,Q37,IF($R$17="USD $",Q37*$D$15,Q37*$E$15))*E37,2) -> 0 | S37: =IFERROR(ROUND(T37/E37,2),0) -> 0 | T37: =ROUND(L37-R37,2) -> 0 | U37: =IFERROR(((K37-(R37/J37))/(R37/J37)),0) -> 0 | V37: =IFERROR(((K37-(R37/J37))/K37),0) -> 0
G38: =ROUND(IF($F$17="USD $", F38*$E$15,F38*$D$15),2) -> 0 | H38: =ROUND(IF($H$17=$G$17,E38*G38,E38*F38),2) -> 0 | J38: =E38 -> 0 | K38: =IFERROR(IF(M38="OEM DISC %",ROUND(IF($K$17=$F$17,F38*(1-N38),G38*(1-N38)),2),IF(M38="MARKUP %",ROUND(R38/J38*(1+N38),2))),0) -> 0 | L38: =ROUND((J38*K38),2) -> 0 | M38: OEM DISC % | N38: 0.45 | R38: =ROUND(IF($R$17=$Q$17,Q38,IF($R$17="USD $",Q38*$D$15,Q38*$E$15))*E38,2) -> 0 | S38: =IFERROR(ROUND(T38/E38,2),0) -> 0 | T38: =ROUND(L38-R38,2) -> 0 | U38: =IFERROR(((K38-(R38/J38))/(R38/J38)),0) -> 0 | V38: =IFERROR(((K38-(R38/J38))/K38),0) -> 0
G39: =ROUND(IF($F$17="USD $", F39*$E$15,F39*$D$15),2) -> 0 | H39: =ROUND(IF($H$17=$G$17,E39*G39,E39*F39),2) -> 0 | J39: =E39 -> 0 | K39: =IFERROR(IF(M39="OEM DISC %",ROUND(IF($K$17=$F$17,F39*(1-N39),G39*(1-N39)),2),IF(M39="MARKUP %",ROUND(R39/J39*(1+N39),2))),0) -> 0 | L39: =ROUND((J39*K39),2) -> 0 | M39: OEM DISC % | N39: 0.45 | R39: =ROUND(IF($R$17=$Q$17,Q39,IF($R$17="USD $",Q39*$D$15,Q39*$E$15))*E39,2) -> 0 | S39: =IFERROR(ROUND(T39/E39,2),0) -> 0 | T39: =ROUND(L39-R39,2) -> 0 | U39: =IFERROR(((K39-(R39/J39))/(R39/J39)),0) -> 0 | V39: =IFERROR(((K39-(R39/J39))/K39),0) -> 0
G40: =ROUND(IF($F$17="USD $", F40*$E$15,F40*$D$15),2) -> 0 | H40: =ROUND(IF($H$17=$G$17,E40*G40,E40*F40),2) -> 0 | J40: =E40 -> 0 | K40: =IFERROR(IF(M40="OEM DISC %",ROUND(IF($K$17=$F$17,F40*(1-N40),G40*(1-N40)),2),IF(M40="MARKUP %",ROUND(R40/J40*(1+N40),2))),0) -> 0 | L40: =ROUND((J40*K40),2) -> 0 | M40: OEM DISC % | N40: 0.45 | R40: =ROUND(IF($R$17=$Q$17,Q40,IF($R$17="USD $",Q40*$D$15,Q40*$E$15))*E40,2) -> 0 | S40: =IFERROR(ROUND(T40/E40,2),0) -> 0 | T40: =ROUND(L40-R40,2) -> 0 | U40: =IFERROR(((K40-(R40/J40))/(R40/J40)),0) -> 0 | V40: =IFERROR(((K40-(R40/J40))/K40),0) -> 0
G41: =ROUND(IF($F$17="USD $", F41*$E$15,F41*$D$15),2) -> 0 | H41: =ROUND(IF($H$17=$G$17,E41*G41,E41*F41),2) -> 0 | J41: =E41 -> 0 | K41: =IFERROR(IF(M41="OEM DISC %",ROUND(IF($K$17=$F$17,F41*(1-N41),G41*(1-N41)),2),IF(M41="MARKUP %",ROUND(R41/J41*(1+N41),2))),0) -> 0 | L41: =ROUND((J41*K41),2) -> 0 | M41: OEM DISC % | N41: 0.45 | R41: =ROUND(IF($R$17=$Q$17,Q41,IF($R$17="USD $",Q41*$D$15,Q41*$E$15))*E41,2) -> 0 | S41: =IFERROR(ROUND(T41/E41,2),0) -> 0 | T41: =ROUND(L41-R41,2) -> 0 | U41: =IFERROR(((K41-(R41/J41))/(R41/J41)),0) -> 0 | V41: =IFERROR(((K41-(R41/J41))/K41),0) -> 0
G42: =ROUND(IF($F$17="USD $", F42*$E$15,F42*$D$15),2) -> 0 | H42: =ROUND(IF($H$17=$G$17,E42*G42,E42*F42),2) -> 0 | J42: =E42 -> 0 | K42: =IFERROR(IF(M42="OEM DISC %",ROUND(IF($K$17=$F$17,F42*(1-N42),G42*(1-N42)),2),IF(M42="MARKUP %",ROUND(R42/J42*(1+N42),2))),0) -> 0 | L42: =ROUND((J42*K42),2) -> 0 | M42: MARKUP % | N42: 0.45 | R42: =ROUND(IF($R$17=$Q$17,Q42,IF($R$17="USD $",Q42*$D$15,Q42*$E$15))*E42,2) -> 0 | S42: =IFERROR(ROUND(T42/E42,2),0) -> 0 | T42: =ROUND(L42-R42,2) -> 0 | U42: =IFERROR(((K42-(R42/J42))/(R42/J42)),0) -> 0 | V42: =IFERROR(((K42-(R42/J42))/K42),0) -> 0
G43: =ROUND(IF($F$17="USD $", F43*$E$15,F43*$D$15),2) -> 0 | H43: =ROUND(IF($H$17=$G$17,E43*G43,E43*F43),2) -> 0 | J43: =E43 -> 0 | K43: =IFERROR(IF(M43="OEM DISC %",ROUND(IF($K$17=$F$17,F43*(1-N43),G43*(1-N43)),2),IF(M43="MARKUP %",ROUND(R43/J43*(1+N43),2))),0) -> 0 | L43: =ROUND((J43*K43),2) -> 0 | M43: OEM DISC % | N43: 0.45 | R43: =ROUND(IF($R$17=$Q$17,Q43,IF($R$17="USD $",Q43*$D$15,Q43*$E$15))*E43,2) -> 0 | S43: =IFERROR(ROUND(T43/E43,2),0) -> 0 | T43: =ROUND(L43-R43,2) -> 0 | U43: =IFERROR(((K43-(R43/J43))/(R43/J43)),0) -> 0 | V43: =IFERROR(((K43-(R43/J43))/K43),0) -> 0
G44: =ROUND(IF($F$17="USD $", F44*$E$15,F44*$D$15),2) -> 0 | H44: =ROUND(IF($H$17=$G$17,E44*G44,E44*F44),2) -> 0 | J44: =E44 -> 0 | K44: =IFERROR(IF(M44="OEM DISC %",ROUND(IF($K$17=$F$17,F44*(1-N44),G44*(1-N44)),2),IF(M44="MARKUP %",ROUND(R44/J44*(1+N44),2))),0) -> 0 | L44: =ROUND((J44*K44),2) -> 0 | M44: OEM DISC % | N44: 0.45 | R44: =ROUND(IF($R$17=$Q$17,Q44,IF($R$17="USD $",Q44*$D$15,Q44*$E$15))*E44,2) -> 0 | S44: =IFERROR(ROUND(T44/E44,2),0) -> 0 | T44: =ROUND(L44-R44,2) -> 0 | U44: =IFERROR(((K44-(R44/J44))/(R44/J44)),0) -> 0 | V44: =IFERROR(((K44-(R44/J44))/K44),0) -> 0
G45: =ROUND(IF($F$17="USD $", F45*$E$15,F45*$D$15),2) -> 0 | H45: =ROUND(IF($H$17=$G$17,E45*G45,E45*F45),2) -> 0 | J45: =E45 -> 0 | K45: =IFERROR(IF(M45="OEM DISC %",ROUND(IF($K$17=$F$17,F45*(1-N45),G45*(1-N45)),2),IF(M45="MARKUP %",ROUND(R45/J45*(1+N45),2))),0) -> 0 | L45: =ROUND((J45*K45),2) -> 0 | M45: OEM DISC % | N45: 0.45 | R45: =ROUND(IF($R$17=$Q$17,Q45,IF($R$17="USD $",Q45*$D$15,Q45*$E$15))*E45,2) -> 0 | S45: =IFERROR(ROUND(T45/E45,2),0) -> 0 | T45: =ROUND(L45-R45,2) -> 0 | U45: =IFERROR(((K45-(R45/J45))/(R45/J45)),0) -> 0 | V45: =IFERROR(((K45-(R45/J45))/K45),0) -> 0
... G48: =ROUND(IF($F$17="USD $", F48*$E$15,F48*$D$15),2) -> 0 | H48: =ROUND(IF($H$17=$G$17,E48*G48,E48*F48),2) -> 0 | J48: =E48 -> 0 | K48: =IFERROR(IF(M48="OEM DISC %",ROUND(IF($K$17=$F$17,F48*(1-N48),G48*(1-N48)),2),IF(M48="MARKUP %",ROUND(R48/J48*(1+N48),2))),0) -> 0 | L48: =ROUND((J48*K48),2) -> 0 | M48: OEM DISC % | N48: 0.45 | R48: =ROUND(IF($R$17=$Q$17,Q48,IF($R$17="USD $",Q48*$D$15,Q48*$E$15))*E48,2) -> 0 | S48: =IFERROR(ROUND(T48/E48,2),0) -> 0 | T48: =ROUND(L48-R48,2) -> 0 | U48: =IFERROR(((K48-(R48/J48))/(R48/J48)),0) -> 0 | V48: =IFERROR(((K48-(R48/J48))/K48),0) -> 0
D49: TOTALS | E49: =SUM(E18:E48) -> 24 | F49: =SUM(F18:F48) -> 13810.24 | G49: =SUM(G18:G48) -> 19610.54 | H49: =SUM(H18:H48) -> 77837.91 | J49: =SUM(J18:J48) -> 24 | K49: =SUM(K18:K48) -> 10785.81 | L49: =SUM(L18:L48) -> 42810.89 | Q49: =SUM(Q18:Q48) -> 0 | R49: =SUM(R18:R48) -> 0 | S49: =SUM(S18:S48) -> 10785.81 | T49: =SUM(T18:T48) -> 42810.89

Sheet CAT 422E
B1: CUSTOMER INFORMATION | D1: MACHINE INFORMATION | H1: MACHINE SERVICE HR INTERVALS | L1: SUMMARY | P1: =K17 -> CAD $ | S1: COMPLETED DEAL INFORMATION
B2: DATE: | D2: UNIT # | F2: BH-07 | H2: ENGINE AIR | L2: OEM MSRP | P2: =H49 -> #REF! | S2: SALES REP
B3: COMPANY: | D3: YEAR | F3: 2012 | H3: ENGINE OIL | L3: GQP LIST | P3: =L49 -> #REF! | S3: ORDER PO #
B4: CUSTOMER: | D4: MAKE | F4: CAT | H4: FUEL FILTERS | L4: $ SAVINGS | P4: =P2-P3 -> #REF! | S4: PROJECT #
B5: PHONE: | D5: MODEL | F5: 422E | H5: HYDRAULIC FILTERS | L5: % SAVINGS | P5: =IFERROR((P2-P3)/P2,"") | S5: CUST INVOICE #
B6: EMAIL: | D6: SERIAL NUMBER | F6: MAW01556 | H6: TRANSMISSION FILTERS | L6: TOTAL ORDER MARGIN | P6: =T49 -> #REF! | S6: PAYMENT TYPE
B7: SALES REP: | D7: ENGINE SER NUMBER | F7: CRS67419 | H7: CAB FILTERS | L7: TOTAL ITEM COST | P7: =R49 -> #REF! | S7: DATE DELIVERED
D8: CURRENT HOURS | H8: UNDERCARRIAGE / TIRES | L8: TOTAL ORDER FREIGHT | P8: =IF(P1=Q14,R14,IF(Q14="CAD $",R14*D15,IF(Q14="USD $",R14*E15,0))) -> 0 | S8: TOTAL COST | T8: NET MARGIN | U8: NET MARKUP % | V8: NET MARGIN %
D9: USAGE/MONTH | F9: Backhoe Loader | L9: TOTAL CUSTOMS/BROKERAGE | P9: =V14 -> #REF! | S9: =P7+P8+P9 -> #REF! | T9: =P3-S9 -> #REF! | U9: =IFERROR(((P3-S9)/S9),0) -> 0 | V9: =IFERROR(T9/P3,0) -> 0
L10: TOTAL NUMBER PIECES | P10: =E49 -> 86
D11: ENTER EXCHANGE RATES $ | F11: OEM MSRP | J11: CUSTOMER SELL PRICE | P11: COST ANALYSIS | Y11: CAD $
Y12: USD $
F13: SHOW OEM MSRP ON QUOTE: | H13: YES | Y13: YES
D14: CAD-USD | E14: USD-CAD | F14: OEM NAME | J14: CUSTOMER TYPE/TIER | L14: IE: VIP - Gold | P14: FREIGHT TOTAL ORDER | Q14: USD $ | S14: CUSTOMS AND BROKERAGE % | T14: 0.025 | U14: BROKERAGE FEES | V14: =ROUND(R49*T14,2) -> #REF! | Y14: NO
D15: =1/E15 -> 0.70422535 | E15: 1.42 | P15: MARKUP LESS THAN 100% REQUIRES MANAGER APPROVAL
B16: PART NUMBER | C16: DESCRIPTION | D16: SERVICE INTERVAL | E16: QTY | F16: UNIT PRICE | H16: EXT AMOUNT | J16: QTY | K16: UNIT PRICE | L16: EXTENDED AMOUNT | M16: PRCING METHOD %OEM / MARKUP | N16: OEM DISC % / MARKUP % | P16: VENDOR | Q16: COST EACH | R16: EXTENDED COST | S16: MARGIN EACH | T16: EXTENDED MARGIN | U16: MARKUP % | V16: MARGIN %
F17: USD $ | G17: =IF(F17="USD $", "CAD $", "USD $") -> CAD $ | H17: =K17 -> CAD $ | K17: CAD $ | Q17: USD $ | R17: =K17 -> CAD $
B18: 7W-2326 | C18: ENGINE OIL FILTER | D18: 250 | E18: 1 | F18: 20.98 | G18: =ROUND(IF($F$17="USD $", F18*$E$15,F18*$D$15),2) -> 29.79 | H18: =ROUND(IF($H$17=$G$17,E18*G18,E18*F18),2) -> 29.79 | J18: =E18 -> 1 | K18: =IFERROR(IF(M18="OEM DISC %",ROUND(IF($K$17=$F$17,F18*(1-N18),G18*(1-N18)),2),IF(M18="MARKUP %",ROUND(R18/J18*(1+N18),2))),0) -> 16.38 | L18: =ROUND((J18*K18),2) -> 16.38 | M18: OEM DISC % | N18: 0.45 | R18: =ROUND(IF($R$17=$Q$17,Q18,IF($R$17="USD $",Q18*$D$15,Q18*$E$15))*E18,2) -> 0 | S18: =IFERROR(ROUND(T18/E18,2),0) -> 16.38 | T18: =ROUND(L18-R18,2) -> 16.38 | U18: =IFERROR(((K18-(R18/J18))/(R18/J18)),0) -> 0 | V18: =IFERROR(((K18-(R18/J18))/K18),0) -> 1 | Z18: 250
C19: FUEL FILTER | G19: =ROUND(IF($F$17="USD $", F19*$E$15,F19*$D$15),2) -> 0 | H19: =ROUND(IF($H$17=$G$17,E19*G19,E19*F19),2) -> 0 | J19: =E19 -> 0 | K19: =IFERROR(IF(M19="OEM DISC %",ROUND(IF($K$17=$F$17,F19*(1-N19),G19*(1-N19)),2),IF(M19="MARKUP %",ROUND(R19/J19*(1+N19),2))),0) -> 0 | L19: =ROUND((J19*K19),2) -> 0 | M19: OEM DISC % | N19: 0.45 | R19: =ROUND(IF($R$17=$Q$17,Q19,IF($R$17="USD $",Q19*$D$15,Q19*$E$15))*E19,2) -> 0 | S19: =IFERROR(ROUND(T19/E19,2),0) -> 0 | T19: =ROUND(L19-R19,2) -> 0 | U19: =IFERROR(((K19-(R19/J19))/(R19/J19)),0) -> 0 | V19: =IFERROR(((K19-(R19/J19))/K19),0) -> 0 | Y19: GQP | Z19: 500
B20: 228-9130 | C20: FUEL WATER SEPARATOR FILTER | D20: 250 | E20: 1 | F20: 46.86 | G20: =ROUND(IF($F$17="USD $", F20*$E$15,F20*$D$15),2) -> 66.54 | H20: =ROUND(IF($H$17=$G$17,E20*G20,E20*F20),2) -> 66.54 | J20: =E20 -> 1 | K20: =IFERROR(IF(M20="OEM DISC %",ROUND(IF($K$17=$F$17,F20*(1-N20),G20*(1-N20)),2),IF(M20="MARKUP %",ROUND(R20/J20*(1+N20),2))),0) -> 36.6 | L20: =ROUND((J20*K20),2) -> 36.6 | M20: OEM DISC % | N20: 0.45 | R20: =ROUND(IF($R$17=$Q$17,Q20,IF($R$17="USD $",Q20*$D$15,Q20*$E$15))*E20,2) -> 0 | S20: =IFERROR(ROUND(T20/E20,2),0) -> 36.6 | T20: =ROUND(L20-R20,2) -> 36.6 | U20: =IFERROR(((K20-(R20/J20))/(R20/J20)),0) -> 0 | V20: =IFERROR(((K20-(R20/J20))/K20),0) -> 1 | Y20: CTP | Z20: 750
C21: TRANSMISSION FILTER | G21: =ROUND(IF($F$17="USD $", F21*$E$15,F21*$D$15),2) -> 0 | H21: =ROUND(IF($H$17=$G$17,E21*G21,E21*F21),2) -> 0 | J21: =E21 -> 0 | K21: =IFERROR(IF(M21="OEM DISC %",ROUND(IF($K$17=$F$17,F21*(1-N21),G21*(1-N21)),2),IF(M21="MARKUP %",ROUND(R21/J21*(1+N21),2))),0) -> 0 | L21: =ROUND((J21*K21),2) -> 0 | M21: OEM DISC % | N21: 0.45 | R21: =ROUND(IF($R$17=$Q$17,Q21,IF($R$17="USD $",Q21*$D$15,Q21*$E$15))*E21,2) -> 0 | S21: =IFERROR(ROUND(T21/E21,2),0) -> 0 | T21: =ROUND(L21-R21,2) -> 0 | U21: =IFERROR(((K21-(R21/J21))/(R21/J21)),0) -> 0 | V21: =IFERROR(((K21-(R21/J21))/K21),0) -> 0 | Y21: BLMQ | Z21: 1000
B22: 119-4740 | C22: HYDRAULIC FILTER | D22: 500 | E22: 1 | G22: =ROUND(IF($F$17="USD $", F22*$E$15,F22*$D$15),2) -> 0 | H22: =ROUND(IF($H$17=$G$17,E22*G22,E22*F22),2) -> 0 | J22: =E22 -> 1 | K22: =IFERROR(IF(M22="OEM DISC %",ROUND(IF($K$17=$F$17,F22*(1-N22),G22*(1-N22)),2),IF(M22="MARKUP %",ROUND(R22/J22*(1+N22),2))),0) -> 0 | L22: =ROUND((J22*K22),2) -> 0 | M22: OEM DISC % | N22: 0.45 | R22: =ROUND(IF($R$17=$Q$17,Q22,IF($R$17="USD $",Q22*$D$15,Q22*$E$15))*E22,2) -> 0 | S22: =IFERROR(ROUND(T22/E22,2),0) -> 0 | T22: =ROUND(L22-R22,2) -> 0 | U22: =IFERROR(((K22-(R22/J22))/(R22/J22)),0) -> 0 | V22: =IFERROR(((K22-(R22/J22))/K22),0) -> 0 | Y22: CAT | Z22: 1200
B23: 293-4053 | C23: PRIMARY AIR FILTER | D23: 500 | E23: 1 | F23: 100.77 | G23: =ROUND(IF($F$17="USD $", F23*$E$15,F23*$D$15),2) -> 143.09 | H23: =ROUND(IF($H$17=$G$17,E23*G23,E23*F23),2) -> 143.09 | J23: =E23 -> 1 | K23: =IFERROR(IF(M23="OEM DISC %",ROUND(IF($K$17=$F$17,F23*(1-N23),G23*(1-N23)),2),IF(M23="MARKUP %",ROUND(R23/J23*(1+N23),2))),0) -> 78.7 | L23: =ROUND((J23*K23),2) -> 78.7 | M23: OEM DISC % | N23: 0.45 | R23: =ROUND(IF($R$17=$Q$17,Q23,IF($R$17="USD $",Q23*$D$15,Q23*$E$15))*E23,2) -> 0 | S23: =IFERROR(ROUND(T23/E23,2),0) -> 78.7 | T23: =ROUND(L23-R23,2) -> 78.7 | U23: =IFERROR(((K23-(R23/J23))/(R23/J23)),0) -> 0 | V23: =IFERROR(((K23-(R23/J23))/K23),0) -> 1 | Y23: FINNING | Z23: 2000
B24: 227-7449 | C24: SECONDARY AIR FILTER | D24: 500 | E24: 1 | F24: 63.13 | G24: =ROUND(IF($F$17="USD $", F24*$E$15,F24*$D$15),2) -> 89.64 | H24: =ROUND(IF($H$17=$G$17,E24*G24,E24*F24),2) -> 89.64 | J24: =E24 -> 1 | K24: =IFERROR(IF(M24="OEM DISC %",ROUND(IF($K$17=$F$17,F24*(1-N24),G24*(1-N24)),2),IF(M24="MARKUP %",ROUND(R24/J24*(1+N24),2))),0) -> 49.3 | L24: =ROUND((J24*K24),2) -> 49.3 | M24: OEM DISC % | N24: 0.45 | R24: =ROUND(IF($R$17=$Q$17,Q24,IF($R$17="USD $",Q24*$D$15,Q24*$E$15))*E24,2) -> 0 | S24: =IFERROR(ROUND(T24/E24,2),0) -> 49.3 | T24: =ROUND(L24-R24,2) -> 49.3 | U24: =IFERROR(((K24-(R24/J24))/(R24/J24)),0) -> 0 | V24: =IFERROR(((K24-(R24/J24))/K24),0) -> 1 | Y24: JD | Z24: 4000
B25: 211-2661 | C25: CABIN AIR FILTER | D25: 250 | E25: 1 | F25: 42.9 | G25: =ROUND(IF($F$17="USD $", F25*$E$15,F25*$D$15),2) -> 60.92 | H25: =ROUND(IF($H$17=$G$17,E25*G25,E25*F25),2) -> 60.92 | J25: =E25 -> 1 | K25: =IFERROR(IF(M25="OEM DISC %",ROUND(IF($K$17=$F$17,F25*(1-N25),G25*(1-N25)),2),IF(M25="MARKUP %",ROUND(R25/J25*(1+N25),2))),0) -> 33.51 | L25: =ROUND((J25*K25),2) -> 33.51 | M25: OEM DISC % | N25: 0.45 | R25: =ROUND(IF($R$17=$Q$17,Q25,IF($R$17="USD $",Q25*$D$15,Q25*$E$15))*E25,2) -> 0 | S25: =IFERROR(ROUND(T25/E25,2),0) -> 33.51 | T25: =ROUND(L25-R25,2) -> 33.51 | U25: =IFERROR(((K25-(R25/J25))/(R25/J25)),0) -> 0 | V25: =IFERROR(((K25-(R25/J25))/K25),0) -> 1 | Y25: BRANDT | Z25: 6000
B26: 211-2660 | C26: CABIN AIR FILTER | D26: 250 | E26: 1 | F26: 52.68 | G26: =ROUND(IF($F$17="USD $", F26*$E$15,F26*$D$15),2) -> 74.81 | H26: =ROUND(IF($H$17=$G$17,E26*G26,E26*F26),2) -> 74.81 | J26: =E26 -> 1 | K26: =IFERROR(IF(M26="OEM DISC %",ROUND(IF($K$17=$F$17,F26*(1-N26),G26*(1-N26)),2),IF(M26="MARKUP %",ROUND(R26/J26*(1+N26),2))),0) -> 41.15 | L26: =ROUND((J26*K26),2) -> 41.15 | M26: OEM DISC % | N26: 0.45 | R26: =ROUND(IF($R$17=$Q$17,Q26,IF($R$17="USD $",Q26*$D$15,Q26*$E$15))*E26,2) -> 0 | S26: =IFERROR(ROUND(T26/E26,2),0) -> 41.15 | T26: =ROUND(L26-R26,2) -> 41.15 | U26: =IFERROR(((K26-(R26/J26))/(R26/J26)),0) -> 0 | V26: =IFERROR(((K26-(R26/J26))/K26),0) -> 1 | Y26: PTI | Z26: 8000
B27: 656-3635 | C27: ENGINE OVERHAUL KIT BRONZE | D27: 10000 | E27: 1 | G27: =ROUND(IF($F$17="USD $", F27*$E$15,F27*$D$15),2) -> 0 | H27: =ROUND(IF($H$17=$G$17,E27*G27,E27*F27),2) -> 0 | J27: =E27 -> 1 | K27: =IFERROR(IF(M27="OEM DISC %",ROUND(IF($K$17=$F$17,F27*(1-N27),G27*(1-N27)),2),IF(M27="MARKUP %",ROUND(R27/J27*(1+N27),2))),0) -> 0 | L27: =ROUND((J27*K27),2) -> 0 | M27: OEM DISC % | N27: 0.45 | R27: =ROUND(IF($R$17=$Q$17,Q27,IF($R$17="USD $",Q27*$D$15,Q27*$E$15))*E27,2) -> 0 | S27: =IFERROR(ROUND(T27/E27,2),0) -> 0 | T27: =ROUND(L27-R27,2) -> 0 | U27: =IFERROR(((K27-(R27/J27))/(R27/J27)),0) -> 0 | V27: =IFERROR(((K27-(R27/J27))/K27),0) -> 0 | Y27: CONEQUIP | Z27: 10000
C28: SEAT GP-SUSPENSION | G28: =ROUND(IF($F$17="USD $", F28*$E$15,F28*$D$15),2) -> 0 | H28: =ROUND(IF($H$17=$G$17,E28*G28,E28*F28),2) -> 0 | J28: =E28 -> 0 | K28: =IFERROR(IF(M28="OEM DISC %",ROUND(IF($K$17=$F$17,F28*(1-N28),G28*(1-N28)),2),IF(M28="MARKUP %",ROUND(R28/J28*(1+N28),2))),0) -> 0 | L28: =ROUND((J28*K28),2) -> 0 | M28: OEM DISC % | N28: 0.45 | R28: =ROUND(IF($R$17=$Q$17,Q28,IF($R$17="USD $",Q28*$D$15,Q28*$E$15))*E28,2) -> 0 | S28: =IFERROR(ROUND(T28/E28,2),0) -> 0 | T28: =ROUND(L28-R28,2) -> 0 | U28: =IFERROR(((K28-(R28/J28))/(R28/J28)),0) -> 0 | V28: =IFERROR(((K28-(R28/J28))/K28),0) -> 0 | Y28: CANDY | Z28: AS REQ'D
B29: 230-6368 | C29: BATTERY | D29: AS REQ'D | E29: 1 | F29: 277.35 | G29: =ROUND(IF($F$17="USD $", F29*$E$15,F29*$D$15),2) -> 393.84 | H29: =ROUND(IF($H$17=$G$17,E29*G29,E29*F29),2) -> 393.84 | J29: =E29 -> 1 | K29: =IFERROR(IF(M29="OEM DISC %",ROUND(IF($K$17=$F$17,F29*(1-N29),G29*(1-N29)),2),IF(M29="MARKUP %",ROUND(R29/J29*(1+N29),2))),0) -> 216.61 | L29: =ROUND((J29*K29),2) -> 216.61 | M29: OEM DISC % | N29: 0.45 | R29: =ROUND(IF($R$17=$Q$17,Q29,IF($R$17="USD $",Q29*$D$15,Q29*$E$15))*E29,2) -> 0 | S29: =IFERROR(ROUND(T29/E29,2),0) -> 216.61 | T29: =ROUND(L29-R29,2) -> 216.61 | U29: =IFERROR(((K29-(R29/J29))/(R29/J29)),0) -> 0 | V29: =IFERROR(((K29-(R29/J29))/K29),0) -> 1 | Y29: U/C
B30: 558-6980 | C30: TURBOCHARGER | D30: 6000 | E30: 1 | F30: 2741.96 | G30: =ROUND(IF($F$17="USD $", F30*$E$15,F30*$D$15),2) -> 3893.58 | H30: =ROUND(IF($H$17=$G$17,E30*G30,E30*F30),2) -> 3893.58 | J30: =E30 -> 1 | K30: =IFERROR(IF(M30="OEM DISC %",ROUND(IF($K$17=$F$17,F30*(1-N30),G30*(1-N30)),2),IF(M30="MARKUP %",ROUND(R30/J30*(1+N30),2))),0) -> 2141.47 | L30: =ROUND((J30*K30),2) -> 2141.47 | M30: OEM DISC % | N30: 0.45 | R30: =ROUND(IF($R$17=$Q$17,Q30,IF($R$17="USD $",Q30*$D$15,Q30*$E$15))*E30,2) -> 0 | S30: =IFERROR(ROUND(T30/E30,2),0) -> 2141.47 | T30: =ROUND(L30-R30,2) -> 2141.47 | U30: =IFERROR(((K30-(R30/J30))/(R30/J30)),0) -> 0 | V30: =IFERROR(((K30-(R30/J30))/K30),0) -> 1
B31: 236-1674 | C31: INJECTOR | D31: 6000 | E31: 4 | F31: 358.1 | G31: =ROUND(IF($F$17="USD $", F31*$E$15,F31*$D$15),2) -> 508.5 | H31: =ROUND(IF($H$17=$G$17,#REF!*G31,#REF!*F31),2) -> #REF! | J31: =#REF! -> #REF! | K31: =IFERROR(IF(M31="OEM DISC %",ROUND(IF($K$17=$F$17,F31*(1-N31),G31*(1-N31)),2),IF(M31="MARKUP %",ROUND(R31/J31*(1+N31),2))),0) -> 279.68 | L31: =ROUND((J31*K31),2) -> #REF! | M31: OEM DISC % | N31: 0.45 | R31: =ROUND(IF($R$17=$Q$17,Q31,IF($R$17="USD $",Q31*$D$15,Q31*$E$15))*#REF!,2) -> #REF! | S31: =IFERROR(ROUND(T31/#REF!,2),0) -> 0 | T31: =ROUND(L31-R31,2) -> #REF! | U31: =IFERROR(((K31-(R31/J31))/(R31/J31)),0) -> 0 | V31: =IFERROR(((K31-(R31/J31))/K31),0) -> 0 | Y31: OEM DISC %
B32: 364-2829 | C32: CRANKSHAFT | D32: 10000 | E32: 1 | F32: 3576.12 | G32: =ROUND(IF($F$17="USD $", F32*$E$15,F32*$D$15),2) -> 5078.09 | H32: =ROUND(IF($H$17=$G$17,E31*G32,E31*F32),2) -> 20312.36 | J32: =E31 -> 4 | K32: =IFERROR(IF(M32="OEM DISC %",ROUND(IF($K$17=$F$17,F32*(1-N32),G32*(1-N32)),2),IF(M32="MARKUP %",ROUND(R32/J32*(1+N32),2))),0) -> 2792.95 | L32: =ROUND((J32*K32),2) -> 11171.8 | M32: OEM DISC % | N32: 0.45 | R32: =ROUND(IF($R$17=$Q$17,Q32,IF($R$17="USD $",Q32*$D$15,Q32*$E$15))*E31,2) -> 0 | S32: =IFERROR(ROUND(T32/E31,2),0) -> 2792.95 | T32: =ROUND(L32-R32,2) -> 11171.8 | U32: =IFERROR(((K32-(R32/J32))/(R32/J32)),0) -> 0 | V32: =IFERROR(((K32-(R32/J32))/K32),0) -> 1 | Y32: MARKUP %
B33: 350-2374 | C33: CAMSHAFT | D33: 10000 | E33: 1 | F33: 528.97 | G33: =ROUND(IF($F$17="USD $", F33*$E$15,F33*$D$15),2) -> 751.14 | H33: =ROUND(IF($H$17=$G$17,E33*G33,E33*F33),2) -> 751.14 | J33: =E33 -> 1 | K33: =IFERROR(IF(M33="OEM DISC %",ROUND(IF($K$17=$F$17,F33*(1-N33),G33*(1-N33)),2),IF(M33="MARKUP %",ROUND(R33/J33*(1+N33),2))),0) -> 413.13 | L33: =ROUND((J33*K33),2) -> 413.13 | M33: OEM DISC % | N33: 0.45 | R33: =ROUND(IF($R$17=$Q$17,Q33,IF($R$17="USD $",Q33*$D$15,Q33*$E$15))*E33,2) -> 0 | S33: =IFERROR(ROUND(T33/E33,2),0) -> 413.13 | T33: =ROUND(L33-R33,2) -> 413.13 | U33: =IFERROR(((K33-(R33/J33))/(R33/J33)),0) -> 0 | V33: =IFERROR(((K33-(R33/J33))/K33),0) -> 1
G34: =ROUND(IF($F$17="USD $", F34*$E$15,F34*$D$15),2) -> 0 | H34: =ROUND(IF($H$17=$G$17,E34*G34,E34*F34),2) -> 0 | J34: =E34 -> 0 | K34: =IFERROR(IF(M34="OEM DISC %",ROUND(IF($K$17=$F$17,F34*(1-N34),G34*(1-N34)),2),IF(M34="MARKUP %",ROUND(R34/J34*(1+N34),2))),0) -> 0 | L34: =ROUND((J34*K34),2) -> 0 | M34: OEM DISC % | N34: 0.45 | R34: =ROUND(IF($R$17=$Q$17,Q34,IF($R$17="USD $",Q34*$D$15,Q34*$E$15))*E34,2) -> 0 | S34: =IFERROR(ROUND(T34/E34,2),0) -> 0 | T34: =ROUND(L34-R34,2) -> 0 | U34: =IFERROR(((K34-(R34/J34))/(R34/J34)),0) -> 0 | V34: =IFERROR(((K34-(R34/J34))/K34),0) -> 0
B35: 135-8203 | C35: TOOTH | D35: 1500 | E35: 8 | G35: =ROUND(IF($F$17="USD $", F35*$E$15,F35*$D$15),2) -> 0 | H35: =ROUND(IF($H$17=$G$17,E35*G35,E35*F35),2) -> 0 | J35: =E35 -> 8 | K35: =IFERROR(IF(M35="OEM DISC %",ROUND(IF($K$17=$F$17,F35*(1-N35),G35*(1-N35)),2),IF(M35="MARKUP %",ROUND(R35/J35*(1+N35),2))),0) -> 0 | L35: =ROUND((J35*K35),2) -> 0 | M35: OEM DISC % | N35: 0.45 | R35: =ROUND(IF($R$17=$Q$17,Q35,IF($R$17="USD $",Q35*$D$15,Q35*$E$15))*E35,2) -> 0 | S35: =IFERROR(ROUND(T35/E35,2),0) -> 0 | T35: =ROUND(L35-R35,2) -> 0 | U35: =IFERROR(((K35-(R35/J35))/(R35/J35)),0) -> 0 | V35: =IFERROR(((K35-(R35/J35))/K35),0) -> 0
B36: 4F-3657 | C36: Bolt-Plow(5/8-11X2.75-IN) | D36: 1500 | E36: 16 | G36: =ROUND(IF($F$17="USD $", F36*$E$15,F36*$D$15),2) -> 0 | H36: =ROUND(IF($H$17=$G$17,E36*G36,E36*F36),2) -> 0 | J36: =E36 -> 16 | K36: =IFERROR(IF(M36="OEM DISC %",ROUND(IF($K$17=$F$17,F36*(1-N36),G36*(1-N36)),2),IF(M36="MARKUP %",ROUND(R36/J36*(1+N36),2))),0) -> 0 | L36: =ROUND((J36*K36),2) -> 0 | M36: OEM DISC % | N36: 0.45 | R36: =ROUND(IF($R$17=$Q$17,Q36,IF($R$17="USD $",Q36*$D$15,Q36*$E$15))*E36,2) -> 0 | S36: =IFERROR(ROUND(T36/E36,2),0) -> 0 | T36: =ROUND(L36-R36,2) -> 0 | U36: =IFERROR(((K36-(R36/J36))/(R36/J36)),0) -> 0 | V36: =IFERROR(((K36-(R36/J36))/K36),0) -> 0
B37: 4K-0367 | C37: Nut-Full(5/8-11-THD) | D37: 1500 | E37: 16 | G37: =ROUND(IF($F$17="USD $", F37*$E$15,F37*$D$15),2) -> 0 | H37: =ROUND(IF($H$17=$G$17,E37*G37,E37*F37),2) -> 0 | J37: =E37 -> 16 | K37: =IFERROR(IF(M37="OEM DISC %",ROUND(IF($K$17=$F$17,F37*(1-N37),G37*(1-N37)),2),IF(M37="MARKUP %",ROUND(R37/J37*(1+N37),2))),0) -> 0 | L37: =ROUND((J37*K37),2) -> 0 | M37: OEM DISC % | N37: 0.45 | R37: =ROUND(IF($R$17=$Q$17,Q37,IF($R$17="USD $",Q37*$D$15,Q37*$E$15))*E37,2) -> 0 | S37: =IFERROR(ROUND(T37/E37,2),0) -> 0 | T37: =ROUND(L37-R37,2) -> 0 | U37: =IFERROR(((K37-(R37/J37))/(R37/J37)),0) -> 0 | V37: =IFERROR(((K37-(R37/J37))/K37),0) -> 0
B38: 118-7110 | C38: CUTTING EDGE | D38: 1500 | E38: 2 | G38: =ROUND(IF($F$17="USD $", F38*$E$15,F38*$D$15),2) -> 0 | H38: =ROUND(IF($H$17=$G$17,E38*G38,E38*F38),2) -> 0 | J38: =E38 -> 2 | K38: =IFERROR(IF(M38="OEM DISC %",ROUND(IF($K$17=$F$17,F38*(1-N38),G38*(1-N38)),2),IF(M38="MARKUP %",ROUND(R38/J38*(1+N38),2))),0) -> 0 | L38: =ROUND((J38*K38),2) -> 0 | M38: OEM DISC % | N38: 0.45 | R38: =ROUND(IF($R$17=$Q$17,Q38,IF($R$17="USD $",Q38*$D$15,Q38*$E$15))*E38,2) -> 0 | S38: =IFERROR(ROUND(T38/E38,2),0) -> 0 | T38: =ROUND(L38-R38,2) -> 0 | U38: =IFERROR(((K38-(R38/J38))/(R38/J38)),0) -> 0 | V38: =IFERROR(((K38-(R38/J38))/K38),0) -> 0
B39: 3F-5108 | C39: Bolt-Plow(5/8-11X2.25-IN) | D39: 1500 | E39: 8 | G39: =ROUND(IF($F$17="USD $", F39*$E$15,F39*$D$15),2) -> 0 | H39: =ROUND(IF($H$17=$G$17,E39*G39,E39*F39),2) -> 0 | J39: =E39 -> 8 | K39: =IFERROR(IF(M39="OEM DISC %",ROUND(IF($K$17=$F$17,F39*(1-N39),G39*(1-N39)),2),IF(M39="MARKUP %",ROUND(R39/J39*(1+N39),2))),0) -> 0 | L39: =ROUND((J39*K39),2) -> 0 | M39: OEM DISC % | N39: 0.45 | R39: =ROUND(IF($R$17=$Q$17,Q39,IF($R$17="USD $",Q39*$D$15,Q39*$E$15))*E39,2) -> 0 | S39: =IFERROR(ROUND(T39/E39,2),0) -> 0 | T39: =ROUND(L39-R39,2) -> 0 | U39: =IFERROR(((K39-(R39/J39))/(R39/J39)),0) -> 0 | V39: =IFERROR(((K39-(R39/J39))/K39),0) -> 0
B40: 4K-0367 | C40: Nut-Full(5/8-11-THD) | D40: 1500 | E40: 8 | G40: =ROUND(IF($F$17="USD $", F40*$E$15,F40*$D$15),2) -> 0 | H40: =ROUND(IF($H$17=$G$17,E40*G40,E40*F40),2) -> 0 | J40: =E40 -> 8 | K40: =IFERROR(IF(M40="OEM DISC %",ROUND(IF($K$17=$F$17,F40*(1-N40),G40*(1-N40)),2),IF(M40="MARKUP %",ROUND(R40/J40*(1+N40),2))),0) -> 0 | L40: =ROUND((J40*K40),2) -> 0 | M40: OEM DISC % | N40: 0.45 | R40: =ROUND(IF($R$17=$Q$17,Q40,IF($R$17="USD $",Q40*$D$15,Q40*$E$15))*E40,2) -> 0 | S40: =IFERROR(ROUND(T40/E40,2),0) -> 0 | T40: =ROUND(L40-R40,2) -> 0 | U40: =IFERROR(((K40-(R40/J40))/(R40/J40)),0) -> 0 | V40: =IFERROR(((K40-(R40/J40))/K40),0) -> 0
B41: 8T-4122 | C41: Washer-Hard(17X32X3.5-MM Thk) | D41: 1500 | E41: 8 | G41: =ROUND(IF($F$17="USD $", F41*$E$15,F41*$D$15),2) -> 0 | H41: =ROUND(IF($H$17=$G$17,E41*G41,E41*F41),2) -> 0 | J41: =E41 -> 8 | K41: =IFERROR(IF(M41="OEM DISC %",ROUND(IF($K$17=$F$17,F41*(1-N41),G41*(1-N41)),2),IF(M41="MARKUP %",ROUND(R41/J41*(1+N41),2))),0) -> 0 | L41: =ROUND((J41*K41),2) -> 0 | M41: OEM DISC % | N41: 0.45 | R41: =ROUND(IF($R$17=$Q$17,Q41,IF($R$17="USD $",Q41*$D$15,Q41*$E$15))*E41,2) -> 0 | S41: =IFERROR(ROUND(T41/E41,2),0) -> 0 | T41: =ROUND(L41-R41,2) -> 0 | U41: =IFERROR(((K41-(R41/J41))/(R41/J41)),0) -> 0 | V41: =IFERROR(((K41-(R41/J41))/K41),0) -> 0
G42: =ROUND(IF($F$17="USD $", F42*$E$15,F42*$D$15),2) -> 0 | H42: =ROUND(IF($H$17=$G$17,E42*G42,E42*F42),2) -> 0 | J42: =E42 -> 0 | K42: =IFERROR(IF(M42="OEM DISC %",ROUND(IF($K$17=$F$17,F42*(1-N42),G42*(1-N42)),2),IF(M42="MARKUP %",ROUND(R42/J42*(1+N42),2))),0) -> 0 | L42: =ROUND((J42*K42),2) -> 0 | M42: MARKUP % | N42: 0.45 | R42: =ROUND(IF($R$17=$Q$17,Q42,IF($R$17="USD $",Q42*$D$15,Q42*$E$15))*E42,2) -> 0 | S42: =IFERROR(ROUND(T42/E42,2),0) -> 0 | T42: =ROUND(L42-R42,2) -> 0 | U42: =IFERROR(((K42-(R42/J42))/(R42/J42)),0) -> 0 | V42: =IFERROR(((K42-(R42/J42))/K42),0) -> 0
C43: Tire (16.9-28) rear | D43: 4000 | E43: 2 | F43: 300 | G43: =ROUND(IF($F$17="USD $", F43*$E$15,F43*$D$15),2) -> 426 | H43: =ROUND(IF($H$17=$G$17,E43*G43,E43*F43),2) -> 852 | J43: =E43 -> 2 | K43: =IFERROR(IF(M43="OEM DISC %",ROUND(IF($K$17=$F$17,F43*(1-N43),G43*(1-N43)),2),IF(M43="MARKUP %",ROUND(R43/J43*(1+N43),2))),0) -> 234.3 | L43: =ROUND((J43*K43),2) -> 468.6 | M43: OEM DISC % | N43: 0.45 | R43: =ROUND(IF($R$17=$Q$17,Q43,IF($R$17="USD $",Q43*$D$15,Q43*$E$15))*E43,2) -> 0 | S43: =IFERROR(ROUND(T43/E43,2),0) -> 234.3 | T43: =ROUND(L43-R43,2) -> 468.6 | U43: =IFERROR(((K43-(R43/J43))/(R43/J43)),0) -> 0 | V43: =IFERROR(((K43-(R43/J43))/K43),0) -> 1
C44: Tire(12.5/80-18) front | D44: 4000 | E44: 2 | F44: 155.98 | G44: =ROUND(IF($F$17="USD $", F44*$E$15,F44*$D$15),2) -> 221.49 | H44: =ROUND(IF($H$17=$G$17,E44*G44,E44*F44),2) -> 442.98 | J44: =E44 -> 2 | K44: =IFERROR(IF(M44="OEM DISC %",ROUND(IF($K$17=$F$17,F44*(1-N44),G44*(1-N44)),2),IF(M44="MARKUP %",ROUND(R44/J44*(1+N44),2))),0) -> 121.82 | L44: =ROUND((J44*K44),2) -> 243.64 | M44: OEM DISC % | N44: 0.45 | R44: =ROUND(IF($R$17=$Q$17,Q44,IF($R$17="USD $",Q44*$D$15,Q44*$E$15))*E44,2) -> 0 | S44: =IFERROR(ROUND(T44/E44,2),0) -> 121.82 | T44: =ROUND(L44-R44,2) -> 243.64 | U44: =IFERROR(((K44-(R44/J44))/(R44/J44)),0) -> 0 | V44: =IFERROR(((K44-(R44/J44))/K44),0) -> 1
G45: =ROUND(IF($F$17="USD $", F45*$E$15,F45*$D$15),2) -> 0 | H45: =ROUND(IF($H$17=$G$17,E45*G45,E45*F45),2) -> 0 | J45: =E45 -> 0 | K45: =IFERROR(IF(M45="OEM DISC %",ROUND(IF($K$17=$F$17,F45*(1-N45),G45*(1-N45)),2),IF(M45="MARKUP %",ROUND(R45/J45*(1+N45),2))),0) -> 0 | L45: =ROUND((J45*K45),2) -> 0 | M45: OEM DISC % | N45: 0.45 | R45: =ROUND(IF($R$17=$Q$17,Q45,IF($R$17="USD $",Q45*$D$15,Q45*$E$15))*E45,2) -> 0 | S45: =IFERROR(ROUND(T45/E45,2),0) -> 0 | T45: =ROUND(L45-R45,2) -> 0 | U45: =IFERROR(((K45-(R45/J45))/(R45/J45)),0) -> 0 | V45: =IFERROR(((K45-(R45/J45))/K45),0) -> 0
G46: =ROUND(IF($F$17="USD $", F46*$E$15,F46*$D$15),2) -> 0 | H46: =ROUND(IF($H$17=$G$17,E46*G46,E46*F46),2) -> 0 | J46: =E46 -> 0 | K46: =IFERROR(IF(M46="OEM DISC %",ROUND(IF($K$17=$F$17,F46*(1-N46),G46*(1-N46)),2),IF(M46="MARKUP %",ROUND(R46/J46*(1+N46),2))),0) -> 0 | L46: =ROUND((J46*K46),2) -> 0 | M46: OEM DISC % | N46: 0.45 | R46: =ROUND(IF($R$17=$Q$17,Q46,IF($R$17="USD $",Q46*$D$15,Q46*$E$15))*E46,2) -> 0 | S46: =IFERROR(ROUND(T46/E46,2),0) -> 0 | T46: =ROUND(L46-R46,2) -> 0 | U46: =IFERROR(((K46-(R46/J46))/(R46/J46)),0) -> 0 | V46: =IFERROR(((K46-(R46/J46))/K46),0) -> 0
G47: =ROUND(IF($F$17="USD $", F47*$E$15,F47*$D$15),2) -> 0 | H47: =ROUND(IF($H$17=$G$17,E47*G47,E47*F47),2) -> 0 | J47: =E47 -> 0 | K47: =IFERROR(IF(M47="OEM DISC %",ROUND(IF($K$17=$F$17,F47*(1-N47),G47*(1-N47)),2),IF(M47="MARKUP %",ROUND(R47/J47*(1+N47),2))),0) -> 0 | L47: =ROUND((J47*K47),2) -> 0 | M47: OEM DISC % | N47: 0.45 | R47: =ROUND(IF($R$17=$Q$17,Q47,IF($R$17="USD $",Q47*$D$15,Q47*$E$15))*E47,2) -> 0 | S47: =IFERROR(ROUND(T47/E47,2),0) -> 0 | T47: =ROUND(L47-R47,2) -> 0 | U47: =IFERROR(((K47-(R47/J47))/(R47/J47)),0) -> 0 | V47: =IFERROR(((K47-(R47/J47))/K47),0) -> 0
G48: =ROUND(IF($F$17="USD $", F48*$E$15,F48*$D$15),2) -> 0 | H48: =ROUND(IF($H$17=$G$17,E48*G48,E48*F48),2) -> 0 | J48: =E48 -> 0 | K48: =IFERROR(IF(M48="OEM DISC %",ROUND(IF($K$17=$F$17,F48*(1-N48),G48*(1-N48)),2),IF(M48="MARKUP %",ROUND(R48/J48*(1+N48),2))),0) -> 0 | L48: =ROUND((J48*K48),2) -> 0 | M48: OEM DISC % | N48: 0.45 | R48: =ROUND(IF($R$17=$Q$17,Q48,IF($R$17="USD $",Q48*$D$15,Q48*$E$15))*E48,2) -> 0 | S48: =IFERROR(ROUND(T48/E48,2),0) -> 0 | T48: =ROUND(L48-R48,2) -> 0 | U48: =IFERROR(((K48-(R48/J48))/(R48/J48)),0) -> 0 | V48: =IFERROR(((K48-(R48/J48))/K48),0) -> 0
D49: TOTALS | E49: =SUM(E18:E48) -> 86 | F49: =SUM(F18:F48) -> 8265.8 | G49: =SUM(G18:G48) -> 11737.43 | H49: =SUM(H18:H48) -> #REF! | J49: =SUM(J18:J48) -> #REF! | K49: =SUM(K18:K48) -> 6455.6 | L49: =SUM(L18:L48) -> #REF! | Q49: =SUM(Q18:Q48) -> 0 | R49: =SUM(R18:R48) -> #REF! | S49: =SUM(S18:S48) -> 6175.92 | T49: =SUM(T18:T48) -> #REF!

Sheet CAT 422F
B1: CUSTOMER INFORMATION | D1: MACHINE INFORMATION | H1: MACHINE SERVICE HR INTERVALS | L1: SUMMARY | P1: =K17 -> CAD $ | S1: COMPLETED DEAL INFORMATION
B2: DATE: | D2: UNIT # | F2: BH-26 | H2: ENGINE AIR | L2: OEM MSRP | P2: =H49 -> 27679.07 | S2: SALES REP
B3: COMPANY: | D3: YEAR | F3: 2009 | H3: ENGINE OIL | L3: GQP LIST | P3: =L49 -> 15223.48 | S3: ORDER PO #
B4: CUSTOMER: | D4: MAKE | F4: CAT | H4: FUEL FILTERS | L4: $ SAVINGS | P4: =P2-P3 -> 12455.59 | S4: PROJECT #
B5: PHONE: | D5: MODEL | F5: 422F | H5: HYDRAULIC FILTERS | L5: % SAVINGS | P5: =IFERROR((P2-P3)/P2,"") -> 0.45000031 | S5: CUST INVOICE #
B6: EMAIL: | D6: SERIAL NUMBER | F6: LRH00638 | H6: TRANSMISSION FILTERS | L6: TOTAL ORDER MARGIN | P6: =T49 -> 15223.48 | S6: PAYMENT TYPE
B7: SALES REP: | D7: ENGINE SER NUMBER | F7: LHX21840 | H7: CAB FILTERS | L7: TOTAL ITEM COST | P7: =R49 -> 0 | S7: DATE DELIVERED
D8: CURRENT HOURS | H8: UNDERCARRIAGE / TIRES | L8: TOTAL ORDER FREIGHT | P8: =IF(P1=Q14,R14,IF(Q14="CAD $",R14*D15,IF(Q14="USD $",R14*E15,0))) -> 0 | S8: TOTAL COST | T8: NET MARGIN | U8: NET MARKUP % | V8: NET MARGIN %
D9: USAGE/MONTH | F9: Backhoe Loader | L9: TOTAL CUSTOMS/BROKERAGE | P9: =V14 -> 0 | S9: =P7+P8+P9 -> 0 | T9: =P3-S9 -> 15223.48 | U9: =IFERROR(((P3-S9)/S9),0) -> 0 | V9: =IFERROR(T9/P3,0) -> 1
L10: TOTAL NUMBER PIECES | P10: =E49 -> 88
D11: ENTER EXCHANGE RATES $ | F11: OEM MSRP | J11: CUSTOMER SELL PRICE | P11: COST ANALYSIS | Y11: CAD $
Y12: USD $
F13: SHOW OEM MSRP ON QUOTE: | H13: YES | Y13: YES
D14: CAD-USD | E14: USD-CAD | F14: OEM NAME | J14: CUSTOMER TYPE/TIER | L14: IE: VIP - Gold | P14: FREIGHT TOTAL ORDER | Q14: USD $ | S14: CUSTOMS AND BROKERAGE % | T14: 0.025 | U14: BROKERAGE FEES | V14: =ROUND(R49*T14,2) -> 0 | Y14: NO
D15: =1/E15 -> 0.70422535 | E15: 1.42 | P15: MARKUP LESS THAN 100% REQUIRES MANAGER APPROVAL
B16: PART NUMBER | C16: DESCRIPTION | D16: SERVICE INTERVAL | E16: QTY | F16: UNIT PRICE | H16: EXT AMOUNT | J16: QTY | K16: UNIT PRICE | L16: EXTENDED AMOUNT | M16: PRCING METHOD %OEM / MARKUP | N16: OEM DISC % / MARKUP % | P16: VENDOR | Q16: COST EACH | R16: EXTENDED COST | S16: MARGIN EACH | T16: EXTENDED MARGIN | U16: MARKUP % | V16: MARGIN %
F17: USD $ | G17: =IF(F17="USD $", "CAD $", "USD $") -> CAD $ | H17: =K17 -> CAD $ | K17: CAD $ | Q17: USD $ | R17: =K17 -> CAD $
G18: =ROUND(IF($F$17="USD $", F18*$E$15,F18*$D$15),2) -> 0 | H18: =ROUND(IF($H$17=$G$17,E18*G18,E18*F18),2) -> 0 | J18: =E18 -> 0 | K18: =IFERROR(IF(M18="OEM DISC %",ROUND(IF($K$17=$F$17,F18*(1-N18),G18*(1-N18)),2),IF(M18="MARKUP %",ROUND(R18/J18*(1+N18),2))),0) -> 0 | L18: =ROUND((J18*K18),2) -> 0 | M18: OEM DISC % | N18: 0.45 | R18: =ROUND(IF($R$17=$Q$17,Q18,IF($R$17="USD $",Q18*$D$15,Q18*$E$15))*E18,2) -> 0 | S18: =IFERROR(ROUND(T18/E18,2),0) -> 0 | T18: =ROUND(L18-R18,2) -> 0 | U18: =IFERROR(((K18-(R18/J18))/(R18/J18)),0) -> 0 | V18: =IFERROR(((K18-(R18/J18))/K18),0) -> 0 | Z18: 250
B19: 7W-2326 | C19: ENGINE OIL FILTER | D19: 250 | E19: 1 | F19: 20.98 | G19: =ROUND(IF($F$17="USD $", F19*$E$15,F19*$D$15),2) -> 29.79 | H19: =ROUND(IF($H$17=$G$17,E19*G19,E19*F19),2) -> 29.79 | J19: =E19 -> 1 | K19: =IFERROR(IF(M19="OEM DISC %",ROUND(IF($K$17=$F$17,F19*(1-N19),G19*(1-N19)),2),IF(M19="MARKUP %",ROUND(R19/J19*(1+N19),2))),0) -> 16.38 | L19: =ROUND((J19*K19),2) -> 16.38 | M19: OEM DISC % | N19: 0.45 | R19: =ROUND(IF($R$17=$Q$17,Q19,IF($R$17="USD $",Q19*$D$15,Q19*$E$15))*E19,2) -> 0 | S19: =IFERROR(ROUND(T19/E19,2),0) -> 16.38 | T19: =ROUND(L19-R19,2) -> 16.38 | U19: =IFERROR(((K19-(R19/J19))/(R19/J19)),0) -> 0 | V19: =IFERROR(((K19-(R19/J19))/K19),0) -> 1 | Y19: GQP | Z19: 500
B20: 361-9554 | C20: FUEL WATER SEPARATOR FILTER | D20: 500 | E20: 1 | F20: 46.86 | G20: =ROUND(IF($F$17="USD $", F20*$E$15,F20*$D$15),2) -> 66.54 | H20: =ROUND(IF($H$17=$G$17,E20*G20,E20*F20),2) -> 66.54 | J20: =E20 -> 1 | K20: =IFERROR(IF(M20="OEM DISC %",ROUND(IF($K$17=$F$17,F20*(1-N20),G20*(1-N20)),2),IF(M20="MARKUP %",ROUND(R20/J20*(1+N20),2))),0) -> 36.6 | L20: =ROUND((J20*K20),2) -> 36.6 | M20: OEM DISC % | N20: 0.45 | R20: =ROUND(IF($R$17=$Q$17,Q20,IF($R$17="USD $",Q20*$D$15,Q20*$E$15))*E20,2) -> 0 | S20: =IFERROR(ROUND(T20/E20,2),0) -> 36.6 | T20: =ROUND(L20-R20,2) -> 36.6 | U20: =IFERROR(((K20-(R20/J20))/(R20/J20)),0) -> 0 | V20: =IFERROR(((K20-(R20/J20))/K20),0) -> 1 | Y20: CTP | Z20: 750
B21: 471-7003 | C21: TRANSMISSION FILTER | D21: 500 | E21: 1 | F21: 38.35 | G21: =ROUND(IF($F$17="USD $", F21*$E$15,F21*$D$15),2) -> 54.46 | H21: =ROUND(IF($H$17=$G$17,E21*G21,E21*F21),2) -> 54.46 | J21: =E21 -> 1 | K21: =IFERROR(IF(M21="OEM DISC %",ROUND(IF($K$17=$F$17,F21*(1-N21),G21*(1-N21)),2),IF(M21="MARKUP %",ROUND(R21/J21*(1+N21),2))),0) -> 29.95 | L21: =ROUND((J21*K21),2) -> 29.95 | M21: OEM DISC % | N21: 0.45 | R21: =ROUND(IF($R$17=$Q$17,Q21,IF($R$17="USD $",Q21*$D$15,Q21*$E$15))*E21,2) -> 0 | S21: =IFERROR(ROUND(T21/E21,2),0) -> 29.95 | T21: =ROUND(L21-R21,2) -> 29.95 | U21: =IFERROR(((K21-(R21/J21))/(R21/J21)),0) -> 0 | V21: =IFERROR(((K21-(R21/J21))/K21),0) -> 1 | Y21: BLMQ | Z21: 1000
B22: 362-1163 | C22: HYDRAULIC FILTER | D22: 500 | E22: 1 | F22: 110.85 | G22: =ROUND(IF($F$17="USD $", F22*$E$15,F22*$D$15),2) -> 157.41 | H22: =ROUND(IF($H$17=$G$17,E22*G22,E22*F22),2) -> 157.41 | J22: =E22 -> 1 | K22: =IFERROR(IF(M22="OEM DISC %",ROUND(IF($K$17=$F$17,F22*(1-N22),G22*(1-N22)),2),IF(M22="MARKUP %",ROUND(R22/J22*(1+N22),2))),0) -> 86.58 | L22: =ROUND((J22*K22),2) -> 86.58 | M22: OEM DISC % | N22: 0.45 | R22: =ROUND(IF($R$17=$Q$17,Q22,IF($R$17="USD $",Q22*$D$15,Q22*$E$15))*E22,2) -> 0 | S22: =IFERROR(ROUND(T22/E22,2),0) -> 86.58 | T22: =ROUND(L22-R22,2) -> 86.58 | U22: =IFERROR(((K22-(R22/J22))/(R22/J22)),0) -> 0 | V22: =IFERROR(((K22-(R22/J22))/K22),0) -> 1 | Y22: CAT | Z22: 1200
B23: 528-0585 | C23: PRIMARY AIR FILTER | D23: 500 | E23: 1 | F23: 130.35 | G23: =ROUND(IF($F$17="USD $", F23*$E$15,F23*$D$15),2) -> 185.1 | H23: =ROUND(IF($H$17=$G$17,E23*G23,E23*F23),2) -> 185.1 | J23: =E23 -> 1 | K23: =IFERROR(IF(M23="OEM DISC %",ROUND(IF($K$17=$F$17,F23*(1-N23),G23*(1-N23)),2),IF(M23="MARKUP %",ROUND(R23/J23*(1+N23),2))),0) -> 101.81 | L23: =ROUND((J23*K23),2) -> 101.81 | M23: OEM DISC % | N23: 0.45 | R23: =ROUND(IF($R$17=$Q$17,Q23,IF($R$17="USD $",Q23*$D$15,Q23*$E$15))*E23,2) -> 0 | S23: =IFERROR(ROUND(T23/E23,2),0) -> 101.81 | T23: =ROUND(L23-R23,2) -> 101.81 | U23: =IFERROR(((K23-(R23/J23))/(R23/J23)),0) -> 0 | V23: =IFERROR(((K23-(R23/J23))/K23),0) -> 1 | Y23: FINNING | Z23: 2000
B24: 346-6688 | C24: SECONDARY AIR FILTER | D24: 250 | E24: 1 | F24: 63.13 | G24: =ROUND(IF($F$17="USD $", F24*$E$15,F24*$D$15),2) -> 89.64 | H24: =ROUND(IF($H$17=$G$17,E24*G24,E24*F24),2) -> 89.64 | J24: =E24 -> 1 | K24: =IFERROR(IF(M24="OEM DISC %",ROUND(IF($K$17=$F$17,F24*(1-N24),G24*(1-N24)),2),IF(M24="MARKUP %",ROUND(R24/J24*(1+N24),2))),0) -> 49.3 | L24: =ROUND((J24*K24),2) -> 49.3 | M24: OEM DISC % | N24: 0.45 | R24: =ROUND(IF($R$17=$Q$17,Q24,IF($R$17="USD $",Q24*$D$15,Q24*$E$15))*E24,2) -> 0 | S24: =IFERROR(ROUND(T24/E24,2),0) -> 49.3 | T24: =ROUND(L24-R24,2) -> 49.3 | U24: =IFERROR(((K24-(R24/J24))/(R24/J24)),0) -> 0 | V24: =IFERROR(((K24-(R24/J24))/K24),0) -> 1 | Y24: JD | Z24: 4000
B25: 211-2661 | C25: CABIN AIR FILTER | D25: 250 | E25: 1 | F25: 42.9 | G25: =ROUND(IF($F$17="USD $", F25*$E$15,F25*$D$15),2) -> 60.92 | H25: =ROUND(IF($H$17=$G$17,E25*G25,E25*F25),2) -> 60.92 | J25: =E25 -> 1 | K25: =IFERROR(IF(M25="OEM DISC %",ROUND(IF($K$17=$F$17,F25*(1-N25),G25*(1-N25)),2),IF(M25="MARKUP %",ROUND(R25/J25*(1+N25),2))),0) -> 33.51 | L25: =ROUND((J25*K25),2) -> 33.51 | M25: OEM DISC % | N25: 0.45 | R25: =ROUND(IF($R$17=$Q$17,Q25,IF($R$17="USD $",Q25*$D$15,Q25*$E$15))*E25,2) -> 0 | S25: =IFERROR(ROUND(T25/E25,2),0) -> 33.51 | T25: =ROUND(L25-R25,2) -> 33.51 | U25: =IFERROR(((K25-(R25/J25))/(R25/J25)),0) -> 0 | V25: =IFERROR(((K25-(R25/J25))/K25),0) -> 1 | Y25: BRANDT | Z25: 6000
B26: 211-2660 | C26: CABIN AIR FILTER | D26: 250 | E26: 1 | F26: 52.68 | G26: =ROUND(IF($F$17="USD $", F26*$E$15,F26*$D$15),2) -> 74.81 | H26: =ROUND(IF($H$17=$G$17,E26*G26,E26*F26),2) -> 74.81 | J26: =E26 -> 1 | K26: =IFERROR(IF(M26="OEM DISC %",ROUND(IF($K$17=$F$17,F26*(1-N26),G26*(1-N26)),2),IF(M26="MARKUP %",ROUND(R26/J26*(1+N26),2))),0) -> 41.15 | L26: =ROUND((J26*K26),2) -> 41.15 | M26: OEM DISC % | N26: 0.45 | R26: =ROUND(IF($R$17=$Q$17,Q26,IF($R$17="USD $",Q26*$D$15,Q26*$E$15))*E26,2) -> 0 | S26: =IFERROR(ROUND(T26/E26,2),0) -> 41.15 | T26: =ROUND(L26-R26,2) -> 41.15 | U26: =IFERROR(((K26-(R26/J26))/(R26/J26)),0) -> 0 | V26: =IFERROR(((K26-(R26/J26))/K26),0) -> 1 | Y26: PTI | Z26: 8000
B27: 656-3635 | C27: ENGINE OVERHAUL KIT BRONZE | D27: 10000 | E27: 1 | G27: =ROUND(IF($F$17="USD $", F27*$E$15,F27*$D$15),2) -> 0 | H27: =ROUND(IF($H$17=$G$17,E27*G27,E27*F27),2) -> 0 | J27: =E27 -> 1 | K27: =IFERROR(IF(M27="OEM DISC %",ROUND(IF($K$17=$F$17,F27*(1-N27),G27*(1-N27)),2),IF(M27="MARKUP %",ROUND(R27/J27*(1+N27),2))),0) -> 0 | L27: =ROUND((J27*K27),2) -> 0 | M27: OEM DISC % | N27: 0.45 | R27: =ROUND(IF($R$17=$Q$17,Q27,IF($R$17="USD $",Q27*$D$15,Q27*$E$15))*E27,2) -> 0 | S27: =IFERROR(ROUND(T27/E27,2),0) -> 0 | T27: =ROUND(L27-R27,2) -> 0 | U27: =IFERROR(((K27-(R27/J27))/(R27/J27)),0) -> 0 | V27: =IFERROR(((K27-(R27/J27))/K27),0) -> 0 | Y27: CONEQUIP | Z27: 10000
B28: 566-1908 | C28: SEAT GP | D28: AS REQ'D | E28: 1 | F28: 7936.92 | G28: =ROUND(IF($F$17="USD $", F28*$E$15,F28*$D$15),2) -> 11270.43 | H28: =ROUND(IF($H$17=$G$17,E28*G28,E28*F28),2) -> 11270.43 | J28: =E28 -> 1 | K28: =IFERROR(IF(M28="OEM DISC %",ROUND(IF($K$17=$F$17,F28*(1-N28),G28*(1-N28)),2),IF(M28="MARKUP %",ROUND(R28/J28*(1+N28),2))),0) -> 6198.74 | L28: =ROUND((J28*K28),2) -> 6198.74 | M28: OEM DISC % | N28: 0.45 | R28: =ROUND(IF($R$17=$Q$17,Q28,IF($R$17="USD $",Q28*$D$15,Q28*$E$15))*E28,2) -> 0 | S28: =IFERROR(ROUND(T28/E28,2),0) -> 6198.74 | T28: =ROUND(L28-R28,2) -> 6198.74 | U28: =IFERROR(((K28-(R28/J28))/(R28/J28)),0) -> 0 | V28: =IFERROR(((K28-(R28/J28))/K28),0) -> 1 | Y28: CANDY | Z28: AS REQ'D
B29: 230-6368 | C29: BATTERY | D29: AS REQ'D | E29: 1 | F29: 277.35 | G29: =ROUND(IF($F$17="USD $", F29*$E$15,F29*$D$15),2) -> 393.84 | H29: =ROUND(IF($H$17=$G$17,E29*G29,E29*F29),2) -> 393.84 | J29: =E29 -> 1 | K29: =IFERROR(IF(M29="OEM DISC %",ROUND(IF($K$17=$F$17,F29*(1-N29),G29*(1-N29)),2),IF(M29="MARKUP %",ROUND(R29/J29*(1+N29),2))),0) -> 216.61 | L29: =ROUND((J29*K29),2) -> 216.61 | M29: OEM DISC % | N29: 0.45 | R29: =ROUND(IF($R$17=$Q$17,Q29,IF($R$17="USD $",Q29*$D$15,Q29*$E$15))*E29,2) -> 0 | S29: =IFERROR(ROUND(T29/E29,2),0) -> 216.61 | T29: =ROUND(L29-R29,2) -> 216.61 | U29: =IFERROR(((K29-(R29/J29))/(R29/J29)),0) -> 0 | V29: =IFERROR(((K29-(R29/J29))/K29),0) -> 1 | Y29: U/C
B30: 558-6980 | C30: TURBOCHARGER | D30: 6000 | E30: 1 | F30: 2741.96 | G30: =ROUND(IF($F$17="USD $", F30*$E$15,F30*$D$15),2) -> 3893.58 | H30: =ROUND(IF($H$17=$G$17,E30*G30,E30*F30),2) -> 3893.58 | J30: =E30 -> 1 | K30: =IFERROR(IF(M30="OEM DISC %",ROUND(IF($K$17=$F$17,F30*(1-N30),G30*(1-N30)),2),IF(M30="MARKUP %",ROUND(R30/J30*(1+N30),2))),0) -> 2141.47 | L30: =ROUND((J30*K30),2) -> 2141.47 | M30: OEM DISC % | N30: 0.45 | R30: =ROUND(IF($R$17=$Q$17,Q30,IF($R$17="USD $",Q30*$D$15,Q30*$E$15))*E30,2) -> 0 | S30: =IFERROR(ROUND(T30/E30,2),0) -> 2141.47 | T30: =ROUND(L30-R30,2) -> 2141.47 | U30: =IFERROR(((K30-(R30/J30))/(R30/J30)),0) -> 0 | V30: =IFERROR(((K30-(R30/J30))/K30),0) -> 1
B31: 266-6830 | C31: INJECTOR | D31: 6000 | E31: 4 | F31: 358.1 | G31: =ROUND(IF($F$17="USD $", F31*$E$15,F31*$D$15),2) -> 508.5 | H31: =ROUND(IF($H$17=$G$17,E31*G31,E31*F31),2) -> 2034 | J31: =E31 -> 4 | K31: =IFERROR(IF(M31="OEM DISC %",ROUND(IF($K$17=$F$17,F31*(1-N31),G31*(1-N31)),2),IF(M31="MARKUP %",ROUND(R31/J31*(1+N31),2))),0) -> 279.68 | L31: =ROUND((J31*K31),2) -> 1118.72 | M31: OEM DISC % | N31: 0.45 | R31: =ROUND(IF($R$17=$Q$17,Q31,IF($R$17="USD $",Q31*$D$15,Q31*$E$15))*E31,2) -> 0 | S31: =IFERROR(ROUND(T31/E31,2),0) -> 279.68 | T31: =ROUND(L31-R31,2) -> 1118.72 | U31: =IFERROR(((K31-(R31/J31))/(R31/J31)),0) -> 0 | V31: =IFERROR(((K31-(R31/J31))/K31),0) -> 1 | Y31: OEM DISC %
B32: 359-0715 | C32: CRANKSHAFT | D32: 10000 | E32: 1 | F32: 3678.99 | G32: =ROUND(IF($F$17="USD $", F32*$E$15,F32*$D$15),2) -> 5224.17 | H32: =ROUND(IF($H$17=$G$17,E32*G32,E32*F32),2) -> 5224.17 | J32: =E32 -> 1 | K32: =IFERROR(IF(M32="OEM DISC %",ROUND(IF($K$17=$F$17,F32*(1-N32),G32*(1-N32)),2),IF(M32="MARKUP %",ROUND(R32/J32*(1+N32),2))),0) -> 2873.29 | L32: =ROUND((J32*K32),2) -> 2873.29 | M32: OEM DISC % | N32: 0.45 | R32: =ROUND(IF($R$17=$Q$17,Q32,IF($R$17="USD $",Q32*$D$15,Q32*$E$15))*E32,2) -> 0 | S32: =IFERROR(ROUND(T32/E32,2),0) -> 2873.29 | T32: =ROUND(L32-R32,2) -> 2873.29 | U32: =IFERROR(((K32-(R32/J32))/(R32/J32)),0) -> 0 | V32: =IFERROR(((K32-(R32/J32))/K32),0) -> 1 | Y32: MARKUP %
B33: 350-2374 | C33: CAMSHAFT | D33: 10000 | E33: 1 | F33: 528.97 | G33: =ROUND(IF($F$17="USD $", F33*$E$15,F33*$D$15),2) -> 751.14 | H33: =ROUND(IF($H$17=$G$17,E33*G33,E33*F33),2) -> 751.14 | J33: =E33 -> 1 | K33: =IFERROR(IF(M33="OEM DISC %",ROUND(IF($K$17=$F$17,F33*(1-N33),G33*(1-N33)),2),IF(M33="MARKUP %",ROUND(R33/J33*(1+N33),2))),0) -> 413.13 | L33: =ROUND((J33*K33),2) -> 413.13 | M33: OEM DISC % | N33: 0.45 | R33: =ROUND(IF($R$17=$Q$17,Q33,IF($R$17="USD $",Q33*$D$15,Q33*$E$15))*E33,2) -> 0 | S33: =IFERROR(ROUND(T33/E33,2),0) -> 413.13 | T33: =ROUND(L33-R33,2) -> 413.13 | U33: =IFERROR(((K33-(R33/J33))/(R33/J33)),0) -> 0 | V33: =IFERROR(((K33-(R33/J33))/K33),0) -> 1
B34: 135-8203 | C34: TOOTH | D34: 1500 | E34: 8 | F34: 111.87 | G34: =ROUND(IF($F$17="USD $", F34*$E$15,F34*$D$15),2) -> 158.86 | H34: =ROUND(IF($H$17=$G$17,E34*G34,E34*F34),2) -> 1270.88 | J34: =E34 -> 8 | K34: =IFERROR(IF(M34="OEM DISC %",ROUND(IF($K$17=$F$17,F34*(1-N34),G34*(1-N34)),2),IF(M34="MARKUP %",ROUND(R34/J34*(1+N34),2))),0) -> 87.37 | L34: =ROUND((J34*K34),2) -> 698.96 | M34: OEM DISC % | N34: 0.45 | R34: =ROUND(IF($R$17=$Q$17,Q34,IF($R$17="USD $",Q34*$D$15,Q34*$E$15))*E34,2) -> 0 | S34: =IFERROR(ROUND(T34/E34,2),0) -> 87.37 | T34: =ROUND(L34-R34,2) -> 698.96 | U34: =IFERROR(((K34-(R34/J34))/(R34/J34)),0) -> 0 | V34: =IFERROR(((K34-(R34/J34))/K34),0) -> 1
B35: 4F-3657 | C35: Bolt-Plow(5/8-11X2.75-IN) | D35: 1500 | E35: 16 | F35: 2.39 | G35: =ROUND(IF($F$17="USD $", F35*$E$15,F35*$D$15),2) -> 3.39 | H35: =ROUND(IF($H$17=$G$17,E35*G35,E35*F35),2) -> 54.24 | J35: =E35 -> 16 | K35: =IFERROR(IF(M35="OEM DISC %",ROUND(IF($K$17=$F$17,F35*(1-N35),G35*(1-N35)),2),IF(M35="MARKUP %",ROUND(R35/J35*(1+N35),2))),0) -> 1.86 | L35: =ROUND((J35*K35),2) -> 29.76 | M35: OEM DISC % | N35: 0.45 | R35: =ROUND(IF($R$17=$Q$17,Q35,IF($R$17="USD $",Q35*$D$15,Q35*$E$15))*E35,2) -> 0 | S35: =IFERROR(ROUND(T35/E35,2),0) -> 1.86 | T35: =ROUND(L35-R35,2) -> 29.76 | U35: =IFERROR(((K35-(R35/J35))/(R35/J35)),0) -> 0 | V35: =IFERROR(((K35-(R35/J35))/K35),0) -> 1
B36: 4K-0367 | C36: Nut-Full(5/8-11-THD) | D36: 1500 | E36: 16 | F36: 1.65 | G36: =ROUND(IF($F$17="USD $", F36*$E$15,F36*$D$15),2) -> 2.34 | H36: =ROUND(IF($H$17=$G$17,E36*G36,E36*F36),2) -> 37.44 | J36: =E36 -> 16 | K36: =IFERROR(IF(M36="OEM DISC %",ROUND(IF($K$17=$F$17,F36*(1-N36),G36*(1-N36)),2),IF(M36="MARKUP %",ROUND(R36/J36*(1+N36),2))),0) -> 1.29 | L36: =ROUND((J36*K36),2) -> 20.64 | M36: OEM DISC % | N36: 0.45 | R36: =ROUND(IF($R$17=$Q$17,Q36,IF($R$17="USD $",Q36*$D$15,Q36*$E$15))*E36,2) -> 0 | S36: =IFERROR(ROUND(T36/E36,2),0) -> 1.29 | T36: =ROUND(L36-R36,2) -> 20.64 | U36: =IFERROR(((K36-(R36/J36))/(R36/J36)),0) -> 0 | V36: =IFERROR(((K36-(R36/J36))/K36),0) -> 1
G37: =ROUND(IF($F$17="USD $", F37*$E$15,F37*$D$15),2) -> 0 | H37: =ROUND(IF($H$17=$G$17,E37*G37,E37*F37),2) -> 0 | J37: =E37 -> 0 | K37: =IFERROR(IF(M37="OEM DISC %",ROUND(IF($K$17=$F$17,F37*(1-N37),G37*(1-N37)),2),IF(M37="MARKUP %",ROUND(R37/J37*(1+N37),2))),0) -> 0 | L37: =ROUND((J37*K37),2) -> 0 | M37: OEM DISC % | N37: 0.45 | R37: =ROUND(IF($R$17=$Q$17,Q37,IF($R$17="USD $",Q37*$D$15,Q37*$E$15))*E37,2) -> 0 | S37: =IFERROR(ROUND(T37/E37,2),0) -> 0 | T37: =ROUND(L37-R37,2) -> 0 | U37: =IFERROR(((K37-(R37/J37))/(R37/J37)),0) -> 0 | V37: =IFERROR(((K37-(R37/J37))/K37),0) -> 0
B38: 118-7110 | C38: Edge-Cutting | D38: 1500 | E38: 2 | F38: 234.01 | G38: =ROUND(IF($F$17="USD $", F38*$E$15,F38*$D$15),2) -> 332.29 | H38: =ROUND(IF($H$17=$G$17,E38*G38,E38*F38),2) -> 664.58 | J38: =E38 -> 2 | K38: =IFERROR(IF(M38="OEM DISC %",ROUND(IF($K$17=$F$17,F38*(1-N38),G38*(1-N38)),2),IF(M38="MARKUP %",ROUND(R38/J38*(1+N38),2))),0) -> 182.76 | L38: =ROUND((J38*K38),2) -> 365.52 | M38: OEM DISC % | N38: 0.45 | R38: =ROUND(IF($R$17=$Q$17,Q38,IF($R$17="USD $",Q38*$D$15,Q38*$E$15))*E38,2) -> 0 | S38: =IFERROR(ROUND(T38/E38,2),0) -> 182.76 | T38: =ROUND(L38-R38,2) -> 365.52 | U38: =IFERROR(((K38-(R38/J38))/(R38/J38)),0) -> 0 | V38: =IFERROR(((K38-(R38/J38))/K38),0) -> 1
B39: 3F-5108 | C39: Bolt-Plow(5/8-11X2.25-IN) | D39: 1500 | E39: 8 | F39: 2.19 | G39: =ROUND(IF($F$17="USD $", F39*$E$15,F39*$D$15),2) -> 3.11 | H39: =ROUND(IF($H$17=$G$17,E39*G39,E39*F39),2) -> 24.88 | J39: =E39 -> 8 | K39: =IFERROR(IF(M39="OEM DISC %",ROUND(IF($K$17=$F$17,F39*(1-N39),G39*(1-N39)),2),IF(M39="MARKUP %",ROUND(R39/J39*(1+N39),2))),0) -> 1.71 | L39: =ROUND((J39*K39),2) -> 13.68 | M39: OEM DISC % | N39: 0.45 | R39: =ROUND(IF($R$17=$Q$17,Q39,IF($R$17="USD $",Q39*$D$15,Q39*$E$15))*E39,2) -> 0 | S39: =IFERROR(ROUND(T39/E39,2),0) -> 1.71 | T39: =ROUND(L39-R39,2) -> 13.68 | U39: =IFERROR(((K39-(R39/J39))/(R39/J39)),0) -> 0 | V39: =IFERROR(((K39-(R39/J39))/K39),0) -> 1
B40: 4K-0367 | C40: Nut-Full(5/8-11-THD) | D40: 1500 | E40: 8 | F40: 1.65 | G40: =ROUND(IF($F$17="USD $", F40*$E$15,F40*$D$15),2) -> 2.34 | H40: =ROUND(IF($H$17=$G$17,E40*G40,E40*F40),2) -> 18.72 | J40: =E40 -> 8 | K40: =IFERROR(IF(M40="OEM DISC %",ROUND(IF($K$17=$F$17,F40*(1-N40),G40*(1-N40)),2),IF(M40="MARKUP %",ROUND(R40/J40*(1+N40),2))),0) -> 1.29 | L40: =ROUND((J40*K40),2) -> 10.32 | M40: OEM DISC % | N40: 0.45 | R40: =ROUND(IF($R$17=$Q$17,Q40,IF($R$17="USD $",Q40*$D$15,Q40*$E$15))*E40,2) -> 0 | S40: =IFERROR(ROUND(T40/E40,2),0) -> 1.29 | T40: =ROUND(L40-R40,2) -> 10.32 | U40: =IFERROR(((K40-(R40/J40))/(R40/J40)),0) -> 0 | V40: =IFERROR(((K40-(R40/J40))/K40),0) -> 1
B41: 8T-4122 | C41: Washer-Hard(17X32X3.5-MM Thk) | D41: 1500 | E41: 8 | F41: 2.42 | G41: =ROUND(IF($F$17="USD $", F41*$E$15,F41*$D$15),2) -> 3.44 | H41: =ROUND(IF($H$17=$G$17,E41*G41,E41*F41),2) -> 27.52 | J41: =E41 -> 8 | K41: =IFERROR(IF(M41="OEM DISC %",ROUND(IF($K$17=$F$17,F41*(1-N41),G41*(1-N41)),2),IF(M41="MARKUP %",ROUND(R41/J41*(1+N41),2))),0) -> 1.89 | L41: =ROUND((J41*K41),2) -> 15.12 | M41: OEM DISC % | N41: 0.45 | R41: =ROUND(IF($R$17=$Q$17,Q41,IF($R$17="USD $",Q41*$D$15,Q41*$E$15))*E41,2) -> 0 | S41: =IFERROR(ROUND(T41/E41,2),0) -> 1.89 | T41: =ROUND(L41-R41,2) -> 15.12 | U41: =IFERROR(((K41-(R41/J41))/(R41/J41)),0) -> 0 | V41: =IFERROR(((K41-(R41/J41))/K41),0) -> 1
G42: =ROUND(IF($F$17="USD $", F42*$E$15,F42*$D$15),2) -> 0 | H42: =ROUND(IF($H$17=$G$17,E42*G42,E42*F42),2) -> 0 | J42: =E42 -> 0 | K42: =IFERROR(IF(M42="OEM DISC %",ROUND(IF($K$17=$F$17,F42*(1-N42),G42*(1-N42)),2),IF(M42="MARKUP %",ROUND(R42/J42*(1+N42),2))),0) -> 0 | L42: =ROUND((J42*K42),2) -> 0 | M42: MARKUP % | N42: 0.45 | R42: =ROUND(IF($R$17=$Q$17,Q42,IF($R$17="USD $",Q42*$D$15,Q42*$E$15))*E42,2) -> 0 | S42: =IFERROR(ROUND(T42/E42,2),0) -> 0 | T42: =ROUND(L42-R42,2) -> 0 | U42: =IFERROR(((K42-(R42/J42))/(R42/J42)),0) -> 0 | V42: =IFERROR(((K42-(R42/J42))/K42),0) -> 0
C43: Tire (16.9-28) rear | D43: 4000 | E43: 2 | F43: 300 | G43: =ROUND(IF($F$17="USD $", F43*$E$15,F43*$D$15),2) -> 426 | H43: =ROUND(IF($H$17=$G$17,E43*G43,E43*F43),2) -> 852 | J43: =E43 -> 2 | K43: =IFERROR(IF(M43="OEM DISC %",ROUND(IF($K$17=$F$17,F43*(1-N43),G43*(1-N43)),2),IF(M43="MARKUP %",ROUND(R43/J43*(1+N43),2))),0) -> 234.3 | L43: =ROUND((J43*K43),2) -> 468.6 | M43: OEM DISC % | N43: 0.45 | R43: =ROUND(IF($R$17=$Q$17,Q43,IF($R$17="USD $",Q43*$D$15,Q43*$E$15))*E43,2) -> 0 | S43: =IFERROR(ROUND(T43/E43,2),0) -> 234.3 | T43: =ROUND(L43-R43,2) -> 468.6 | U43: =IFERROR(((K43-(R43/J43))/(R43/J43)),0) -> 0 | V43: =IFERROR(((K43-(R43/J43))/K43),0) -> 1
C44: Tire(12.5/80-18) front | D44: 4000 | E44: 2 | F44: 155.98 | G44: =ROUND(IF($F$17="USD $", F44*$E$15,F44*$D$15),2) -> 221.49 | H44: =ROUND(IF($H$17=$G$17,E44*G44,E44*F44),2) -> 442.98 | J44: =E44 -> 2 | K44: =IFERROR(IF(M44="OEM DISC %",ROUND(IF($K$17=$F$17,F44*(1-N44),G44*(1-N44)),2),IF(M44="MARKUP %",ROUND(R44/J44*(1+N44),2))),0) -> 121.82 | L44: =ROUND((J44*K44),2) -> 243.64 | M44: OEM DISC % | N44: 0.45 | R44: =ROUND(IF($R$17=$Q$17,Q44,IF($R$17="USD $",Q44*$D$15,Q44*$E$15))*E44,2) -> 0 | S44: =IFERROR(ROUND(T44/E44,2),0) -> 121.82 | T44: =ROUND(L44-R44,2) -> 243.64 | U44: =IFERROR(((K44-(R44/J44))/(R44/J44)),0) -> 0 | V44: =IFERROR(((K44-(R44/J44))/K44),0) -> 1
G45: =ROUND(IF($F$17="USD $", F45*$E$15,F45*$D$15),2) -> 0 | H45: =ROUND(IF($H$17=$G$17,E45*G45,E45*F45),2) -> 0 | J45: =E45 -> 0 | K45: =IFERROR(IF(M45="OEM DISC %",ROUND(IF($K$17=$F$17,F45*(1-N45),G45*(1-N45)),2),IF(M45="MARKUP %",ROUND(R45/J45*(1+N45),2))),0) -> 0 | L45: =ROUND((J45*K45),2) -> 0 | M45: OEM DISC % | N45: 0.45 | R45: =ROUND(IF($R$17=$Q$17,Q45,IF($R$17="USD $",Q45*$D$15,Q45*$E$15))*E45,2) -> 0 | S45: =IFERROR(ROUND(T45/E45,2),0) -> 0 | T45: =ROUND(L45-R45,2) -> 0 | U45: =IFERROR(((K45-(R45/J45))/(R45/J45)),0) -> 0 | V45: =IFERROR(((K45-(R45/J45))/K45),0) -> 0
G46: =ROUND(IF($F$17="USD $", F46*$E$15,F46*$D$15),2) -> 0 | H46: =ROUND(IF($H$17=$G$17,E46*G46,E46*F46),2) -> 0 | J46: =E46 -> 0 | K46: =IFERROR(IF(M46="OEM DISC %",ROUND(IF($K$17=$F$17,F46*(1-N46),G46*(1-N46)),2),IF(M46="MARKUP %",ROUND(R46/J46*(1+N46),2))),0) -> 0 | L46: =ROUND((J46*K46),2) -> 0 | M46: OEM DISC % | N46: 0.45 | R46: =ROUND(IF($R$17=$Q$17,Q46,IF($R$17="USD $",Q46*$D$15,Q46*$E$15))*E46,2) -> 0 | S46: =IFERROR(ROUND(T46/E46,2),0) -> 0 | T46: =ROUND(L46-R46,2) -> 0 | U46: =IFERROR(((K46-(R46/J46))/(R46/J46)),0) -> 0 | V46: =IFERROR(((K46-(R46/J46))/K46),0) -> 0
G47: =ROUND(IF($F$17="USD $", F47*$E$15,F47*$D$15),2) -> 0 | H47: =ROUND(IF($H$17=$G$17,E47*G47,E47*F47),2) -> 0 | J47: =E47 -> 0 | K47: =IFERROR(IF(M47="OEM DISC %",ROUND(IF($K$17=$F$17,F47*(1-N47),G47*(1-N47)),2),IF(M47="MARKUP %",ROUND(R47/J47*(1+N47),2))),0) -> 0 | L47: =ROUND((J47*K47),2) -> 0 | M47: OEM DISC % | N47: 0.45 | R47: =ROUND(IF($R$17=$Q$17,Q47,IF($R$17="USD $",Q47*$D$15,Q47*$E$15))*E47,2) -> 0 | S47: =IFERROR(ROUND(T47/E47,2),0) -> 0 | T47: =ROUND(L47-R47,2) -> 0 | U47: =IFERROR(((K47-(R47/J47))/(R47/J47)),0) -> 0 | V47: =IFERROR(((K47-(R47/J47))/K47),0) -> 0
G48: =ROUND(IF($F$17="USD $", F48*$E$15,F48*$D$15),2) -> 0 | H48: =ROUND(IF($H$17=$G$17,E48*G48,E48*F48),2) -> 0 | J48: =E48 -> 0 | K48: =IFERROR(IF(M48="OEM DISC %",ROUND(IF($K$17=$F$17,F48*(1-N48),G48*(1-N48)),2),IF(M48="MARKUP %",ROUND(R48/J48*(1+N48),2))),0) -> 0 | L48: =ROUND((J48*K48),2) -> 0 | M48: OEM DISC % | N48: 0.45 | R48: =ROUND(IF($R$17=$Q$17,Q48,IF($R$17="USD $",Q48*$D$15,Q48*$E$15))*E48,2) -> 0 | S48: =IFERROR(ROUND(T48/E48,2),0) -> 0 | T48: =ROUND(L48-R48,2) -> 0 | U48: =IFERROR(((K48-(R48/J48))/(R48/J48)),0) -> 0 | V48: =IFERROR(((K48-(R48/J48))/K48),0) -> 0
D49: TOTALS | E49: =SUM(E18:E48) -> 88 | F49: =SUM(F18:F48) -> 16840.55 | G49: =SUM(G18:G48) -> 23913.59 | H49: =SUM(H18:H48) -> 27679.07 | J49: =SUM(J18:J48) -> 88 | K49: =SUM(K18:K48) -> 13152.49 | L49: =SUM(L18:L48) -> 15223.48 | Q49: =SUM(Q18:Q48) -> 0 | R49: =SUM(R18:R48) -> 0 | S49: =SUM(S18:S48) -> 13152.49 | T49: =SUM(T18:T48) -> 15223.48

Sheet CAT 390DL
B1: CUSTOMER INFORMATION | D1: MACHINE INFORMATION | H1: MACHINE SERVICE HR INTERVALS | L1: SUMMARY | P1: =K17 -> CAD $ | S1: COMPLETED DEAL INFORMATION
B2: DATE: | D2: UNIT # | F2: EXC-46 | H2: ENGINE AIR | L2: OEM MSRP | P2: =H49 -> 35855.13 | S2: SALES REP
B3: COMPANY: | D3: YEAR | F3: 2011 | H3: ENGINE OIL | L3: GQP LIST | P3: =L49 -> 19720.34 | S3: ORDER PO #
B4: CUSTOMER: | D4: MAKE | F4: CAT | H4: FUEL FILTERS | L4: $ SAVINGS | P4: =P2-P3 -> 16134.79 | S4: PROJECT #
B5: PHONE: | D5: MODEL | F5: 390DL | H5: HYDRAULIC FILTERS | L5: % SAVINGS | P5: =IFERROR((P2-P3)/P2,"") -> 0.44999948 | S5: CUST INVOICE #
B6: EMAIL: | D6: SERIAL NUMBER | F6: WAP00233 | H6: TRANSMISSION FILTERS | L6: TOTAL ORDER MARGIN | P6: =T49 -> 19720.34 | S6: PAYMENT TYPE
B7: SALES REP: | D7: ENGINE SER NUMBER | F7: TXH01194 | H7: CAB FILTERS | L7: TOTAL ITEM COST | P7: =R49 -> 0 | S7: DATE DELIVERED
D8: CURRENT HOURS | H8: UNDERCARRIAGE / TIRES | L8: TOTAL ORDER FREIGHT | P8: =IF(P1=Q14,R14,IF(Q14="CAD $",R14*D15,IF(Q14="USD $",R14*E15,0))) -> 0 | S8: TOTAL COST | T8: NET MARGIN | U8: NET MARKUP % | V8: NET MARGIN %
D9: USAGE/MONTH | F9: Hydraulic Excavator | L9: TOTAL CUSTOMS/BROKERAGE | P9: =V14 -> 0 | S9: =P7+P8+P9 -> 0 | T9: =P3-S9 -> 19720.34 | U9: =IFERROR(((P3-S9)/S9),0) -> 0 | V9: =IFERROR(T9/P3,0) -> 1
L10: TOTAL NUMBER PIECES | P10: =E49 -> 22
D11: ENTER EXCHANGE RATES $ | F11: OEM MSRP | J11: CUSTOMER SELL PRICE | P11: COST ANALYSIS | Y11: CAD $
Y12: USD $
F13: SHOW OEM MSRP ON QUOTE: | H13: YES | Y13: YES
D14: CAD-USD | E14: USD-CAD | F14: OEM NAME | J14: CUSTOMER TYPE/TIER | L14: IE: VIP - Gold | P14: FREIGHT TOTAL ORDER | Q14: USD $ | S14: CUSTOMS AND BROKERAGE % | T14: 0.025 | U14: BROKERAGE FEES | V14: =ROUND(R49*T14,2) -> 0 | Y14: NO
D15: =1/E15 -> 0.70422535 | E15: 1.42 | P15: MARKUP LESS THAN 100% REQUIRES MANAGER APPROVAL
B16: PART NUMBER | C16: DESCRIPTION | D16: SERVICE INTERVAL | E16: QTY | F16: UNIT PRICE | H16: EXT AMOUNT | J16: QTY | K16: UNIT PRICE | L16: EXTENDED AMOUNT | M16: PRCING METHOD %OEM / MARKUP | N16: OEM DISC % / MARKUP % | P16: VENDOR | Q16: COST EACH | R16: EXTENDED COST | S16: MARGIN EACH | T16: EXTENDED MARGIN | U16: MARKUP % | V16: MARGIN %
F17: USD $ | G17: =IF(F17="USD $", "CAD $", "USD $") -> CAD $ | H17: =K17 -> CAD $ | K17: CAD $ | Q17: USD $ | R17: =K17 -> CAD $
B18: 1R-1808 | C18: ENGINE OIL FILTER | D18: 250 | E18: 1 | F18: 37.21 | G18: =ROUND(IF($F$17="USD $", F18*$E$15,F18*$D$15),2) -> 52.84 | H18: =ROUND(IF($H$17=$G$17,E18*G18,E18*F18),2) -> 52.84 | J18: =E18 -> 1 | K18: =IFERROR(IF(M18="OEM DISC %",ROUND(IF($K$17=$F$17,F18*(1-N18),G18*(1-N18)),2),IF(M18="MARKUP %",ROUND(R18/J18*(1+N18),2))),0) -> 29.06 | L18: =ROUND((J18*K18),2) -> 29.06 | M18: OEM DISC % | N18: 0.45 | R18: =ROUND(IF($R$17=$Q$17,Q18,IF($R$17="USD $",Q18*$D$15,Q18*$E$15))*E18,2) -> 0 | S18: =IFERROR(ROUND(T18/E18,2),0) -> 29.06 | T18: =ROUND(L18-R18,2) -> 29.06 | U18: =IFERROR(((K18-(R18/J18))/(R18/J18)),0) -> 0 | V18: =IFERROR(((K18-(R18/J18))/K18),0) -> 1 | Z18: 250
B19: 326-1643 | C19: WATER FUEL SEPARATOR FUEL | D19: 500 | E19: 1 | F19: 47.54 | G19: =ROUND(IF($F$17="USD $", F19*$E$15,F19*$D$15),2) -> 67.51 | H19: =ROUND(IF($H$17=$G$17,E19*G19,E19*F19),2) -> 67.51 | J19: =E19 -> 1 | K19: =IFERROR(IF(M19="OEM DISC %",ROUND(IF($K$17=$F$17,F19*(1-N19),G19*(1-N19)),2),IF(M19="MARKUP %",ROUND(R19/J19*(1+N19),2))),0) -> 37.13 | L19: =ROUND((J19*K19),2) -> 37.13 | M19: OEM DISC % | N19: 0.45 | R19: =ROUND(IF($R$17=$Q$17,Q19,IF($R$17="USD $",Q19*$D$15,Q19*$E$15))*E19,2) -> 0 | S19: =IFERROR(ROUND(T19/E19,2),0) -> 37.13 | T19: =ROUND(L19-R19,2) -> 37.13 | U19: =IFERROR(((K19-(R19/J19))/(R19/J19)),0) -> 0 | V19: =IFERROR(((K19-(R19/J19))/K19),0) -> 1 | Y19: GQP | Z19: 500
B20: 1r-0755 | C20: FUEL FILTER | D20: 250 | E20: 2 | F20: 86.75 | G20: =ROUND(IF($F$17="USD $", F20*$E$15,F20*$D$15),2) -> 123.19 | H20: =ROUND(IF($H$17=$G$17,E20*G20,E20*F20),2) -> 246.38 | J20: =E20 -> 2 | K20: =IFERROR(IF(M20="OEM DISC %",ROUND(IF($K$17=$F$17,F20*(1-N20),G20*(1-N20)),2),IF(M20="MARKUP %",ROUND(R20/J20*(1+N20),2))),0) -> 67.75 | L20: =ROUND((J20*K20),2) -> 135.5 | M20: OEM DISC % | N20: 0.45 | R20: =ROUND(IF($R$17=$Q$17,Q20,IF($R$17="USD $",Q20*$D$15,Q20*$E$15))*E20,2) -> 0 | S20: =IFERROR(ROUND(T20/E20,2),0) -> 67.75 | T20: =ROUND(L20-R20,2) -> 135.5 | U20: =IFERROR(((K20-(R20/J20))/(R20/J20)),0) -> 0 | V20: =IFERROR(((K20-(R20/J20))/K20),0) -> 1 | Y20: CTP | Z20: 750
B21: 179-9806 | C21: HYDRAULIC FILTER | D21: 500 | E21: 1 | F21: 155.71 | G21: =ROUND(IF($F$17="USD $", F21*$E$15,F21*$D$15),2) -> 221.11 | H21: =ROUND(IF($H$17=$G$17,E21*G21,E21*F21),2) -> 221.11 | J21: =E21 -> 1 | K21: =IFERROR(IF(M21="OEM DISC %",ROUND(IF($K$17=$F$17,F21*(1-N21),G21*(1-N21)),2),IF(M21="MARKUP %",ROUND(R21/J21*(1+N21),2))),0) -> 121.61 | L21: =ROUND((J21*K21),2) -> 121.61 | M21: OEM DISC % | N21: 0.45 | R21: =ROUND(IF($R$17=$Q$17,Q21,IF($R$17="USD $",Q21*$D$15,Q21*$E$15))*E21,2) -> 0 | S21: =IFERROR(ROUND(T21/E21,2),0) -> 121.61 | T21: =ROUND(L21-R21,2) -> 121.61 | U21: =IFERROR(((K21-(R21/J21))/(R21/J21)),0) -> 0 | V21: =IFERROR(((K21-(R21/J21))/K21),0) -> 1 | Y21: BLMQ | Z21: 1000
B22: 419-8528 | C22: HYDRAULIC FILTER | D22: 500 | E22: 1 | F22: 1234.83 | G22: =ROUND(IF($F$17="USD $", F22*$E$15,F22*$D$15),2) -> 1753.46 | H22: =ROUND(IF($H$17=$G$17,E22*G22,E22*F22),2) -> 1753.46 | J22: =E22 -> 1 | K22: =IFERROR(IF(M22="OEM DISC %",ROUND(IF($K$17=$F$17,F22*(1-N22),G22*(1-N22)),2),IF(M22="MARKUP %",ROUND(R22/J22*(1+N22),2))),0) -> 964.4 | L22: =ROUND((J22*K22),2) -> 964.4 | M22: OEM DISC % | N22: 0.45 | R22: =ROUND(IF($R$17=$Q$17,Q22,IF($R$17="USD $",Q22*$D$15,Q22*$E$15))*E22,2) -> 0 | S22: =IFERROR(ROUND(T22/E22,2),0) -> 964.4 | T22: =ROUND(L22-R22,2) -> 964.4 | U22: =IFERROR(((K22-(R22/J22))/(R22/J22)),0) -> 0 | V22: =IFERROR(((K22-(R22/J22))/K22),0) -> 1 | Y22: CAT | Z22: 1200
B23: 106-3969 | C23: PRIMARY AIR FILTER ELEMENT | D23: 500 | E23: 1 | F23: 192.49 | G23: =ROUND(IF($F$17="USD $", F23*$E$15,F23*$D$15),2) -> 273.34 | H23: =ROUND(IF($H$17=$G$17,E23*G23,E23*F23),2) -> 273.34 | J23: =E23 -> 1 | K23: =IFERROR(IF(M23="OEM DISC %",ROUND(IF($K$17=$F$17,F23*(1-N23),G23*(1-N23)),2),IF(M23="MARKUP %",ROUND(R23/J23*(1+N23),2))),0) -> 150.34 | L23: =ROUND((J23*K23),2) -> 150.34 | M23: OEM DISC % | N23: 0.45 | R23: =ROUND(IF($R$17=$Q$17,Q23,IF($R$17="USD $",Q23*$D$15,Q23*$E$15))*E23,2) -> 0 | S23: =IFERROR(ROUND(T23/E23,2),0) -> 150.34 | T23: =ROUND(L23-R23,2) -> 150.34 | U23: =IFERROR(((K23-(R23/J23))/(R23/J23)),0) -> 0 | V23: =IFERROR(((K23-(R23/J23))/K23),0) -> 1 | Y23: FINNING | Z23: 2000
B24: 106-3973 | C24: SECONDARY AIR FILTER ELEMENT | D24: 250 | E24: 1 | F24: 133.9 | G24: =ROUND(IF($F$17="USD $", F24*$E$15,F24*$D$15),2) -> 190.14 | H24: =ROUND(IF($H$17=$G$17,E24*G24,E24*F24),2) -> 190.14 | J24: =E24 -> 1 | K24: =IFERROR(IF(M24="OEM DISC %",ROUND(IF($K$17=$F$17,F24*(1-N24),G24*(1-N24)),2),IF(M24="MARKUP %",ROUND(R24/J24*(1+N24),2))),0) -> 104.58 | L24: =ROUND((J24*K24),2) -> 104.58 | M24: OEM DISC % | N24: 0.45 | R24: =ROUND(IF($R$17=$Q$17,Q24,IF($R$17="USD $",Q24*$D$15,Q24*$E$15))*E24,2) -> 0 | S24: =IFERROR(ROUND(T24/E24,2),0) -> 104.58 | T24: =ROUND(L24-R24,2) -> 104.58 | U24: =IFERROR(((K24-(R24/J24))/(R24/J24)),0) -> 0 | V24: =IFERROR(((K24-(R24/J24))/K24),0) -> 1 | Y24: JD | Z24: 4000
B25: 293-1183 | C25: CABIN AIR FILTER | D25: 250 | E25: 1 | F25: 29.17 | G25: =ROUND(IF($F$17="USD $", F25*$E$15,F25*$D$15),2) -> 41.42 | H25: =ROUND(IF($H$17=$G$17,E25*G25,E25*F25),2) -> 41.42 | J25: =E25 -> 1 | K25: =IFERROR(IF(M25="OEM DISC %",ROUND(IF($K$17=$F$17,F25*(1-N25),G25*(1-N25)),2),IF(M25="MARKUP %",ROUND(R25/J25*(1+N25),2))),0) -> 22.78 | L25: =ROUND((J25*K25),2) -> 22.78 | M25: OEM DISC % | N25: 0.45 | R25: =ROUND(IF($R$17=$Q$17,Q25,IF($R$17="USD $",Q25*$D$15,Q25*$E$15))*E25,2) -> 0 | S25: =IFERROR(ROUND(T25/E25,2),0) -> 22.78 | T25: =ROUND(L25-R25,2) -> 22.78 | U25: =IFERROR(((K25-(R25/J25))/(R25/J25)),0) -> 0 | V25: =IFERROR(((K25-(R25/J25))/K25),0) -> 1 | Y25: BRANDT | Z25: 6000
B26: 293-1184 | C26: CABIN AIR FILTER | D26: 250 | E26: 1 | F26: 27.44 | G26: =ROUND(IF($F$17="USD $", F26*$E$15,F26*$D$15),2) -> 38.96 | H26: =ROUND(IF($H$17=$G$17,E26*G26,E26*F26),2) -> 38.96 | J26: =E26 -> 1 | K26: =IFERROR(IF(M26="OEM DISC %",ROUND(IF($K$17=$F$17,F26*(1-N26),G26*(1-N26)),2),IF(M26="MARKUP %",ROUND(R26/J26*(1+N26),2))),0) -> 21.43 | L26: =ROUND((J26*K26),2) -> 21.43 | M26: OEM DISC % | N26: 0.45 | R26: =ROUND(IF($R$17=$Q$17,Q26,IF($R$17="USD $",Q26*$D$15,Q26*$E$15))*E26,2) -> 0 | S26: =IFERROR(ROUND(T26/E26,2),0) -> 21.43 | T26: =ROUND(L26-R26,2) -> 21.43 | U26: =IFERROR(((K26-(R26/J26))/(R26/J26)),0) -> 0 | V26: =IFERROR(((K26-(R26/J26))/K26),0) -> 1 | Y26: PTI | Z26: 8000
G27: =ROUND(IF($F$17="USD $", F27*$E$15,F27*$D$15),2) -> 0 | H27: =ROUND(IF($H$17=$G$17,E27*G27,E27*F27),2) -> 0 | J27: =E27 -> 0 | K27: =IFERROR(IF(M27="OEM DISC %",ROUND(IF($K$17=$F$17,F27*(1-N27),G27*(1-N27)),2),IF(M27="MARKUP %",ROUND(R27/J27*(1+N27),2))),0) -> 0 | L27: =ROUND((J27*K27),2) -> 0 | M27: OEM DISC % | N27: 0.45 | R27: =ROUND(IF($R$17=$Q$17,Q27,IF($R$17="USD $",Q27*$D$15,Q27*$E$15))*E27,2) -> 0 | S27: =IFERROR(ROUND(T27/E27,2),0) -> 0 | T27: =ROUND(L27-R27,2) -> 0 | U27: =IFERROR(((K27-(R27/J27))/(R27/J27)),0) -> 0 | V27: =IFERROR(((K27-(R27/J27))/K27),0) -> 0 | Y27: CONEQUIP | Z27: 10000
B28: 440-1637 | C28: ENGINE OVERHAUL KIT | D28: 10000 | E28: 1 | G28: =ROUND(IF($F$17="USD $", F28*$E$15,F28*$D$15),2) -> 0 | H28: =ROUND(IF($H$17=$G$17,E28*G28,E28*F28),2) -> 0 | J28: =E28 -> 1 | K28: =IFERROR(IF(M28="OEM DISC %",ROUND(IF($K$17=$F$17,F28*(1-N28),G28*(1-N28)),2),IF(M28="MARKUP %",ROUND(R28/J28*(1+N28),2))),0) -> 0 | L28: =ROUND((J28*K28),2) -> 0 | M28: OEM DISC % | N28: 0.45 | R28: =ROUND(IF($R$17=$Q$17,Q28,IF($R$17="USD $",Q28*$D$15,Q28*$E$15))*E28,2) -> 0 | S28: =IFERROR(ROUND(T28/E28,2),0) -> 0 | T28: =ROUND(L28-R28,2) -> 0 | U28: =IFERROR(((K28-(R28/J28))/(R28/J28)),0) -> 0 | V28: =IFERROR(((K28-(R28/J28))/K28),0) -> 0 | Y28: CANDY | Z28: AS REQ'D
G29: =ROUND(IF($F$17="USD $", F29*$E$15,F29*$D$15),2) -> 0 | H29: =ROUND(IF($H$17=$G$17,E29*G29,E29*F29),2) -> 0 | J29: =E29 -> 0 | K29: =IFERROR(IF(M29="OEM DISC %",ROUND(IF($K$17=$F$17,F29*(1-N29),G29*(1-N29)),2),IF(M29="MARKUP %",ROUND(R29/J29*(1+N29),2))),0) -> 0 | L29: =ROUND((J29*K29),2) -> 0 | M29: OEM DISC % | N29: 0.45 | R29: =ROUND(IF($R$17=$Q$17,Q29,IF($R$17="USD $",Q29*$D$15,Q29*$E$15))*E29,2) -> 0 | S29: =IFERROR(ROUND(T29/E29,2),0) -> 0 | T29: =ROUND(L29-R29,2) -> 0 | U29: =IFERROR(((K29-(R29/J29))/(R29/J29)),0) -> 0 | V29: =IFERROR(((K29-(R29/J29))/K29),0) -> 0 | Y29: U/C
B30: 327-6512 | C30: SEAT GP | D30: AS REQ'D | E30: 1 | F30: 1702.51 | G30: =ROUND(IF($F$17="USD $", F30*$E$15,F30*$D$15),2) -> 2417.56 | H30: =ROUND(IF($H$17=$G$17,E30*G30,E30*F30),2) -> 2417.56 | J30: =E30 -> 1 | K30: =IFERROR(IF(M30="OEM DISC %",ROUND(IF($K$17=$F$17,F30*(1-N30),G30*(1-N30)),2),IF(M30="MARKUP %",ROUND(R30/J30*(1+N30),2))),0) -> 1329.66 | L30: =ROUND((J30*K30),2) -> 1329.66 | M30: OEM DISC % | N30: 0.45 | R30: =ROUND(IF($R$17=$Q$17,Q30,IF($R$17="USD $",Q30*$D$15,Q30*$E$15))*E30,2) -> 0 | S30: =IFERROR(ROUND(T30/E30,2),0) -> 1329.66 | T30: =ROUND(L30-R30,2) -> 1329.66 | U30: =IFERROR(((K30-(R30/J30))/(R30/J30)),0) -> 0 | V30: =IFERROR(((K30-(R30/J30))/K30),0) -> 1
B31: 153-5710 | C31: BATTERY | D31: AS REQ'D | E31: 2 | F31: 366.44 | G31: =ROUND(IF($F$17="USD $", F31*$E$15,F31*$D$15),2) -> 520.34 | H31: =ROUND(IF($H$17=$G$17,E31*G31,E31*F31),2) -> 1040.68 | J31: =E31 -> 2 | K31: =IFERROR(IF(M31="OEM DISC %",ROUND(IF($K$17=$F$17,F31*(1-N31),G31*(1-N31)),2),IF(M31="MARKUP %",ROUND(R31/J31*(1+N31),2))),0) -> 286.19 | L31: =ROUND((J31*K31),2) -> 572.38 | M31: OEM DISC % | N31: 0.45 | R31: =ROUND(IF($R$17=$Q$17,Q31,IF($R$17="USD $",Q31*$D$15,Q31*$E$15))*E31,2) -> 0 | S31: =IFERROR(ROUND(T31/E31,2),0) -> 286.19 | T31: =ROUND(L31-R31,2) -> 572.38 | U31: =IFERROR(((K31-(R31/J31))/(R31/J31)),0) -> 0 | V31: =IFERROR(((K31-(R31/J31))/K31),0) -> 1 | Y31: OEM DISC %
B32: 362-0838 | C32: TURBOCHARGER GP | D32: 6000 | E32: 1 | F32: 12436.78 | G32: =ROUND(IF($F$17="USD $", F32*$E$15,F32*$D$15),2) -> 17660.23 | H32: =ROUND(IF($H$17=$G$17,E32*G32,E32*F32),2) -> 17660.23 | J32: =E32 -> 1 | K32: =IFERROR(IF(M32="OEM DISC %",ROUND(IF($K$17=$F$17,F32*(1-N32),G32*(1-N32)),2),IF(M32="MARKUP %",ROUND(R32/J32*(1+N32),2))),0) -> 9713.13 | L32: =ROUND((J32*K32),2) -> 9713.13 | M32: OEM DISC % | N32: 0.45 | R32: =ROUND(IF($R$17=$Q$17,Q32,IF($R$17="USD $",Q32*$D$15,Q32*$E$15))*E32,2) -> 0 | S32: =IFERROR(ROUND(T32/E32,2),0) -> 9713.13 | T32: =ROUND(L32-R32,2) -> 9713.13 | U32: =IFERROR(((K32-(R32/J32))/(R32/J32)),0) -> 0 | V32: =IFERROR(((K32-(R32/J32))/K32),0) -> 1 | Y32: MARKUP %
B33: 253-0616 | C33: INJECTOR GP | D33: 6000 | E33: 6 | F33: 1391.02 | G33: =ROUND(IF($F$17="USD $", F33*$E$15,F33*$D$15),2) -> 1975.25 | H33: =ROUND(IF($H$17=$G$17,E33*G33,E33*F33),2) -> 11851.5 | J33: =E33 -> 6 | K33: =IFERROR(IF(M33="OEM DISC %",ROUND(IF($K$17=$F$17,F33*(1-N33),G33*(1-N33)),2),IF(M33="MARKUP %",ROUND(R33/J33*(1+N33),2))),0) -> 1086.39 | L33: =ROUND((J33*K33),2) -> 6518.34 | M33: OEM DISC % | N33: 0.45 | R33: =ROUND(IF($R$17=$Q$17,Q33,IF($R$17="USD $",Q33*$D$15,Q33*$E$15))*E33,2) -> 0 | S33: =IFERROR(ROUND(T33/E33,2),0) -> 1086.39 | T33: =ROUND(L33-R33,2) -> 6518.34 | U33: =IFERROR(((K33-(R33/J33))/(R33/J33)),0) -> 0 | V33: =IFERROR(((K33-(R33/J33))/K33),0) -> 1
G34: =ROUND(IF($F$17="USD $", F34*$E$15,F34*$D$15),2) -> 0 | H34: =ROUND(IF($H$17=$G$17,E34*G34,E34*F34),2) -> 0 | J34: =E34 -> 0 | K34: =IFERROR(IF(M34="OEM DISC %",ROUND(IF($K$17=$F$17,F34*(1-N34),G34*(1-N34)),2),IF(M34="MARKUP %",ROUND(R34/J34*(1+N34),2))),0) -> 0 | L34: =ROUND((J34*K34),2) -> 0 | M34: OEM DISC % | N34: 0.45 | R34: =ROUND(IF($R$17=$Q$17,Q34,IF($R$17="USD $",Q34*$D$15,Q34*$E$15))*E34,2) -> 0 | S34: =IFERROR(ROUND(T34/E34,2),0) -> 0 | T34: =ROUND(L34-R34,2) -> 0 | U34: =IFERROR(((K34-(R34/J34))/(R34/J34)),0) -> 0 | V34: =IFERROR(((K34-(R34/J34))/K34),0) -> 0
G35: =ROUND(IF($F$17="USD $", F35*$E$15,F35*$D$15),2) -> 0 | H35: =ROUND(IF($H$17=$G$17,E35*G35,E35*F35),2) -> 0 | J35: =E35 -> 0 | K35: =IFERROR(IF(M35="OEM DISC %",ROUND(IF($K$17=$F$17,F35*(1-N35),G35*(1-N35)),2),IF(M35="MARKUP %",ROUND(R35/J35*(1+N35),2))),0) -> 0 | L35: =ROUND((J35*K35),2) -> 0 | M35: OEM DISC % | N35: 0.45 | R35: =ROUND(IF($R$17=$Q$17,Q35,IF($R$17="USD $",Q35*$D$15,Q35*$E$15))*E35,2) -> 0 | S35: =IFERROR(ROUND(T35/E35,2),0) -> 0 | T35: =ROUND(L35-R35,2) -> 0 | U35: =IFERROR(((K35-(R35/J35))/(R35/J35)),0) -> 0 | V35: =IFERROR(((K35-(R35/J35))/K35),0) -> 0
C36: 390DL COMPLETE UNDERCARRIAGE KIT | D36: 5000 | E36: 1 | G36: =ROUND(IF($F$17="USD $", F36*$E$15,F36*$D$15),2) -> 0 | H36: =ROUND(IF($H$17=$G$17,E36*G36,E36*F36),2) -> 0 | J36: =E36 -> 1 | K36: =IFERROR(IF(M36="OEM DISC %",ROUND(IF($K$17=$F$17,F36*(1-N36),G36*(1-N36)),2),IF(M36="MARKUP %",ROUND(R36/J36*(1+N36),2))),0) -> 0 | L36: =ROUND((J36*K36),2) -> 0 | M36: OEM DISC % | N36: 0.45 | R36: =ROUND(IF($R$17=$Q$17,Q36,IF($R$17="USD $",Q36*$D$15,Q36*$E$15))*E36,2) -> 0 | S36: =IFERROR(ROUND(T36/E36,2),0) -> 0 | T36: =ROUND(L36-R36,2) -> 0 | U36: =IFERROR(((K36-(R36/J36))/(R36/J36)),0) -> 0 | V36: =IFERROR(((K36-(R36/J36))/K36),0) -> 0
G37: =ROUND(IF($F$17="USD $", F37*$E$15,F37*$D$15),2) -> 0 | H37: =ROUND(IF($H$17=$G$17,E37*G37,E37*F37),2) -> 0 | J37: =E37 -> 0 | K37: =IFERROR(IF(M37="OEM DISC %",ROUND(IF($K$17=$F$17,F37*(1-N37),G37*(1-N37)),2),IF(M37="MARKUP %",ROUND(R37/J37*(1+N37),2))),0) -> 0 | L37: =ROUND((J37*K37),2) -> 0 | M37: OEM DISC % | N37: 0.45 | R37: =ROUND(IF($R$17=$Q$17,Q37,IF($R$17="USD $",Q37*$D$15,Q37*$E$15))*E37,2) -> 0 | S37: =IFERROR(ROUND(T37/E37,2),0) -> 0 | T37: =ROUND(L37-R37,2) -> 0 | U37: =IFERROR(((K37-(R37/J37))/(R37/J37)),0) -> 0 | V37: =IFERROR(((K37-(R37/J37))/K37),0) -> 0
G38: =ROUND(IF($F$17="USD $", F38*$E$15,F38*$D$15),2) -> 0 | H38: =ROUND(IF($H$17=$G$17,E38*G38,E38*F38),2) -> 0 | J38: =E38 -> 0 | K38: =IFERROR(IF(M38="OEM DISC %",ROUND(IF($K$17=$F$17,F38*(1-N38),G38*(1-N38)),2),IF(M38="MARKUP %",ROUND(R38/J38*(1+N38),2))),0) -> 0 | L38: =ROUND((J38*K38),2) -> 0 | M38: OEM DISC % | N38: 0.45 | R38: =ROUND(IF($R$17=$Q$17,Q38,IF($R$17="USD $",Q38*$D$15,Q38*$E$15))*E38,2) -> 0 | S38: =IFERROR(ROUND(T38/E38,2),0) -> 0 | T38: =ROUND(L38-R38,2) -> 0 | U38: =IFERROR(((K38-(R38/J38))/(R38/J38)),0) -> 0 | V38: =IFERROR(((K38-(R38/J38))/K38),0) -> 0
G39: =ROUND(IF($F$17="USD $", F39*$E$15,F39*$D$15),2) -> 0 | H39: =ROUND(IF($H$17=$G$17,E39*G39,E39*F39),2) -> 0 | J39: =E39 -> 0 | K39: =IFERROR(IF(M39="OEM DISC %",ROUND(IF($K$17=$F$17,F39*(1-N39),G39*(1-N39)),2),IF(M39="MARKUP %",ROUND(R39/J39*(1+N39),2))),0) -> 0 | L39: =ROUND((J39*K39),2) -> 0 | M39: OEM DISC % | N39: 0.45 | R39: =ROUND(IF($R$17=$Q$17,Q39,IF($R$17="USD $",Q39*$D$15,Q39*$E$15))*E39,2) -> 0 | S39: =IFERROR(ROUND(T39/E39,2),0) -> 0 | T39: =ROUND(L39-R39,2) -> 0 | U39: =IFERROR(((K39-(R39/J39))/(R39/J39)),0) -> 0 | V39: =IFERROR(((K39-(R39/J39))/K39),0) -> 0
G40: =ROUND(IF($F$17="USD $", F40*$E$15,F40*$D$15),2) -> 0 | H40: =ROUND(IF($H$17=$G$17,E40*G40,E40*F40),2) -> 0 | J40: =E40 -> 0 | K40: =IFERROR(IF(M40="OEM DISC %",ROUND(IF($K$17=$F$17,F40*(1-N40),G40*(1-N40)),2),IF(M40="MARKUP %",ROUND(R40/J40*(1+N40),2))),0) -> 0 | L40: =ROUND((J40*K40),2) -> 0 | M40: OEM DISC % | N40: 0.45 | R40: =ROUND(IF($R$17=$Q$17,Q40,IF($R$17="USD $",Q40*$D$15,Q40*$E$15))*E40,2) -> 0 | S40: =IFERROR(ROUND(T40/E40,2),0) -> 0 | T40: =ROUND(L40-R40,2) -> 0 | U40: =IFERROR(((K40-(R40/J40))/(R40/J40)),0) -> 0 | V40: =IFERROR(((K40-(R40/J40))/K40),0) -> 0
G41: =ROUND(IF($F$17="USD $", F41*$E$15,F41*$D$15),2) -> 0 | H41: =ROUND(IF($H$17=$G$17,E41*G41,E41*F41),2) -> 0 | J41: =E41 -> 0 | K41: =IFERROR(IF(M41="OEM DISC %",ROUND(IF($K$17=$F$17,F41*(1-N41),G41*(1-N41)),2),IF(M41="MARKUP %",ROUND(R41/J41*(1+N41),2))),0) -> 0 | L41: =ROUND((J41*K41),2) -> 0 | M41: OEM DISC % | N41: 0.45 | R41: =ROUND(IF($R$17=$Q$17,Q41,IF($R$17="USD $",Q41*$D$15,Q41*$E$15))*E41,2) -> 0 | S41: =IFERROR(ROUND(T41/E41,2),0) -> 0 | T41: =ROUND(L41-R41,2) -> 0 | U41: =IFERROR(((K41-(R41/J41))/(R41/J41)),0) -> 0 | V41: =IFERROR(((K41-(R41/J41))/K41),0) -> 0
G42: =ROUND(IF($F$17="USD $", F42*$E$15,F42*$D$15),2) -> 0 | H42: =ROUND(IF($H$17=$G$17,E42*G42,E42*F42),2) -> 0 | J42: =E42 -> 0 | K42: =IFERROR(IF(M42="OEM DISC %",ROUND(IF($K$17=$F$17,F42*(1-N42),G42*(1-N42)),2),IF(M42="MARKUP %",ROUND(R42/J42*(1+N42),2))),0) -> 0 | L42: =ROUND((J42*K42),2) -> 0 | M42: MARKUP % | N42: 0.45 | R42: =ROUND(IF($R$17=$Q$17,Q42,IF($R$17="USD $",Q42*$D$15,Q42*$E$15))*E42,2) -> 0 | S42: =IFERROR(ROUND(T42/E42,2),0) -> 0 | T42: =ROUND(L42-R42,2) -> 0 | U42: =IFERROR(((K42-(R42/J42))/(R42/J42)),0) -> 0 | V42: =IFERROR(((K42-(R42/J42))/K42),0) -> 0
G43: =ROUND(IF($F$17="USD $", F43*$E$15,F43*$D$15),2) -> 0 | H43: =ROUND(IF($H$17=$G$17,E43*G43,E43*F43),2) -> 0 | J43: =E43 -> 0 | K43: =IFERROR(IF(M43="OEM DISC %",ROUND(IF($K$17=$F$17,F43*(1-N43),G43*(1-N43)),2),IF(M43="MARKUP %",ROUND(R43/J43*(1+N43),2))),0) -> 0 | L43: =ROUND((J43*K43),2) -> 0 | M43: OEM DISC % | N43: 0.45 | R43: =ROUND(IF($R$17=$Q$17,Q43,IF($R$17="USD $",Q43*$D$15,Q43*$E$15))*E43,2) -> 0 | S43: =IFERROR(ROUND(T43/E43,2),0) -> 0 | T43: =ROUND(L43-R43,2) -> 0 | U43: =IFERROR(((K43-(R43/J43))/(R43/J43)),0) -> 0 | V43: =IFERROR(((K43-(R43/J43))/K43),0) -> 0
G44: =ROUND(IF($F$17="USD $", F44*$E$15,F44*$D$15),2) -> 0 | H44: =ROUND(IF($H$17=$G$17,E44*G44,E44*F44),2) -> 0 | J44: =E44 -> 0 | K44: =IFERROR(IF(M44="OEM DISC %",ROUND(IF($K$17=$F$17,F44*(1-N44),G44*(1-N44)),2),IF(M44="MARKUP %",ROUND(R44/J44*(1+N44),2))),0) -> 0 | L44: =ROUND((J44*K44),2) -> 0 | M44: OEM DISC % | N44: 0.45 | R44: =ROUND(IF($R$17=$Q$17,Q44,IF($R$17="USD $",Q44*$D$15,Q44*$E$15))*E44,2) -> 0 | S44: =IFERROR(ROUND(T44/E44,2),0) -> 0 | T44: =ROUND(L44-R44,2) -> 0 | U44: =IFERROR(((K44-(R44/J44))/(R44/J44)),0) -> 0 | V44: =IFERROR(((K44-(R44/J44))/K44),0) -> 0
G45: =ROUND(IF($F$17="USD $", F45*$E$15,F45*$D$15),2) -> 0 | H45: =ROUND(IF($H$17=$G$17,E45*G45,E45*F45),2) -> 0 | J45: =E45 -> 0 | K45: =IFERROR(IF(M45="OEM DISC %",ROUND(IF($K$17=$F$17,F45*(1-N45),G45*(1-N45)),2),IF(M45="MARKUP %",ROUND(R45/J45*(1+N45),2))),0) -> 0 | L45: =ROUND((J45*K45),2) -> 0 | M45: OEM DISC % | N45: 0.45 | R45: =ROUND(IF($R$17=$Q$17,Q45,IF($R$17="USD $",Q45*$D$15,Q45*$E$15))*E45,2) -> 0 | S45: =IFERROR(ROUND(T45/E45,2),0) -> 0 | T45: =ROUND(L45-R45,2) -> 0 | U45: =IFERROR(((K45-(R45/J45))/(R45/J45)),0) -> 0 | V45: =IFERROR(((K45-(R45/J45))/K45),0) -> 0
G46: =ROUND(IF($F$17="USD $", F46*$E$15,F46*$D$15),2) -> 0 | H46: =ROUND(IF($H$17=$G$17,E46*G46,E46*F46),2) -> 0 | J46: =E46 -> 0 | K46: =IFERROR(IF(M46="OEM DISC %",ROUND(IF($K$17=$F$17,F46*(1-N46),G46*(1-N46)),2),IF(M46="MARKUP %",ROUND(R46/J46*(1+N46),2))),0) -> 0 | L46: =ROUND((J46*K46),2) -> 0 | M46: OEM DISC % | N46: 0.45 | R46: =ROUND(IF($R$17=$Q$17,Q46,IF($R$17="USD $",Q46*$D$15,Q46*$E$15))*E46,2) -> 0 | S46: =IFERROR(ROUND(T46/E46,2),0) -> 0 | T46: =ROUND(L46-R46,2) -> 0 | U46: =IFERROR(((K46-(R46/J46))/(R46/J46)),0) -> 0 | V46: =IFERROR(((K46-(R46/J46))/K46),0) -> 0
G47: =ROUND(IF($F$17="USD $", F47*$E$15,F47*$D$15),2) -> 0 | H47: =ROUND(IF($H$17=$G$17,E47*G47,E47*F47),2) -> 0 | J47: =E47 -> 0 | K47: =IFERROR(IF(M47="OEM DISC %",ROUND(IF($K$17=$F$17,F47*(1-N47),G47*(1-N47)),2),IF(M47="MARKUP %",ROUND(R47/J47*(1+N47),2))),0) -> 0 | L47: =ROUND((J47*K47),2) -> 0 | M47: OEM DISC % | N47: 0.45 | R47: =ROUND(IF($R$17=$Q$17,Q47,IF($R$17="USD $",Q47*$D$15,Q47*$E$15))*E47,2) -> 0 | S47: =IFERROR(ROUND(T47/E47,2),0) -> 0 | T47: =ROUND(L47-R47,2) -> 0 | U47: =IFERROR(((K47-(R47/J47))/(R47/J47)),0) -> 0 | V47: =IFERROR(((K47-(R47/J47))/K47),0) -> 0
G48: =ROUND(IF($F$17="USD $", F48*$E$15,F48*$D$15),2) -> 0 | H48: =ROUND(IF($H$17=$G$17,E48*G48,E48*F48),2) -> 0 | J48: =E48 -> 0 | K48: =IFERROR(IF(M48="OEM DISC %",ROUND(IF($K$17=$F$17,F48*(1-N48),G48*(1-N48)),2),IF(M48="MARKUP %",ROUND(R48/J48*(1+N48),2))),0) -> 0 | L48: =ROUND((J48*K48),2) -> 0 | M48: OEM DISC % | N48: 0.45 | R48: =ROUND(IF($R$17=$Q$17,Q48,IF($R$17="USD $",Q48*$D$15,Q48*$E$15))*E48,2) -> 0 | S48: =IFERROR(ROUND(T48/E48,2),0) -> 0 | T48: =ROUND(L48-R48,2) -> 0 | U48: =IFERROR(((K48-(R48/J48))/(R48/J48)),0) -> 0 | V48: =IFERROR(((K48-(R48/J48))/K48),0) -> 0
D49: TOTALS | E49: =SUM(E18:E48) -> 22 | F49: =SUM(F18:F48) -> 17841.79 | G49: =SUM(G18:G48) -> 25335.35 | H49: =SUM(H18:H48) -> 35855.13 | J49: =SUM(J18:J48) -> 22 | K49: =SUM(K18:K48) -> 13934.45 | L49: =SUM(L18:L48) -> 19720.34 | Q49: =SUM(Q18:Q48) -> 0 | R49: =SUM(R18:R48) -> 0 | S49: =SUM(S18:S48) -> 13934.45 | T49: =SUM(T18:T48) -> 19720.34

Sheet CAT 390DL UNDERCARRIAGE
B1: CUSTOMER INFORMATION | D1: MACHINE INFORMATION | H1: MACHINE SERVICE HR INTERVALS | L1: SUMMARY | P1: =K17 -> CAD $ | S1: COMPLETED DEAL INFORMATION
B2: DATE: | D2: UNIT # | F2: EXC-46 - UC | H2: ENGINE AIR | L2: OEM MSRP | P2: =H49 -> 248463.84 | S2: SALES REP
B3: COMPANY: | D3: YEAR | F3: 2011 | H3: ENGINE OIL | L3: GQP LIST | P3: =L49 -> 136655.66 | S3: ORDER PO #
B4: CUSTOMER: | D4: MAKE | F4: CAT | H4: FUEL FILTERS | L4: $ SAVINGS | P4: =P2-P3 -> 111808.18 | S4: PROJECT #
B5: PHONE: | D5: MODEL | F5: 390DL - UC | H5: HYDRAULIC FILTERS | L5: % SAVINGS | P5: =IFERROR((P2-P3)/P2,"") -> 0.44999779 | S5: CUST INVOICE #
B6: EMAIL: | D6: SERIAL NUMBER | F6: WAP00233 - UC | H6: TRANSMISSION FILTERS | L6: TOTAL ORDER MARGIN | P6: =T49 -> 136655.66 | S6: PAYMENT TYPE
B7: SALES REP: | D7: ENGINE SER NUMBER | F7: TXH01194 | H7: CAB FILTERS | L7: TOTAL ITEM COST | P7: =R49 -> 0 | S7: DATE DELIVERED
D8: CURRENT HOURS | H8: UNDERCARRIAGE / TIRES | L8: TOTAL ORDER FREIGHT | P8: =IF(P1=Q14,R14,IF(Q14="CAD $",R14*D15,IF(Q14="USD $",R14*E15,0))) -> 0 | S8: TOTAL COST | T8: NET MARGIN | U8: NET MARKUP % | V8: NET MARGIN %
D9: USAGE/MONTH | F9: Hydraulic Excavator | L9: TOTAL CUSTOMS/BROKERAGE | P9: =V14 -> 0 | S9: =P7+P8+P9 -> 0 | T9: =P3-S9 -> 136655.66 | U9: =IFERROR(((P3-S9)/S9),0) -> 0 | V9: =IFERROR(T9/P3,0) -> 1
L10: TOTAL NUMBER PIECES | P10: =E49 -> 1096
D11: ENTER EXCHANGE RATES $ | F11: OEM MSRP | J11: CUSTOMER SELL PRICE | P11: COST ANALYSIS | Y11: CAD $
Y12: USD $
F13: SHOW OEM MSRP ON QUOTE: | H13: YES | Y13: YES
D14: CAD-USD | E14: USD-CAD | F14: OEM NAME | J14: CUSTOMER TYPE/TIER | L14: IE: VIP - Gold | P14: FREIGHT TOTAL ORDER | Q14: USD $ | S14: CUSTOMS AND BROKERAGE % | T14: 0.025 | U14: BROKERAGE FEES | V14: =ROUND(R49*T14,2) -> 0 | Y14: NO
D15: =1/E15 -> 0.70422535 | E15: 1.42 | P15: MARKUP LESS THAN 100% REQUIRES MANAGER APPROVAL
B16: PART NUMBER | C16: DESCRIPTION | D16: SERVICE INTERVAL | E16: QTY | F16: UNIT PRICE | H16: EXT AMOUNT | J16: QTY | K16: UNIT PRICE | L16: EXTENDED AMOUNT | M16: PRCING METHOD %OEM / MARKUP | N16: OEM DISC % / MARKUP % | P16: VENDOR | Q16: COST EACH | R16: EXTENDED COST | S16: MARGIN EACH | T16: EXTENDED MARGIN | U16: MARKUP % | V16: MARGIN %
F17: USD $ | G17: =IF(F17="USD $", "CAD $", "USD $") -> CAD $ | H17: =K17 -> CAD $ | K17: CAD $ | Q17: USD $ | R17: =K17 -> CAD $
B18: 567-7867 | C18: IDLER GROUP | D18: 5000 | E18: 2 | F18: 11641.3 | G18: =ROUND(IF($F$17="USD $", F18*$E$15,F18*$D$15),2) -> 16530.65 | H18: =ROUND(IF($H$17=$G$17,E18*G18,E18*F18),2) -> 33061.3 | J18: =E18 -> 2 | K18: =IFERROR(IF(M18="OEM DISC %",ROUND(IF($K$17=$F$17,F18*(1-N18),G18*(1-N18)),2),IF(M18="MARKUP %",ROUND(R18/J18*(1+N18),2))),0) -> 9091.86 | L18: =ROUND((J18*K18),2) -> 18183.72 | M18: OEM DISC % | N18: 0.45 | R18: =ROUND(IF($R$17=$Q$17,Q18,IF($R$17="USD $",Q18*$D$15,Q18*$E$15))*E18,2) -> 0 | S18: =IFERROR(ROUND(T18/E18,2),0) -> 9091.86 | T18: =ROUND(L18-R18,2) -> 18183.72 | U18: =IFERROR(((K18-(R18/J18))/(R18/J18)),0) -> 0 | V18: =IFERROR(((K18-(R18/J18))/K18),0) -> 1 | Z18: 250
G19: =ROUND(IF($F$17="USD $", F19*$E$15,F19*$D$15),2) -> 0 | H19: =ROUND(IF($H$17=$G$17,E19*G19,E19*F19),2) -> 0 | J19: =E19 -> 0 | K19: =IFERROR(IF(M19="OEM DISC %",ROUND(IF($K$17=$F$17,F19*(1-N19),G19*(1-N19)),2),IF(M19="MARKUP %",ROUND(R19/J19*(1+N19),2))),0) -> 0 | L19: =ROUND((J19*K19),2) -> 0 | M19: OEM DISC % | N19: 0.45 | R19: =ROUND(IF($R$17=$Q$17,Q19,IF($R$17="USD $",Q19*$D$15,Q19*$E$15))*E19,2) -> 0 | S19: =IFERROR(ROUND(T19/E19,2),0) -> 0 | T19: =ROUND(L19-R19,2) -> 0 | U19: =IFERROR(((K19-(R19/J19))/(R19/J19)),0) -> 0 | V19: =IFERROR(((K19-(R19/J19))/K19),0) -> 0 | Y19: GQP | Z19: 500
B20: 542-4530 | C20: TRACK LINK | D20: 5000 | E20: 2 | F20: 34757.46 | G20: =ROUND(IF($F$17="USD $", F20*$E$15,F20*$D$15),2) -> 49355.59 | H20: =ROUND(IF($H$17=$G$17,E20*G20,E20*F20),2) -> 98711.18 | J20: =E20 -> 2 | K20: =IFERROR(IF(M20="OEM DISC %",ROUND(IF($K$17=$F$17,F20*(1-N20),G20*(1-N20)),2),IF(M20="MARKUP %",ROUND(R20/J20*(1+N20),2))),0) -> 27145.57 | L20: =ROUND((J20*K20),2) -> 54291.14 | M20: OEM DISC % | N20: 0.45 | R20: =ROUND(IF($R$17=$Q$17,Q20,IF($R$17="USD $",Q20*$D$15,Q20*$E$15))*E20,2) -> 0 | S20: =IFERROR(ROUND(T20/E20,2),0) -> 27145.57 | T20: =ROUND(L20-R20,2) -> 54291.14 | U20: =IFERROR(((K20-(R20/J20))/(R20/J20)),0) -> 0 | V20: =IFERROR(((K20-(R20/J20))/K20),0) -> 1 | Y20: CTP | Z20: 750
B21: 596-3517 | C21: TRACK SHOE | D21: 5000 | E21: 102 | F21: 282.04 | G21: =ROUND(IF($F$17="USD $", F21*$E$15,F21*$D$15),2) -> 400.5 | H21: =ROUND(IF($H$17=$G$17,E21*G21,E21*F21),2) -> 40851 | J21: =E21 -> 102 | K21: =IFERROR(IF(M21="OEM DISC %",ROUND(IF($K$17=$F$17,F21*(1-N21),G21*(1-N21)),2),IF(M21="MARKUP %",ROUND(R21/J21*(1+N21),2))),0) -> 220.28 | L21: =ROUND((J21*K21),2) -> 22468.56 | M21: OEM DISC % | N21: 0.45 | R21: =ROUND(IF($R$17=$Q$17,Q21,IF($R$17="USD $",Q21*$D$15,Q21*$E$15))*E21,2) -> 0 | S21: =IFERROR(ROUND(T21/E21,2),0) -> 220.28 | T21: =ROUND(L21-R21,2) -> 22468.56 | U21: =IFERROR(((K21-(R21/J21))/(R21/J21)),0) -> 0 | V21: =IFERROR(((K21-(R21/J21))/K21),0) -> 1 | Y21: BLMQ | Z21: 1000
B22: 301-2301 | C22: Bolt-Track(M30X2X97-MM) | D22: 5000 | E22: 408 | F22: 16.39 | G22: =ROUND(IF($F$17="USD $", F22*$E$15,F22*$D$15),2) -> 23.27 | H22: =ROUND(IF($H$17=$G$17,E22*G22,E22*F22),2) -> 9494.16 | J22: =E22 -> 408 | K22: =IFERROR(IF(M22="OEM DISC %",ROUND(IF($K$17=$F$17,F22*(1-N22),G22*(1-N22)),2),IF(M22="MARKUP %",ROUND(R22/J22*(1+N22),2))),0) -> 12.8 | L22: =ROUND((J22*K22),2) -> 5222.4 | M22: OEM DISC % | N22: 0.45 | R22: =ROUND(IF($R$17=$Q$17,Q22,IF($R$17="USD $",Q22*$D$15,Q22*$E$15))*E22,2) -> 0 | S22: =IFERROR(ROUND(T22/E22,2),0) -> 12.8 | T22: =ROUND(L22-R22,2) -> 5222.4 | U22: =IFERROR(((K22-(R22/J22))/(R22/J22)),0) -> 0 | V22: =IFERROR(((K22-(R22/J22))/K22),0) -> 1 | Y22: CAT | Z22: 1200
B23: 174-0222 | C23: Nut-Track(M30X2-THD) | D23: 5000 | E23: 408 | F23: 6.01 | G23: =ROUND(IF($F$17="USD $", F23*$E$15,F23*$D$15),2) -> 8.53 | H23: =ROUND(IF($H$17=$G$17,E23*G23,E23*F23),2) -> 3480.24 | J23: =E23 -> 408 | K23: =IFERROR(IF(M23="OEM DISC %",ROUND(IF($K$17=$F$17,F23*(1-N23),G23*(1-N23)),2),IF(M23="MARKUP %",ROUND(R23/J23*(1+N23),2))),0) -> 4.69 | L23: =ROUND((J23*K23),2) -> 1913.52 | M23: OEM DISC % | N23: 0.45 | R23: =ROUND(IF($R$17=$Q$17,Q23,IF($R$17="USD $",Q23*$D$15,Q23*$E$15))*E23,2) -> 0 | S23: =IFERROR(ROUND(T23/E23,2),0) -> 4.69 | T23: =ROUND(L23-R23,2) -> 1913.52 | U23: =IFERROR(((K23-(R23/J23))/(R23/J23)),0) -> 0 | V23: =IFERROR(((K23-(R23/J23))/K23),0) -> 1 | Y23: FINNING | Z23: 2000
B24: 366-3380 | C24: SINGLE FLANGE TRACK ROLLER | D24: 5000 | E24: 18 | F24: 1932.51 | G24: =ROUND(IF($F$17="USD $", F24*$E$15,F24*$D$15),2) -> 2744.16 | H24: =ROUND(IF($H$17=$G$17,E24*G24,E24*F24),2) -> 49394.88 | J24: =E24 -> 18 | K24: =IFERROR(IF(M24="OEM DISC %",ROUND(IF($K$17=$F$17,F24*(1-N24),G24*(1-N24)),2),IF(M24="MARKUP %",ROUND(R24/J24*(1+N24),2))),0) -> 1509.29 | L24: =ROUND((J24*K24),2) -> 27167.22 | M24: OEM DISC % | N24: 0.45 | R24: =ROUND(IF($R$17=$Q$17,Q24,IF($R$17="USD $",Q24*$D$15,Q24*$E$15))*E24,2) -> 0 | S24: =IFERROR(ROUND(T24/E24,2),0) -> 1509.29 | T24: =ROUND(L24-R24,2) -> 27167.22 | U24: =IFERROR(((K24-(R24/J24))/(R24/J24)),0) -> 0 | V24: =IFERROR(((K24-(R24/J24))/K24),0) -> 1 | Y24: JD | Z24: 4000
B25: 542-8380 | C25: CARRIER ROLLER | D25: 5000 | E25: 6 | F25: 865.46 | G25: =ROUND(IF($F$17="USD $", F25*$E$15,F25*$D$15),2) -> 1228.95 | H25: =ROUND(IF($H$17=$G$17,E25*G25,E25*F25),2) -> 7373.7 | J25: =E25 -> 6 | K25: =IFERROR(IF(M25="OEM DISC %",ROUND(IF($K$17=$F$17,F25*(1-N25),G25*(1-N25)),2),IF(M25="MARKUP %",ROUND(R25/J25*(1+N25),2))),0) -> 675.92 | L25: =ROUND((J25*K25),2) -> 4055.52 | M25: OEM DISC % | N25: 0.45 | R25: =ROUND(IF($R$17=$Q$17,Q25,IF($R$17="USD $",Q25*$D$15,Q25*$E$15))*E25,2) -> 0 | S25: =IFERROR(ROUND(T25/E25,2),0) -> 675.92 | T25: =ROUND(L25-R25,2) -> 4055.52 | U25: =IFERROR(((K25-(R25/J25))/(R25/J25)),0) -> 0 | V25: =IFERROR(((K25-(R25/J25))/K25),0) -> 1 | Y25: BRANDT | Z25: 6000
B26: 447-1727 | C26: Bolt(M30X3.5X150-MM) | D26: 5000 | E26: 72 | F26: 45.88 | G26: =ROUND(IF($F$17="USD $", F26*$E$15,F26*$D$15),2) -> 65.15 | H26: =ROUND(IF($H$17=$G$17,E26*G26,E26*F26),2) -> 4690.8 | J26: =E26 -> 72 | K26: =IFERROR(IF(M26="OEM DISC %",ROUND(IF($K$17=$F$17,F26*(1-N26),G26*(1-N26)),2),IF(M26="MARKUP %",ROUND(R26/J26*(1+N26),2))),0) -> 35.83 | L26: =ROUND((J26*K26),2) -> 2579.76 | M26: OEM DISC % | N26: 0.45 | R26: =ROUND(IF($R$17=$Q$17,Q26,IF($R$17="USD $",Q26*$D$15,Q26*$E$15))*E26,2) -> 0 | S26: =IFERROR(ROUND(T26/E26,2),0) -> 35.83 | T26: =ROUND(L26-R26,2) -> 2579.76 | U26: =IFERROR(((K26-(R26/J26))/(R26/J26)),0) -> 0 | V26: =IFERROR(((K26-(R26/J26))/K26),0) -> 1 | Y26: PTI | Z26: 8000
B27: 7X-2584 | C27: Bolt(M30X3.5X140-MM) | D27: 5000 | E27: 6 | F27: 51.43 | G27: =ROUND(IF($F$17="USD $", F27*$E$15,F27*$D$15),2) -> 73.03 | H27: =ROUND(IF($H$17=$G$17,E27*G27,E27*F27),2) -> 438.18 | J27: =E27 -> 6 | K27: =IFERROR(IF(M27="OEM DISC %",ROUND(IF($K$17=$F$17,F27*(1-N27),G27*(1-N27)),2),IF(M27="MARKUP %",ROUND(R27/J27*(1+N27),2))),0) -> 40.17 | L27: =ROUND((J27*K27),2) -> 241.02 | M27: OEM DISC % | N27: 0.45 | R27: =ROUND(IF($R$17=$Q$17,Q27,IF($R$17="USD $",Q27*$D$15,Q27*$E$15))*E27,2) -> 0 | S27: =IFERROR(ROUND(T27/E27,2),0) -> 40.17 | T27: =ROUND(L27-R27,2) -> 241.02 | U27: =IFERROR(((K27-(R27/J27))/(R27/J27)),0) -> 0 | V27: =IFERROR(((K27-(R27/J27))/K27),0) -> 1 | Y27: CONEQUIP | Z27: 10000
B28: 9X-8258 | C28: Washer(33X56X6-MM Thk) | D28: 5000 | E28: 72 | F28: 9.47 | G28: =ROUND(IF($F$17="USD $", F28*$E$15,F28*$D$15),2) -> 13.45 | H28: =ROUND(IF($H$17=$G$17,E28*G28,E28*F28),2) -> 968.4 | J28: =E28 -> 72 | K28: =IFERROR(IF(M28="OEM DISC %",ROUND(IF($K$17=$F$17,F28*(1-N28),G28*(1-N28)),2),IF(M28="MARKUP %",ROUND(R28/J28*(1+N28),2))),0) -> 7.4 | L28: =ROUND((J28*K28),2) -> 532.8 | M28: OEM DISC % | N28: 0.45 | R28: =ROUND(IF($R$17=$Q$17,Q28,IF($R$17="USD $",Q28*$D$15,Q28*$E$15))*E28,2) -> 0 | S28: =IFERROR(ROUND(T28/E28,2),0) -> 7.4 | T28: =ROUND(L28-R28,2) -> 532.8 | U28: =IFERROR(((K28-(R28/J28))/(R28/J28)),0) -> 0 | V28: =IFERROR(((K28-(R28/J28))/K28),0) -> 1 | Y28: CANDY | Z28: AS REQ'D
G29: =ROUND(IF($F$17="USD $", F29*$E$15,F29*$D$15),2) -> 0 | H29: =ROUND(IF($H$17=$G$17,E29*G29,E29*F29),2) -> 0 | J29: =E29 -> 0 | K29: =IFERROR(IF(M29="OEM DISC %",ROUND(IF($K$17=$F$17,F29*(1-N29),G29*(1-N29)),2),IF(M29="MARKUP %",ROUND(R29/J29*(1+N29),2))),0) -> 0 | L29: =ROUND((J29*K29),2) -> 0 | M29: OEM DISC % | N29: 0.45 | R29: =ROUND(IF($R$17=$Q$17,Q29,IF($R$17="USD $",Q29*$D$15,Q29*$E$15))*E29,2) -> 0 | S29: =IFERROR(ROUND(T29/E29,2),0) -> 0 | T29: =ROUND(L29-R29,2) -> 0 | U29: =IFERROR(((K29-(R29/J29))/(R29/J29)),0) -> 0 | V29: =IFERROR(((K29-(R29/J29))/K29),0) -> 0 | Y29: U/C
G30: =ROUND(IF($F$17="USD $", F30*$E$15,F30*$D$15),2) -> 0 | H30: =ROUND(IF($H$17=$G$17,E30*G30,E30*F30),2) -> 0 | J30: =E30 -> 0 | K30: =IFERROR(IF(M30="OEM DISC %",ROUND(IF($K$17=$F$17,F30*(1-N30),G30*(1-N30)),2),IF(M30="MARKUP %",ROUND(R30/J30*(1+N30),2))),0) -> 0 | L30: =ROUND((J30*K30),2) -> 0 | M30: OEM DISC % | N30: 0.45 | R30: =ROUND(IF($R$17=$Q$17,Q30,IF($R$17="USD $",Q30*$D$15,Q30*$E$15))*E30,2) -> 0 | S30: =IFERROR(ROUND(T30/E30,2),0) -> 0 | T30: =ROUND(L30-R30,2) -> 0 | U30: =IFERROR(((K30-(R30/J30))/(R30/J30)),0) -> 0 | V30: =IFERROR(((K30-(R30/J30))/K30),0) -> 0
G31: =ROUND(IF($F$17="USD $", F31*$E$15,F31*$D$15),2) -> 0 | H31: =ROUND(IF($H$17=$G$17,E31*G31,E31*F31),2) -> 0 | J31: =E31 -> 0 | K31: =IFERROR(IF(M31="OEM DISC %",ROUND(IF($K$17=$F$17,F31*(1-N31),G31*(1-N31)),2),IF(M31="MARKUP %",ROUND(R31/J31*(1+N31),2))),0) -> 0 | L31: =ROUND((J31*K31),2) -> 0 | M31: OEM DISC % | N31: 0.45 | R31: =ROUND(IF($R$17=$Q$17,Q31,IF($R$17="USD $",Q31*$D$15,Q31*$E$15))*E31,2) -> 0 | S31: =IFERROR(ROUND(T31/E31,2),0) -> 0 | T31: =ROUND(L31-R31,2) -> 0 | U31: =IFERROR(((K31-(R31/J31))/(R31/J31)),0) -> 0 | V31: =IFERROR(((K31-(R31/J31))/K31),0) -> 0 | Y31: OEM DISC %
G32: =ROUND(IF($F$17="USD $", F32*$E$15,F32*$D$15),2) -> 0 | H32: =ROUND(IF($H$17=$G$17,E32*G32,E32*F32),2) -> 0 | J32: =E32 -> 0 | K32: =IFERROR(IF(M32="OEM DISC %",ROUND(IF($K$17=$F$17,F32*(1-N32),G32*(1-N32)),2),IF(M32="MARKUP %",ROUND(R32/J32*(1+N32),2))),0) -> 0 | L32: =ROUND((J32*K32),2) -> 0 | M32: OEM DISC % | N32: 0.45 | R32: =ROUND(IF($R$17=$Q$17,Q32,IF($R$17="USD $",Q32*$D$15,Q32*$E$15))*E32,2) -> 0 | S32: =IFERROR(ROUND(T32/E32,2),0) -> 0 | T32: =ROUND(L32-R32,2) -> 0 | U32: =IFERROR(((K32-(R32/J32))/(R32/J32)),0) -> 0 | V32: =IFERROR(((K32-(R32/J32))/K32),0) -> 0 | Y32: MARKUP %
G33: =ROUND(IF($F$17="USD $", F33*$E$15,F33*$D$15),2) -> 0 | H33: =ROUND(IF($H$17=$G$17,E33*G33,E33*F33),2) -> 0 | J33: =E33 -> 0 | K33: =IFERROR(IF(M33="OEM DISC %",ROUND(IF($K$17=$F$17,F33*(1-N33),G33*(1-N33)),2),IF(M33="MARKUP %",ROUND(R33/J33*(1+N33),2))),0) -> 0 | L33: =ROUND((J33*K33),2) -> 0 | M33: OEM DISC % | N33: 0.45 | R33: =ROUND(IF($R$17=$Q$17,Q33,IF($R$17="USD $",Q33*$D$15,Q33*$E$15))*E33,2) -> 0 | S33: =IFERROR(ROUND(T33/E33,2),0) -> 0 | T33: =ROUND(L33-R33,2) -> 0 | U33: =IFERROR(((K33-(R33/J33))/(R33/J33)),0) -> 0 | V33: =IFERROR(((K33-(R33/J33))/K33),0) -> 0
G34: =ROUND(IF($F$17="USD $", F34*$E$15,F34*$D$15),2) -> 0 | H34: =ROUND(IF($H$17=$G$17,E34*G34,E34*F34),2) -> 0 | J34: =E34 -> 0 | K34: =IFERROR(IF(M34="OEM DISC %",ROUND(IF($K$17=$F$17,F34*(1-N34),G34*(1-N34)),2),IF(M34="MARKUP %",ROUND(R34/J34*(1+N34),2))),0) -> 0 | L34: =ROUND((J34*K34),2) -> 0 | M34: OEM DISC % | N34: 0.45 | R34: =ROUND(IF($R$17=$Q$17,Q34,IF($R$17="USD $",Q34*$D$15,Q34*$E$15))*E34,2) -> 0 | S34: =IFERROR(ROUND(T34/E34,2),0) -> 0 | T34: =ROUND(L34-R34,2) -> 0 | U34: =IFERROR(((K34-(R34/J34))/(R34/J34)),0) -> 0 | V34: =IFERROR(((K34-(R34/J34))/K34),0) -> 0
G35: =ROUND(IF($F$17="USD $", F35*$E$15,F35*$D$15),2) -> 0 | H35: =ROUND(IF($H$17=$G$17,E35*G35,E35*F35),2) -> 0 | J35: =E35 -> 0 | K35: =IFERROR(IF(M35="OEM DISC %",ROUND(IF($K$17=$F$17,F35*(1-N35),G35*(1-N35)),2),IF(M35="MARKUP %",ROUND(R35/J35*(1+N35),2))),0) -> 0 | L35: =ROUND((J35*K35),2) -> 0 | M35: OEM DISC % | N35: 0.45 | R35: =ROUND(IF($R$17=$Q$17,Q35,IF($R$17="USD $",Q35*$D$15,Q35*$E$15))*E35,2) -> 0 | S35: =IFERROR(ROUND(T35/E35,2),0) -> 0 | T35: =ROUND(L35-R35,2) -> 0 | U35: =IFERROR(((K35-(R35/J35))/(R35/J35)),0) -> 0 | V35: =IFERROR(((K35-(R35/J35))/K35),0) -> 0
G36: =ROUND(IF($F$17="USD $", F36*$E$15,F36*$D$15),2) -> 0 | H36: =ROUND(IF($H$17=$G$17,E36*G36,E36*F36),2) -> 0 | J36: =E36 -> 0 | K36: =IFERROR(IF(M36="OEM DISC %",ROUND(IF($K$17=$F$17,F36*(1-N36),G36*(1-N36)),2),IF(M36="MARKUP %",ROUND(R36/J36*(1+N36),2))),0) -> 0 | L36: =ROUND((J36*K36),2) -> 0 | M36: OEM DISC % | N36: 0.45 | R36: =ROUND(IF($R$17=$Q$17,Q36,IF($R$17="USD $",Q36*$D$15,Q36*$E$15))*E36,2) -> 0 | S36: =IFERROR(ROUND(T36/E36,2),0) -> 0 | T36: =ROUND(L36-R36,2) -> 0 | U36: =IFERROR(((K36-(R36/J36))/(R36/J36)),0) -> 0 | V36: =IFERROR(((K36-(R36/J36))/K36),0) -> 0
G37: =ROUND(IF($F$17="USD $", F37*$E$15,F37*$D$15),2) -> 0 | H37: =ROUND(IF($H$17=$G$17,E37*G37,E37*F37),2) -> 0 | J37: =E37 -> 0 | K37: =IFERROR(IF(M37="OEM DISC %",ROUND(IF($K$17=$F$17,F37*(1-N37),G37*(1-N37)),2),IF(M37="MARKUP %",ROUND(R37/J37*(1+N37),2))),0) -> 0 | L37: =ROUND((J37*K37),2) -> 0 | M37: OEM DISC % | N37: 0.45 | R37: =ROUND(IF($R$17=$Q$17,Q37,IF($R$17="USD $",Q37*$D$15,Q37*$E$15))*E37,2) -> 0 | S37: =IFERROR(ROUND(T37/E37,2),0) -> 0 | T37: =ROUND(L37-R37,2) -> 0 | U37: =IFERROR(((K37-(R37/J37))/(R37/J37)),0) -> 0 | V37: =IFERROR(((K37-(R37/J37))/K37),0) -> 0
G38: =ROUND(IF($F$17="USD $", F38*$E$15,F38*$D$15),2) -> 0 | H38: =ROUND(IF($H$17=$G$17,E38*G38,E38*F38),2) -> 0 | J38: =E38 -> 0 | K38: =IFERROR(IF(M38="OEM DISC %",ROUND(IF($K$17=$F$17,F38*(1-N38),G38*(1-N38)),2),IF(M38="MARKUP %",ROUND(R38/J38*(1+N38),2))),0) -> 0 | L38: =ROUND((J38*K38),2) -> 0 | M38: OEM DISC % | N38: 0.45 | R38: =ROUND(IF($R$17=$Q$17,Q38,IF($R$17="USD $",Q38*$D$15,Q38*$E$15))*E38,2) -> 0 | S38: =IFERROR(ROUND(T38/E38,2),0) -> 0 | T38: =ROUND(L38-R38,2) -> 0 | U38: =IFERROR(((K38-(R38/J38))/(R38/J38)),0) -> 0 | V38: =IFERROR(((K38-(R38/J38))/K38),0) -> 0
G39: =ROUND(IF($F$17="USD $", F39*$E$15,F39*$D$15),2) -> 0 | H39: =ROUND(IF($H$17=$G$17,E39*G39,E39*F39),2) -> 0 | J39: =E39 -> 0 | K39: =IFERROR(IF(M39="OEM DISC %",ROUND(IF($K$17=$F$17,F39*(1-N39),G39*(1-N39)),2),IF(M39="MARKUP %",ROUND(R39/J39*(1+N39),2))),0) -> 0 | L39: =ROUND((J39*K39),2) -> 0 | M39: OEM DISC % | N39: 0.45 | R39: =ROUND(IF($R$17=$Q$17,Q39,IF($R$17="USD $",Q39*$D$15,Q39*$E$15))*E39,2) -> 0 | S39: =IFERROR(ROUND(T39/E39,2),0) -> 0 | T39: =ROUND(L39-R39,2) -> 0 | U39: =IFERROR(((K39-(R39/J39))/(R39/J39)),0) -> 0 | V39: =IFERROR(((K39-(R39/J39))/K39),0) -> 0
G40: =ROUND(IF($F$17="USD $", F40*$E$15,F40*$D$15),2) -> 0 | H40: =ROUND(IF($H$17=$G$17,E40*G40,E40*F40),2) -> 0 | J40: =E40 -> 0 | K40: =IFERROR(IF(M40="OEM DISC %",ROUND(IF($K$17=$F$17,F40*(1-N40),G40*(1-N40)),2),IF(M40="MARKUP %",ROUND(R40/J40*(1+N40),2))),0) -> 0 | L40: =ROUND((J40*K40),2) -> 0 | M40: OEM DISC % | N40: 0.45 | R40: =ROUND(IF($R$17=$Q$17,Q40,IF($R$17="USD $",Q40*$D$15,Q40*$E$15))*E40,2) -> 0 | S40: =IFERROR(ROUND(T40/E40,2),0) -> 0 | T40: =ROUND(L40-R40,2) -> 0 | U40: =IFERROR(((K40-(R40/J40))/(R40/J40)),0) -> 0 | V40: =IFERROR(((K40-(R40/J40))/K40),0) -> 0
G41: =ROUND(IF($F$17="USD $", F41*$E$15,F41*$D$15),2) -> 0 | H41: =ROUND(IF($H$17=$G$17,E41*G41,E41*F41),2) -> 0 | J41: =E41 -> 0 | K41: =IFERROR(IF(M41="OEM DISC %",ROUND(IF($K$17=$F$17,F41*(1-N41),G41*(1-N41)),2),IF(M41="MARKUP %",ROUND(R41/J41*(1+N41),2))),0) -> 0 | L41: =ROUND((J41*K41),2) -> 0 | M41: OEM DISC % | N41: 0.45 | R41: =ROUND(IF($R$17=$Q$17,Q41,IF($R$17="USD $",Q41*$D$15,Q41*$E$15))*E41,2) -> 0 | S41: =IFERROR(ROUND(T41/E41,2),0) -> 0 | T41: =ROUND(L41-R41,2) -> 0 | U41: =IFERROR(((K41-(R41/J41))/(R41/J41)),0) -> 0 | V41: =IFERROR(((K41-(R41/J41))/K41),0) -> 0
G42: =ROUND(IF($F$17="USD $", F42*$E$15,F42*$D$15),2) -> 0 | H42: =ROUND(IF($H$17=$G$17,E42*G42,E42*F42),2) -> 0 | J42: =E42 -> 0 | K42: =IFERROR(IF(M42="OEM DISC %",ROUND(IF($K$17=$F$17,F42*(1-N42),G42*(1-N42)),2),IF(M42="MARKUP %",ROUND(R42/J42*(1+N42),2))),0) -> 0 | L42: =ROUND((J42*K42),2) -> 0 | M42: MARKUP % | N42: 0.45 | R42: =ROUND(IF($R$17=$Q$17,Q42,IF($R$17="USD $",Q42*$D$15,Q42*$E$15))*E42,2) -> 0 | S42: =IFERROR(ROUND(T42/E42,2),0) -> 0 | T42: =ROUND(L42-R42,2) -> 0 | U42: =IFERROR(((K42-(R42/J42))/(R42/J42)),0) -> 0 | V42: =IFERROR(((K42-(R42/J42))/K42),0) -> 0
G43: =ROUND(IF($F$17="USD $", F43*$E$15,F43*$D$15),2) -> 0 | H43: =ROUND(IF($H$17=$G$17,E43*G43,E43*F43),2) -> 0 | J43: =E43 -> 0 | K43: =IFERROR(IF(M43="OEM DISC %",ROUND(IF($K$17=$F$17,F43*(1-N43),G43*(1-N43)),2),IF(M43="MARKUP %",ROUND(R43/J43*(1+N43),2))),0) -> 0 | L43: =ROUND((J43*K43),2) -> 0 | M43: OEM DISC % | N43: 0.45 | R43: =ROUND(IF($R$17=$Q$17,Q43,IF($R$17="USD $",Q43*$D$15,Q43*$E$15))*E43,2) -> 0 | S43: =IFERROR(ROUND(T43/E43,2),0) -> 0 | T43: =ROUND(L43-R43,2) -> 0 | U43: =IFERROR(((K43-(R43/J43))/(R43/J43)),0) -> 0 | V43: =IFERROR(((K43-(R43/J43))/K43),0) -> 0
G44: =ROUND(IF($F$17="USD $", F44*$E$15,F44*$D$15),2) -> 0 | H44: =ROUND(IF($H$17=$G$17,E44*G44,E44*F44),2) -> 0 | J44: =E44 -> 0 | K44: =IFERROR(IF(M44="OEM DISC %",ROUND(IF($K$17=$F$17,F44*(1-N44),G44*(1-N44)),2),IF(M44="MARKUP %",ROUND(R44/J44*(1+N44),2))),0) -> 0 | L44: =ROUND((J44*K44),2) -> 0 | M44: OEM DISC % | N44: 0.45 | R44: =ROUND(IF($R$17=$Q$17,Q44,IF($R$17="USD $",Q44*$D$15,Q44*$E$15))*E44,2) -> 0 | S44: =IFERROR(ROUND(T44/E44,2),0) -> 0 | T44: =ROUND(L44-R44,2) -> 0 | U44: =IFERROR(((K44-(R44/J44))/(R44/J44)),0) -> 0 | V44: =IFERROR(((K44-(R44/J44))/K44),0) -> 0
... G48: =ROUND(IF($F$17="USD $", F48*$E$15,F48*$D$15),2) -> 0 | H48: =ROUND(IF($H$17=$G$17,E48*G48,E48*F48),2) -> 0 | J48: =E48 -> 0 | K48: =IFERROR(IF(M48="OEM DISC %",ROUND(IF($K$17=$F$17,F48*(1-N48),G48*(1-N48)),2),IF(M48="MARKUP %",ROUND(R48/J48*(1+N48),2))),0) -> 0 | L48: =ROUND((J48*K48),2) -> 0 | M48: OEM DISC % | N48: 0.45 | R48: =ROUND(IF($R$17=$Q$17,Q48,IF($R$17="USD $",Q48*$D$15,Q48*$E$15))*E48,2) -> 0 | S48: =IFERROR(ROUND(T48/E48,2),0) -> 0 | T48: =ROUND(L48-R48,2) -> 0 | U48: =IFERROR(((K48-(R48/J48))/(R48/J48)),0) -> 0 | V48: =IFERROR(((K48-(R48/J48))/K48),0) -> 0
D49: TOTALS | E49: =SUM(E18:E48) -> 1096 | F49: =SUM(F18:F48) -> 49607.95 | G49: =SUM(G18:G48) -> 70443.28 | H49: =SUM(H18:H48) -> 248463.84 | J49: =SUM(J18:J48) -> 1096 | K49: =SUM(K18:K48) -> 38743.81 | L49: =SUM(L18:L48) -> 136655.66 | Q49: =SUM(Q18:Q48) -> 0 | R49: =SUM(R18:R48) -> 0 | S49: =SUM(S18:S48) -> 38743.81 | T49: =SUM(T18:T48) -> 136655.66

Sheet CAT 385CL
B1: CUSTOMER INFORMATION | D1: MACHINE INFORMATION | H1: MACHINE SERVICE HR INTERVALS | L1: SUMMARY | P1: =K17 -> CAD $ | S1: COMPLETED DEAL INFORMATION
B2: DATE: | D2: UNIT # | F2: EXC-48 | H2: ENGINE AIR | L2: OEM MSRP | P2: =H49 -> 336008.96 | S2: SALES REP
B3: COMPANY: | D3: YEAR | F3: 2010 | H3: ENGINE OIL | L3: GQP LIST | P3: =L49 -> 182870.52 | S3: ORDER PO #
B4: CUSTOMER: | D4: MAKE | F4: CAT | H4: FUEL FILTERS | L4: $ SAVINGS | P4: =P2-P3 -> 153138.44 | S4: PROJECT #
B5: PHONE: | D5: MODEL | F5: 385CL | H5: HYDRAULIC FILTERS | L5: % SAVINGS | P5: =IFERROR((P2-P3)/P2,"") -> 0.45575701 | S5: CUST INVOICE #
B6: EMAIL: | D6: SERIAL NUMBER | F6: KGB00479 | H6: TRANSMISSION FILTERS | L6: TOTAL ORDER MARGIN | P6: =T49 -> 182870.52 | S6: PAYMENT TYPE
B7: SALES REP: | D7: ENGINE SER NUMBER | F7: RHX08340 | H7: CAB FILTERS | L7: TOTAL ITEM COST | P7: =R49 -> 0 | S7: DATE DELIVERED
D8: CURRENT HOURS | H8: UNDERCARRIAGE / TIRES | L8: TOTAL ORDER FREIGHT | P8: =IF(P1=Q14,R14,IF(Q14="CAD $",R14*D15,IF(Q14="USD $",R14*E15,0))) -> 0 | S8: TOTAL COST | T8: NET MARGIN | U8: NET MARKUP % | V8: NET MARGIN %
D9: USAGE/MONTH | F9: Hydraulic Excavator | L9: TOTAL CUSTOMS/BROKERAGE | P9: =V14 -> 0 | S9: =P7+P8+P9 -> 0 | T9: =P3-S9 -> 182870.52 | U9: =IFERROR(((P3-S9)/S9),0) -> 0 | V9: =IFERROR(T9/P3,0) -> 1
L10: TOTAL NUMBER PIECES | P10: =E49 -> 975
D11: ENTER EXCHANGE RATES $ | F11: OEM MSRP | J11: CUSTOMER SELL PRICE | P11: COST ANALYSIS | Y11: CAD $
Y12: USD $
F13: SHOW OEM MSRP ON QUOTE: | H13: YES | Y13: YES
D14: CAD-USD | E14: USD-CAD | F14: OEM NAME | J14: CUSTOMER TYPE/TIER | L14: IE: VIP - Gold | P14: FREIGHT TOTAL ORDER | Q14: USD $ | S14: CUSTOMS AND BROKERAGE % | T14: 0.025 | U14: BROKERAGE FEES | V14: =ROUND(R49*T14,2) -> 0 | Y14: NO
D15: =1/E15 -> 0.70422535 | E15: 1.42 | P15: MARKUP LESS THAN 100% REQUIRES MANAGER APPROVAL
B16: PART NUMBER | C16: DESCRIPTION | D16: SERVICE INTERVAL | E16: QTY | F16: UNIT PRICE | H16: EXT AMOUNT | J16: QTY | K16: UNIT PRICE | L16: EXTENDED AMOUNT | M16: PRCING METHOD %OEM / MARKUP | N16: OEM DISC % / MARKUP % | P16: VENDOR | Q16: COST EACH | R16: EXTENDED COST | S16: MARGIN EACH | T16: EXTENDED MARGIN | U16: MARKUP % | V16: MARGIN %
F17: USD $ | G17: =IF(F17="USD $", "CAD $", "USD $") -> CAD $ | H17: =K17 -> CAD $ | K17: CAD $ | Q17: USD $ | R17: =K17 -> CAD $
B18: 1R-1808 | C18: ENGINE OIL FILTER | D18: 250 | E18: 1 | F18: 38.21 | G18: =ROUND(IF($F$17="USD $", F18*$E$15,F18*$D$15),2) -> 54.26 | H18: =ROUND(IF($H$17=$G$17,E18*G18,E18*F18),2) -> 54.26 | J18: =E18 -> 1 | K18: =IFERROR(IF(M18="OEM DISC %",ROUND(IF($K$17=$F$17,F18*(1-N18),G18*(1-N18)),2),IF(M18="MARKUP %",ROUND(R18/J18*(1+N18),2))),0) -> 29.84 | L18: =ROUND((J18*K18),2) -> 29.84 | M18: OEM DISC % | N18: 0.45 | R18: =ROUND(IF($R$17=$Q$17,Q18,IF($R$17="USD $",Q18*$D$15,Q18*$E$15))*E18,2) -> 0 | S18: =IFERROR(ROUND(T18/E18,2),0) -> 29.84 | T18: =ROUND(L18-R18,2) -> 29.84 | U18: =IFERROR(((K18-(R18/J18))/(R18/J18)),0) -> 0 | V18: =IFERROR(((K18-(R18/J18))/K18),0) -> 1 | Z18: 250
B19: 1R-0755 | C19: FUEL FILTER | D19: 250 | E19: 1 | F19: 86.75 | G19: =ROUND(IF($F$17="USD $", F19*$E$15,F19*$D$15),2) -> 123.19 | H19: =ROUND(IF($H$17=$G$17,E19*G19,E19*F19),2) -> 123.19 | J19: =E19 -> 1 | K19: =IFERROR(IF(M19="OEM DISC %",ROUND(IF($K$17=$F$17,F19*(1-N19),G19*(1-N19)),2),IF(M19="MARKUP %",ROUND(R19/J19*(1+N19),2))),0) -> 67.75 | L19: =ROUND((J19*K19),2) -> 67.75 | M19: OEM DISC % | N19: 0.45 | R19: =ROUND(IF($R$17=$Q$17,Q19,IF($R$17="USD $",Q19*$D$15,Q19*$E$15))*E19,2) -> 0 | S19: =IFERROR(ROUND(T19/E19,2),0) -> 67.75 | T19: =ROUND(L19-R19,2) -> 67.75 | U19: =IFERROR(((K19-(R19/J19))/(R19/J19)),0) -> 0 | V19: =IFERROR(((K19-(R19/J19))/K19),0) -> 1 | Y19: GQP | Z19: 500
B20: 326-1643 | C20: FUEL WATER SEPARATOR FILTER | D20: 500 | E20: 1 | F20: 71.3 | G20: =ROUND(IF($F$17="USD $", F20*$E$15,F20*$D$15),2) -> 101.25 | H20: =ROUND(IF($H$17=$G$17,E20*G20,E20*F20),2) -> 101.25 | J20: =E20 -> 1 | K20: =IFERROR(IF(M20="OEM DISC %",ROUND(IF($K$17=$F$17,F20*(1-N20),G20*(1-N20)),2),IF(M20="MARKUP %",ROUND(R20/J20*(1+N20),2))),0) -> 55.69 | L20: =ROUND((J20*K20),2) -> 55.69 | M20: OEM DISC % | N20: 0.45 | R20: =ROUND(IF($R$17=$Q$17,Q20,IF($R$17="USD $",Q20*$D$15,Q20*$E$15))*E20,2) -> 0 | S20: =IFERROR(ROUND(T20/E20,2),0) -> 55.69 | T20: =ROUND(L20-R20,2) -> 55.69 | U20: =IFERROR(((K20-(R20/J20))/(R20/J20)),0) -> 0 | V20: =IFERROR(((K20-(R20/J20))/K20),0) -> 1 | Y20: CTP | Z20: 750
B21: 179-9806 | C21: TRANSMISSION FILTER | D21: 500 | E21: 1 | F21: 155.71 | G21: =ROUND(IF($F$17="USD $", F21*$E$15,F21*$D$15),2) -> 221.11 | H21: =ROUND(IF($H$17=$G$17,E21*G21,E21*F21),2) -> 221.11 | J21: =E21 -> 1 | K21: =IFERROR(IF(M21="OEM DISC %",ROUND(IF($K$17=$F$17,F21*(1-N21),G21*(1-N21)),2),IF(M21="MARKUP %",ROUND(R21/J21*(1+N21),2))),0) -> 121.61 | L21: =ROUND((J21*K21),2) -> 121.61 | M21: OEM DISC % | N21: 0.45 | R21: =ROUND(IF($R$17=$Q$17,Q21,IF($R$17="USD $",Q21*$D$15,Q21*$E$15))*E21,2) -> 0 | S21: =IFERROR(ROUND(T21/E21,2),0) -> 121.61 | T21: =ROUND(L21-R21,2) -> 121.61 | U21: =IFERROR(((K21-(R21/J21))/(R21/J21)),0) -> 0 | V21: =IFERROR(((K21-(R21/J21))/K21),0) -> 1 | Y21: BLMQ | Z21: 1000
B22: 4T-6788 | C22: HYDRAULIC FILTER | D22: 500 | E22: 1 | F22: 38.21 | G22: =ROUND(IF($F$17="USD $", F22*$E$15,F22*$D$15),2) -> 54.26 | H22: =ROUND(IF($H$17=$G$17,E22*G22,E22*F22),2) -> 54.26 | J22: =E22 -> 1 | K22: =IFERROR(IF(M22="OEM DISC %",ROUND(IF($K$17=$F$17,F22*(1-N22),G22*(1-N22)),2),IF(M22="MARKUP %",ROUND(R22/J22*(1+N22),2))),0) -> 29.84 | L22: =ROUND((J22*K22),2) -> 29.84 | M22: OEM DISC % | N22: 0.45 | R22: =ROUND(IF($R$17=$Q$17,Q22,IF($R$17="USD $",Q22*$D$15,Q22*$E$15))*E22,2) -> 0 | S22: =IFERROR(ROUND(T22/E22,2),0) -> 29.84 | T22: =ROUND(L22-R22,2) -> 29.84 | U22: =IFERROR(((K22-(R22/J22))/(R22/J22)),0) -> 0 | V22: =IFERROR(((K22-(R22/J22))/K22),0) -> 1 | Y22: CAT | Z22: 1200
B23: 106-3969 | C23: PRIMARY AIR FILTER | D23: 500 | E23: 1 | F23: 192.49 | G23: =ROUND(IF($F$17="USD $", F23*$E$15,F23*$D$15),2) -> 273.34 | H23: =ROUND(IF($H$17=$G$17,E23*G23,E23*F23),2) -> 273.34 | J23: =E23 -> 1 | K23: =IFERROR(IF(M23="OEM DISC %",ROUND(IF($K$17=$F$17,F23*(1-N23),G23*(1-N23)),2),IF(M23="MARKUP %",ROUND(R23/J23*(1+N23),2))),0) -> 150.34 | L23: =ROUND((J23*K23),2) -> 150.34 | M23: OEM DISC % | N23: 0.45 | R23: =ROUND(IF($R$17=$Q$17,Q23,IF($R$17="USD $",Q23*$D$15,Q23*$E$15))*E23,2) -> 0 | S23: =IFERROR(ROUND(T23/E23,2),0) -> 150.34 | T23: =ROUND(L23-R23,2) -> 150.34 | U23: =IFERROR(((K23-(R23/J23))/(R23/J23)),0) -> 0 | V23: =IFERROR(((K23-(R23/J23))/K23),0) -> 1 | Y23: FINNING | Z23: 2000
B24: 106-3973 | C24: SECONDARY AIR FILTER | D24: 250 | E24: 1 | F24: 133.9 | G24: =ROUND(IF($F$17="USD $", F24*$E$15,F24*$D$15),2) -> 190.14 | H24: =ROUND(IF($H$17=$G$17,E24*G24,E24*F24),2) -> 190.14 | J24: =E24 -> 1 | K24: =IFERROR(IF(M24="OEM DISC %",ROUND(IF($K$17=$F$17,F24*(1-N24),G24*(1-N24)),2),IF(M24="MARKUP %",ROUND(R24/J24*(1+N24),2))),0) -> 104.58 | L24: =ROUND((J24*K24),2) -> 104.58 | M24: OEM DISC % | N24: 0.45 | R24: =ROUND(IF($R$17=$Q$17,Q24,IF($R$17="USD $",Q24*$D$15,Q24*$E$15))*E24,2) -> 0 | S24: =IFERROR(ROUND(T24/E24,2),0) -> 104.58 | T24: =ROUND(L24-R24,2) -> 104.58 | U24: =IFERROR(((K24-(R24/J24))/(R24/J24)),0) -> 0 | V24: =IFERROR(((K24-(R24/J24))/K24),0) -> 1 | Y24: JD | Z24: 4000
B25: 293-1183 | C25: CABIN AIR FILTER | D25: 250 | E25: 1 | F25: 43.76 | G25: =ROUND(IF($F$17="USD $", F25*$E$15,F25*$D$15),2) -> 62.14 | H25: =ROUND(IF($H$17=$G$17,E25*G25,E25*F25),2) -> 62.14 | J25: =E25 -> 1 | K25: =IFERROR(IF(M25="OEM DISC %",ROUND(IF($K$17=$F$17,F25*(1-N25),G25*(1-N25)),2),IF(M25="MARKUP %",ROUND(R25/J25*(1+N25),2))),0) -> 34.18 | L25: =ROUND((J25*K25),2) -> 34.18 | M25: OEM DISC % | N25: 0.45 | R25: =ROUND(IF($R$17=$Q$17,Q25,IF($R$17="USD $",Q25*$D$15,Q25*$E$15))*E25,2) -> 0 | S25: =IFERROR(ROUND(T25/E25,2),0) -> 34.18 | T25: =ROUND(L25-R25,2) -> 34.18 | U25: =IFERROR(((K25-(R25/J25))/(R25/J25)),0) -> 0 | V25: =IFERROR(((K25-(R25/J25))/K25),0) -> 1 | Y25: BRANDT | Z25: 6000
B26: 293-1184 | C26: CABIN AIR FILTER | D26: 250 | E26: 1 | F26: 41.17 | G26: =ROUND(IF($F$17="USD $", F26*$E$15,F26*$D$15),2) -> 58.46 | H26: =ROUND(IF($H$17=$G$17,E26*G26,E26*F26),2) -> 58.46 | J26: =E26 -> 1 | K26: =IFERROR(IF(M26="OEM DISC %",ROUND(IF($K$17=$F$17,F26*(1-N26),G26*(1-N26)),2),IF(M26="MARKUP %",ROUND(R26/J26*(1+N26),2))),0) -> 32.15 | L26: =ROUND((J26*K26),2) -> 32.15 | M26: OEM DISC % | N26: 0.45 | R26: =ROUND(IF($R$17=$Q$17,Q26,IF($R$17="USD $",Q26*$D$15,Q26*$E$15))*E26,2) -> 0 | S26: =IFERROR(ROUND(T26/E26,2),0) -> 32.15 | T26: =ROUND(L26-R26,2) -> 32.15 | U26: =IFERROR(((K26-(R26/J26))/(R26/J26)),0) -> 0 | V26: =IFERROR(((K26-(R26/J26))/K26),0) -> 1 | Y26: PTI | Z26: 8000
G27: =ROUND(IF($F$17="USD $", F27*$E$15,F27*$D$15),2) -> 0 | H27: =ROUND(IF($H$17=$G$17,E27*G27,E27*F27),2) -> 0 | J27: =E27 -> 0 | K27: =IFERROR(IF(M27="OEM DISC %",ROUND(IF($K$17=$F$17,F27*(1-N27),G27*(1-N27)),2),IF(M27="MARKUP %",ROUND(R27/J27*(1+N27),2))),0) -> 0 | L27: =ROUND((J27*K27),2) -> 0 | M27: OEM DISC % | N27: 0.45 | R27: =ROUND(IF($R$17=$Q$17,Q27,IF($R$17="USD $",Q27*$D$15,Q27*$E$15))*E27,2) -> 0 | S27: =IFERROR(ROUND(T27/E27,2),0) -> 0 | T27: =ROUND(L27-R27,2) -> 0 | U27: =IFERROR(((K27-(R27/J27))/(R27/J27)),0) -> 0 | V27: =IFERROR(((K27-(R27/J27))/K27),0) -> 0 | Y27: CONEQUIP | Z27: 10000
B28: 327-6512 | C28: SEAT GP-SUSPENSION | D28: AS REQ'D | E28: 1 | F28: 1702.51 | G28: =ROUND(IF($F$17="USD $", F28*$E$15,F28*$D$15),2) -> 2417.56 | H28: =ROUND(IF($H$17=$G$17,E28*G28,E28*F28),2) -> 2417.56 | J28: =E28 -> 1 | K28: =IFERROR(IF(M28="OEM DISC %",ROUND(IF($K$17=$F$17,F28*(1-N28),G28*(1-N28)),2),IF(M28="MARKUP %",ROUND(R28/J28*(1+N28),2))),0) -> 1329.66 | L28: =ROUND((J28*K28),2) -> 1329.66 | M28: OEM DISC % | N28: 0.45 | R28: =ROUND(IF($R$17=$Q$17,Q28,IF($R$17="USD $",Q28*$D$15,Q28*$E$15))*E28,2) -> 0 | S28: =IFERROR(ROUND(T28/E28,2),0) -> 1329.66 | T28: =ROUND(L28-R28,2) -> 1329.66 | U28: =IFERROR(((K28-(R28/J28))/(R28/J28)),0) -> 0 | V28: =IFERROR(((K28-(R28/J28))/K28),0) -> 1 | Y28: CANDY | Z28: AS REQ'D
B29: 153-5710 | C29: BATTERY | D29: AS REQ'D | E29: 2 | F29: 551.85 | G29: =ROUND(IF($F$17="USD $", F29*$E$15,F29*$D$15),2) -> 783.63 | H29: =ROUND(IF($H$17=$G$17,E29*G29,E29*F29),2) -> 1567.26 | J29: =E29 -> 2 | K29: =IFERROR(IF(M29="OEM DISC %",ROUND(IF($K$17=$F$17,F29*(1-N29),G29*(1-N29)),2),IF(M29="MARKUP %",ROUND(R29/J29*(1+N29),2))),0) -> 431 | L29: =ROUND((J29*K29),2) -> 862 | M29: OEM DISC % | N29: 0.45 | R29: =ROUND(IF($R$17=$Q$17,Q29,IF($R$17="USD $",Q29*$D$15,Q29*$E$15))*E29,2) -> 0 | S29: =IFERROR(ROUND(T29/E29,2),0) -> 431 | T29: =ROUND(L29-R29,2) -> 862 | U29: =IFERROR(((K29-(R29/J29))/(R29/J29)),0) -> 0 | V29: =IFERROR(((K29-(R29/J29))/K29),0) -> 1 | Y29: U/C
B30: 362-0838 | C30: TURBOCHARGER | D30: 6000 | E30: 1 | F30: 12787.87 | G30: =ROUND(IF($F$17="USD $", F30*$E$15,F30*$D$15),2) -> 18158.78 | H30: =ROUND(IF($H$17=$G$17,E30*G30,E30*F30),2) -> 18158.78 | J30: =E30 -> 1 | K30: =IFERROR(IF(M30="OEM DISC %",ROUND(IF($K$17=$F$17,F30*(1-N30),G30*(1-N30)),2),IF(M30="MARKUP %",ROUND(R30/J30*(1+N30),2))),0) -> 9987.33 | L30: =ROUND((J30*K30),2) -> 9987.33 | M30: OEM DISC % | N30: 0.45 | R30: =ROUND(IF($R$17=$Q$17,Q30,IF($R$17="USD $",Q30*$D$15,Q30*$E$15))*E30,2) -> 0 | S30: =IFERROR(ROUND(T30/E30,2),0) -> 9987.33 | T30: =ROUND(L30-R30,2) -> 9987.33 | U30: =IFERROR(((K30-(R30/J30))/(R30/J30)),0) -> 0 | V30: =IFERROR(((K30-(R30/J30))/K30),0) -> 1
B31: 253-0616 | C31: INJECTOR | D31: 6000 | E31: 6 | F31: 1430.29 | G31: =ROUND(IF($F$17="USD $", F31*$E$15,F31*$D$15),2) -> 2031.01 | H31: =ROUND(IF($H$17=$G$17,E31*G31,E31*F31),2) -> 12186.06 | J31: =E31 -> 6 | K31: =IFERROR(IF(M31="OEM DISC %",ROUND(IF($K$17=$F$17,F31*(1-N31),G31*(1-N31)),2),IF(M31="MARKUP %",ROUND(R31/J31*(1+N31),2))),0) -> 1117.06 | L31: =ROUND((J31*K31),2) -> 6702.36 | M31: OEM DISC % | N31: 0.45 | R31: =ROUND(IF($R$17=$Q$17,Q31,IF($R$17="USD $",Q31*$D$15,Q31*$E$15))*E31,2) -> 0 | S31: =IFERROR(ROUND(T31/E31,2),0) -> 1117.06 | T31: =ROUND(L31-R31,2) -> 6702.36 | U31: =IFERROR(((K31-(R31/J31))/(R31/J31)),0) -> 0 | V31: =IFERROR(((K31-(R31/J31))/K31),0) -> 1 | Y31: OEM DISC %
B32: 468-5119 | C32: CRANKSHAFT | D32: 10000 | E32: 1 | F32: 19323.96 | G32: =ROUND(IF($F$17="USD $", F32*$E$15,F32*$D$15),2) -> 27440.02 | H32: =ROUND(IF($H$17=$G$17,E32*G32,E32*F32),2) -> 27440.02 | J32: =E32 -> 1 | K32: =IFERROR(IF(M32="OEM DISC %",ROUND(IF($K$17=$F$17,F32*(1-N32),G32*(1-N32)),2),IF(M32="MARKUP %",ROUND(R32/J32*(1+N32),2))),0) -> 15092.01 | L32: =ROUND((J32*K32),2) -> 15092.01 | M32: OEM DISC % | N32: 0.45 | R32: =ROUND(IF($R$17=$Q$17,Q32,IF($R$17="USD $",Q32*$D$15,Q32*$E$15))*E32,2) -> 0 | S32: =IFERROR(ROUND(T32/E32,2),0) -> 15092.01 | T32: =ROUND(L32-R32,2) -> 15092.01 | U32: =IFERROR(((K32-(R32/J32))/(R32/J32)),0) -> 0 | V32: =IFERROR(((K32-(R32/J32))/K32),0) -> 1 | Y32: MARKUP %
B33: 332-7298 | C33: CAMSHAFT | D33: 10000 | E33: 1 | F33: 3576.6 | G33: =ROUND(IF($F$17="USD $", F33*$E$15,F33*$D$15),2) -> 5078.77 | H33: =ROUND(IF($H$17=$G$17,E33*G33,E33*F33),2) -> 5078.77 | J33: =E33 -> 1 | K33: =IFERROR(IF(M33="OEM DISC %",ROUND(IF($K$17=$F$17,F33*(1-N33),G33*(1-N33)),2),IF(M33="MARKUP %",ROUND(R33/J33*(1+N33),2))),0) -> 2793.32 | L33: =ROUND((J33*K33),2) -> 2793.32 | M33: OEM DISC % | N33: 0.45 | R33: =ROUND(IF($R$17=$Q$17,Q33,IF($R$17="USD $",Q33*$D$15,Q33*$E$15))*E33,2) -> 0 | S33: =IFERROR(ROUND(T33/E33,2),0) -> 2793.32 | T33: =ROUND(L33-R33,2) -> 2793.32 | U33: =IFERROR(((K33-(R33/J33))/(R33/J33)),0) -> 0 | V33: =IFERROR(((K33-(R33/J33))/K33),0) -> 1
B34: 583-9493 | C34: CYLINDER HEAD AS | D34: 10000 | E34: 1 | F34: 9677.14 | G34: =ROUND(IF($F$17="USD $", F34*$E$15,F34*$D$15),2) -> 13741.54 | H34: =ROUND(IF($H$17=$G$17,E34*G34,E34*F34),2) -> 13741.54 | J34: =E34 -> 1 | K34: =IFERROR(IF(M34="OEM DISC %",ROUND(IF($K$17=$F$17,F34*(1-N34),G34*(1-N34)),2),IF(M34="MARKUP %",ROUND(R34/J34*(1+N34),2))),0) -> 7557.85 | L34: =ROUND((J34*K34),2) -> 7557.85 | M34: OEM DISC % | N34: 0.45 | R34: =ROUND(IF($R$17=$Q$17,Q34,IF($R$17="USD $",Q34*$D$15,Q34*$E$15))*E34,2) -> 0 | S34: =IFERROR(ROUND(T34/E34,2),0) -> 7557.85 | T34: =ROUND(L34-R34,2) -> 7557.85 | U34: =IFERROR(((K34-(R34/J34))/(R34/J34)),0) -> 0 | V34: =IFERROR(((K34-(R34/J34))/K34),0) -> 1
B35: 444-7577 | C35: BUCKET TIP | D35: 500 | E35: 5 | F35: 1232.03 | G35: =ROUND(IF($F$17="USD $", F35*$E$15,F35*$D$15),2) -> 1749.48 | H35: =ROUND(IF($H$17=$G$17,E35*G35,E35*F35),2) -> 8747.4 | J35: =E35 -> 5 | K35: =IFERROR(IF(M35="OEM DISC %",ROUND(IF($K$17=$F$17,F35*(1-N35),G35*(1-N35)),2),IF(M35="MARKUP %",ROUND(R35/J35*(1+N35),2))),0) -> 962.21 | L35: =ROUND((J35*K35),2) -> 4811.05 | M35: OEM DISC % | N35: 0.45 | R35: =ROUND(IF($R$17=$Q$17,Q35,IF($R$17="USD $",Q35*$D$15,Q35*$E$15))*E35,2) -> 0 | S35: =IFERROR(ROUND(T35/E35,2),0) -> 962.21 | T35: =ROUND(L35-R35,2) -> 4811.05 | U35: =IFERROR(((K35-(R35/J35))/(R35/J35)),0) -> 0 | V35: =IFERROR(((K35-(R35/J35))/K35),0) -> 1
B36: 567-7867 | C36: Idler | D36: 5000 | E36: 2 | F36: 11766.04 | G36: =ROUND(IF($F$17="USD $", F36*$E$15,F36*$D$15),2) -> 16707.78 | H36: =ROUND(IF($H$17=$G$17,E36*G36,E36*F36),2) -> 33415.56 | J36: =E36 -> 2 | K36: =IFERROR(IF(M36="OEM DISC %",ROUND(IF($K$17=$F$17,F36*(1-N36),G36*(1-N36)),2),IF(M36="MARKUP %",ROUND(R36/J36*(1+N36),2))),0) -> 9189.28 | L36: =ROUND((J36*K36),2) -> 18378.56 | M36: OEM DISC % | N36: 0.45 | R36: =ROUND(IF($R$17=$Q$17,Q36,IF($R$17="USD $",Q36*$D$15,Q36*$E$15))*E36,2) -> 0 | S36: =IFERROR(ROUND(T36/E36,2),0) -> 9189.28 | T36: =ROUND(L36-R36,2) -> 18378.56 | U36: =IFERROR(((K36-(R36/J36))/(R36/J36)),0) -> 0 | V36: =IFERROR(((K36-(R36/J36))/K36),0) -> 1
B37: 542-8380 | C37: Roller GP-Track Carrier | D37: 5000 | E37: 6 | F37: 874.73 | G37: =ROUND(IF($F$17="USD $", F37*$E$15,F37*$D$15),2) -> 1242.12 | H37: =ROUND(IF($H$17=$G$17,E37*G37,E37*F37),2) -> 7452.72 | J37: =E37 -> 6 | K37: =IFERROR(IF(M37="OEM DISC %",ROUND(IF($K$17=$F$17,F37*(1-N37),G37*(1-N37)),2),IF(M37="MARKUP %",ROUND(R37/J37*(1+N37),2))),0) -> 683.17 | L37: =ROUND((J37*K37),2) -> 4099.02 | M37: OEM DISC % | N37: 0.45 | R37: =ROUND(IF($R$17=$Q$17,Q37,IF($R$17="USD $",Q37*$D$15,Q37*$E$15))*E37,2) -> 0 | S37: =IFERROR(ROUND(T37/E37,2),0) -> 683.17 | T37: =ROUND(L37-R37,2) -> 4099.02 | U37: =IFERROR(((K37-(R37/J37))/(R37/J37)),0) -> 0 | V37: =IFERROR(((K37-(R37/J37))/K37),0) -> 1
B38: 366-3380 | C38: Roller GP-Track-Single Flange | D38: 5000 | E38: 18 | F38: 1953.22 | G38: =ROUND(IF($F$17="USD $", F38*$E$15,F38*$D$15),2) -> 2773.57 | H38: =ROUND(IF($H$17=$G$17,E38*G38,E38*F38),2) -> 49924.26 | J38: =E38 -> 18 | K38: =IFERROR(IF(M38="OEM DISC %",ROUND(IF($K$17=$F$17,F38*(1-N38),G38*(1-N38)),2),IF(M38="MARKUP %",ROUND(R38/J38*(1+N38),2))),0) -> 1525.46 | L38: =ROUND((J38*K38),2) -> 27458.28 | M38: OEM DISC % | N38: 0.45 | R38: =ROUND(IF($R$17=$Q$17,Q38,IF($R$17="USD $",Q38*$D$15,Q38*$E$15))*E38,2) -> 0 | S38: =IFERROR(ROUND(T38/E38,2),0) -> 1525.46 | T38: =ROUND(L38-R38,2) -> 27458.28 | U38: =IFERROR(((K38-(R38/J38))/(R38/J38)),0) -> 0 | V38: =IFERROR(((K38-(R38/J38))/K38),0) -> 1
B39: 246-0506 | C39: Link AS-Track | D39: 5000 | E39: 2 | F39: 35129.86 | G39: =ROUND(IF($F$17="USD $", F39*$E$15,F39*$D$15),2) -> 49884.4 | H39: =ROUND(IF($H$17=$G$17,E39*G39,E39*F39),2) -> 99768.8 | J39: =E39 -> 2 | K39: =IFERROR(IF(M39="OEM DISC %",ROUND(IF($K$17=$F$17,F39*(1-N39),G39*(1-N39)),2),IF(M39="MARKUP %",ROUND(R39/J39*(1+N39),2))),0) -> 27436.42 | L39: =ROUND((J39*K39),2) -> 54872.84 | M39: OEM DISC % | N39: 0.45 | R39: =ROUND(IF($R$17=$Q$17,Q39,IF($R$17="USD $",Q39*$D$15,Q39*$E$15))*E39,2) -> 0 | S39: =IFERROR(ROUND(T39/E39,2),0) -> 27436.42 | T39: =ROUND(L39-R39,2) -> 54872.84 | U39: =IFERROR(((K39-(R39/J39))/(R39/J39)),0) -> 0 | V39: =IFERROR(((K39-(R39/J39))/K39),0) -> 1
B40: 174-0223 | C40: TRACK SHOE | D40: 5000 | E40: 102 | F40: 245.46 | G40: =ROUND(IF($F$17="USD $", F40*$E$15,F40*$D$15),2) -> 348.55 | H40: =ROUND(IF($H$17=$G$17,E40*G40,E40*F40),2) -> 35552.1 | J40: =E40 -> 102 | K40: =IFERROR(IF(M40="OEM DISC %",ROUND(IF($K$17=$F$17,F40*(1-N40),G40*(1-N40)),2),IF(M40="MARKUP %",ROUND(R40/J40*(1+N40),2))),0) -> 191.7 | L40: =ROUND((J40*K40),2) -> 19553.4 | M40: OEM DISC % | N40: 0.45 | R40: =ROUND(IF($R$17=$Q$17,Q40,IF($R$17="USD $",Q40*$D$15,Q40*$E$15))*E40,2) -> 0 | S40: =IFERROR(ROUND(T40/E40,2),0) -> 191.7 | T40: =ROUND(L40-R40,2) -> 19553.4 | U40: =IFERROR(((K40-(R40/J40))/(R40/J40)),0) -> 0 | V40: =IFERROR(((K40-(R40/J40))/K40),0) -> 1
B41: 174-0221 | C41: TRACK BOLT | D41: 5000 | E41: 408 | F41: 15.7 | G41: =ROUND(IF($F$17="USD $", F41*$E$15,F41*$D$15),2) -> 22.29 | H41: =ROUND(IF($H$17=$G$17,E41*G41,E41*F41),2) -> 9094.32 | J41: =E41 -> 408 | K41: =IFERROR(IF(M41="OEM DISC %",ROUND(IF($K$17=$F$17,F41*(1-N41),G41*(1-N41)),2),IF(M41="MARKUP %",ROUND(R41/J41*(1+N41),2))),0) -> 12.26 | L41: =ROUND((J41*K41),2) -> 5002.08 | M41: OEM DISC % | N41: 0.45 | R41: =ROUND(IF($R$17=$Q$17,Q41,IF($R$17="USD $",Q41*$D$15,Q41*$E$15))*E41,2) -> 0 | S41: =IFERROR(ROUND(T41/E41,2),0) -> 12.26 | T41: =ROUND(L41-R41,2) -> 5002.08 | U41: =IFERROR(((K41-(R41/J41))/(R41/J41)),0) -> 0 | V41: =IFERROR(((K41-(R41/J41))/K41),0) -> 1
B42: 174-0222 | C42: TRACK NUT | D42: 5000 | E42: 408 | F42: 6.07 | G42: =ROUND(IF($F$17="USD $", F42*$E$15,F42*$D$15),2) -> 8.62 | H42: =ROUND(IF($H$17=$G$17,E42*G42,E42*F42),2) -> 3516.96 | J42: =E42 -> 408 | K42: =IFERROR(IF(M42="OEM DISC %",ROUND(IF($K$17=$F$17,F42*(1-N42),G42*(1-N42)),2),IF(M42="MARKUP %",ROUND(R42/J42*(1+N42),2))),0) -> 0 | L42: =ROUND((J42*K42),2) -> 0 | M42: MARKUP % | N42: 0.45 | R42: =ROUND(IF($R$17=$Q$17,Q42,IF($R$17="USD $",Q42*$D$15,Q42*$E$15))*E42,2) -> 0 | S42: =IFERROR(ROUND(T42/E42,2),0) -> 0 | T42: =ROUND(L42-R42,2) -> 0 | U42: =IFERROR(((K42-(R42/J42))/(R42/J42)),0) -> 0 | V42: =IFERROR(((K42-(R42/J42))/K42),0) -> 0
B43: 639-7792 | C43: 23 TEETH SPROCKET | D43: 5000 | E43: 2 | F43: 2397.43 | G43: =ROUND(IF($F$17="USD $", F43*$E$15,F43*$D$15),2) -> 3404.35 | H43: =ROUND(IF($H$17=$G$17,E43*G43,E43*F43),2) -> 6808.7 | J43: =E43 -> 2 | K43: =IFERROR(IF(M43="OEM DISC %",ROUND(IF($K$17=$F$17,F43*(1-N43),G43*(1-N43)),2),IF(M43="MARKUP %",ROUND(R43/J43*(1+N43),2))),0) -> 1872.39 | L43: =ROUND((J43*K43),2) -> 3744.78 | M43: OEM DISC % | N43: 0.45 | R43: =ROUND(IF($R$17=$Q$17,Q43,IF($R$17="USD $",Q43*$D$15,Q43*$E$15))*E43,2) -> 0 | S43: =IFERROR(ROUND(T43/E43,2),0) -> 1872.39 | T43: =ROUND(L43-R43,2) -> 3744.78 | U43: =IFERROR(((K43-(R43/J43))/(R43/J43)),0) -> 0 | V43: =IFERROR(((K43-(R43/J43))/K43),0) -> 1
G44: =ROUND(IF($F$17="USD $", F44*$E$15,F44*$D$15),2) -> 0 | H44: =ROUND(IF($H$17=$G$17,E44*G44,E44*F44),2) -> 0 | J44: =E44 -> 0 | K44: =IFERROR(IF(M44="OEM DISC %",ROUND(IF($K$17=$F$17,F44*(1-N44),G44*(1-N44)),2),IF(M44="MARKUP %",ROUND(R44/J44*(1+N44),2))),0) -> 0 | L44: =ROUND((J44*K44),2) -> 0 | M44: OEM DISC % | N44: 0.45 | R44: =ROUND(IF($R$17=$Q$17,Q44,IF($R$17="USD $",Q44*$D$15,Q44*$E$15))*E44,2) -> 0 | S44: =IFERROR(ROUND(T44/E44,2),0) -> 0 | T44: =ROUND(L44-R44,2) -> 0 | U44: =IFERROR(((K44-(R44/J44))/(R44/J44)),0) -> 0 | V44: =IFERROR(((K44-(R44/J44))/K44),0) -> 0
G45: =ROUND(IF($F$17="USD $", F45*$E$15,F45*$D$15),2) -> 0 | H45: =ROUND(IF($H$17=$G$17,E45*G45,E45*F45),2) -> 0 | J45: =E45 -> 0 | K45: =IFERROR(IF(M45="OEM DISC %",ROUND(IF($K$17=$F$17,F45*(1-N45),G45*(1-N45)),2),IF(M45="MARKUP %",ROUND(R45/J45*(1+N45),2))),0) -> 0 | L45: =ROUND((J45*K45),2) -> 0 | M45: OEM DISC % | N45: 0.45 | R45: =ROUND(IF($R$17=$Q$17,Q45,IF($R$17="USD $",Q45*$D$15,Q45*$E$15))*E45,2) -> 0 | S45: =IFERROR(ROUND(T45/E45,2),0) -> 0 | T45: =ROUND(L45-R45,2) -> 0 | U45: =IFERROR(((K45-(R45/J45))/(R45/J45)),0) -> 0 | V45: =IFERROR(((K45-(R45/J45))/K45),0) -> 0
G46: =ROUND(IF($F$17="USD $", F46*$E$15,F46*$D$15),2) -> 0 | H46: =ROUND(IF($H$17=$G$17,E46*G46,E46*F46),2) -> 0 | J46: =E46 -> 0 | K46: =IFERROR(IF(M46="OEM DISC %",ROUND(IF($K$17=$F$17,F46*(1-N46),G46*(1-N46)),2),IF(M46="MARKUP %",ROUND(R46/J46*(1+N46),2))),0) -> 0 | L46: =ROUND((J46*K46),2) -> 0 | M46: OEM DISC % | N46: 0.45 | R46: =ROUND(IF($R$17=$Q$17,Q46,IF($R$17="USD $",Q46*$D$15,Q46*$E$15))*E46,2) -> 0 | S46: =IFERROR(ROUND(T46/E46,2),0) -> 0 | T46: =ROUND(L46-R46,2) -> 0 | U46: =IFERROR(((K46-(R46/J46))/(R46/J46)),0) -> 0 | V46: =IFERROR(((K46-(R46/J46))/K46),0) -> 0
G47: =ROUND(IF($F$17="USD $", F47*$E$15,F47*$D$15),2) -> 0 | H47: =ROUND(IF($H$17=$G$17,E47*G47,E47*F47),2) -> 0 | J47: =E47 -> 0 | K47: =IFERROR(IF(M47="OEM DISC %",ROUND(IF($K$17=$F$17,F47*(1-N47),G47*(1-N47)),2),IF(M47="MARKUP %",ROUND(R47/J47*(1+N47),2))),0) -> 0 | L47: =ROUND((J47*K47),2) -> 0 | M47: OEM DISC % | N47: 0.45 | R47: =ROUND(IF($R$17=$Q$17,Q47,IF($R$17="USD $",Q47*$D$15,Q47*$E$15))*E47,2) -> 0 | S47: =IFERROR(ROUND(T47/E47,2),0) -> 0 | T47: =ROUND(L47-R47,2) -> 0 | U47: =IFERROR(((K47-(R47/J47))/(R47/J47)),0) -> 0 | V47: =IFERROR(((K47-(R47/J47))/K47),0) -> 0
G48: =ROUND(IF($F$17="USD $", F48*$E$15,F48*$D$15),2) -> 0 | H48: =ROUND(IF($H$17=$G$17,E48*G48,E48*F48),2) -> 0 | J48: =E48 -> 0 | K48: =IFERROR(IF(M48="OEM DISC %",ROUND(IF($K$17=$F$17,F48*(1-N48),G48*(1-N48)),2),IF(M48="MARKUP %",ROUND(R48/J48*(1+N48),2))),0) -> 0 | L48: =ROUND((J48*K48),2) -> 0 | M48: OEM DISC % | N48: 0.45 | R48: =ROUND(IF($R$17=$Q$17,Q48,IF($R$17="USD $",Q48*$D$15,Q48*$E$15))*E48,2) -> 0 | S48: =IFERROR(ROUND(T48/E48,2),0) -> 0 | T48: =ROUND(L48-R48,2) -> 0 | U48: =IFERROR(((K48-(R48/J48))/(R48/J48)),0) -> 0 | V48: =IFERROR(((K48-(R48/J48))/K48),0) -> 0
D49: TOTALS | E49: =SUM(E18:E48) -> 975 | F49: =SUM(F18:F48) -> 103472.26 | G49: =SUM(G18:G48) -> 146930.62 | H49: =SUM(H18:H48) -> 336008.96 | J49: =SUM(J18:J48) -> 975 | K49: =SUM(K18:K48) -> 80807.1 | L49: =SUM(L18:L48) -> 182870.52 | Q49: =SUM(Q18:Q48) -> 0 | R49: =SUM(R18:R48) -> 0 | S49: =SUM(S18:S48) -> 80807.1 | T49: =SUM(T18:T48) -> 182870.52

Sheet CAT DP30NT Forklift
B1: CUSTOMER INFORMATION | D1: MACHINE INFORMATION | H1: MACHINE SERVICE HR INTERVALS | L1: SUMMARY | P1: =K17 -> CAD $ | S1: COMPLETED DEAL INFORMATION
B2: DATE: | D2: UNIT # | F2: FL-20 | H2: ENGINE AIR | L2: OEM MSRP | P2: =H49 -> 6398.48 | S2: SALES REP
B3: COMPANY: | D3: YEAR | F3: 2017 | H3: ENGINE OIL | L3: GQP LIST | P3: =L49 -> 3519.16 | S3: ORDER PO #
B4: CUSTOMER: | D4: MAKE | F4: CAT | H4: FUEL FILTERS | L4: $ SAVINGS | P4: =P2-P3 -> 2879.32 | S4: PROJECT #
B5: PHONE: | D5: MODEL | F5: DP30NT | H5: HYDRAULIC FILTERS | L5: % SAVINGS | P5: =IFERROR((P2-P3)/P2,"") -> 0.45000063 | S5: CUST INVOICE #
B6: EMAIL: | D6: SERIAL NUMBER | F6: CT14E-17785 | H6: TRANSMISSION FILTERS | L6: TOTAL ORDER MARGIN | P6: =T49 -> 3519.16 | S6: PAYMENT TYPE
B7: SALES REP: | D7: ENGINE SER NUMBER | F7: S4S-296499 | H7: CAB FILTERS | L7: TOTAL ITEM COST | P7: =R49 -> 0 | S7: DATE DELIVERED
D8: CURRENT HOURS | H8: UNDERCARRIAGE / TIRES | L8: TOTAL ORDER FREIGHT | P8: =IF(P1=Q14,R14,IF(Q14="CAD $",R14*D15,IF(Q14="USD $",R14*E15,0))) -> 0 | S8: TOTAL COST | T8: NET MARGIN | U8: NET MARKUP % | V8: NET MARGIN %
D9: USAGE/MONTH | F9: Forklift | L9: TOTAL CUSTOMS/BROKERAGE | P9: =V14 -> 0 | S9: =P7+P8+P9 -> 0 | T9: =P3-S9 -> 3519.16 | U9: =IFERROR(((P3-S9)/S9),0) -> 0 | V9: =IFERROR(T9/P3,0) -> 1
L10: TOTAL NUMBER PIECES | P10: =E49 -> 19
D11: ENTER EXCHANGE RATES $ | F11: OEM MSRP | J11: CUSTOMER SELL PRICE | P11: COST ANALYSIS | Y11: CAD $
Y12: USD $
F13: SHOW OEM MSRP ON QUOTE: | H13: YES | Y13: YES
D14: CAD-USD | E14: USD-CAD | F14: OEM NAME | J14: CUSTOMER TYPE/TIER | L14: IE: VIP - Gold | P14: FREIGHT TOTAL ORDER | Q14: USD $ | S14: CUSTOMS AND BROKERAGE % | T14: 0.025 | U14: BROKERAGE FEES | V14: =ROUND(R49*T14,2) -> 0 | Y14: NO
D15: =1/E15 -> 0.70422535 | E15: 1.42 | P15: MARKUP LESS THAN 100% REQUIRES MANAGER APPROVAL
B16: PART NUMBER | C16: DESCRIPTION | D16: SERVICE INTERVAL | E16: QTY | F16: UNIT PRICE | H16: EXT AMOUNT | J16: QTY | K16: UNIT PRICE | L16: EXTENDED AMOUNT | M16: PRCING METHOD %OEM / MARKUP | N16: OEM DISC % / MARKUP % | P16: VENDOR | Q16: COST EACH | R16: EXTENDED COST | S16: MARGIN EACH | T16: EXTENDED MARGIN | U16: MARKUP % | V16: MARGIN %
F17: USD $ | G17: =IF(F17="USD $", "CAD $", "USD $") -> CAD $ | H17: =K17 -> CAD $ | K17: CAD $ | Q17: USD $ | R17: =K17 -> CAD $
B18: 32A94-00070 | C18: Engine Overhaul Kit | D18: 10000 | E18: 1 | F18: 359.48 | G18: =ROUND(IF($F$17="USD $", F18*$E$15,F18*$D$15),2) -> 510.46 | H18: =ROUND(IF($H$17=$G$17,E18*G18,E18*F18),2) -> 510.46 | J18: =E18 -> 1 | K18: =IFERROR(IF(M18="OEM DISC %",ROUND(IF($K$17=$F$17,F18*(1-N18),G18*(1-N18)),2),IF(M18="MARKUP %",ROUND(R18/J18*(1+N18),2))),0) -> 280.75 | L18: =ROUND((J18*K18),2) -> 280.75 | M18: OEM DISC % | N18: 0.45 | R18: =ROUND(IF($R$17=$Q$17,Q18,IF($R$17="USD $",Q18*$D$15,Q18*$E$15))*E18,2) -> 0 | S18: =IFERROR(ROUND(T18/E18,2),0) -> 280.75 | T18: =ROUND(L18-R18,2) -> 280.75 | U18: =IFERROR(((K18-(R18/J18))/(R18/J18)),0) -> 0 | V18: =IFERROR(((K18-(R18/J18))/K18),0) -> 1 | Z18: 250
C19: Turbo Charger | E19: 1 | G19: =ROUND(IF($F$17="USD $", F19*$E$15,F19*$D$15),2) -> 0 | H19: =ROUND(IF($H$17=$G$17,E19*G19,E19*F19),2) -> 0 | J19: =E19 -> 1 | K19: =IFERROR(IF(M19="OEM DISC %",ROUND(IF($K$17=$F$17,F19*(1-N19),G19*(1-N19)),2),IF(M19="MARKUP %",ROUND(R19/J19*(1+N19),2))),0) -> 0 | L19: =ROUND((J19*K19),2) -> 0 | M19: OEM DISC % | N19: 0.45 | R19: =ROUND(IF($R$17=$Q$17,Q19,IF($R$17="USD $",Q19*$D$15,Q19*$E$15))*E19,2) -> 0 | S19: =IFERROR(ROUND(T19/E19,2),0) -> 0 | T19: =ROUND(L19-R19,2) -> 0 | U19: =IFERROR(((K19-(R19/J19))/(R19/J19)),0) -> 0 | V19: =IFERROR(((K19-(R19/J19))/K19),0) -> 0 | Y19: GQP | Z19: 500
B20: 32A30-01023 | C20: Cylinder Head | D20: 10000 | E20: 1 | G20: =ROUND(IF($F$17="USD $", F20*$E$15,F20*$D$15),2) -> 0 | H20: =ROUND(IF($H$17=$G$17,E20*G20,E20*F20),2) -> 0 | J20: =E20 -> 1 | K20: =IFERROR(IF(M20="OEM DISC %",ROUND(IF($K$17=$F$17,F20*(1-N20),G20*(1-N20)),2),IF(M20="MARKUP %",ROUND(R20/J20*(1+N20),2))),0) -> 0 | L20: =ROUND((J20*K20),2) -> 0 | M20: OEM DISC % | N20: 0.45 | R20: =ROUND(IF($R$17=$Q$17,Q20,IF($R$17="USD $",Q20*$D$15,Q20*$E$15))*E20,2) -> 0 | S20: =IFERROR(ROUND(T20/E20,2),0) -> 0 | T20: =ROUND(L20-R20,2) -> 0 | U20: =IFERROR(((K20-(R20/J20))/(R20/J20)),0) -> 0 | V20: =IFERROR(((K20-(R20/J20))/K20),0) -> 0 | Y20: CTP | Z20: 750
B21: 32C61-6000 | C21: Injectors | D21: 6000 | E21: 4 | F21: 57.87 | G21: =ROUND(IF($F$17="USD $", F21*$E$15,F21*$D$15),2) -> 82.18 | H21: =ROUND(IF($H$17=$G$17,E21*G21,E21*F21),2) -> 328.72 | J21: =E21 -> 4 | K21: =IFERROR(IF(M21="OEM DISC %",ROUND(IF($K$17=$F$17,F21*(1-N21),G21*(1-N21)),2),IF(M21="MARKUP %",ROUND(R21/J21*(1+N21),2))),0) -> 45.2 | L21: =ROUND((J21*K21),2) -> 180.8 | M21: OEM DISC % | N21: 0.45 | R21: =ROUND(IF($R$17=$Q$17,Q21,IF($R$17="USD $",Q21*$D$15,Q21*$E$15))*E21,2) -> 0 | S21: =IFERROR(ROUND(T21/E21,2),0) -> 45.2 | T21: =ROUND(L21-R21,2) -> 180.8 | U21: =IFERROR(((K21-(R21/J21))/(R21/J21)),0) -> 0 | V21: =IFERROR(((K21-(R21/J21))/K21),0) -> 1 | Y21: BLMQ | Z21: 1000
B22: 32A20-00080 | C22: Crankshaft | D22: 10000 | E22: 1 | F22: 948.94 | G22: =ROUND(IF($F$17="USD $", F22*$E$15,F22*$D$15),2) -> 1347.49 | H22: =ROUND(IF($H$17=$G$17,E22*G22,E22*F22),2) -> 1347.49 | J22: =E22 -> 1 | K22: =IFERROR(IF(M22="OEM DISC %",ROUND(IF($K$17=$F$17,F22*(1-N22),G22*(1-N22)),2),IF(M22="MARKUP %",ROUND(R22/J22*(1+N22),2))),0) -> 741.12 | L22: =ROUND((J22*K22),2) -> 741.12 | M22: OEM DISC % | N22: 0.45 | R22: =ROUND(IF($R$17=$Q$17,Q22,IF($R$17="USD $",Q22*$D$15,Q22*$E$15))*E22,2) -> 0 | S22: =IFERROR(ROUND(T22/E22,2),0) -> 741.12 | T22: =ROUND(L22-R22,2) -> 741.12 | U22: =IFERROR(((K22-(R22/J22))/(R22/J22)),0) -> 0 | V22: =IFERROR(((K22-(R22/J22))/K22),0) -> 1 | Y22: CAT | Z22: 1200
B23: 32A05-00101 | C23: Camshaft | D23: 10000 | E23: 1 | F23: 247.5 | G23: =ROUND(IF($F$17="USD $", F23*$E$15,F23*$D$15),2) -> 351.45 | H23: =ROUND(IF($H$17=$G$17,E23*G23,E23*F23),2) -> 351.45 | J23: =E23 -> 1 | K23: =IFERROR(IF(M23="OEM DISC %",ROUND(IF($K$17=$F$17,F23*(1-N23),G23*(1-N23)),2),IF(M23="MARKUP %",ROUND(R23/J23*(1+N23),2))),0) -> 193.3 | L23: =ROUND((J23*K23),2) -> 193.3 | M23: OEM DISC % | N23: 0.45 | R23: =ROUND(IF($R$17=$Q$17,Q23,IF($R$17="USD $",Q23*$D$15,Q23*$E$15))*E23,2) -> 0 | S23: =IFERROR(ROUND(T23/E23,2),0) -> 193.3 | T23: =ROUND(L23-R23,2) -> 193.3 | U23: =IFERROR(((K23-(R23/J23))/(R23/J23)),0) -> 0 | V23: =IFERROR(((K23-(R23/J23))/K23),0) -> 1 | Y23: FINNING | Z23: 2000
B24: 32A40-00100 | C24: Engine Oil Filter | D24: 250 | E24: 1 | F24: 19.99 | G24: =ROUND(IF($F$17="USD $", F24*$E$15,F24*$D$15),2) -> 28.39 | H24: =ROUND(IF($H$17=$G$17,E24*G24,E24*F24),2) -> 28.39 | J24: =E24 -> 1 | K24: =IFERROR(IF(M24="OEM DISC %",ROUND(IF($K$17=$F$17,F24*(1-N24),G24*(1-N24)),2),IF(M24="MARKUP %",ROUND(R24/J24*(1+N24),2))),0) -> 15.61 | L24: =ROUND((J24*K24),2) -> 15.61 | M24: OEM DISC % | N24: 0.45 | R24: =ROUND(IF($R$17=$Q$17,Q24,IF($R$17="USD $",Q24*$D$15,Q24*$E$15))*E24,2) -> 0 | S24: =IFERROR(ROUND(T24/E24,2),0) -> 15.61 | T24: =ROUND(L24-R24,2) -> 15.61 | U24: =IFERROR(((K24-(R24/J24))/(R24/J24)),0) -> 0 | V24: =IFERROR(((K24-(R24/J24))/K24),0) -> 1 | Y24: JD | Z24: 4000
B25: 344621-21040 | C25: Fuel Filter | D25: 250 | E25: 1 | F25: 10.57 | G25: =ROUND(IF($F$17="USD $", F25*$E$15,F25*$D$15),2) -> 15.01 | H25: =ROUND(IF($H$17=$G$17,E25*G25,E25*F25),2) -> 15.01 | J25: =E25 -> 1 | K25: =IFERROR(IF(M25="OEM DISC %",ROUND(IF($K$17=$F$17,F25*(1-N25),G25*(1-N25)),2),IF(M25="MARKUP %",ROUND(R25/J25*(1+N25),2))),0) -> 8.26 | L25: =ROUND((J25*K25),2) -> 8.26 | M25: OEM DISC % | N25: 0.45 | R25: =ROUND(IF($R$17=$Q$17,Q25,IF($R$17="USD $",Q25*$D$15,Q25*$E$15))*E25,2) -> 0 | S25: =IFERROR(ROUND(T25/E25,2),0) -> 8.26 | T25: =ROUND(L25-R25,2) -> 8.26 | U25: =IFERROR(((K25-(R25/J25))/(R25/J25)),0) -> 0 | V25: =IFERROR(((K25-(R25/J25))/K25),0) -> 1 | Y25: BRANDT | Z25: 6000
C26: Air Filter (Outer) | E26: 1 | G26: =ROUND(IF($F$17="USD $", F26*$E$15,F26*$D$15),2) -> 0 | H26: =ROUND(IF($H$17=$G$17,E26*G26,E26*F26),2) -> 0 | J26: =E26 -> 1 | K26: =IFERROR(IF(M26="OEM DISC %",ROUND(IF($K$17=$F$17,F26*(1-N26),G26*(1-N26)),2),IF(M26="MARKUP %",ROUND(R26/J26*(1+N26),2))),0) -> 0 | L26: =ROUND((J26*K26),2) -> 0 | M26: OEM DISC % | N26: 0.45 | R26: =ROUND(IF($R$17=$Q$17,Q26,IF($R$17="USD $",Q26*$D$15,Q26*$E$15))*E26,2) -> 0 | S26: =IFERROR(ROUND(T26/E26,2),0) -> 0 | T26: =ROUND(L26-R26,2) -> 0 | U26: =IFERROR(((K26-(R26/J26))/(R26/J26)),0) -> 0 | V26: =IFERROR(((K26-(R26/J26))/K26),0) -> 0 | Y26: PTI | Z26: 8000
C27: Air Filter (Inner) | E27: 1 | G27: =ROUND(IF($F$17="USD $", F27*$E$15,F27*$D$15),2) -> 0 | H27: =ROUND(IF($H$17=$G$17,E27*G27,E27*F27),2) -> 0 | J27: =E27 -> 1 | K27: =IFERROR(IF(M27="OEM DISC %",ROUND(IF($K$17=$F$17,F27*(1-N27),G27*(1-N27)),2),IF(M27="MARKUP %",ROUND(R27/J27*(1+N27),2))),0) -> 0 | L27: =ROUND((J27*K27),2) -> 0 | M27: OEM DISC % | N27: 0.45 | R27: =ROUND(IF($R$17=$Q$17,Q27,IF($R$17="USD $",Q27*$D$15,Q27*$E$15))*E27,2) -> 0 | S27: =IFERROR(ROUND(T27/E27,2),0) -> 0 | T27: =ROUND(L27-R27,2) -> 0 | U27: =IFERROR(((K27-(R27/J27))/(R27/J27)),0) -> 0 | V27: =IFERROR(((K27-(R27/J27))/K27),0) -> 0 | Y27: CONEQUIP | Z27: 10000
C28: Hydraulic Filter | E28: 1 | G28: =ROUND(IF($F$17="USD $", F28*$E$15,F28*$D$15),2) -> 0 | H28: =ROUND(IF($H$17=$G$17,E28*G28,E28*F28),2) -> 0 | J28: =E28 -> 1 | K28: =IFERROR(IF(M28="OEM DISC %",ROUND(IF($K$17=$F$17,F28*(1-N28),G28*(1-N28)),2),IF(M28="MARKUP %",ROUND(R28/J28*(1+N28),2))),0) -> 0 | L28: =ROUND((J28*K28),2) -> 0 | M28: OEM DISC % | N28: 0.45 | R28: =ROUND(IF($R$17=$Q$17,Q28,IF($R$17="USD $",Q28*$D$15,Q28*$E$15))*E28,2) -> 0 | S28: =IFERROR(ROUND(T28/E28,2),0) -> 0 | T28: =ROUND(L28-R28,2) -> 0 | U28: =IFERROR(((K28-(R28/J28))/(R28/J28)),0) -> 0 | V28: =IFERROR(((K28-(R28/J28))/K28),0) -> 0 | Y28: CANDY | Z28: AS REQ'D
C29: Transmission Filter | E29: 1 | G29: =ROUND(IF($F$17="USD $", F29*$E$15,F29*$D$15),2) -> 0 | H29: =ROUND(IF($H$17=$G$17,E29*G29,E29*F29),2) -> 0 | J29: =E29 -> 1 | K29: =IFERROR(IF(M29="OEM DISC %",ROUND(IF($K$17=$F$17,F29*(1-N29),G29*(1-N29)),2),IF(M29="MARKUP %",ROUND(R29/J29*(1+N29),2))),0) -> 0 | L29: =ROUND((J29*K29),2) -> 0 | M29: OEM DISC % | N29: 0.45 | R29: =ROUND(IF($R$17=$Q$17,Q29,IF($R$17="USD $",Q29*$D$15,Q29*$E$15))*E29,2) -> 0 | S29: =IFERROR(ROUND(T29/E29,2),0) -> 0 | T29: =ROUND(L29-R29,2) -> 0 | U29: =IFERROR(((K29-(R29/J29))/(R29/J29)),0) -> 0 | V29: =IFERROR(((K29-(R29/J29))/K29),0) -> 0 | Y29: U/C
B30: 28x9-15 | C30: Tire Size | E30: 4 | F30: 672 | G30: =ROUND(IF($F$17="USD $", F30*$E$15,F30*$D$15),2) -> 954.24 | H30: =ROUND(IF($H$17=$G$17,E30*G30,E30*F30),2) -> 3816.96 | J30: =E30 -> 4 | K30: =IFERROR(IF(M30="OEM DISC %",ROUND(IF($K$17=$F$17,F30*(1-N30),G30*(1-N30)),2),IF(M30="MARKUP %",ROUND(R30/J30*(1+N30),2))),0) -> 524.83 | L30: =ROUND((J30*K30),2) -> 2099.32 | M30: OEM DISC % | N30: 0.45 | R30: =ROUND(IF($R$17=$Q$17,Q30,IF($R$17="USD $",Q30*$D$15,Q30*$E$15))*E30,2) -> 0 | S30: =IFERROR(ROUND(T30/E30,2),0) -> 524.83 | T30: =ROUND(L30-R30,2) -> 2099.32 | U30: =IFERROR(((K30-(R30/J30))/(R30/J30)),0) -> 0 | V30: =IFERROR(((K30-(R30/J30))/K30),0) -> 1
G31: =ROUND(IF($F$17="USD $", F31*$E$15,F31*$D$15),2) -> 0 | H31: =ROUND(IF($H$17=$G$17,E31*G31,E31*F31),2) -> 0 | J31: =E31 -> 0 | K31: =IFERROR(IF(M31="OEM DISC %",ROUND(IF($K$17=$F$17,F31*(1-N31),G31*(1-N31)),2),IF(M31="MARKUP %",ROUND(R31/J31*(1+N31),2))),0) -> 0 | L31: =ROUND((J31*K31),2) -> 0 | M31: OEM DISC % | N31: 0.45 | R31: =ROUND(IF($R$17=$Q$17,Q31,IF($R$17="USD $",Q31*$D$15,Q31*$E$15))*E31,2) -> 0 | S31: =IFERROR(ROUND(T31/E31,2),0) -> 0 | T31: =ROUND(L31-R31,2) -> 0 | U31: =IFERROR(((K31-(R31/J31))/(R31/J31)),0) -> 0 | V31: =IFERROR(((K31-(R31/J31))/K31),0) -> 0 | Y31: OEM DISC %
G32: =ROUND(IF($F$17="USD $", F32*$E$15,F32*$D$15),2) -> 0 | H32: =ROUND(IF($H$17=$G$17,E32*G32,E32*F32),2) -> 0 | J32: =E32 -> 0 | K32: =IFERROR(IF(M32="OEM DISC %",ROUND(IF($K$17=$F$17,F32*(1-N32),G32*(1-N32)),2),IF(M32="MARKUP %",ROUND(R32/J32*(1+N32),2))),0) -> 0 | L32: =ROUND((J32*K32),2) -> 0 | M32: OEM DISC % | N32: 0.45 | R32: =ROUND(IF($R$17=$Q$17,Q32,IF($R$17="USD $",Q32*$D$15,Q32*$E$15))*E32,2) -> 0 | S32: =IFERROR(ROUND(T32/E32,2),0) -> 0 | T32: =ROUND(L32-R32,2) -> 0 | U32: =IFERROR(((K32-(R32/J32))/(R32/J32)),0) -> 0 | V32: =IFERROR(((K32-(R32/J32))/K32),0) -> 0 | Y32: MARKUP %
G33: =ROUND(IF($F$17="USD $", F33*$E$15,F33*$D$15),2) -> 0 | H33: =ROUND(IF($H$17=$G$17,E33*G33,E33*F33),2) -> 0 | J33: =E33 -> 0 | K33: =IFERROR(IF(M33="OEM DISC %",ROUND(IF($K$17=$F$17,F33*(1-N33),G33*(1-N33)),2),IF(M33="MARKUP %",ROUND(R33/J33*(1+N33),2))),0) -> 0 | L33: =ROUND((J33*K33),2) -> 0 | M33: OEM DISC % | N33: 0.45 | R33: =ROUND(IF($R$17=$Q$17,Q33,IF($R$17="USD $",Q33*$D$15,Q33*$E$15))*E33,2) -> 0 | S33: =IFERROR(ROUND(T33/E33,2),0) -> 0 | T33: =ROUND(L33-R33,2) -> 0 | U33: =IFERROR(((K33-(R33/J33))/(R33/J33)),0) -> 0 | V33: =IFERROR(((K33-(R33/J33))/K33),0) -> 0
G34: =ROUND(IF($F$17="USD $", F34*$E$15,F34*$D$15),2) -> 0 | H34: =ROUND(IF($H$17=$G$17,E34*G34,E34*F34),2) -> 0 | J34: =E34 -> 0 | K34: =IFERROR(IF(M34="OEM DISC %",ROUND(IF($K$17=$F$17,F34*(1-N34),G34*(1-N34)),2),IF(M34="MARKUP %",ROUND(R34/J34*(1+N34),2))),0) -> 0 | L34: =ROUND((J34*K34),2) -> 0 | M34: OEM DISC % | N34: 0.45 | R34: =ROUND(IF($R$17=$Q$17,Q34,IF($R$17="USD $",Q34*$D$15,Q34*$E$15))*E34,2) -> 0 | S34: =IFERROR(ROUND(T34/E34,2),0) -> 0 | T34: =ROUND(L34-R34,2) -> 0 | U34: =IFERROR(((K34-(R34/J34))/(R34/J34)),0) -> 0 | V34: =IFERROR(((K34-(R34/J34))/K34),0) -> 0
G35: =ROUND(IF($F$17="USD $", F35*$E$15,F35*$D$15),2) -> 0 | H35: =ROUND(IF($H$17=$G$17,E35*G35,E35*F35),2) -> 0 | J35: =E35 -> 0 | K35: =IFERROR(IF(M35="OEM DISC %",ROUND(IF($K$17=$F$17,F35*(1-N35),G35*(1-N35)),2),IF(M35="MARKUP %",ROUND(R35/J35*(1+N35),2))),0) -> 0 | L35: =ROUND((J35*K35),2) -> 0 | M35: OEM DISC % | N35: 0.45 | R35: =ROUND(IF($R$17=$Q$17,Q35,IF($R$17="USD $",Q35*$D$15,Q35*$E$15))*E35,2) -> 0 | S35: =IFERROR(ROUND(T35/E35,2),0) -> 0 | T35: =ROUND(L35-R35,2) -> 0 | U35: =IFERROR(((K35-(R35/J35))/(R35/J35)),0) -> 0 | V35: =IFERROR(((K35-(R35/J35))/K35),0) -> 0
G36: =ROUND(IF($F$17="USD $", F36*$E$15,F36*$D$15),2) -> 0 | H36: =ROUND(IF($H$17=$G$17,E36*G36,E36*F36),2) -> 0 | J36: =E36 -> 0 | K36: =IFERROR(IF(M36="OEM DISC %",ROUND(IF($K$17=$F$17,F36*(1-N36),G36*(1-N36)),2),IF(M36="MARKUP %",ROUND(R36/J36*(1+N36),2))),0) -> 0 | L36: =ROUND((J36*K36),2) -> 0 | M36: OEM DISC % | N36: 0.45 | R36: =ROUND(IF($R$17=$Q$17,Q36,IF($R$17="USD $",Q36*$D$15,Q36*$E$15))*E36,2) -> 0 | S36: =IFERROR(ROUND(T36/E36,2),0) -> 0 | T36: =ROUND(L36-R36,2) -> 0 | U36: =IFERROR(((K36-(R36/J36))/(R36/J36)),0) -> 0 | V36: =IFERROR(((K36-(R36/J36))/K36),0) -> 0
G37: =ROUND(IF($F$17="USD $", F37*$E$15,F37*$D$15),2) -> 0 | H37: =ROUND(IF($H$17=$G$17,E37*G37,E37*F37),2) -> 0 | J37: =E37 -> 0 | K37: =IFERROR(IF(M37="OEM DISC %",ROUND(IF($K$17=$F$17,F37*(1-N37),G37*(1-N37)),2),IF(M37="MARKUP %",ROUND(R37/J37*(1+N37),2))),0) -> 0 | L37: =ROUND((J37*K37),2) -> 0 | M37: OEM DISC % | N37: 0.45 | R37: =ROUND(IF($R$17=$Q$17,Q37,IF($R$17="USD $",Q37*$D$15,Q37*$E$15))*E37,2) -> 0 | S37: =IFERROR(ROUND(T37/E37,2),0) -> 0 | T37: =ROUND(L37-R37,2) -> 0 | U37: =IFERROR(((K37-(R37/J37))/(R37/J37)),0) -> 0 | V37: =IFERROR(((K37-(R37/J37))/K37),0) -> 0
G38: =ROUND(IF($F$17="USD $", F38*$E$15,F38*$D$15),2) -> 0 | H38: =ROUND(IF($H$17=$G$17,E38*G38,E38*F38),2) -> 0 | J38: =E38 -> 0 | K38: =IFERROR(IF(M38="OEM DISC %",ROUND(IF($K$17=$F$17,F38*(1-N38),G38*(1-N38)),2),IF(M38="MARKUP %",ROUND(R38/J38*(1+N38),2))),0) -> 0 | L38: =ROUND((J38*K38),2) -> 0 | M38: OEM DISC % | N38: 0.45 | R38: =ROUND(IF($R$17=$Q$17,Q38,IF($R$17="USD $",Q38*$D$15,Q38*$E$15))*E38,2) -> 0 | S38: =IFERROR(ROUND(T38/E38,2),0) -> 0 | T38: =ROUND(L38-R38,2) -> 0 | U38: =IFERROR(((K38-(R38/J38))/(R38/J38)),0) -> 0 | V38: =IFERROR(((K38-(R38/J38))/K38),0) -> 0
G39: =ROUND(IF($F$17="USD $", F39*$E$15,F39*$D$15),2) -> 0 | H39: =ROUND(IF($H$17=$G$17,E39*G39,E39*F39),2) -> 0 | J39: =E39 -> 0 | K39: =IFERROR(IF(M39="OEM DISC %",ROUND(IF($K$17=$F$17,F39*(1-N39),G39*(1-N39)),2),IF(M39="MARKUP %",ROUND(R39/J39*(1+N39),2))),0) -> 0 | L39: =ROUND((J39*K39),2) -> 0 | M39: OEM DISC % | N39: 0.45 | R39: =ROUND(IF($R$17=$Q$17,Q39,IF($R$17="USD $",Q39*$D$15,Q39*$E$15))*E39,2) -> 0 | S39: =IFERROR(ROUND(T39/E39,2),0) -> 0 | T39: =ROUND(L39-R39,2) -> 0 | U39: =IFERROR(((K39-(R39/J39))/(R39/J39)),0) -> 0 | V39: =IFERROR(((K39-(R39/J39))/K39),0) -> 0
G40: =ROUND(IF($F$17="USD $", F40*$E$15,F40*$D$15),2) -> 0 | H40: =ROUND(IF($H$17=$G$17,E40*G40,E40*F40),2) -> 0 | J40: =E40 -> 0 | K40: =IFERROR(IF(M40="OEM DISC %",ROUND(IF($K$17=$F$17,F40*(1-N40),G40*(1-N40)),2),IF(M40="MARKUP %",ROUND(R40/J40*(1+N40),2))),0) -> 0 | L40: =ROUND((J40*K40),2) -> 0 | M40: OEM DISC % | N40: 0.45 | R40: =ROUND(IF($R$17=$Q$17,Q40,IF($R$17="USD $",Q40*$D$15,Q40*$E$15))*E40,2) -> 0 | S40: =IFERROR(ROUND(T40/E40,2),0) -> 0 | T40: =ROUND(L40-R40,2) -> 0 | U40: =IFERROR(((K40-(R40/J40))/(R40/J40)),0) -> 0 | V40: =IFERROR(((K40-(R40/J40))/K40),0) -> 0
G41: =ROUND(IF($F$17="USD $", F41*$E$15,F41*$D$15),2) -> 0 | H41: =ROUND(IF($H$17=$G$17,E41*G41,E41*F41),2) -> 0 | J41: =E41 -> 0 | K41: =IFERROR(IF(M41="OEM DISC %",ROUND(IF($K$17=$F$17,F41*(1-N41),G41*(1-N41)),2),IF(M41="MARKUP %",ROUND(R41/J41*(1+N41),2))),0) -> 0 | L41: =ROUND((J41*K41),2) -> 0 | M41: OEM DISC % | N41: 0.45 | R41: =ROUND(IF($R$17=$Q$17,Q41,IF($R$17="USD $",Q41*$D$15,Q41*$E$15))*E41,2) -> 0 | S41: =IFERROR(ROUND(T41/E41,2),0) -> 0 | T41: =ROUND(L41-R41,2) -> 0 | U41: =IFERROR(((K41-(R41/J41))/(R41/J41)),0) -> 0 | V41: =IFERROR(((K41-(R41/J41))/K41),0) -> 0
G42: =ROUND(IF($F$17="USD $", F42*$E$15,F42*$D$15),2) -> 0 | H42: =ROUND(IF($H$17=$G$17,E42*G42,E42*F42),2) -> 0 | J42: =E42 -> 0 | K42: =IFERROR(IF(M42="OEM DISC %",ROUND(IF($K$17=$F$17,F42*(1-N42),G42*(1-N42)),2),IF(M42="MARKUP %",ROUND(R42/J42*(1+N42),2))),0) -> 0 | L42: =ROUND((J42*K42),2) -> 0 | M42: MARKUP % | N42: 0.45 | R42: =ROUND(IF($R$17=$Q$17,Q42,IF($R$17="USD $",Q42*$D$15,Q42*$E$15))*E42,2) -> 0 | S42: =IFERROR(ROUND(T42/E42,2),0) -> 0 | T42: =ROUND(L42-R42,2) -> 0 | U42: =IFERROR(((K42-(R42/J42))/(R42/J42)),0) -> 0 | V42: =IFERROR(((K42-(R42/J42))/K42),0) -> 0
G43: =ROUND(IF($F$17="USD $", F43*$E$15,F43*$D$15),2) -> 0 | H43: =ROUND(IF($H$17=$G$17,E43*G43,E43*F43),2) -> 0 | J43: =E43 -> 0 | K43: =IFERROR(IF(M43="OEM DISC %",ROUND(IF($K$17=$F$17,F43*(1-N43),G43*(1-N43)),2),IF(M43="MARKUP %",ROUND(R43/J43*(1+N43),2))),0) -> 0 | L43: =ROUND((J43*K43),2) -> 0 | M43: OEM DISC % | N43: 0.45 | R43: =ROUND(IF($R$17=$Q$17,Q43,IF($R$17="USD $",Q43*$D$15,Q43*$E$15))*E43,2) -> 0 | S43: =IFERROR(ROUND(T43/E43,2),0) -> 0 | T43: =ROUND(L43-R43,2) -> 0 | U43: =IFERROR(((K43-(R43/J43))/(R43/J43)),0) -> 0 | V43: =IFERROR(((K43-(R43/J43))/K43),0) -> 0
G44: =ROUND(IF($F$17="USD $", F44*$E$15,F44*$D$15),2) -> 0 | H44: =ROUND(IF($H$17=$G$17,E44*G44,E44*F44),2) -> 0 | J44: =E44 -> 0 | K44: =IFERROR(IF(M44="OEM DISC %",ROUND(IF($K$17=$F$17,F44*(1-N44),G44*(1-N44)),2),IF(M44="MARKUP %",ROUND(R44/J44*(1+N44),2))),0) -> 0 | L44: =ROUND((J44*K44),2) -> 0 | M44: OEM DISC % | N44: 0.45 | R44: =ROUND(IF($R$17=$Q$17,Q44,IF($R$17="USD $",Q44*$D$15,Q44*$E$15))*E44,2) -> 0 | S44: =IFERROR(ROUND(T44/E44,2),0) -> 0 | T44: =ROUND(L44-R44,2) -> 0 | U44: =IFERROR(((K44-(R44/J44))/(R44/J44)),0) -> 0 | V44: =IFERROR(((K44-(R44/J44))/K44),0) -> 0
... G48: =ROUND(IF($F$17="USD $", F48*$E$15,F48*$D$15),2) -> 0 | H48: =ROUND(IF($H$17=$G$17,E48*G48,E48*F48),2) -> 0 | J48: =E48 -> 0 | K48: =IFERROR(IF(M48="OEM DISC %",ROUND(IF($K$17=$F$17,F48*(1-N48),G48*(1-N48)),2),IF(M48="MARKUP %",ROUND(R48/J48*(1+N48),2))),0) -> 0 | L48: =ROUND((J48*K48),2) -> 0 | M48: OEM DISC % | N48: 0.45 | R48: =ROUND(IF($R$17=$Q$17,Q48,IF($R$17="USD $",Q48*$D$15,Q48*$E$15))*E48,2) -> 0 | S48: =IFERROR(ROUND(T48/E48,2),0) -> 0 | T48: =ROUND(L48-R48,2) -> 0 | U48: =IFERROR(((K48-(R48/J48))/(R48/J48)),0) -> 0 | V48: =IFERROR(((K48-(R48/J48))/K48),0) -> 0
D49: TOTALS | E49: =SUM(E18:E48) -> 19 | F49: =SUM(F18:F48) -> 2316.35 | G49: =SUM(G18:G48) -> 3289.22 | H49: =SUM(H18:H48) -> 6398.48 | J49: =SUM(J18:J48) -> 19 | K49: =SUM(K18:K48) -> 1809.07 | L49: =SUM(L18:L48) -> 3519.16 | Q49: =SUM(Q18:Q48) -> 0 | R49: =SUM(R18:R48) -> 0 | S49: =SUM(S18:S48) -> 1809.07 | T49: =SUM(T18:T48) -> 3519.16

Sheet CAT DP30NT Forklift (2)
B1: CUSTOMER INFORMATION | D1: MACHINE INFORMATION | H1: MACHINE SERVICE HR INTERVALS | L1: SUMMARY | P1: =K17 -> CAD $ | S1: COMPLETED DEAL INFORMATION
B2: DATE: | D2: UNIT # | F2: FL-21 | H2: ENGINE AIR | L2: OEM MSRP | P2: =H49 -> 6398.48 | S2: SALES REP
B3: COMPANY: | D3: YEAR | F3: 2017 | H3: ENGINE OIL | L3: GQP LIST | P3: =L49 -> 3519.16 | S3: ORDER PO #
B4: CUSTOMER: | D4: MAKE | F4: CAT | H4: FUEL FILTERS | L4: $ SAVINGS | P4: =P2-P3 -> 2879.32 | S4: PROJECT #
B5: PHONE: | D5: MODEL | F5: DP30NT | H5: HYDRAULIC FILTERS | L5: % SAVINGS | P5: =IFERROR((P2-P3)/P2,"") -> 0.45000063 | S5: CUST INVOICE #
B6: EMAIL: | D6: SERIAL NUMBER | F6: CT14E-17982 | H6: TRANSMISSION FILTERS | L6: TOTAL ORDER MARGIN | P6: =T49 -> 3519.16 | S6: PAYMENT TYPE
B7: SALES REP: | D7: ENGINE SER NUMBER | F7: S4S-298947 | H7: CAB FILTERS | L7: TOTAL ITEM COST | P7: =R49 -> 0 | S7: DATE DELIVERED
D8: CURRENT HOURS | H8: UNDERCARRIAGE / TIRES | L8: TOTAL ORDER FREIGHT | P8: =IF(P1=Q14,R14,IF(Q14="CAD $",R14*D15,IF(Q14="USD $",R14*E15,0))) -> 0 | S8: TOTAL COST | T8: NET MARGIN | U8: NET MARKUP % | V8: NET MARGIN %
D9: USAGE/MONTH | F9: Forklift | L9: TOTAL CUSTOMS/BROKERAGE | P9: =V14 -> 0 | S9: =P7+P8+P9 -> 0 | T9: =P3-S9 -> 3519.16 | U9: =IFERROR(((P3-S9)/S9),0) -> 0 | V9: =IFERROR(T9/P3,0) -> 1
